Workbook

Sheet Read Me
A1: Microsoft Excel – Beginner to Advanced
A2: Subject: Microsoft Excel · Learner: Self learner, English · Cards: 40
A3: Source: Claude knowledge
A5: How to study a card
A6: 1. Read Side 1 only. Try to say the meaning, answer or formula out loud before looking further.
A7: 2. Check yourself against Side 2. Read the examples and the common mistake.
A8: 3. Do the practice on Side 3 without looking back. Then mark Status: New → Learning → Known.
A9: 4. Review on days 1, 3, 7, 15, 30, 60 after first study: write the date or ✓ in that day's column.
A10: Got it wrong on a review? Start that card's days again from Day 1.
A11: 5. Follow 'Study order': prerequisites come first, then easy to hard.
A13: Colours
A14: Shaded cells were added by Claude, not taken from your own book or notes. Check them against a trusted source,
A15: and mark the card 'Fix' in the OK / Fix column if anything is wrong. Unshaded cells came from your source.

Sheet Code concept (56-pt) cards
A1: Card | F1: Side 1 · Recognition | R1: Side 2 · Understanding | AT1: Side 3 · Real life & Practice | BD1: Auto | BF1: My review
A2: ID | B2: Topic | C2: Level | D2: Study order | E2: Source | F2: Concept | G2: Recall cue | H2: Read aloud | I2: Type | J2: How often used | K2: Importance (1-5) | L2: Origin / why it exists | M2: Pro tip | N2: Typing hint | O2: Memory story | P2: Picture it | Q2: Emotion hook | R2: Meaning (short) | S2: Meaning in learner's language | T2: Code | U2: Output | V2: Explanation | W2: Simple explanation (Hinglish) | X2: Real-life analogy | Y2: Syntax pattern | Z2: Anatomy | AA2: Example 1 | AB2: Example 2 | AC2: Example 3 | AD2: Variation | AE2: Used with | AF2: Related concepts | AG2: Alternatives | AH2: Family / group | AI2: Where it is used | AJ2: Mini conversation | AK2: Common mistake | AL2: Commonly confused with | AM2: Avoid / don't | AN2: Wrong code | AO2: Right code | AP2: Memory trick | AQ2: Real life: project / work | AR2: Real life: interview / exam | AS2: Real life: daily life | AT2: MCQ question | AU2: MCQ options | AV2: MCQ answer | AW2: Why that answer | AX2: Fill the blank | AY2: Task in learner's language | AZ2: Task answer | BA2: Write your own | BB2: Practice question | BC2: Practice answer | BD2: Importance ★ | BE2: Quick recall (reverse) | BF2: Status | BG2: Day 1 | BH2: Day 3 | BI2: Day 7 | BJ2: Day 15 | BK2: Day 30 | BL2: Day 60 | BM2: OK / Fix | BN2: My note
A3: XL-001 | B3: 01 Basics & Cells | C3: Beginner | D3: 1 | E3: Claude knowledge | F3: Cells, ranges and cell references | G3: How does Excel name one box on the sheet, and how do you point to a whole block of boxes in a formula? | H3: cell = सेल | range = रेंज | reference = रेफ़रेंस | I3: Core concept | J3: Very high | K3: 5 | L3: A worksheet is a grid, so each box needs an address; the column letter plus row number, like C3, works like a map coordinate. | M3: Click a cell and look at the Name Box on the left of the formula bar to see its exact address. | N3: Write the column letter first, then the row number: C3, not 3C. A colon joins two corners of a range. | O3: Think of a cinema seat: Row 3, Seat C is C3. A range A1:B2 is a small group of friends booking four seats together. | P3: A chessboard where one square glows with the label C3 and a rectangle of four squares is outlined in green. | Q3: The calm feeling of finally knowing exactly where every number lives. | R3: A cell is one box on the sheet, and a range is a block of cells. | S3: सेल = शीट का एक खाना; रेंज = कई खानों का समूह | T3: A1: 10 A2: 20 A3: 30 B1: =SUM(A1:A3) | U3: 60 | V3: A cell address is the column letter followed by the row number. A range uses a colon between its first and last cell, so A1:A3 means A1, A2 and A3. Formulas use these addresses so the answer updates when the numbers change. | W3: Har khane ka ek address hota hai, jaise A1. Kai khane ek saath lene hon to colon lagate hain, jaise A1:A3. Formula me address likhne se number badalne par answer khud badal jata hai. | X3: Like a cinema seat number: row and seat together tell you exactly one seat, and a seat block is a group of neighbouring seats. | Y3: =FUNCTION(first_cell:last_cell) | Z3: A = column letter | 1 = row number | A1 = one cell | A1:A3 = range from A1 down to A3 | AA3: A1: 10 B1: =A1 (shows 10, B1 just points to one cell) | AB3: A1: 10 A2: 20 A3: 30 B1: =SUM(A1:A3) (shows 60, a range down one column) | AC3: A1: 5 A2: 10 B1: 15 B2: 20 C1: =SUM(A1:B2) (shows 50, a block across two columns) | AD3: =SUM(A1,A3) adds only A1 and A3 (comma picks separate cells) =SUM(A:A) adds the whole column A Name Box: type D10 and press Enter to jump to D10 | AE3: SUM, AVERAGE, Name Box, formulas | AF3: Worksheet, Workbook, Named range, Table | AG3: Named range, Excel Table column reference | AH3: cell, range, row, column, address, selection | AI3: Budgets and totals | Marks sheets | Any formula you write | AJ3: A: My total shows 0, what did I do wrong? | B: Check your range; you may have typed A1:A2 instead of A1:A3 and missed a row. | AK3: ✗ A1:A3 means only the two cells A1 and A3 → ✓ A1:A3 means every cell from A1 through A3, including A2 | AL3: A1:A3 vs A1,A3: the colon takes the whole block, the comma takes only the cells you name. | AM3: Do not type numbers into a formula when the cell address can be used, or the answer will not update. | AN3: A1: 10 A2: 20 A3: 30 B1: =SUM(A1,A3) | AO3: A1: 10 A2: 20 A3: 30 B1: =SUM(A1:A3) | AP3: Colon = continues through all cells; comma = counts only the ones named. | AQ3: A school clerk sums the marks of one student by pointing a formula at the row range of that student. | AR3: Interview question: What is the difference between a cell reference and a range, and which symbol makes a range? | AS3: It is like telling a friend your flat number instead of saying the whole street, and a floor range instead of one flat. | AT3: A sheet has A1 = 4, A2 = 6, A3 = 8 and A4 = 10. What does =SUM(A2:A4) return? | AU3: A) 18 B) 24 C) 28 D) 30 | AV3: B | AW3: A2:A4 covers A2, A3 and A4, so 6 + 8 + 10 = 24; 28 would include A1 only by mistake, and 30 is a different total. | AX3: The address of the cell in column C and row 3 is ____ → C3 | AY3: Write a formula that adds the numbers in cells B2 down to B6. | AZ3: B7: =SUM(B2:B6) | BA3: Type five numbers in column A and write a SUM formula for them in A6. | BB3: A1: 4 A2: 6 A3: 8 A4: 10 B1: =SUM(A2:A4) What does B1 show? | BC3: 24 | BD3: =IF(K3="","",REPT("★",K3)&REPT("☆",5-K3)&" ("&K3&"/5)") | BE3: =IF(S3="","","Meaning: "&S3&" = ______ (Answer: "&F3&")") | BF3: New
A4: XL-002 | B4: 01 Basics & Cells | C4: Beginner | D4: 2 | E4: Claude knowledge | F4: Data types: text, number, date | G4: Why can a cell that looks like a number refuse to add up, and what does Excel secretly store behind a date? | H4: text = टेक्स्ट | number = नंबर | date = डेट | I4: Core concept | J4: Very high | K4: 5 | L4: Excel must know whether a value is a word, an amount or a day, because each kind follows different maths rules. | M4: If a number sits on the left of its cell, it is probably stored as text, so check it before you add it. | N4: Typing an apostrophe before a number, like '100, makes Excel store it as text on purpose. | O4: Excel is a strict clerk with three boxes marked Words, Amounts and Days, and he drops every entry into one box without asking you. | P4: Three coloured trays on a desk, with a paper marked 100 sitting in the Words tray looking out of place. | Q4: Relief when a total that showed the wrong value finally starts adding correctly. | R4: Excel stores each entry as text, a number or a date, and treats them differently. | S4: टेक्स्ट = शब्द, नंबर = संख्या, डेट = तारीख | T4: A1: 100 A2: '100 (typed with an apostrophe, so it is text) B1: =ISNUMBER(A1) B2: =ISNUMBER(A2) | U4: B1 shows TRUE and B2 shows FALSE | V4: ISNUMBER checks if a cell holds a real number. A1 is a number, but A2 was stored as text because of the apostrophe, even though it looks the same. Dates are numbers too: Excel counts days from 1 January 1900, and 1 January 2024 is stored as 45292. | W4: Excel teen cheez alag rakhta hai: text, number aur date. Text ke andar 100 likha ho to wo jodne me nahi aata. Date asal me ek number hai jo din ginta hai. | X4: Like a bank counter with separate windows for cash, cheques and letters, each handled by different rules. | Y4: =ISNUMBER(cell) | =ISTEXT(cell) | Z4: ISNUMBER = test function | cell = what to check | result = TRUE or FALSE | AA4: A1: Asha B1: =ISTEXT(A1) (shows TRUE, a word is text) | AB4: A1: 100 A2: '100 B1: =SUM(A1:A2) (shows 100, SUM skips the text one) | AC4: A1: =DATE(2024,1,1) A2: =DATE(2024,3,1) B1: =A2-A1 (cell format General, shows 60 days) | AD4: Format cell as General to see the date serial number, for example 45292 =VALUE(A2) converts text like "100" into the number 100 Data tab > Text to Columns > Finish converts a column of text numbers | AE4: ISNUMBER, ISTEXT, VALUE, Format Cells | AF4: Number format, Text to Columns, Date serial number, VALUE | AG4: VALUE function, Text to Columns, multiply by 1 | AH4: text, number, date, time, logical, error value | AI4: Importing data from other systems | Cleaning mark lists | Date calculations like due dates | AJ4: A: My SUM ignores some numbers in the column, why? | B: They are probably stored as text; look for left-aligned values and convert them. | AK4: ✗ Anything that looks like a number is a number → ✓ A value can look like 100 but be stored as text, and then SUM ignores it | AL4: Text 100 vs number 100: text looks the same but is ignored by SUM and sorts like a word. | AM4: Do not type numbers with extra spaces or apostrophes if you need to calculate with them. | AN4: A1: 100 A2: '100 A3: 50 B1: =SUM(A1:A3) (expecting 250) | AO4: A1: 100 A2: '100 A3: 50 B2: =VALUE(A2) B1: =SUM(A1,B2,A3) (shows 250) | AP4: Left = Letters (text), Right = Right numbers; this is the default alignment. | AQ4: A sales analyst imports a CSV and converts text numbers so that totals match the source report. | AR4: Interview question: Why does SUM give the wrong total when some numbers are stored as text? | AS4: It is like a shopkeeper who counts only real notes and puts photocopies of notes aside. | AT4: A cell shows 2500 on the left side of the cell, and SUM leaves it out. What is the most likely reason? | AU4: A) It is stored as text B) It is formatted as currency C) It is stored as a date D) The column is too narrow | AV4: A | AW4: Numbers align right by default and SUM skips text; currency or date formats do not make SUM skip a value. | AX4: Excel stores the date 1 January 2024 internally as the number ____ → 45292 | AY4: Write a formula that tells whether cell A1 holds a number. | AZ4: B1: =ISNUMBER(A1) | BA4: Type a number and the same number with an apostrophe, then compare them with ISNUMBER. | BB4: A1: 50 A2: '50 (text) A3: 50 B1: =SUM(A1:A3) What does B1 show? | BC4: 100 | BD4: =IF(K4="","",REPT("★",K4)&REPT("☆",5-K4)&" ("&K4&"/5)") | BE4: =IF(S4="","","Meaning: "&S4&" = ______ (Answer: "&F4&")") | BF4: New
A5: XL-003 | B5: 01 Basics & Cells | C5: Beginner | D5: 3 | E5: Claude knowledge | F5: AutoFill and the fill handle | G5: Which tiny square at a cell's corner lets you drag a pattern or formula down a column? | H5: AutoFill = ऑटोफ़िल | fill handle = फ़िल हैंडल | I5: Excel feature | J5: Very high | K5: 5 | L5: Typing the same pattern a hundred times is slow, so Excel guesses the pattern and repeats it for you. | M5: Double-click the fill handle to fill down as far as the data in the next column goes. | N5: Select the cell, then grab the small square at its bottom-right corner; the pointer turns into a thin black plus. | O5: The fill handle is a tiny tap at the corner of a water tank; pull it down and the pattern pours into every cell below. | P5: A green square at the corner of a cell, being dragged down while numbers appear one after another. | Q5: A happy surprise when a whole column fills itself in one second. | R5: AutoFill copies or continues a pattern by dragging the fill handle. | S5: ऑटोफ़िल = खींचकर पैटर्न या फ़ॉर्मूला अपने आप भरना | T5: A1: 1 A2: 2 Select A1:A2, drag the fill handle down to A5 | U5: A3 shows 3, A4 shows 4, A5 shows 5 | V5: Excel reads the first two values to find the step, here +1, and continues it. For text such as day names it continues the built-in list. For formulas it copies the formula and moves the relative references. | W5: Do cell select karke handle kheenchoge to Excel pattern samajh kar aage bhar deta hai. Ek hi number ho to wo copy ho jata hai. Formula ho to wo bhi neeche copy hota hai. | X5: Like showing a child 2, 4 and then saying carry on; the child continues 6, 8, 10 by the same rule. | Y5: Select cells > drag the fill handle (bottom-right square) | Z5: Selected cells = the pattern | fill handle = small square | drag direction = where the pattern continues | AA5: A1: 1 A2: 2 Select A1:A2, drag the handle to A5 (A5 shows 5, a number series) | AB5: A1: Mon Drag the handle down to A3 (A2 shows Tue, A3 shows Wed, a text list) | AC5: A1: 5 A2: 7 A3: 9 B1: =A1*2 Double-click the handle of B1 (B2 shows 14, B3 shows 18, a formula copy) | AD5: A single number such as 5 is copied, not counted, when you drag Hold Ctrl while dragging a single number to make it count up (Windows) Click the small Auto Fill Options button after dragging to choose Copy Cells or Fill Series | AE5: Fill series, relative references, Flash Fill, Ctrl+D | AF5: Relative reference, Custom lists, Ctrl+D, Flash Fill | AG5: Ctrl+D to fill down, Home tab > Fill > Series | AH5: AutoFill, fill handle, fill series, fill down, fill right, series | AI5: Serial numbers on a list | Dates and months across columns | Copying one formula to every row | AJ5: A: I typed 1 and dragged but I got 1, 1, 1; why? | B: A single number is copied, so enter 1 and 2 first and drag both cells. | AK5: ✗ Dragging one number always counts up, 1, 2, 3 → ✓ A single number is copied; give two cells to show the step, or hold Ctrl while dragging | AL5: Fill handle vs Ctrl+D: the handle drags to any distance and pattern, Ctrl+D copies the cell above into the selected cells. | AM5: Do not drag blindly over a long list when double-clicking the fill handle does the work in one move. | AN5: A1: 1 Drag the handle down to A5 (expecting 1, 2, 3, 4, 5) | AO5: A1: 1 A2: 2 Select A1:A2 and drag the handle down to A5 | AP5: Two cells show the step; one cell shows only copy. | AQ5: An office assistant numbers 200 employee rows by dragging the handle instead of typing every number. | AR5: Interview question: How do you quickly copy a formula down 500 rows without dragging? | AS5: It is like a teacher writing the first two roll numbers and asking the class monitor to continue the list. | AT5: A1 contains 5 and nothing else. You drag the fill handle from A1 down to A3 without pressing any key. What does A3 show? | AU5: A) 3 B) 5 C) 7 D) 15 | AV5: B | AW5: One plain number is copied, so A2 and A3 both show 5; counting needs two example cells or the Ctrl key. | AX5: The small square at the bottom-right corner of a selected cell is called the ____ → fill handle | AY5: Fill the numbers 10, 20, 30, 40 in column A using only two typed cells. | AZ5: A1: 10 A2: 20 Select A1:A2 and drag the fill handle down to A4 | BA5: Type Jan in one cell and drag it across to see the months continue. | BB5: A1: 10 A2: 20 You select A1:A2 and drag the fill handle down to A4. What does A4 show? | BC5: 40 | BD5: =IF(K5="","",REPT("★",K5)&REPT("☆",5-K5)&" ("&K5&"/5)") | BE5: =IF(S5="","","Meaning: "&S5&" = ______ (Answer: "&F5&")") | BF5: New
A6: XL-004 | B6: 01 Basics & Cells | C6: Beginner | D6: 4 | E6: Claude knowledge | F6: Flash Fill | G6: Which feature watches one example you type and then completes the whole column without a formula? | H6: Flash Fill = फ़्लैश फ़िल | I6: Excel feature | J6: Medium | K6: 3 | L6: Added in Excel 2013, it learns a pattern from your typed example so you can split or join text without writing formulas. | M6: Press Ctrl+E on Windows right after typing the first example to apply it instantly. On other versions use Data tab > Flash Fill. | N6: Type the first result in the cell next to your data, move to the next cell below, then press Ctrl+E. | O6: A parrot hears you say Asha once and then repeats the first name for every row on its own. | P6: A column of full names with a lightning bolt, and the first names appearing in the next column row by row. | Q6: A little delight when messy text sorts itself out in a blink. | R6: Flash Fill copies a pattern you typed once to the other rows. | S6: फ़्लैश फ़िल = एक उदाहरण देखकर बाकी पंक्तियाँ अपने आप भरना | T6: A1: Asha Rao A2: Sita Devi B1: Asha (typed by you) Click B2, press Ctrl+E | U6: B2 shows Sita | V6: Excel compares your typed example with the cell beside it and finds the pattern, here the first word. It then fills the rest of the column using that pattern. The result is plain text, not a formula, so it will not update later. | W6: Pehli row me jo chahiye wo khud likho, phir Ctrl+E dabao. Excel pattern pehchan kar baaki sab bhar deta hai. Ye formula nahi hai, sirf text hai. | X6: Like showing a tailor one sample shirt, then asking him to stitch the rest in exactly the same style. | Y6: Type first example > Ctrl+E (or Data tab > Flash Fill) | Z6: Source column = the data | typed example = the pattern | Ctrl+E = apply to all rows | AA6: A1: Asha Rao A2: Sita Devi B1: Asha Click B2, press Ctrl+E (B2 shows Sita, a split) | AB6: A1: Asha B1: Rao C1: Asha Rao (typed) Click C2, press Ctrl+E (joins first and last name for each row) | AC6: A1: 9876543210 B1: 98765-43210 (typed) Click B2, press Ctrl+E (adds a dash in the same place for all rows) | AD6: Data tab > Flash Fill does the same as Ctrl+E File > Options > Advanced > Automatically Flash Fill turns the live suggestion on or off If the grey preview appears while you type, press Enter to accept it | AE6: Text to Columns, LEFT, MID, CONCAT | AF6: Text to Columns, LEFT and RIGHT, TEXTJOIN, AutoFill | AG6: Text to Columns, LEFT/MID/RIGHT formulas, TEXTSPLIT in Microsoft 365 | AH6: Flash Fill, pattern, split, join, extract, clean | AI6: Splitting full names | Fixing phone number format | Making email IDs from names | AJ6: A: I have full names in one column, can I get only first names fast? | B: Type the first name once next to it and press Ctrl+E. | AK6: ✗ Flash Fill creates a formula that updates when the data changes → ✓ Flash Fill writes fixed values, so you must run it again after the source changes | AL6: Flash Fill vs AutoFill: Flash Fill learns a text pattern from an example, while AutoFill continues a number or list series. | AM6: Do not trust Flash Fill blindly on messy data; always scan the results for wrong rows. | AN6: A1: Asha Rao A2: Sita Devi Select B2 and press Ctrl+E with B1 left empty | AO6: A1: Asha Rao A2: Sita Devi B1: Asha (typed) Click B2, press Ctrl+E | AP6: Type one, press Ctrl+E, check all. | AQ6: A data entry person splits 1,000 full names into first and last name columns in a few seconds. | AR6: Interview question: How can you split a name column without writing a formula? | AS6: It is like showing a friend one correctly written address label and asking him to copy the style on the rest. | AT6: You used Flash Fill to get first names in column B. Later you change the name in A2. What happens to the value in B2? | AU6: A) It updates by itself B) It turns into an error C) It stays as it was D) It is deleted | AV6: C | AW6: Flash Fill pastes fixed values, not formulas, so B2 does not follow A2 afterwards. | AX6: The Windows shortcut for Flash Fill is Ctrl + ____ → E | AY6: Column A has full names. Get only the first name in column B using Flash Fill. | AZ6: B1: type the first name by hand Click B2 and press Ctrl+E | BA6: Take five full names and use Flash Fill to make short names such as A. Rao. | BB6: A1: Ravi Kumar A2: Sita Devi You type Ravi in B1, click B2 and press Ctrl+E. What does B2 show? | BC6: Sita | BD6: =IF(K6="","",REPT("★",K6)&REPT("☆",5-K6)&" ("&K6&"/5)") | BE6: =IF(S6="","","Meaning: "&S6&" = ______ (Answer: "&F6&")") | BF6: New
A7: XL-005 | B7: 01 Basics & Cells | C7: Beginner | D7: 5 | E7: Claude knowledge | F7: Relative vs absolute references ($) | G7: Why does a copied formula sometimes point to the wrong cell, and what sign pins a cell in place? | H7: absolute = एब्सोल्यूट | relative = रिलेटिव | dollar sign = डॉलर साइन | I7: Core concept | J7: Very high | K7: 5 | L7: Excel moves references when you copy a formula, and the dollar sign was added so you can lock a part that must not move. | M7: Press F4 while the cursor is on a reference to cycle through A1, $A$1, A$1 and $A1 (on some laptops press Fn+F4). | N7: The dollar sign goes before the part to lock: $B$1 locks column and row, B$1 locks only the row. | O7: A dollar sign is a pin that nails the cell to the board, so the formula cannot slide it when you copy it. | P7: A cell with a gold pin pushed through it while other cell references slide downward with the copied formulas. | Q7: A moment of relief when a whole column of answers turns out right after one tiny dollar sign. | R7: A relative reference moves when copied; an absolute reference with dollar signs stays fixed. | S7: रिलेटिव = कॉपी करने पर बदलता है; एब्सोल्यूट ($) = जगह पर टिका रहता है | T7: A2: 200 A3: 300 B1: 0.1 (rate) C2: =A2*$B$1 C3: =A3*$B$1 | U7: C2 shows 20 and C3 shows 30 | V7: When C2 is copied down, A2 becomes A3 because it is relative. $B$1 stays B1 because both its column and row are locked. This lets every row use the same rate cell. | W7: Normal reference formula ke saath neeche khisakta hai. Dollar lagane se wo cell wahi rukta hai. Isliye rate wale cell par $ lagate hain. | X7: Like asking each student to check the person next to them (relative), but also asking everyone to look at one fixed notice board (absolute). | Y7: A1 (relative) | $A$1 (absolute) | A$1 or $A1 (mixed) | Z7: $ before the letter = lock the column | $ before the number = lock the row | no $ = free to move | AA7: A2: 200 A3: 300 C2: =A2*2 (copied to C3 it becomes =A3*2 and shows 600, relative) | AB7: A2: 200 A3: 300 B1: 0.1 C2: =A2*$B$1 (copied to C3 it stays $B$1 and shows 30, absolute) | AC7: A2: 2 A3: 3 B1: 4 C1: 5 B2: =$A2*B$1 (shows 8; copied to C3 it becomes =$A3*C$1 and shows 15, mixed) | AD7: F4 once makes $A$1, twice makes A$1, three times makes $A1, four times gives A1 again Named range, for example Rate, works like an absolute reference Copying a formula right changes the column letter; copying down changes the row number | AE7: AutoFill, SUM, VLOOKUP, percentage calculations | AF7: AutoFill, Named range, Mixed reference, F4 key | AG7: Named range, Excel Table structured references | AH7: relative, absolute, mixed, anchor, lock, F4 | AI7: Applying one tax or discount rate to a price list | Multiplication tables | Lookup tables that must not shift | AJ7: A: Only my first row is right after I drag the formula down; the rest show zero. | B: Your rate cell moved; press F4 to lock it as $B$1. | AK7: ✗ A copied formula always points to the same cells as the original → ✓ A normal reference shifts when copied; only the ones with $ stay fixed | AL7: B1 vs $B$1: B1 shifts when copied, $B$1 never shifts. | AM7: Do not copy a formula that uses a fixed rate cell without first adding the dollar signs. | AN7: B1: 10 A2: 200 A3: 300 C2: =A2*B1 C3 (copied) becomes =A3*B2 and shows 0 | AO7: B1: 10 A2: 200 A3: 300 C2: =A2*$B$1 C3 (copied) stays =A3*$B$1 and shows 3000 | AP7: Dollar = Done moving; no dollar means the cell can wander. | AQ7: A finance analyst applies one GST rate cell to hundreds of price rows using $ in the formula. | AR7: Interview question: What does $A$1 mean, and when would you use it instead of A1? | AS7: It is like fixing one price tag to a shelf so that it does not move while the other items change places. | AT7: C2 holds =A2*B1. You copy C2 down to C3. What does C3 contain? | AU7: A) =A3*B1 B) =A3*B2 C) =A2*B2 D) =A3*$B$1 | AV7: B | AW7: Without dollar signs both references move down by one row, so A2 becomes A3 and B1 becomes B2. | AX7: To lock both the column and row of B1 in a formula, write ____ → $B$1 | AY7: Price is in A2:A4 and the discount rate is in D1. Write the formula for C2 so it can be copied down. | AZ7: C2: =A2*$D$1 | BA7: Make a small price list and one tax cell, then copy a formula that uses the tax with a dollar sign. | BB7: A1: 5 B2: 10 B3: 20 C2: =B2*$A$1 You copy C2 to C3. What does C3 show? | BC7: 100 | BD7: =IF(K7="","",REPT("★",K7)&REPT("☆",5-K7)&" ("&K7&"/5)") | BE7: =IF(S7="","","Meaning: "&S7&" = ______ (Answer: "&F7&")") | BF7: New
A8: XL-006 | B8: 02 Basic Functions | C8: Beginner | D8: 6 | E8: Claude knowledge | F8: SUM and AutoSum | G8: Which function adds a block of numbers, and what shortcut types it for you? | H8: SUM = सम | AutoSum = ऑटो-सम | I8: Function | J8: Very high | K8: 5 | L8: Adding is the most common job in a spreadsheet, so Excel gives a ready-made function and a button for it. | M8: Select the cells below a column and press Alt+= on Windows to get the SUM written for you. | N8: Type =SUM( then select the range with the mouse and close the bracket; do not forget the equals sign. | O8: A shopkeeper tips all the coins from a tray into one pile, and the pile's weight is the SUM. | P8: A column of numbers with a bold total line under it, drawn as a green rectangle with the formula. | Q8: Confidence from seeing the correct total appear without a calculator. | R8: SUM adds all the numbers in the cells you give it. | S8: SUM = जोड़ना, सारी संख्याओं का कुल | T8: A1: 10 A2: 20 A3: 30 A4: =SUM(A1:A3) | U8: 60 | V8: SUM adds every number in the range. It ignores text and empty cells in the range. AutoSum, on the Home tab or with Alt+=, writes the SUM formula and guesses the range for you. | W8: SUM sab number jod deta hai. Text ya khali cell ho to use chhod deta hai. Alt+= dabane se Excel khud formula likh deta hai. | X8: Like emptying all small piles of money on a table into one big pile and counting that pile. | Y8: =SUM(number1, [number2], ...) | Z8: = starts a formula | SUM = function name | ( ) = brackets | A1:A3 = numbers to add | AA8: A1: 10 A2: 20 A3: 30 A4: =SUM(A1:A3) (shows 60, a simple range) | AB8: A1: 10 A2: 20 A3: 30 B1: =SUM(A1:A3,5) (shows 65, a range plus a typed number) | AC8: A1: 10 A2: n/a A3: 30 B1: =SUM(A1:A3) (shows 40, the text n/a is ignored) | AD8: =SUM(A:A) adds the whole column A Select A4 under the numbers and press Alt+= then Enter (Windows) for AutoSum Home tab > Editing group > AutoSum button (the sigma sign) does the same | AE8: AVERAGE, SUMIF, AutoSum, Alt+= | AF8: SUMIF, SUMIFS, AVERAGE, COUNT | AG8: Plus signs like =A1+A2+A3, the status bar total, SUMIF for conditions | AH8: SUM, SUMIF, SUMIFS, SUMPRODUCT, SUBTOTAL, AutoSum | AI8: Monthly expense totals | Marks totals | Sales reports | AJ8: A: How do I add the whole column quickly? | B: Click the empty cell below it and press Alt+=, then Enter. | AK8: ✗ SUM will turn text like "five" into 5 → ✓ SUM ignores text in a range, so type real numbers | AL8: SUM vs SUBTOTAL: SUM adds everything in the range, while SUBTOTAL can skip rows hidden by a filter. | AM8: Do not add a long column with plus signs when one SUM range can do it. | AN8: A1: 10 A2: 20 A3: 30 A4: SUM(A1:A3) | AO8: A1: 10 A2: 20 A3: 30 A4: =SUM(A1:A3) | AP8: SUM = Stack Up Many numbers. | AQ8: An accounts assistant totals daily sales in a month column with one SUM formula. | AR8: Interview question: How do you add a column of numbers quickly, and what does SUM do with text? | AS8: It is like adding up all the bills on a monthly grocery list. | AT8: A1 = 2, A2 holds the text '3 (typed with an apostrophe) and A3 = 4. What does =SUM(A1:A3) show? | AU8: A) 9 B) 6 C) #VALUE! D) 2 | AV8: B | AW8: SUM skips text inside a range, so only 2 and 4 are added; 9 would count the text as 3. | AX8: The Windows shortcut for AutoSum is Alt + ____ → = | AY8: Add the numbers in A1 to A2 and also B2 in one formula. | AZ8: C1: =SUM(A1:A2,B2) | BA8: Type five expenses in a column and use AutoSum to get the total. | BB8: A1: 12 A2: 8 B1: 5 B2: 15 C1: =SUM(A1:A2,B2) What does C1 show? | BC8: 35 | BD8: =IF(K8="","",REPT("★",K8)&REPT("☆",5-K8)&" ("&K8&"/5)") | BE8: =IF(S8="","","Meaning: "&S8&" = ______ (Answer: "&F8&")") | BF8: New
A9: XL-007 | B9: 02 Basic Functions | C9: Beginner | D9: 7 | E9: Claude knowledge | F9: AVERAGE, MIN and MAX | G9: Which three functions give the typical, smallest and biggest number of a list? | H9: AVERAGE = एवरेज | MIN = मिन | MAX = मैक्स | I9: Function | J9: Very high | K9: 5 | L9: These names come from the maths words average, minimum and maximum, which are needed in almost every report. | M9: Click the AutoSum drop-down arrow on the Home tab to pick Average, Min or Max without typing. | N9: Spell AVERAGE fully, because =AVG( is not an Excel function and gives a #NAME? error. | O9: Three friends stand in a line by height: the shortest is MIN, the tallest is MAX and the typical height is AVERAGE. | P9: A row of bars with the smallest in blue, the tallest in orange and a dotted line across the middle. | Q9: A sense of control when you can summarise a long list in three quick numbers. | R9: AVERAGE gives the mean, MIN the lowest and MAX the highest value. | S9: एवरेज = औसत, MIN = सबसे छोटा, MAX = सबसे बड़ा | T9: A1: 70 A2: 80 A3: 90 A4: 60 B1: =AVERAGE(A1:A4) B2: =MIN(A1:A4) B3: =MAX(A1:A4) | U9: B1 shows 75, B2 shows 60, B3 shows 90 | V9: AVERAGE adds the numbers and divides by how many numbers there are: (70+80+90+60)/4 = 75. MIN finds the lowest, which is 60, and MAX finds the highest, which is 90. All three ignore text and empty cells in a range. | W9: AVERAGE sab jodkar number ginti se bhaag deta hai. MIN sabse chhota aur MAX sabse bada number batata hai. Khali ya text cell ginti me nahi aate. | X9: Like checking a class: the shortest student, the tallest student and the typical height of all students. | Y9: =AVERAGE(range) | =MIN(range) | =MAX(range) | Z9: AVERAGE, MIN, MAX = function names | range = cells to look at | brackets = hold the range | AA9: A1: 70 A2: 80 A3: 90 A4: 60 B1: =AVERAGE(A1:A4) (shows 75, the mean) | AB9: A1: 70 A2: 80 A3: 90 B1: =MAX(A1:A3,100) (shows 100, a typed number joins the range) | AC9: A1: -5 A2: 3 A3: 0 B1: =MIN(A1:A3) (shows -5, negatives count too) | AD9: =AVERAGE(A1:A4) skips blank cells but counts zero =LARGE(A1:A4,2) gives the second biggest number Status bar at the bottom shows Average, Count and Sum for selected cells | AE9: SUM, COUNT, IF, LARGE, SMALL | AF9: MEDIAN, LARGE, SMALL, COUNT | AG9: MEDIAN, LARGE and SMALL, PivotTable summaries | AH9: AVERAGE, AVERAGEIF, MIN, MAX, MEDIAN, LARGE | AI9: Class marks analysis | Price comparison | Sales performance reports | AJ9: A: My class average looks too low, why? | B: Check whether absent students were typed as 0, because zero is counted but blank is not. | AK9: ✗ AVERAGE ignores zero values like blanks → ✓ AVERAGE counts a typed 0 as a number, but skips empty cells | AL9: AVERAGE vs MEDIAN: AVERAGE is the sum divided by the count, MEDIAN is the middle value when sorted. | AM9: Do not type 0 for missing marks if the average must skip them; leave the cell blank. | AN9: A1: 70 A2: 80 A3: 90 B1: =AVG(A1:A3) | AO9: A1: 70 A2: 80 A3: 90 B1: =AVERAGE(A1:A3) | AP9: MIN is little, MAX is big, AVERAGE is the middle ground. | AQ9: A teacher finds the highest, lowest and average score of a class test in three cells. | AR9: Interview question: What is the difference between AVERAGE and MEDIAN, and how does a zero affect AVERAGE? | AS9: It is like checking the cheapest, costliest and usual price of tomatoes in the market. | AT9: Cells A1, A2, A3 hold 50, 0 (typed zero) and 100. What does =AVERAGE(A1:A3) show? | AU9: A) 75 B) 50 C) 150 D) 0 | AV9: B | AW9: The zero counts as a value, so the total 150 is divided by 3 giving 50; 75 would ignore the zero. | AX9: The function that returns the biggest number in a range is ____ → MAX | AY9: Find the lowest mark in cells A1 to A5 using a formula. | AZ9: B1: =MIN(A1:A5) | BA9: Type six marks and write all three formulas, then check them with your eyes. | BB9: A1: 4 A2: 8 A3: (empty) A4: 12 B1: =AVERAGE(A1:A4) What does B1 show? | BC9: 8 | BD9: =IF(K9="","",REPT("★",K9)&REPT("☆",5-K9)&" ("&K9&"/5)") | BE9: =IF(S9="","","Meaning: "&S9&" = ______ (Answer: "&F9&")") | BF9: New
A10: XL-008 | B10: 02 Basic Functions | C10: Beginner | D10: 8 | E10: Claude knowledge | F10: COUNT, COUNTA and COUNTBLANK | G10: Which functions count only numbers, count every filled cell, or count the empty ones? | H10: COUNT = काउंट | COUNTA = काउंट-ए | COUNTBLANK = काउंट-ब्लैंक | I10: Function | J10: High | K10: 4 | L10: Lists often need to be counted, not added, so Excel gives separate counters for numbers, any entry and empty cells. | M10: Select a range and look at the status bar: Count there shows how many filled cells you picked. | N10: COUNTBLANK is one word with no space; COUNTA ends with a capital A that means All entries. | O10: A bus conductor counts tickets (COUNT numbers), every passenger (COUNTA) and the empty seats (COUNTBLANK). | P10: A bus with some seats filled by people with number tickets and some seats left empty and dotted. | Q10: A quiet satisfaction when attendance or form counts match. | R10: COUNT counts numbers, COUNTA counts any filled cell and COUNTBLANK counts empty cells. | S10: COUNT = सिर्फ़ संख्याएँ गिनो, COUNTA = भरे हुए सारे खाने, COUNTBLANK = खाली खाने | T10: A1: 10 A2: Asha A3: (empty) A4: 25 B1: =COUNT(A1:A4) B2: =COUNTA(A1:A4) B3: =COUNTBLANK(A1:A4) | U10: B1 shows 2, B2 shows 3, B3 shows 1 | V10: COUNT counts only numbers (10 and 25), so it gives 2. COUNTA counts every cell that holds something, here 10, Asha and 25, so it gives 3. COUNTBLANK counts the single empty cell A3, and it also counts cells that hold a formula returning empty text. | W10: COUNT sirf number ginta hai. COUNTA jo bhi likha ho wo sab ginta hai. COUNTBLANK khali khane ginta hai. | X10: Like counting only the ticket numbers, then every person on the bus, then the empty seats. | Y10: =COUNT(range) | =COUNTA(range) | =COUNTBLANK(range) | Z10: COUNT = numbers only | COUNTA = anything filled | COUNTBLANK = empty cells | range = where to look | AA10: A1: 10 A2: Asha A3: 25 B1: =COUNT(A1:A3) (shows 2, numbers only) | AB10: A1: Ravi A2: Sita A3: Amit B1: =COUNTA(A1:A3) (shows 3, names are counted) | AC10: B1: P B2: (empty) B3: P B4: (empty) C1: =COUNTBLANK(B1:B4) (shows 2, empty attendance rows) | AD10: =COUNTA(A:A)-1 counts the entries in a column after removing a header row =COUNTIF(A1:A10,"P") counts only cells equal to P =ROWS(A1:A10)-COUNTA(A1:A10) also gives the empty cells count | AE10: COUNTIF, SUM, IF, ISBLANK | AF10: COUNTIF, COUNTIFS, ISBLANK, ROWS | AG10: COUNTIF, status bar Count, PivotTable count | AH10: COUNT, COUNTA, COUNTBLANK, COUNTIF, COUNTIFS, ROWS | AI10: Attendance sheets | Survey responses | Checking missing data in a form | AJ10: A: I need to know how many students submitted their name. | B: Use COUNTA on the name column; COUNT would give zero since names are text. | AK10: ✗ COUNT counts every filled cell → ✓ COUNT counts only numbers; use COUNTA to count text and numbers together | AL10: COUNT vs COUNTA: COUNT counts numbers only, COUNTA counts any non-empty cell including text. | AM10: Do not use COUNT on a column of names, because it will return 0. | AN10: A1: Ravi A2: Sita A3: Amit B1: =COUNT(A1:A3) (expecting 3) | AO10: A1: Ravi A2: Sita A3: Amit B1: =COUNTA(A1:A3) | AP10: A in COUNTA = All entries; COUNT alone = numbers only. | AQ10: A coordinator counts how many feedback forms are still blank using COUNTBLANK. | AR10: Interview question: What is the difference between COUNT and COUNTA, and how do you count empty cells? | AS10: It is like counting how many seats on a train are taken and how many are still free. | AT10: A1 = 5, A2 = Amit, A3 is empty and A4 = 9. What does =COUNT(A1:A4) return? | AU10: A) 4 B) 3 C) 2 D) 1 | AV10: C | AW10: COUNT counts only numbers, so 5 and 9 give 2; 3 would be COUNTA, which also counts the name. | AX10: The function that counts empty cells in a range is ____ → COUNTBLANK | AY10: Count how many cells from A1 to A10 contain anything at all. | AZ10: B1: =COUNTA(A1:A10) | BA10: Make a short list with a name, a number and a blank cell, and write all three counting formulas. | BB10: A1: 7 A2: hello A3: (empty) A4: 3 A5: (empty) B1: =COUNTA(A1:A5)-COUNT(A1:A5) What does B1 show? | BC10: 1 | BD10: =IF(K10="","",REPT("★",K10)&REPT("☆",5-K10)&" ("&K10&"/5)") | BE10: =IF(S10="","","Meaning: "&S10&" = ______ (Answer: "&F10&")") | BF10: New
A11: XL-009 | B11: 02 Basic Functions | C11: Beginner | D11: 9 | E11: Claude knowledge | F11: ROUND, ROUNDUP and ROUNDDOWN | G11: Which three functions change a number to fewer digits, rounding normally, always up or always down? | H11: ROUND = राउंड | ROUNDUP = राउंड-अप | ROUNDDOWN = राउंड-डाउन | I11: Function | J11: High | K11: 4 | L11: Calculations such as tax or interest give long decimals, so Excel offers functions that cut them to the digits you need. | M11: A negative digits value, like -2, rounds to the left of the decimal point, to hundreds. | N11: The second argument counts digits after the decimal point; ROUND(7.456,2) needs the comma and the 2. | O11: A lift stops at a floor: ROUND goes to the nearest floor, ROUNDUP always goes up and ROUNDDOWN always goes down. | P11: A glass lift in a tall building with three buttons, an up arrow, a down arrow and a middle button. | Q11: Tidy satisfaction when long decimals become clean amounts. | R11: These functions change the stored value to a chosen number of digits. | S11: ROUND = पास की पूर्ण संख्या पर, ROUNDUP = हमेशा ऊपर, ROUNDDOWN = हमेशा नीचे | T11: A1: 7.456 B1: =ROUND(A1,2) B2: =ROUNDUP(A1,2) B3: =ROUNDDOWN(A1,2) | U11: B1 shows 7.46, B2 shows 7.46, B3 shows 7.45 | V11: ROUND looks at the next digit, 6, and rounds up to 7.46. ROUNDUP always moves away from zero, so it also gives 7.46. ROUNDDOWN always cuts toward zero, so it gives 7.45. The second number is how many decimal places to keep. | W11: ROUND paas wali value par le jata hai. ROUNDUP hamesha upar le jata hai aur ROUNDDOWN hamesha neeche. Doosra number batata hai kitne decimal rakhne hain. | X11: Like deciding the bus fare: round to the nearest rupee, always charge up, or always drop the paise. | Y11: =ROUND(number, num_digits) | Z11: number = value or cell | num_digits = decimals to keep | negative digits = round tens, hundreds | AA11: A1: 2.5 B1: =ROUND(A1,0) (shows 3, a half rounds away from zero) | AB11: A1: 1234 B1: =ROUND(A1,-2) (shows 1200, a negative digits value rounds to hundreds) | AC11: A1: 9.99 B1: =ROUNDDOWN(A1,0) (shows 9, the decimals are cut off) | AD11: =ROUNDUP(4.01,0) gives 5 =ROUNDDOWN(-3.7,0) gives -3 because it moves toward zero =INT(7.9) gives 7 and always goes to the lower whole number | AE11: SUM, IF, percentage formulas, currency | AF11: INT, TRUNC, CEILING, FLOOR | AG11: INT, TRUNC, Number format with fewer decimals, MROUND | AH11: ROUND, ROUNDUP, ROUNDDOWN, INT, TRUNC, MROUND | AI11: Bills and invoices | Tax and interest calculations | Marks converted to whole numbers | AJ11: A: I formatted the cell to two decimals, but my total is off by a paisa. | B: Formatting only changes the display; use ROUND to change the actual value. | AK11: ✗ Formatting a cell to 2 decimals also rounds the stored number → ✓ Format only changes how it looks; ROUND changes the stored value | AL11: ROUNDDOWN vs INT: for negative numbers ROUNDDOWN moves toward zero, while INT moves to the lower whole number. | AM11: Do not rely on cell formatting when the rounded value must be used in later formulas. | AN11: A1: 7.456 B1: =ROUND(A1) (expecting 7.46) | AO11: A1: 7.456 B1: =ROUND(A1,2) | AP11: ROUND is Regular, UP is Upwards always, DOWN is Down always. | AQ11: A billing clerk rounds each line item to two decimals so that the invoice total matches the bank amount. | AR11: Interview question: What is the difference between formatting to two decimals and using ROUND? | AS11: It is like a shopkeeper rounding the bill to the nearest rupee when no small change is available. | AT11: What does the formula =ROUNDDOWN(-3.7,0) return? | AU11: A) -4 B) -3 C) -3.7 D) 0 | AV11: B | AW11: ROUNDDOWN moves toward zero, so -3.7 becomes -3; -4 would be ROUNDUP, which moves away from zero. | AX11: =ROUND(1234,-2) gives ____ → 1200 | AY11: Round the number in A1 to one decimal place and always upwards. | AZ11: B1: =ROUNDUP(A1,1) | BA11: Take the number 5.678 and write ROUND, ROUNDUP and ROUNDDOWN to two decimals. | BB11: A1: 15.249 B1: =ROUNDUP(A1,1) What does B1 show? | BC11: 15.3 | BD11: =IF(K11="","",REPT("★",K11)&REPT("☆",5-K11)&" ("&K11&"/5)") | BE11: =IF(S11="","","Meaning: "&S11&" = ______ (Answer: "&F11&")") | BF11: New
A12: XL-010 | B12: 03 Formatting & Organising | C12: Beginner | D12: 10 | E12: Claude knowledge | F12: Number formats (currency, date, percent) | G12: How can the same stored value appear as money, as a percentage or as a calendar date? | H12: format = फ़ॉर्मेट | currency = करेंसी | percent = परसेंट | I12: Excel feature | J12: Very high | K12: 5 | L12: Excel stores one plain value, and number formats were added so the same value can be shown in a readable style. | M12: Press Ctrl+1 to open Format Cells with all the number formats and decimal options in one place. | N12: On Windows, Ctrl+Shift+4 is currency, Ctrl+Shift+5 is percent and Ctrl+Shift+3 is date; the symbol depends on your region. | O12: A cell wears a costume: the same value 0.25 can go to the party as 25%, and 1234.5 puts on a rupee or dollar sign. | P12: One plain number in the middle with three outfits beside it labelled money, percent and date. | Q12: Pride when a plain sheet suddenly looks like a professional report. | R12: A number format changes how a value looks without changing the value itself. | S12: नंबर फ़ॉर्मेट = वही संख्या अलग रूप में दिखाना (पैसा, प्रतिशत, तारीख) | T12: A1: 0.25 Select A1, press Ctrl+Shift+5 (Home tab > Number group > %) | U12: A1 shows 25% | V12: The number format changes only the display. The stored value of A1 is still 0.25, and Percentage format multiplies it by 100 for display and adds the % sign. Dates are stored as serial numbers, so Date format turns 45292 into a calendar date. | W12: Number format sirf dikhane ka tareeka badalta hai, asli value wahi rehti hai. 0.25 ko percent format dene par 25% dikhta hai. Date bhi asal me ek number hai jise date jaisa dikhaya jata hai. | X12: Like a person who stays the same but wears different clothes for office, a wedding or a gym. | Y12: Ctrl+1 > Number tab > choose Category (Currency, Percentage, Date) | Z12: Category = type of format | Decimal places = digits shown | Symbol = currency sign | AA12: A1: 1234.5 Select A1, press Ctrl+Shift+4 (shows $1,234.50 with US English settings, a currency format) | AB12: A1: 0.25 Select A1, press Ctrl+Shift+5 (shows 25%, a percent format) | AC12: A1: 45292 Select A1, press Ctrl+Shift+3 (shows 1-Jan-24 with US English settings, a date format) | AD12: Ctrl+1 > Currency lets you choose the symbol such as the rupee Home tab > Increase Decimal or Decrease Decimal changes the digits shown Typing 25% directly in an empty cell stores 0.25 with Percentage format | AE12: ROUND, TEXT, Format Cells, Home tab | AF12: Format Cells, ROUND, TEXT function, Date serial number | AG12: TEXT function, Accounting format, Custom number formats | AH12: General, Number, Currency, Accounting, Percentage, Date | AI12: Invoices and price lists | Growth and discount percentages | Date columns in schedules | AJ12: A: I typed 0.5 but I want to show 50%. Should I type 50 instead? | B: No, keep 0.5 and apply the Percentage format. | AK12: ✗ Applying the Percentage format to 5 changes it into 5% → ✓ It shows 500%, because the format multiplies the stored value by 100 | AL12: Number format vs ROUND: a format changes only how the value looks, ROUND changes the stored value. | AM12: Do not type the currency symbol by hand when a Currency format can add it for you. | AN12: A1: 5 Select A1 and apply Percentage format (expecting 5%) | AO12: A1: 0.05 Select A1 and press Ctrl+Shift+5 (shows 5%) | AP12: Shift+4 is the dollar key, Shift+5 is the percent key. | AQ12: A finance assistant formats a price column as currency and a growth column as percent before sending a report. | AR12: Interview question: If you format 0.25 as a percentage, what is stored in the cell? | AS12: It is like the same weight shown in kilograms on one scale and in grams on another. | AT12: You type 25% directly into an empty cell. What value does Excel store in that cell? | AU12: A) 25 B) 0.25 C) 2.5 D) 0.025 | AV12: B | AW12: Excel stores a percent as a fraction of 1, so 25% is 0.25; the % sign is only how it is displayed. | AX12: The Windows shortcut to apply Percentage format is Ctrl+Shift+____ → 5 | AY12: Make the number 1234.5 in cell A1 appear as currency with two decimals. | AZ12: Select A1 and press Ctrl+Shift+4 | BA12: Type 0.18 and show it as a percent, then type a big number and show it as currency. | BB12: A1: 0.07 Select A1 and press Ctrl+Shift+5. What does A1 show? | BC12: 7% | BD12: =IF(K12="","",REPT("★",K12)&REPT("☆",5-K12)&" ("&K12&"/5)") | BE12: =IF(S12="","","Meaning: "&S12&" = ______ (Answer: "&F12&")") | BF12: New
A13: XL-011 | B13: 03 Formatting & Organising | C13: Beginner | D13: 11 | E13: Claude knowledge | F13: Sort | G13: Which Excel feature puts rows in order, such as A to Z or smallest to largest, without retyping anything? | H13: Sort = सॉर्ट (sort) | I13: Data tab feature | J13: Very high | K13: 5 | L13: The word sort means to arrange things in order; Excel has had a Sort button on the Data tab for many versions to reorder rows by one or more columns. | M13: Click one cell inside your table before sorting so Excel picks the whole table, and rows stay together. | N13: No typing needed. Click one cell in the column, then Data tab > Sort A to Z or Sort Z to A. | O13: A teacher lines up students by height for a photo: the tallest goes first and every student keeps their own bag with them. | P13: A long line of school children standing from shortest to tallest, each holding their own bag. | Q13: The calm feeling of a messy list turning neat in one click. | R13: Sort rearranges the rows of a table in order based on the values in one or more columns. | S13: डेटा को क्रम में लगाना (A से Z या छोटे से बड़े) | T13: A1: Name B1: Marks A2: Ravi B2: 72 A3: Asha B3: 90 A4: Meena B4: 65 Steps: click B2 > Data tab > Sort Largest to Smallest | U13: Rows become: Asha 90, Ravi 72, Meena 65 (each name stays with its own marks) | V13: Sort reorders whole rows, not just the column you clicked, as long as Excel sees your data as one table. The header row stays on top when Excel detects headers. You can sort text A to Z, numbers small to large, or dates old to new. | W13: Sort ka matlab hai list ko order me lagana. Ek cell par click karo, Data tab me Sort dabao, aur poori row apne data ke saath move hoti hai. | X13: Like arranging books on a shelf by their title: every book moves to a new spot, but each book stays in one piece. | Y13: Data tab > Sort A to Z / Sort Z to A, or Data tab > Sort for the full dialog | Z13: Data tab = where the buttons live | Sort A to Z = smallest or alphabetical first | Sort Z to A = largest or reverse alphabetical first | Sort dialog = choose column, order and extra levels | AA13: A1: Name A2: Ravi A3: Asha A4: Meena Steps: click A2 > Data tab > Sort A to Z Result: Asha, Meena, Ravi | AB13: A1: Class, B1: Marks (class A and B mixed) Steps: Data tab > Sort > Sort by Class (A to Z) > Add Level > Then by Marks (Largest to Smallest) > OK Result: classes grouped, and highest marks first inside each class | AC13: Select only column B (Marks) and click Sort Smallest to Largest Excel asks: Expand the selection or Continue with the current selection Choose Expand the selection so names move with the marks | AD13: Data tab > Sort > Add Level (sort by two columns) Data tab > Sort > My data has headers (tick when row 1 is headings) Data tab > Sort > Order: Custom List... (for Low, Medium, High) | AE13: Filter, Excel Tables, Freeze Panes, Conditional Formatting | AF13: Filter, SORT function, Custom Lists, Excel Tables | AG13: SORT function (Microsoft 365 or Excel 2021 or later), Filter button drop-down sort options | AH13: Sort, Filter, Group, Rank, Order | AI13: Ranking students by marks | Arranging a customer list A to Z | Putting dates in order before a report | AJ13: A: My marks list is all mixed up and I need the topper first. | B: Click any cell in the Marks column, then use Data tab > Sort Largest to Smallest. | AK13: ✗ Sorting one column changes only that column's order → ✓ If you select only one column and choose Continue with the current selection, the other columns do not move and the rows no longer match; pick Expand the selection | AL13: Sort vs Filter: Sort changes the order of all rows, while Filter only hides rows that do not match and keeps the order. | AM13: Do not select a single column in the middle of a table and sort it alone, because the rows will no longer match. | AN13: Select only B2:B4 > Data tab > Sort Smallest to Largest > Continue with the current selection | AO13: Click one cell inside the table (for example B2) > Data tab > Sort Smallest to Largest (or choose Expand the selection) | AP13: Sort = Same rows Stay together, they only change order. | AQ13: A teacher sorts the class result sheet by total marks so the top ten students are at the top of the report. | AR13: Interviewer asks: How do you sort a table by two columns, such as Department and then Salary? | AS13: Arranging contacts in your phone by name so you can find a friend quickly. | AT13: You select only column B (Marks) in a Name and Marks table and sort it, choosing Continue with the current selection. What happens to the names in column A? | AU13: A) They move together with the marks B) They stay where they were, so names no longer match marks C) They are sorted A to Z as well D) Excel deletes them | AV13: B | AW13: Continue with the current selection sorts only the selected cells, so column A is untouched and the rows no longer match. | AX13: To keep names with their marks, choose ____ the selection when Excel asks → Expand | AY13: Make a small list of three items with prices and put it in order from the lowest price to the highest. | AZ13: A1: Item B1: Price A2: Pen B2: 20 A3: Book B3: 50 A4: Ink B4: 5 Steps: click B2 > Data tab > Sort Smallest to Largest Result: Ink 5, Pen 20, Book 50 | BA13: Write down five of your own expenses in two columns and sort them from the biggest amount to the smallest. | BB13: A1: Item, B1: Price. A2: Pen 20, A3: Book 50, A4: Ink 5. You click B2 and use Data tab > Sort Smallest to Largest. In what order do the items appear from row 2 to row 4? | BC13: Ink, Pen, Book (prices 5, 20, 50) | BD13: =IF(K13="","",REPT("★",K13)&REPT("☆",5-K13)&" ("&K13&"/5)") | BE13: =IF(S13="","","Meaning: "&S13&" = ______ (Answer: "&F13&")") | BF13: New
A14: XL-012 | B14: 03 Formatting & Organising | C14: Beginner | D14: 12 | E14: Claude knowledge | F14: Filter | G14: Which Excel feature lets you show only the rows you want, such as one city, while the other rows stay safe but out of sight? | H14: Filter = फ़िल्टर (filter) | I14: Data tab feature | J14: Very high | K14: 5 | L14: A filter lets some things pass and blocks others; Excel borrowed the word for AutoFilter, which adds small drop-down arrows to the header row. | M14: Press Ctrl+Shift+L to turn filter arrows on or off quickly on Windows Excel. | N14: Click a cell in your table, then press Ctrl+Shift+L. Do not select a blank row first. | O14: A tea strainer lets only the liquid through and keeps the leaves aside, but the leaves are still in the strainer, not thrown away. | P14: A tea strainer over a cup, with tea leaves resting in it and clear tea dripping through. | Q14: Relief when a huge sheet shrinks to just the rows you care about. | R14: Filter hides the rows that do not match your condition and shows only the rows that do. | S14: सिर्फ़ ज़रूरी पंक्तियाँ दिखाना, बाकी छिपाना | T14: A1: Name B1: City A2: Asha B2: Delhi A3: Ravi B3: Pune A4: Meena B4: Delhi Steps: click A1 > Ctrl+Shift+L > click arrow in B1 > untick Select All > tick Delhi > OK | U14: Only Asha and Meena rows are visible; row 3 (Ravi) is hidden, not deleted, and the row numbers on the left skip from 2 to 4 | V14: Filter adds a drop-down arrow to each header cell. When you pick values, Excel hides every row that does not match. The hidden rows are still in the sheet and come back when you clear the filter. | W14: Filter se aap sirf wahi rows dekhte ho jo aapko chahiye. Baaki rows delete nahi hoti, bas chhup jaati hain, aur filter hatane par wapas aa jaati hain. | X14: Like a shop website's filter for Size: M, which hides other sizes but does not remove them from the shop. | Y14: Data tab > Filter (or Ctrl+Shift+L), then use the arrow in a header cell | Z14: Header arrow = opens the filter menu | Tick boxes = choose which values to show | Text Filters / Number Filters = conditions such as contains or greater than | Clear = removes the filter | AA14: Text filter: click arrow in City > tick only Delhi > OK Result: only rows where City is Delhi are shown | AB14: Number filter: A1: Item, B1: Qty. A2: Pen 10, A3: Book 3, A4: Ink 7 Click arrow in Qty > Number Filters > Greater Than > 5 > OK Result: Pen and Ink rows are shown | AC14: Remove the filter: Data tab > Clear (to show all rows again) or press Ctrl+Shift+L to switch the arrows off Result: all rows are visible again | AD14: Text Filters > Contains... (names that include some letters) Number Filters > Top 10... (largest values) Filter by Color (cell colour or font colour) | AE14: Sort, Excel Tables, Conditional Formatting, Freeze Panes | AF14: Sort, Advanced Filter, FILTER function, Slicers | AG14: FILTER function (Microsoft 365 or Excel 2021 or later), Advanced Filter, PivotTable | AH14: Filter, AutoFilter, Slicer, Search box, Clear | AI14: Looking at one city or one month of sales | Finding all unpaid fees in a list | Checking only the rows that need follow-up | AJ14: A: I only want to see the students from class 10, but the sheet has 500 rows. | B: Press Ctrl+Shift+L, click the arrow on the Class column and tick only 10. | AK14: ✗ Filter deletes the rows that do not match → ✓ Filter only hides them; they come back when you clear the filter, so your data is safe | AL14: Filter vs Sort: Filter hides rows that do not match, while Sort keeps every row and only changes their order. | AM14: Do not copy numbers from a filtered sheet and assume hidden rows are included; check what was visible before you total or send it. | AN14: Select row 3 (Ravi) > right-click > Delete to remove people who are not in Delhi | AO14: Click A1 > Ctrl+Shift+L > click arrow in City > tick only Delhi > OK | AP14: Filter = Few rows Visible, rest Hidden (not gone). | AQ14: A shop owner filters the sales sheet to one product and one month to prepare a short report. | AR14: Interviewer asks: What is the difference between hiding rows with Filter and deleting them? | AS14: Using the Show only vegetarian option on a food app to see fewer dishes. | AT14: After you filter a City column to show only Delhi, where do the Pune rows go? | AU14: A) They are permanently deleted B) They are moved to a new sheet C) They are hidden but still in the sheet D) They are changed to Delhi | AV14: C | AW14: Filter only hides non-matching rows; the row numbers skip, and clearing the filter brings them back. | AX14: The keyboard shortcut to turn filter arrows on or off is ____ → Ctrl+Shift+L | AY14: Show only the items that have a quantity greater than 5 from a small three-row list. | AZ14: A1: Item B1: Qty A2: Pen B2: 10 A3: Book B3: 3 A4: Ink B4: 7 Steps: click A1 > Ctrl+Shift+L > arrow in B1 > Number Filters > Greater Than > 5 > OK Result: Pen and Ink are visible | BA14: Make a list of ten of your friends with their cities and filter it to show only one city. | BB14: A1: Item, B1: Qty. A2: Pen 10, A3: Book 3, A4: Ink 7. You apply Number Filters > Greater Than > 5 on Qty. Which items stay visible? | BC14: Pen and Ink (Book is hidden) | BD14: =IF(K14="","",REPT("★",K14)&REPT("☆",5-K14)&" ("&K14&"/5)") | BE14: =IF(S14="","","Meaning: "&S14&" = ______ (Answer: "&F14&")") | BF14: New
... A24: XL-022 | B24: 04 Logic | C24: Intermediate | D24: 22 | E24: Claude knowledge | F24: IFERROR | G24: Which function replaces an ugly error value with a friendly message or a blank? | H24: IFERROR = इफ-एरर | I24: Logical function | J24: Very high | K24: 5 | L24: Real sheets often show errors like #DIV/0! that scare readers, so Excel (from 2007) added one function that catches any error and shows something else instead. | M24: Use IFERROR only on the part that may fail, and never use it to hide errors you have not understood. | N24: Two arguments: the formula first, the fallback second. Remember the word is one piece, IFERROR, with no space. | O24: A goalkeeper stands under your formula; when an error shot comes in, he catches it and throws a smiling message back. | P24: A goalkeeper in a bright jersey catching a red ball marked with a hash sign and handing a note that says Check B1. | Q24: Relief when a report full of red errors suddenly looks clean and professional. | R24: IFERROR returns your formula's result, but if that formula gives any error, it returns a value you choose. | S24: अगर फ़ॉर्मूले में एरर आए तो उसकी जगह अपनी पसंद का मान दिखाना | T24: A1: 10 B1: 0 C1: =IFERROR(A1/B1,"Check B1") | U24: Check B1 | V24: A1/B1 divides by zero, so it gives #DIV/0!. IFERROR sees the error and shows the second argument instead. If there was no error, you would see the normal result. | W24: Pehle Excel tumhara formula chalata hai. Agar error aaye to tumhara diya hua message dikhata hai, nahi to normal answer dikhata hai. | X24: Like a spare tyre in a car: you only use it when the main one fails, and normally you never notice it. | Y24: =IFERROR(value, value_if_error) | Z24: value = the formula or cell that may give an error | value_if_error = what to show when it does | AA24: A1: 10 B1: 0 C1: =IFERROR(A1/B1,0) | AB24: A1: 10 B1: 4 C1: =IFERROR(A1/B1,"n/a") | AC24: A1: Asha B1: 50 A2: Meena B2: 60 D1: Ravi E1: =IFERROR(VLOOKUP(D1,A1:B2,2,FALSE),"Not found") | AD24: =IFERROR(A1/B1,"") - shows a blank cell on error =IFNA(VLOOKUP(D1,A1:B2,2,FALSE),"Not found") - catches only #N/A =IFERROR(A1/B1,0) - shows 0 on error | AE24: VLOOKUP, XLOOKUP, division, INDEX and MATCH | AF24: IFNA, ISERROR, IF, error values | AG24: IFNA, IF with ISERROR, ISNUMBER checks | AH24: IFERROR, IFNA, ISERROR, ISERR, ISNA, IF | AI24: Percentage columns that divide by zero | Lookups for names that may be missing | Dashboards that must look clean | AJ24: A: My percent column shows #DIV/0! in empty rows, how can I hide it? | B: Wrap the formula in IFERROR and give an empty text like "" as the second argument. | AK24: ✗ IFERROR fixes the real problem in the formula → ✓ IFERROR only hides the error message; the wrong data or formula is still there | AL24: IFERROR vs IFNA: IFERROR catches every error type, while IFNA catches only #N/A, so IFNA is safer when you only expect a missing lookup. | AM24: Do not wrap a whole big formula in IFERROR without testing it first, because it can hide real mistakes. | AN24: A1: 10 B1: 0 C1: =IFERROR("Error",A1/B1) | AO24: A1: 10 B1: 0 C1: =IFERROR(A1/B1,"Error") | AP24: Try first, rescue second: formula first, fallback second. | AQ24: A sales report uses IFERROR around its growth percent so that new products with no old sales do not show errors. | AR24: Interview question: what is the difference between IFERROR and IFNA, and when would you pick IFNA? | AS24: Like an auto reply that says I am away when nobody can answer your call. | AT24: A1 holds the text abc. What does =IFERROR(A1*2,"Bad") show? | AU24: A) 0 B) #VALUE! C) Bad D) abc | AV24: C | AW24: Multiplying text by 2 gives #VALUE!, and IFERROR replaces that error with Bad. The error itself is never shown. | AX24: =____(A1/B1,"Check") → IFERROR | AY24: In A1 write 8 and in B1 write 0. In C1 divide A1 by B1, but show the number -1 if the division fails. | AZ24: A1: 8 B1: 0 C1: =IFERROR(A1/B1,-1) | BA24: Write a formula that divides two of your own numbers and shows the word Retry when the second number is zero. | BB24: A1: 8 B1: 0 C1: =IFERROR(A1/B1,-1) What does C1 show? | BC24: -1 | BD24: =IF(K24="","",REPT("★",K24)&REPT("☆",5-K24)&" ("&K24&"/5)") | BE24: =IF(S24="","","Meaning: "&S24&" = ______ (Answer: "&F24&")") | BF24: New
A25: XL-023 | B25: 04 Logic | C25: Intermediate | D25: 23 | E25: Claude knowledge | F25: Common errors: #N/A, #REF!, #DIV/0!, #VALUE! | G25: What do the error codes that start with a hash sign tell you about what went wrong in a formula? | H25: #N/A = हैश एन-ए, #REF! = हैश रेफ़, #DIV/0! = हैश डिव ज़ीरो, #VALUE! = हैश वैल्यू | I25: Error values | J25: Very high | K25: 5 | L25: Excel shows a special error value instead of a wrong number, so the code itself is a clue; for example DIV/0 is short for division by zero and REF is short for reference. | M25: Read the code first: each one points to a different cause, so the code saves you from guessing. | N25: These are shown by Excel, you do not type them. They always begin with # and most end with ! (but #N/A has a slash). | O25: Four warning lamps on a car dashboard: one for dividing by zero, one for a lost cell, one for a missing item and one for the wrong kind of value. | P25: A car dashboard with four small red lamps, each labelled with a different hash-sign code. | Q25: Panic when red codes appear, then calm once you know each code has a simple cause. | R25: Error values are codes that Excel shows when a formula cannot give a proper answer, and each code names a different cause. | S25: फ़ॉर्मूला सही उत्तर न दे पाए तो Excel जो एरर कोड दिखाता है | T25: A1: 10 B1: 0 C1: =A1/B1 | U25: #DIV/0! | V25: #DIV/0! means a division by zero or by an empty cell. #N/A means a looked-up value was not found. #REF! means the formula points to a cell that no longer exists. #VALUE! means a number was expected but the cell holds text or a wrong type. | W25: Har error ka matlab alag hota hai. #DIV/0! zero se divide, #N/A value mili nahi, #REF! cell delete ho gaya, #VALUE! number ki jagah text. | X25: Like the different error messages from an ATM: wrong PIN, low balance and card blocked each need a different fix. | Y25: #DIV/0! = divide by zero | #N/A = not available | #REF! = invalid reference | #VALUE! = wrong type of value | Z25: #DIV/0! = divisor is 0 or blank | #N/A = lookup found nothing | #REF! = referred cell or column was deleted | #VALUE! = text where a number is needed | AA25: A1: 10 B1: 0 C1: =A1/B1 | AB25: A1: Asha B1: 50 A2: Meena B2: 60 D1: =VLOOKUP("Ravi",A1:B2,2,FALSE) | AC25: A1: 5 B1: 7 C1: =A1+B1 Then delete column B. The formula now shows =A1+#REF! and the result is #REF! | AD25: =A1+1 with A1 = Asha - #VALUE!, because text cannot be added =A1/B1 with B1 empty - #DIV/0!, because an empty cell counts as 0 =IFERROR(A1/B1,"") - hides any of these errors | AE25: IFERROR, IFNA, VLOOKUP, Trace Precedents | AF25: IFERROR, ISERROR, Formula Auditing, VLOOKUP | AG25: IFERROR to hide them, Formulas tab > Error Checking to find them | AH25: #DIV/0!, #N/A, #REF!, #VALUE!, #NAME?, #NUM!, #NULL! | AI25: Fixing broken reports | Checking lookups that did not match | Cleaning data before sharing a file | AJ25: A: My VLOOKUP shows #N/A, is my formula broken? | B: Not always, it usually means the value you search for is not in the first column of the table. | AK25: ✗ Every error means my formula is typed wrong → ✓ Often the formula is fine and the data is the problem, such as a zero, a missing name or text instead of a number | AL25: #N/A vs #REF!: #N/A means the value was not found, while #REF! means the formula points to a cell or column that was deleted. | AM25: Do not just paste values over errors to hide them, find the cause so the same error does not return. | AN25: A1: 10 kg B1: =A1*2 | AO25: A1: 10 B1: =A1*2 C1: kg | AP25: DIV = divide, REF = reference, N/A = not available, VALUE = wrong value type. | AQ25: An analyst checks a monthly report and uses the error code to find that deleted columns caused #REF! in totals. | AR25: Interview question: what does #N/A mean in a VLOOKUP and how can you handle it? | AS25: Like a phone saying number not found versus number not reachable: the message tells you what to do next. | AT25: A name that is not in the list is searched with =VLOOKUP("Zoya",A1:B3,2,FALSE). Which error appears? | AU25: A) #REF! B) #N/A C) #VALUE! D) #DIV/0! | AV25: B | AW25: A lookup that finds no match returns #N/A. #REF! would need a column number larger than the table, which is not the case here. | AX25: Dividing a number by an empty cell gives ____ → #DIV/0! | AY25: In A1 write 20 and in B1 write 0. In C1 divide A1 by B1 and note which error appears. | AZ25: A1: 20 B1: 0 C1: =A1/B1 C1 shows #DIV/0! | BA25: Make each of the four errors on purpose in a new sheet and write a short note on what caused each one. | BB25: A1: 20 B1: 0 C1: =A1/B1 What does C1 show? | BC25: #DIV/0! | BD25: =IF(K25="","",REPT("★",K25)&REPT("☆",5-K25)&" ("&K25&"/5)") | BE25: =IF(S25="","","Meaning: "&S25&" = ______ (Answer: "&F25&")") | BF25: New
A26: XL-024 | B26: 05 Conditional Maths | C26: Intermediate | D26: 24 | E26: Claude knowledge | F26: COUNTIF and SUMIF | G26: Which two functions count or add only the cells that meet one condition, such as only one city? | H26: COUNTIF = काउंट-इफ, SUMIF = सम-इफ | I26: Conditional function | J26: Very high | K26: 5 | L26: Plain COUNT and SUM treat every cell the same, but users needed totals for one group only, so Excel added versions that first check a condition (IF) and then count or add. | M26: Put the condition in a cell and point to it, so you can change the city or limit without editing the formula. | N26: Put text conditions inside double quotes, for example "Delhi", and put comparisons inside quotes too, for example ">100". | O26: A cashier sorting coins counts only the five-rupee coins into the box; COUNTIF counts the matching coins and SUMIF adds up their value. | P26: A hand picking only the red marbles out of a mixed bowl and then counting or weighing them. | Q26: Satisfaction when one formula answers a question like how many sales came from Delhi. | R26: COUNTIF counts the cells that meet one condition, and SUMIF adds the numbers that meet one condition. | S26: एक शर्त पूरी करने वाले सेल गिनना या उनका जोड़ निकालना | T26: A1: Delhi A2: Pune A3: Delhi A4: Goa A5: Delhi B1: 100 B2: 200 B3: 150 B4: 50 B5: 300 D1: =COUNTIF(A1:A5,"Delhi") D2: =SUMIF(A1:A5,"Delhi",B1:B5) | U26: D1 shows 3 D2 shows 550 | V26: COUNTIF looks at A1:A5 and counts the cells equal to Delhi, which is 3. SUMIF checks the same range for Delhi and adds the matching numbers in B1:B5, which are 100, 150 and 300, giving 550. | W26: COUNTIF gintii karta hai kitne cells condition se match karte hain. SUMIF unhi rows ke numbers jod deta hai. Order yaad rakho: range, condition, phir sum range. | X26: Like a teacher counting only the girls in a class, or adding only the girls' marks, while ignoring the boys. | Y26: =COUNTIF(range, criteria) =SUMIF(range, criteria, [sum_range]) | Z26: range = cells that are checked | criteria = the condition such as "Delhi" or ">100" | sum_range = the numbers to add (if left out, the checked range itself is added) | AA26: A1: Delhi A2: Pune A3: Delhi B1: 100 B2: 200 B3: 150 D1: =COUNTIF(A1:A3,"Delhi") | AB26: B1: 100 B2: 200 B3: 150 B4: 50 B5: 300 D1: =SUMIF(B1:B5,">100") | AC26: A1: Delhi A2: Pune A3: Delhi A4: Goa A5: Delhi D1: =COUNTIF(A1:A5,"P*") | AD26: =COUNTIF(A1:A5,D1) - condition taken from cell D1 =COUNTIF(B1:B5,">=150") - counts values 150 or more =COUNTIF(A1:A5,"<>Delhi") - counts cells that are not Delhi | AE26: Wildcards (* and ?), comparison signs, cell references, COUNTIFS | AF26: COUNTIFS, SUMIFS, COUNT, SUM | AG26: COUNTIFS, SUMIFS, SUMPRODUCT, PivotTable | AH26: COUNT, COUNTA, COUNTIF, COUNTIFS, SUM, SUMIF, SUMIFS | AI26: Total sales for one city | Counting students who passed | Adding expenses of one category | AJ26: A: How can I add only the sales of Delhi from this long list? | B: Use SUMIF, give the city column, the word Delhi and then the sales column. | AK26: ✗ SUMIF takes the condition first and then the range → ✓ The order is range, criteria and then sum_range | AL26: SUMIF vs SUMIFS: SUMIF handles one condition and puts sum_range last, while SUMIFS handles many conditions and puts sum_range first. | AM26: Do not forget the quotes around conditions with signs, such as ">100"; writing >100 without quotes gives an error. | AN26: A1: Delhi A2: Pune A3: Delhi A4: Goa A5: Delhi B1: 100 B2: 200 B3: 150 B4: 50 B5: 300 D1: =SUMIF(B1:B5,"Delhi",A1:A5) | AO26: A1: Delhi A2: Pune A3: Delhi A4: Goa A5: Delhi B1: 100 B2: 200 B3: 150 B4: 50 B5: 300 D1: =SUMIF(A1:A5,"Delhi",B1:B5) | AP26: Check where, check what, then add which: range, criteria, sum_range. | AQ26: A shop owner uses SUMIF to get the total sales of each product from a long daily sales list. | AR26: Interview question: how do you total the sales of only one region, and how do you count the rows for it? | AS26: Like counting only the red cars in a parking lot, or adding only their prices. | AT26: B1:B5 holds 100, 200, 150, 50 and 300. What does =COUNTIF(B1:B5,">100") show? | AU26: A) 2 B) 3 C) 4 D) 650 | AV26: B | AW26: The values above 100 are 200, 150 and 300, which makes 3 cells; 650 is their sum, which is what SUMIF would give. | AX26: =____(A1:A5,"Delhi") counts the cells that equal Delhi → COUNTIF | AY26: A1 to A4 hold Red, Blue, Red, Red and B1 to B4 hold 5, 3, 2, 10. Add only the numbers where the colour is Red. | AZ26: A1: Red A2: Blue A3: Red A4: Red B1: 5 B2: 3 B3: 2 B4: 10 D1: =SUMIF(A1:A4,"Red",B1:B4) | BA26: Take your own small list of expenses with categories and write a formula to total only one category. | BB26: A1: Red A2: Blue A3: Red A4: Red B1: 5 B2: 3 B3: 2 B4: 10 D1: =SUMIF(A1:A4,"Red",B1:B4) What does D1 show? | BC26: 17 | BD26: =IF(K26="","",REPT("★",K26)&REPT("☆",5-K26)&" ("&K26&"/5)") | BE26: =IF(S26="","","Meaning: "&S26&" = ______ (Answer: "&F26&")") | BF26: New
A27: XL-025 | B27: 05 Conditional Maths | C27: Intermediate | D27: 25 | E27: Claude knowledge | F27: COUNTIFS and SUMIFS | G27: Which functions count or add only the rows that meet two or more conditions at the same time? | H27: COUNTIFS = काउंट-इफ़-एस, SUMIFS = सम-इफ़-एस | I27: Conditional function | J27: High | K27: 5 | L27: COUNTIF and SUMIF allowed only one condition, so Excel 2007 added versions with an S at the end that accept many conditions, all of which must be true together. | M27: In SUMIFS the sum range comes first, then each pair of range and condition, and all ranges must be the same size. | N27: Write pairs one after another: range, condition, range, condition. Every condition with a sign needs quotes, like ">100". | O27: A security guard at a gate checks both your ID and your ticket, and only people who pass both checks are counted or paid. | P27: A tall gate with two scanners, one reading a card and one reading a ticket, and a counter above it clicking up. | Q27: Confidence when a question with two filters, like Delhi and January, gets one exact number. | R27: COUNTIFS counts and SUMIFS adds the rows where all of your conditions are true together. | S27: एक साथ कई शर्तें पूरी होने पर गिनना या जोड़ना | T27: A1: Delhi A2: Delhi A3: Pune A4: Delhi A5: Pune B1: Jan B2: Feb B3: Jan B4: Jan B5: Feb C1: 100 C2: 150 C3: 200 C4: 300 C5: 50 E1: =COUNTIFS(A1:A5,"Delhi",B1:B5,"Jan") E2: =SUMIFS(C1:C5,A1:A5,"Delhi",B1:B5,"Jan") | U27: E1 shows 2 E2 shows 400 | V27: Rows 1 and 4 are both Delhi and Jan, so COUNTIFS gives 2. SUMIFS adds the sales of those two rows, 100 and 300, which gives 400. | W27: Yahan har condition sahi honi chahiye, tabhi row count ya add hoti hai. SUMIFS me pehle wo column likho jise add karna hai, phir conditions. | X27: Like a job filter on a website: you want jobs in Delhi and full time, and a job must match both to be shown. | Y27: =COUNTIFS(range1, criteria1, [range2, criteria2], ...) =SUMIFS(sum_range, range1, criteria1, [range2, criteria2], ...) | Z27: sum_range = numbers to add (SUMIFS only, written first) | range = cells to check | criteria = condition for that range | all ranges = must have the same size | AA27: A1: Delhi A2: Delhi A3: Pune B1: Jan B2: Feb B3: Jan E1: =COUNTIFS(A1:A3,"Delhi",B1:B3,"Jan") | AB27: A1: Delhi A2: Delhi A3: Pune A4: Delhi C1: 100 C2: 150 C3: 200 C4: 300 E1: =SUMIFS(C1:C4,A1:A4,"Delhi",C1:C4,">100") | AC27: C1: 100 C2: 150 C3: 200 C4: 300 C5: 50 E1: =COUNTIFS(C1:C5,">=100",C1:C5,"<=200") | AD27: =COUNTIFS(A1:A5,"Pune") - works with just one condition too =SUMIFS(C1:C5,A1:A5,E1,B1:B5,E2) - conditions taken from cells E1 and E2 =COUNTIFS(C1:C5,">=100",C1:C5,"<=200") - same range used twice to make a between check | AE27: Wildcards, date conditions, cell references, PivotTable | AF27: COUNTIF, SUMIF, AVERAGEIFS, SUMPRODUCT | AG27: SUMPRODUCT, PivotTable, FILTER with SUM (Microsoft 365) | AH27: COUNTIF, COUNTIFS, SUMIF, SUMIFS, AVERAGEIF, AVERAGEIFS, MAXIFS | AI27: Sales for one city in one month | Counting students who scored between two limits | Adding expenses by category and date | AJ27: A: I need sales of Delhi but only for January, can SUMIF do that? | B: Use SUMIFS, it takes more than one condition and all of them must be true. | AK27: ✗ COUNTIFS counts a row if any one condition is true → ✓ COUNTIFS counts a row only when all the conditions are true at the same time (it is AND, not OR) | AL27: SUMIFS vs SUMIF: SUMIFS writes the sum range first and allows many conditions, while SUMIF writes the sum range last and allows one. | AM27: Do not use ranges of different sizes in one SUMIFS formula, because Excel will show a #VALUE! error. | AN27: C1: 100 C2: 150 C3: 200 A1: Delhi A2: Delhi A3: Pune E1: =SUMIFS(A1:A3,"Delhi",C1:C3) | AO27: C1: 100 C2: 150 C3: 200 A1: Delhi A2: Delhi A3: Pune E1: =SUMIFS(C1:C3,A1:A3,"Delhi") | AP27: SUMIFS starts with the sum: first what to add, then every where and what. | AQ27: A finance team uses SUMIFS to get total spend for one department in one quarter from a large expense list. | AR27: Interview question: how do you total sales for one region and one month, and how does SUMIFS differ from SUMIF? | AS27: Like searching a shopping site for shoes that are black and under 2000 rupees. | AT27: With the table in the card, what does =SUMIFS(C1:C5,A1:A5,"Pune",B1:B5,"Feb") show? | AU27: A) 250 B) 200 C) 50 D) 0 | AV27: C | AW27: Only row 5 is both Pune and Feb, and its sales are 50. 250 is all Pune sales and 200 is Pune in Jan. | AX27: =____(A1:A5,"Delhi",B1:B5,"Jan") counts rows that match both conditions → COUNTIFS | AY27: Using the same table, count the rows where the city is Delhi and the month is Feb. | AZ27: E1: =COUNTIFS(A1:A5,"Delhi",B1:B5,"Feb") | BA27: Make a small table of your own with category, month and amount, then total one category for one month. | BB27: A1: Delhi A2: Delhi A3: Pune A4: Delhi A5: Pune B1: Jan B2: Feb B3: Jan B4: Jan B5: Feb C1: 100 C2: 150 C3: 200 C4: 300 C5: 50 E1: =SUMIFS(C1:C5,B1:B5,"Jan",C1:C5,">100") What does E1 show? | BC27: 500 | BD27: =IF(K27="","",REPT("★",K27)&REPT("☆",5-K27)&" ("&K27&"/5)") | BE27: =IF(S27="","","Meaning: "&S27&" = ______ (Answer: "&F27&")") | BF27: New
A28: XL-026 | B28: 06 Lookup | C28: Intermediate | D28: 26 | E28: Claude knowledge | F28: VLOOKUP | G28: Which function searches the first column of a table for a value and brings back something from the same row? | H28: VLOOKUP = वी-लुकअप | I28: Lookup function | J28: Very high | K28: 5 | L28: The V stands for vertical, because it searches down the first column of a table. It has been in Excel for decades and is still widely used even though XLOOKUP is newer. | M28: Almost always type FALSE (or 0) as the last argument so that you get an exact match. | N28: Four arguments in order: what to find, where to look, which column number, FALSE. Do not forget the last FALSE. | O28: A librarian looks down the first column of the catalogue for your book number, then walks across the same row to read the shelf name. | P28: A finger sliding down a list of IDs and then turning right along the row to read the name. | Q28: Delight when a long list is matched to names in seconds instead of by eye. | R28: VLOOKUP finds a value in the first column of a table and returns a value from another column of the same row. | S28: टेबल के पहले कॉलम में खोजकर उसी पंक्ति की दूसरी जानकारी लाना | T28: A1: 101 B1: Asha A2: 102 B2: Ravi A3: 103 B3: Meena D1: 102 E1: =VLOOKUP(D1,A1:B3,2,FALSE) | U28: Ravi | V28: Excel looks for 102 in the first column of A1:B3 and finds it in row 2. It then returns the value from column 2 of the table in that row, which is Ravi. FALSE makes sure only an exact match is accepted. | W28: Pehle column me ID dhundo, phir usi row me aage jao aur jo column number diya hai wahan se value le aao. Last me FALSE likho warna galat match mil sakta hai. | X28: Like looking up a name in a phone book and then reading the number next to it on the same line. | Y28: =VLOOKUP(lookup_value, table_array, col_index_num, [range_lookup]) | Z28: lookup_value = what you search for | table_array = the table, whose first column is searched | col_index_num = which column of the table to return, counting from 1 | range_lookup = FALSE for exact match, TRUE for approximate | AA28: A1: 101 B1: Asha A2: 102 B2: Ravi A3: 103 B3: Meena D1: 102 E1: =VLOOKUP(D1,A1:B3,2,FALSE) | AB28: A1: 0 B1: F A2: 50 B2: C A3: 80 B3: A E1: =VLOOKUP(65,A1:B3,2,TRUE) | AC28: A1: 101 B1: Asha C1: 500 A2: 102 B2: Ravi C2: 700 A3: 103 B3: Meena C3: 650 E1: =VLOOKUP(103,A1:C3,3,FALSE) | AD28: =VLOOKUP(D1,A1:B3,2,0) - 0 works the same as FALSE =VLOOKUP(104,A1:B3,2,FALSE) - gives #N/A when the value is not found =VLOOKUP(D1,A1:B3,3,FALSE) - gives #REF! because the table has only 2 columns | AE28: IFERROR, absolute references ($A$1:$B$3), TRIM, data validation lists | AF28: HLOOKUP, XLOOKUP, INDEX and MATCH, IFERROR | AG28: XLOOKUP, INDEX and MATCH, FILTER (Microsoft 365) | AH28: VLOOKUP, HLOOKUP, XLOOKUP, LOOKUP, MATCH, INDEX | AI28: Finding a price from a product code | Matching student names to roll numbers | Bringing data from one sheet into another | AJ28: A: Why does my VLOOKUP give a wrong name for some IDs? | B: You left out the last argument, so Excel did an approximate match, add FALSE to get an exact match. | AK28: ✗ VLOOKUP can return a value from a column on the left of the search column → ✓ VLOOKUP always searches the first column of the table and can only return from that column or columns to its right | AL28: VLOOKUP vs HLOOKUP: VLOOKUP searches down the first column, while HLOOKUP searches across the first row. | AM28: Do not leave out the last argument, because the default is an approximate match that can give wrong answers on unsorted data. | AN28: A1: 101 B1: Asha A2: 102 B2: Ravi A3: 103 B3: Meena D1: 102 E1: =VLOOKUP(D1,A1:B3,3,FALSE) | AO28: A1: 101 B1: Asha A2: 102 B2: Ravi A3: 103 B3: Meena D1: 102 E1: =VLOOKUP(D1,A1:B3,2,FALSE) | AP28: V for vertical, then four steps: find what, in where, which column, FALSE for exact. | AQ28: An accounts clerk uses VLOOKUP to pull each customer's name and city into an invoice list from a master customer table. | AR28: Interview question: why do you add FALSE at the end of a VLOOKUP and what happens if you leave it out? | AS28: Like finding a student by roll number on a result list and reading the marks in the same row. | AT28: A1:B3 holds IDs 101, 102, 103 with names in column B. What does =VLOOKUP(104,A1:B3,2,FALSE) show? | AU28: A) Meena B) 0 C) #N/A D) #REF! | AV28: C | AW28: 104 is not in the first column, so an exact lookup gives #N/A. #REF! would appear only if the column number were larger than the table. | AX28: =VLOOKUP(D1,A1:B3,2,____) gives an exact match when the last argument is → FALSE | AY28: A1 to A3 hold Pen, Book, Bag and B1 to B3 hold 10, 50, 300. In D1 write Book. Find its price and multiply it by 2. | AZ28: A1: Pen B1: 10 A2: Book B2: 50 A3: Bag B3: 300 D1: Book E1: =VLOOKUP(D1,A1:B3,2,FALSE)*2 | BA28: Make a small price list of five items and write a VLOOKUP that shows the price of any item you type. | BB28: A1: Pen B1: 10 A2: Book B2: 50 A3: Bag B3: 300 D1: Book E1: =VLOOKUP(D1,A1:B3,2,FALSE)*2 What does E1 show? | BC28: 100 | BD28: =IF(K28="","",REPT("★",K28)&REPT("☆",5-K28)&" ("&K28&"/5)") | BE28: =IF(S28="","","Meaning: "&S28&" = ______ (Answer: "&F28&")") | BF28: New
A29: XL-027 | B29: 06 Lookup | C29: Advanced | D29: 27 | E29: Claude knowledge | F29: INDEX and MATCH | G29: Which pair of functions can look up a value in any column, even one to the left of the search column? | H29: INDEX = इंडेक्स, MATCH = मैच | I29: Lookup function pair | J29: High | K29: 4 | L29: VLOOKUP can only return a value to the right of the column it searches, so users paired two older functions to look in any direction. That pairing became the standard flexible lookup before XLOOKUP existed. | M29: Use 0 as the third argument of MATCH for an exact match, and keep the INDEX range and MATCH range the same size. | N29: Write MATCH inside INDEX: =INDEX(return_range, MATCH(value, search_range, 0)). Count the closing brackets. | O29: MATCH is a detective who says the suspect is in seat number 2; INDEX is the clerk who walks to seat number 2 and reads the name tag. | P29: A detective pointing at the second seat in a row while a clerk reads the card on that seat. | Q29: Feeling of power when you can finally look up to the left, where VLOOKUP could not go. | R29: MATCH finds the position of a value in a list, and INDEX uses that position to return a value from another list. | S29: MATCH से स्थान ढूँढकर INDEX से उस स्थान की वैल्यू निकालना | T29: A1: Asha A2: Ravi A3: Meena B1: 50 B2: 70 B3: 60 D1: =INDEX(B1:B3,MATCH("Ravi",A1:A3,0)) | U29: 70 | V29: MATCH("Ravi",A1:A3,0) finds Ravi in position 2 of the list. INDEX(B1:B3,2) then returns the second value of B1:B3, which is 70. The 0 in MATCH means exact match. | W29: Pehle MATCH batata hai naam kaun si position par hai. Phir INDEX us position par dusre column se value nikalta hai. Dono milkar VLOOKUP jaisa kaam karte hain. | X29: Like finding which locker number holds your bag (MATCH) and then opening that locker to take the bag out (INDEX). | Y29: =INDEX(array, row_num, [column_num]) =MATCH(lookup_value, lookup_array, [match_type]) =INDEX(return_range, MATCH(value, search_range, 0)) | Z29: INDEX array = where the answer lives | row_num = which row of that range | MATCH lookup_array = where to search | match_type 0 = exact match | AA29: A1: Asha A2: Ravi A3: Meena B1: 50 B2: 70 B3: 60 D1: =INDEX(B1:B3,MATCH("Ravi",A1:A3,0)) | AB29: A1: Asha B1: 101 A2: Ravi B2: 102 A3: Meena B3: 103 D1: =INDEX(A1:A3,MATCH(103,B1:B3,0)) | AC29: A1: (empty) B1: Jan C1: Feb A2: Delhi B2: 10 C2: 20 A3: Pune B3: 30 C3: 40 E1: =INDEX(B2:C3,MATCH("Pune",A2:A3,0),MATCH("Feb",B1:C1,0)) | AD29: =MATCH("Ravi",A1:A3,0) - shows 2, the position only =INDEX(B1:B3,2) - shows 70, the second item =IFERROR(INDEX(B1:B3,MATCH("Zoya",A1:A3,0)),"Not found") - friendly message when missing | AE29: IFERROR, absolute references, two-way lookups, data validation lists | AF29: VLOOKUP, XLOOKUP, MATCH, OFFSET | AG29: VLOOKUP, XLOOKUP (Excel 2021 and Microsoft 365) | AH29: INDEX, MATCH, VLOOKUP, HLOOKUP, XLOOKUP, LOOKUP, XMATCH | AI29: Looking up a value to the left of the key column | Two-way lookups by row name and column name | Large sheets where inserting columns must not break formulas | AJ29: A: My ID is in column B but the name is in column A, VLOOKUP cannot go left. | B: Use INDEX on the name column and MATCH on the ID column, that works in either direction. | AK29: ✗ INDEX and MATCH are only a harder way to write VLOOKUP → ✓ They can look in any direction and keep working when columns are inserted, which VLOOKUP's fixed column number cannot | AL29: INDEX vs MATCH: INDEX gives the value at a position, while MATCH gives the position of a value. | AM29: Do not leave out the 0 in MATCH on unsorted data, because Excel may pick a wrong row instead of an exact match. | AN29: A1: Asha A2: Ravi A3: Meena B1: 50 B2: 70 B3: 60 D1: =INDEX(B1:B3,MATCH("Ravi",A1:A3)) | AO29: A1: Asha A2: Ravi A3: Meena B1: 50 B2: 70 B3: 60 D1: =INDEX(B1:B3,MATCH("Ravi",A1:A3,0)) | AP29: MATCH finds the spot, INDEX fetches the stuff at that spot. | AQ29: An analyst uses INDEX and MATCH to pull a product price by code even when the code column sits to the right of the price column. | AR29: Interview question: why do many people prefer INDEX and MATCH over VLOOKUP? | AS29: Like asking the bell number of a flat from the notice board, then pressing that bell. | AT29: A1:A3 holds Asha, Ravi, Meena and B1:B3 holds 50, 70, 60. What does =INDEX(B1:B3,MATCH("Meena",A1:A3,0)) show? | AU29: A) 3 B) 60 C) 70 D) Meena | AV29: B | AW29: MATCH gives position 3 and INDEX returns the third value of B1:B3, which is 60. The answer 3 would come from MATCH alone. | AX29: =INDEX(B1:B3,____("Ravi",A1:A3,0)) finds the position of Ravi → MATCH | AY29: A1 to A3 hold Pen, Book, Bag and B1 to B3 hold 10, 50, 300. Find the item name whose price is 50 using INDEX and MATCH. | AZ29: A1: Pen B1: 10 A2: Book B2: 50 A3: Bag B3: 300 D1: =INDEX(A1:A3,MATCH(50,B1:B3,0)) | BA29: Take a table with an ID column to the right of a name column and write a lookup that finds the name from an ID. | BB29: A1: Pen B1: 10 A2: Book B2: 50 A3: Bag B3: 300 D1: =INDEX(A1:A3,MATCH(50,B1:B3,0)) What does D1 show? | BC29: Book | BD29: =IF(K29="","",REPT("★",K29)&REPT("☆",5-K29)&" ("&K29&"/5)") | BE29: =IF(S29="","","Meaning: "&S29&" = ______ (Answer: "&F29&")") | BF29: New
A30: XL-028 | B30: 06 Lookup | C30: Advanced | D30: 28 | E30: Claude knowledge | F30: XLOOKUP | G30: Which newer lookup function can search in any direction and has a built-in message for when nothing is found? | H30: XLOOKUP = एक्स-लुकअप | I30: Lookup function | J30: High | K30: 5 | L30: XLOOKUP was introduced by Microsoft to replace VLOOKUP and HLOOKUP with one simpler function. It is available in Microsoft 365 and Excel 2021 and later, but not in Excel 2019 or older. | M30: Use the fourth argument to show a friendly message such as Not found instead of wrapping the formula in IFERROR. | N30: Give the search range and the return range as two separate ranges of the same size, with no column number. | O30: X marks the spot on a treasure map: you give the thing to find, the row of clues to search, and the row where the treasure is listed. | P30: A treasure map with a big X over one row, an arrow pointing sideways to the matching value. | Q30: Relief at not having to count column numbers any more. | R30: XLOOKUP searches one range for a value and returns the matching item from another range. | S30: एक रेंज में खोजकर दूसरी रेंज से मिलती-जुलती वैल्यू देना | T30: A1: Asha A2: Ravi A3: Meena B1: 50 B2: 70 B3: 60 D1: =XLOOKUP("Ravi",A1:A3,B1:B3) | U30: 70 | V30: XLOOKUP finds Ravi in A1:A3, which is the second item, and returns the second item of B1:B3, which is 70. By default it looks for an exact match, so you do not need to type FALSE. | W30: Pehla range me value dhundo, dusre range se answer lao. Column number ginna nahi padta aur exact match apne aap hota hai. | X30: Like finding a name on the left page of a register and reading the marks on the matching line of the right page. | Y30: =XLOOKUP(lookup_value, lookup_array, return_array, [if_not_found], [match_mode], [search_mode]) | Z30: lookup_value = what to find | lookup_array = where to search | return_array = where the answer comes from | if_not_found = message when no match | match_mode = 0 exact, -1 exact or next smaller, 1 exact or next larger, 2 wildcard | AA30: A1: Asha A2: Ravi A3: Meena B1: 50 B2: 70 B3: 60 D1: =XLOOKUP("Ravi",A1:A3,B1:B3) | AB30: A1: Asha A2: Ravi A3: Meena B1: 50 B2: 70 B3: 60 D1: =XLOOKUP("Zoya",A1:A3,B1:B3,"Not found") | AC30: A1: 0 A2: 50 A3: 80 B1: F B2: C B3: A D1: =XLOOKUP(65,A1:A3,B1:B3,,-1) | AD30: =XLOOKUP("ravi",A1:A3,B1:B3) - upper and lower case do not matter =XLOOKUP("R*",A1:A3,B1:B3,"None",2) - match mode 2 allows wildcards =XLOOKUP("Ravi",A1:A3,B1:B3,"None",0,-1) - search mode -1 searches from the last item to the first | AE30: IFERROR, wildcards, FILTER, UNIQUE | AF30: VLOOKUP, INDEX and MATCH, XMATCH, FILTER | AG30: VLOOKUP, INDEX and MATCH, LOOKUP | AH30: XLOOKUP, XMATCH, VLOOKUP, HLOOKUP, INDEX, MATCH, FILTER | AI30: Looking up prices or names in modern workbooks | Looking up to the left of the key column | Grading with approximate match | AJ30: A: Can I find a value to the left without using INDEX and MATCH? | B: Yes, XLOOKUP can, but your Excel must be Microsoft 365 or Excel 2021 or later. | AK30: ✗ XLOOKUP works in every Excel version like VLOOKUP → ✓ XLOOKUP needs Microsoft 365 or Excel 2021 or later and will show #NAME? in older versions | AL30: XLOOKUP vs VLOOKUP: XLOOKUP takes separate search and return ranges and does an exact match by default, while VLOOKUP needs a column number and defaults to approximate. | AM30: Do not share a file that uses XLOOKUP with people who have Excel 2019 or older, because they will see errors. | AN30: A1: Asha A2: Ravi A3: Meena B1: 50 B2: 70 B3: 60 D1: =XLOOKUP("Ravi",A1:B3,2) | AO30: A1: Asha A2: Ravi A3: Meena B1: 50 B2: 70 B3: 60 D1: =XLOOKUP("Ravi",A1:A3,B1:B3) | AP30: X marks it: find, search here, return from there. | AQ30: A team on Microsoft 365 uses XLOOKUP to pull each product's price and shows Not found for new codes that are not yet in the list. | AR30: Interview question: how is XLOOKUP better than VLOOKUP, and which versions of Excel support it? | AS30: Like finding a contact in your phone and reading the number saved next to that name. | AT30: A1:A3 holds Asha, Ravi, Meena and B1:B3 holds 50, 70, 60. What does =XLOOKUP("ravi",A1:A3,B1:B3) show? | AU30: A) 70 B) #N/A C) 50 D) 60 | AV30: A | AW30: XLOOKUP ignores upper and lower case, so ravi matches Ravi in position 2 and returns 70. | AX30: =____("Ravi",A1:A3,B1:B3) is the lookup function that needs Microsoft 365 or Excel 2021 → XLOOKUP | AY30: A1 to A3 hold Pen, Book, Bag and B1 to B3 hold 10, 50, 300. Look up Cap and show the words Not found if it is missing. | AZ30: A1: Pen B1: 10 A2: Book B2: 50 A3: Bag B3: 300 D1: =XLOOKUP("Cap",A1:A3,B1:B3,"Not found") | BA30: Rewrite one of your older VLOOKUP formulas as an XLOOKUP and note what became simpler. | BB30: A1: Pen B1: 10 A2: Book B2: 50 A3: Bag B3: 300 D1: =XLOOKUP("Cap",A1:A3,B1:B3,"Not found") What does D1 show? | BC30: Not found | BD30: =IF(K30="","",REPT("★",K30)&REPT("☆",5-K30)&" ("&K30&"/5)") | BE30: =IF(S30="","","Meaning: "&S30&" = ______ (Answer: "&F30&")") | BF30: New
A31: XL-029 | B31: 07 Text | C31: Beginner | D31: 29 | E31: Claude knowledge | F31: LEFT, RIGHT and MID | G31: Which functions pull out the first few, last few or middle few characters from a piece of text? | H31: LEFT = लेफ़्ट, RIGHT = राइट, MID = मिड | I31: Text function | J31: High | K31: 4 | L31: Text in sheets often has useful parts joined together, like a code with a year inside, so Excel gives three functions to cut a piece from the left end, the right end or the middle. | M31: Count the start position for MID carefully, because spaces and dashes count as characters too. | N31: LEFT and RIGHT take two arguments, MID takes three. Always give the text first. | O31: A baker cuts a long loaf: LEFT takes the left end, RIGHT takes the right end and MID takes a slice from the middle. | P31: A long loaf of bread on a board with three coloured slices cut from the left, the middle and the right. | Q31: Satisfaction when a messy code splits into neat parts without any retyping. | R31: LEFT, RIGHT and MID return a chosen number of characters from the start, the end or the middle of text. | S31: टेक्स्ट के शुरू, अंत या बीच से कुछ अक्षर निकालना | T31: A1: EDU-2025-07 B1: =LEFT(A1,3) B2: =RIGHT(A1,2) B3: =MID(A1,5,4) | U31: B1 shows EDU B2 shows 07 B3 shows 2025 | V31: LEFT takes the first 3 characters, RIGHT takes the last 2 characters, and MID starts at character 5 and takes 4 characters. The dash counts as character 4, so the year starts at 5. | W31: LEFT shuru se, RIGHT aakhir se aur MID beech se akshar nikalta hai. MID me batana padta hai kahan se shuru karna hai aur kitne akshar lene hain. | X31: Like cutting a train ticket number: the first digits show the train, the last digits show the seat. | Y31: =LEFT(text, [num_chars]) =RIGHT(text, [num_chars]) =MID(text, start_num, num_chars) | Z31: text = the cell or text to cut | num_chars = how many characters to take | start_num = position of the first character to take (MID only, counting from 1) | AA31: A1: EDU-2025-07 B1: =MID(A1,5,4) | AB31: A1: Asha Rao B1: =LEFT(A1,FIND(" ",A1)-1) | AC31: A1: 98765 B1: =LEFT(A1,2) | AD31: =RIGHT(A1) - last 1 character, because num_chars defaults to 1 =MID(A1,6,3) - with Asha Rao, gives Rao =VALUE(LEFT(A1,2)) - turns the cut text into a real number | AE31: FIND, LEN, VALUE, TRIM | AF31: FIND, SEARCH, LEN, TEXTBEFORE | AG31: Data tab > Text to Columns, Flash Fill (Ctrl+E), TEXTBEFORE and TEXTAFTER (Microsoft 365) | AH31: LEFT, RIGHT, MID, LEN, FIND, SEARCH, TRIM | AI31: Splitting codes like invoice numbers | Taking first names from full names | Getting the year or area code from an ID | AJ31: A: How do I get just the year out of a code like EDU-2025-07? | B: Use MID, start at character 5 and take 4 characters, that gives 2025. | AK31: ✗ The result of LEFT on a number is still a number → ✓ LEFT, RIGHT and MID always return text, so use VALUE if you need to calculate with the result | AL31: LEFT vs RIGHT: LEFT cuts from the start of the text, while RIGHT cuts from the end of the text. | AM31: Do not count start positions by eye in long text; use FIND to locate the dash or space instead. | AN31: A1: EDU-2025-07 B1: =LEFT(3,A1) | AO31: A1: EDU-2025-07 B1: =LEFT(A1,3) | AP31: Text first, number second: LEFT(text, how many). | AQ31: A data clerk uses MID to pull the year out of thousands of invoice numbers so they can be grouped by year. | AR31: Interview question: how do you take the first name from a full name stored in one cell? | AS31: Like reading only the first three letters of a bus number to know which route it belongs to. | AT31: A1 holds INV-4501. What does =MID(A1,5,2) show? | AU31: A) 4501 B) 45 C) -4 D) 50 | AV31: B | AW31: The characters are I, N, V, dash, then 4 is at position 5, so taking 2 characters gives 45. The answer 4501 would need 4 characters. | AX31: =____(A1,3) gives the first 3 characters of the text in A1 → LEFT | AY31: In A1 write ORDER-9087. In B1 show the first 5 letters, a slash, and the last 2 characters joined together. | AZ31: A1: ORDER-9087 B1: =LEFT(A1,5)&"/"&RIGHT(A1,2) | BA31: Write your own phone number or ID in a cell and use these functions to split it into two or three parts. | BB31: A1: ORDER-9087 B1: =LEFT(A1,5)&"/"&RIGHT(A1,2) What does B1 show? | BC31: ORDER/87 | BD31: =IF(K31="","",REPT("★",K31)&REPT("☆",5-K31)&" ("&K31&"/5)") | BE31: =IF(S31="","","Meaning: "&S31&" = ______ (Answer: "&F31&")") | BF31: New
A32: XL-030 | B32: 07 Text | C32: Beginner | D32: 30 | E32: Claude knowledge | F32: LEN, TRIM and CLEAN | G32: Which functions count characters, remove extra spaces and remove hidden line breaks from text? | H32: LEN = लेन, TRIM = ट्रिम, CLEAN = क्लीन | I32: Text function | J32: High | K32: 4 | L32: Data copied from websites or other software often has extra spaces and hidden characters, so Excel gives LEN to measure text, TRIM to remove extra spaces and CLEAN to remove non-printing characters. | M32: Use =TRIM(CLEAN(A1)) before lookups when data was copied from outside, because hidden spaces cause #N/A. | N32: Each takes one cell or text as its only argument. Do not type spaces between the function name and the bracket. | O32: A tailor measures the cloth with LEN, trims the loose threads with TRIM, and cleans away the dust with CLEAN. | P32: A tailor with a measuring tape, small scissors and a brush working on one piece of cloth. | Q32: Relief when a lookup that never matched suddenly works after the text is cleaned. | R32: LEN counts the characters in text, TRIM removes extra spaces, and CLEAN removes hidden non-printing characters. | S32: अक्षर गिनना, फालतू स्पेस हटाना और छिपे हुए अक्षर साफ़ करना | T32: A1: (two spaces)Asha(three spaces)Rao(two spaces) B1: =LEN(A1) B2: =TRIM(A1) B3: =LEN(TRIM(A1)) | U32: B1 shows 14 B2 shows Asha Rao B3 shows 8 | V32: The text has 2 leading spaces, Asha (4), 3 spaces, Rao (3) and 2 trailing spaces, so LEN gives 14. TRIM removes the spaces at both ends and keeps only one space between words, leaving Asha Rao, which has 8 characters. | W32: LEN akshar ginta hai, spaces ko bhi. TRIM shuru aur aakhir ke spaces hata deta hai aur beech me sirf ek space chhodta hai. CLEAN chhipe hue line break jaise akshar hata deta hai. | X32: Like tidying a shelf: LEN counts the books, TRIM removes the gaps, and CLEAN wipes the dust. | Y32: =LEN(text) =TRIM(text) =CLEAN(text) | Z32: text = a cell or text value | LEN = returns a number | TRIM = returns text with single spaces between words | CLEAN = returns text without non-printing characters | AA32: A1: 9876543210 B1: =LEN(A1)=10 | AB32: A1: (two spaces)Ravi(three spaces)Kumar(two spaces) B1: =TRIM(A1) | AC32: A1: =CHAR(10) joined between Hi and there, so the cell holds a line break B1: =CLEAN(A1) | AD32: =LEN(A1)-LEN(TRIM(A1)) - number of extra spaces removed by TRIM =TRIM(SUBSTITUTE(A1,CHAR(160)," ")) - TRIM alone does not remove non-breaking spaces from the web =TRIM(CLEAN(A1)) - fixes both spaces and hidden characters | AE32: VLOOKUP, SUBSTITUTE, data validation, LEFT and RIGHT | AF32: SUBSTITUTE, PROPER, UPPER, LOWER | AG32: Find and Replace (Ctrl+H), Flash Fill (Ctrl+E), Power Query Trim and Clean | AH32: LEN, TRIM, CLEAN, SUBSTITUTE, UPPER, LOWER, PROPER | AI32: Cleaning names before a lookup | Checking that phone numbers have 10 digits | Fixing text copied from websites | AJ32: A: My VLOOKUP says #N/A even though the name is clearly in the list. | B: Check for extra spaces with LEN, then use TRIM on the name and try again. | AK32: ✗ TRIM removes every space from the text → ✓ TRIM removes spaces at the start and end and reduces spaces between words to one, but it does not remove them all | AL32: TRIM vs CLEAN: TRIM removes extra spaces, while CLEAN removes non-printing characters like line breaks. | AM32: Do not type over cleaned data in place without a backup, copy the TRIM results and paste them as values in a new column. | AN32: A1: Hi(line break)there B1: =TRIM(A1) | AO32: A1: Hi(line break)there B1: =CLEAN(A1) | AP32: LEN = length, TRIM = trim spaces, CLEAN = clean hidden marks. | AQ32: A data clerk runs TRIM and CLEAN on a customer list so that lookups and duplicate checks work correctly. | AR32: Interview question: a lookup fails although both names look the same, how do you find and fix the cause? | AS32: Like removing extra spaces and stray marks from a message before sending it. | AT32: A1 holds two spaces, then Hi, then two spaces. What does =LEN(TRIM(A1)) show? | AU32: A) 6 B) 4 C) 2 D) 0 | AV32: C | AW32: TRIM removes all the spaces at both ends, leaving Hi, which has 2 characters. 6 would be LEN without TRIM. | AX32: =____(A1) removes extra spaces from the text in A1 → TRIM | AY32: In A1 write Meena with two spaces on each side. In B1 show how many characters Meena has after the extra spaces are removed. | AZ32: A1: (two spaces)Meena(two spaces) B1: =LEN(TRIM(A1)) | BA32: Type your name in a cell with spaces on both sides and use LEN and TRIM to prove the spaces are there and then gone. | BB32: A1: (one space)Ravi(two spaces)Kumar(one space) B1: =LEN(A1)-LEN(TRIM(A1)) What does B1 show? | BC32: 3 | BD32: =IF(K32="","",REPT("★",K32)&REPT("☆",5-K32)&" ("&K32&"/5)") | BE32: =IF(S32="","","Meaning: "&S32&" = ______ (Answer: "&F32&")") | BF32: New
A33: XL-031 | B33: 07 Text | C33: Intermediate | D33: 31 | E33: Claude knowledge | F33: TEXTJOIN, CONCAT and the & operator | G33: How do you glue the text from two or more cells into one cell? | H33: TEXTJOIN = टेक्स्ट-जॉइन, CONCAT = कॉन्कैट, & = एम्परसैंड (and) | I33: Text function and operator | J33: Very high | K33: 4 | L33: The & operator has been in Excel for decades. CONCAT and TEXTJOIN were added later (Excel 2019 and Microsoft 365) to join whole ranges and to use a separator. | M33: Use TEXTJOIN when you have a separator and a range, because it can skip empty cells for you. | N33: Put text inside double quotes, like " ". A missing quote gives an error. | O33: Think of a train. The & is a small hook joining two coaches, CONCAT joins a whole row of coaches, and TEXTJOIN adds a seat label between each coach. | P33: Three train coaches with names written on them, each linked by a hook, and a small comma sign between each pair. | Q33: Relief when ten messy columns become one clean name column in a second. | R33: These tools join the text of several cells into one piece of text. | S33: कई सेल का टेक्स्ट जोड़कर एक सेल में लिखना | T33: A1: Asha B1: Rao C1: =A1&" "&B1 D1: =TEXTJOIN(", ",TRUE,A1:B1) E1: =CONCAT(A1,"-",B1) | U33: C1 shows Asha Rao D1 shows Asha, Rao E1 shows Asha-Rao | V33: The & operator joins two pieces of text, and you add your own space inside quotes. CONCAT joins everything you give it, including a full range, but has no separator. TEXTJOIN takes a separator first, then TRUE or FALSE for skipping empty cells, then the cells. | W33: Agar do cell ka text ek cell me chahiye to & use karo. Bahut cells ko comma ya dash ke saath jodna ho to TEXTJOIN sabse aasaan hai. CONCAT bas cells ko bina kisi gap ke chipka deta hai. | X33: Like stringing beads on a thread: & ties two beads, CONCAT ties a whole row, and TEXTJOIN puts a small spacer bead between each one. | Y33: =A1&B1 | =CONCAT(text1, [text2], ...) | =TEXTJOIN(delimiter, ignore_empty, text1, [text2], ...) | Z33: delimiter = text placed between items, in quotes | ignore_empty = TRUE skips blank cells, FALSE keeps them | text1 = a cell or a range to join | AA33: A1: Order B1: 5 C1: =A1&" "&B1 | AB33: A1: Red A2: (empty cell) A3: Blue B1: =TEXTJOIN(", ",TRUE,A1:A3) | AC33: A1: 4 A2: 5 A3: 6 B1: =CONCAT(A1:A3) | AD33: A1: Red A2: (empty cell) A3: Blue B1: =TEXTJOIN("-",FALSE,A1:A3) shows Red--Blue because FALSE keeps the empty cell B2: =TEXTJOIN("-",TRUE,A1:A3) shows Red-Blue | AE33: TRIM, UPPER, LEFT, TEXT | AF33: CONCATENATE, TRIM, SUBSTITUTE | AG33: The older CONCATENATE function, Flash Fill (Ctrl+E), Power Query merge columns | AH33: &, CONCAT, CONCATENATE, TEXTJOIN, TEXTSPLIT | AI33: Joining first name and last name | Making a comma-separated list of items | Building an ID or a message from several columns | AJ33: A: My first names and last names are in two columns, but I need one full name column. | B: Type =A2&" "&B2 in the first row and drag it down, and you get full names with a space. | AK33: ✗ I can join two text cells with the plus sign, like =A1+B1 → ✓ The + sign is for numbers and gives #VALUE! with text, so use & instead | AL33: CONCAT vs TEXTJOIN: CONCAT only glues items together, while TEXTJOIN also puts a separator between them and can skip empty cells. | AM33: Do not use CONCAT when you need a separator, because you would have to type the separator again and again. | AN33: A1: Asha B1: Rao C1: =A1+B1 | AO33: A1: Asha B1: Rao C1: =A1&" "&B1 | AP33: & means "and": Asha and Rao become Asha Rao. | AQ33: A sales sheet often joins city and state columns into one address line before it is printed on a label. | AR33: Interview: What is the difference between CONCATENATE, CONCAT and TEXTJOIN? | AS33: It is like writing your full name on a form by joining your first name and surname with a space. | AT33: A1 has Hi, A2 is an empty cell, A3 has Yes. What does =TEXTJOIN("-",TRUE,A1:A3) show? | AU33: A) Hi-Yes B) Hi-blank-Yes C) Yes-Hi D) #VALUE! | AV33: A | AW33: TRUE tells TEXTJOIN to skip the empty cell, so only one dash is placed between Hi and Yes. FALSE would give Hi--Yes. | AX33: =____(", ",TRUE,A1:A3) joins the range with commas and skips empty cells → TEXTJOIN | AY33: A1 has a first name and B1 has a last name. Write a formula in C1 that shows both names with one space between them. | AZ33: A1: Asha B1: Rao C1: =A1&" "&B1 | BA33: Write a formula that joins your own city and country with a comma and a space. | BB33: A1: Sun A2: Mon A3: Tue B1: =TEXTJOIN("/",TRUE,A1:A3) What does B1 show? | BC33: Sun/Mon/Tue | BD33: =IF(K33="","",REPT("★",K33)&REPT("☆",5-K33)&" ("&K33&"/5)") | BE33: =IF(S33="","","Meaning: "&S33&" = ______ (Answer: "&F33&")") | BF33: New
A34: XL-032 | B34: 07 Text | C34: Intermediate | D34: 32 | E34: Claude knowledge | F34: TEXT function | G34: Which function lets you decide how a number or date looks, but gives it back as text? | H34: TEXT = टेक्स्ट | I34: Text function | J34: High | K34: 4 | L34: Excel stores numbers and dates as plain numbers inside. TEXT was made so you can show them in a chosen format when you join them with other words. | M34: Use TEXT when you put a date or percentage inside a sentence, or the sentence will show the raw serial number. | N34: The format goes in double quotes, like "dd-mm-yyyy". Month is mm and minutes are also mm, so check the result. | O34: A tailor takes a plain cloth number and stitches it into a chosen style. After stitching, it is a finished shirt that you can no longer measure like cloth. | P34: A tailor shop where a plain roll of cloth marked 0.256 comes out as a shirt labelled 26 percent. | Q34: Satisfaction when a messy number turns into a neat sentence that reads well. | R34: TEXT changes a number or date into text shown in the format you choose. | S34: नंबर या तारीख को चुने हुए फ़ॉर्मेट में टेक्स्ट बनाना | T34: A1: 3.14159 B1: =TEXT(A1,"0.00") B2: =TEXT(0.256,"0%") B3: =TEXT(DATE(2024,8,15),"dd-mm-yyyy") | U34: B1 shows 3.14 B2 shows 26% B3 shows 15-08-2024 | V34: TEXT takes a value and a format code in quotes. It returns text that looks the way the code says, so 0.00 means two decimals and 0% means percentage. The result is text, so you cannot add it up like a number. | W34: TEXT ka kaam hai number ya date ko aapke pasand ke style me dikhana. Jaise 0.256 ko 26% likhna. Lekin result text ban jata hai, isliye uspar sum nahi chalta. | X34: Like putting a price in a printed price tag: the tag looks nice, but you cannot do maths on the paper any more. | Y34: =TEXT(value, format_text) | Z34: value = the number or date or a cell | format_text = the format code inside double quotes | AA34: A1: 1234567 B1: =TEXT(A1,"#,##0") | AB34: B1: =TEXT(DATE(2024,8,15),"dddd") | AC34: A1: Score B1: 0.256 C1: ="Pass rate: "&TEXT(B1,"0%") | AD34: =TEXT(7,"000") shows 007 so leading zeros stay =TEXT(DATE(2024,8,15),"mmm yyyy") shows Aug 2024 =TEXT(1234.5,"0.0") shows 1234.5 | AE34: DATE, TODAY, & operator, TEXTJOIN | AF34: Format Cells (Ctrl+1), VALUE, DATE | AG34: Format Cells (Ctrl+1) when you only need to change how a cell looks | AH34: TEXT, VALUE, FIXED, DOLLAR, NUMBERVALUE | AI34: Showing a date inside a sentence | Adding leading zeros to codes | Showing percentages or money inside a message | AJ34: A: My sentence shows 45519 instead of the date. | B: Wrap the date in TEXT, like TEXT(A1,"dd-mm-yyyy"), and it will look like a date. | AK34: ✗ After TEXT(A1,"0.00") the result is still a number I can add → ✓ The result is text, so use VALUE or keep the original cell for calculations | AL34: TEXT function vs Format Cells: Format Cells only changes how a cell looks and keeps the number, while TEXT makes a new text value. | AM34: Do not use TEXT on a column that you plan to sum or sort as numbers later. | AN34: B1: ="Date: "&DATE(2024,8,15) | AO34: B1: ="Date: "&TEXT(DATE(2024,8,15),"dd-mm-yyyy") | AP34: TEXT = Tailor the look, but it becomes TEXT. | AQ34: A monthly report header uses TEXT to show the month name, such as "Report for Aug 2024", from a date cell. | AR34: Interview: How do you show a date as the day name, like Monday, using a formula? | AS34: It is like writing the amount on a cheque in a fixed style so everyone reads it the same way. | AT34: B1: =TEXT(0.256,"0%") What do you get, and what type of value is it? | AU34: A) The number 0.256 B) The number 26 C) The text 26% D) The text 0.256% | AV34: C | AW34: The format 0% multiplies by 100 and adds the sign, and TEXT always returns text, so it is the text 26%. | AX34: =____(7,"000") shows 007 → TEXT | AY34: A1 has the number 1234567. Show it with commas in B1 using TEXT. | AZ34: A1: 1234567 B1: =TEXT(A1,"#,##0") | BA34: Write a formula that shows today's date inside a sentence like "Today is 06-10-2026". | BB34: B1: =TEXT(DATE(2024,8,15),"dddd") Which day name does B1 show? | BC34: Thursday | BD34: =IF(K34="","",REPT("★",K34)&REPT("☆",5-K34)&" ("&K34&"/5)") | BE34: =IF(S34="","","Meaning: "&S34&" = ______ (Answer: "&F34&")") | BF34: New
A35: XL-033 | B35: 07 Text | C35: Intermediate | D35: 33 | E35: Claude knowledge | F35: Text to Columns | G35: Which Data tab tool cuts one column of text into many columns at a comma or space? | H35: Text to Columns = टेक्स्ट टू कॉलम्स | I35: Data tool (Data tab) | J35: High | K35: 4 | L35: Data from other systems often arrives in one long column with commas or spaces. This wizard was built to split such data into separate columns quickly. | M35: Always make sure the cells to the right are empty, because Text to Columns writes over them. | N35: Windows shortcut Alt, A, E opens the wizard. Press the keys one after the other, not together. | O35: Imagine a long loaf of bread with a comma written on it at every cut mark. You run a knife along the commas and get neat slices in separate boxes. | P35: A long loaf with commas drawn on it being cut into slices that fall into a row of boxes. | Q35: Relief when one jammed column opens into clean columns without any typing. | R35: Text to Columns splits the text of one column into several columns using a separator or a fixed width. | S35: एक कॉलम के टेक्स्ट को कई कॉलम में बाँटना | T35: A1: Asha,Rao,Delhi Steps: select A1 > Data tab > Text to Columns > Delimited > Next > tick Comma > Finish | U35: A1 shows Asha, B1 shows Rao, C1 shows Delhi | V35: The wizard has three steps. Step 1 chooses Delimited (a separator) or Fixed width. Step 2 chooses the separator, and step 3 lets you pick the format of each new column and where to put it. The original column is replaced unless you change the destination. | W35: Jab ek hi cell me comma ya space se alag kiya hua data ho, to Text to Columns usse alag alag cell me tod deta hai. Dhyan rakho ki dahine taraf ke cell me data hoga to wo mit jayega. | X35: Like sorting a mixed bag of letters into pigeonholes by the stamp on each one. | Y35: Data tab > Data Tools group > Text to Columns (Alt, A, E) | Z35: Delimited = split at a separator like comma | Fixed width = split at set positions | Destination = where the new columns start | Column data format = General, Text or Date for each part | AA35: A1: Asha,Rao,Delhi Select A1 > Data tab > Text to Columns > Delimited > Comma > Finish Result: three cells in A1:C1 | AB35: A1: 110045 Select A1 > Text to Columns > Fixed width > click a break line after the 3rd digit > Next > click the second column and choose Text > Finish Result: A1 shows 110 and B1 shows 045 (with General, B1 would show 45) | AC35: A1: 00123,Delhi (imported text) Select A1 > Text to Columns > Delimited > Comma > Next > click the first column and choose Text > Finish Result: A1 shows 00123 and B1 shows Delhi (with General, A1 would show 123) | AD35: Step 2 can use Space, Tab, Semicolon or Other (type your own sign, like -) Step 2 has the option Treat consecutive delimiters as one Step 3 Destination box lets you choose C1 so that the original column stays safe | AE35: TRIM, Flash Fill, VALUE, Paste Special | AF35: Flash Fill (Ctrl+E), TEXTSPLIT, Power Query | AG35: Flash Fill (Ctrl+E), TEXTSPLIT (Microsoft 365), Power Query split column | AH35: Text to Columns, Flash Fill, LEFT, MID, RIGHT, TEXTSPLIT | AI35: Splitting CSV text pasted into one column | Separating full names into first and last name | Fixing numbers that are stored as text | AJ35: A: I pasted a file and all my data landed in column A with commas. | B: Select column A and use Data, Text to Columns, choose Delimited and Comma. Then each part gets its own column. | AK35: ✗ Text to Columns keeps my original column and puts the parts beside it → ✓ It replaces the original cells and anything to its right, so set a Destination first if you want to keep the original | AL35: Text to Columns vs Flash Fill: Text to Columns splits using a fixed rule you choose, while Flash Fill guesses a pattern from an example you type. | AM35: Do not run it on a column that has important data in the cells to its right. | AN35: Select column A, which has full names, and run Text to Columns without checking the cells in column B that already hold ages | AO35: Insert two empty columns after column A first, or set Destination to an empty area like D1, then run Text to Columns | AP35: Text to Columns = cut the loaf at the commas. | AQ35: A teacher pastes a list of names and marks from a text file, then splits it into a name column and a marks column. | AR35: Interview: How would you split "Asha Rao" into first name and last name for 5000 rows? | AS35: It is like cutting an address written on one line into house, street and city boxes on a form. | AT35: A1 holds Pune;Agra;Delhi. Which separator should you choose in the wizard to place each city in its own column? | AU35: A) Comma B) Space C) Semicolon D) Tab | AV35: C | AW35: The cities are separated by semicolon signs, so the Semicolon box must be ticked. Choosing Comma would leave the whole text in one cell. | AX35: Data tab > ____ to Columns splits one column into many → Text | AY35: A1 has Asha,Rao,Delhi. Split it into three columns using the wizard. | AZ35: Select A1 > Data tab > Text to Columns > Delimited > Next > tick Comma > Finish | BA35: Type three words with commas in one cell and split them into three cells yourself. | BB35: A1: 10;20;30 B1 and C1 are empty You use Text to Columns on A1, Delimited, Semicolon. What do A1, B1 and C1 show? | BC35: A1 shows 10, B1 shows 20, C1 shows 30 | BD35: =IF(K35="","",REPT("★",K35)&REPT("☆",5-K35)&" ("&K35&"/5)") | BE35: =IF(S35="","","Meaning: "&S35&" = ______ (Answer: "&F35&")") | BF35: New
A36: XL-034 | B36: 08 Dates | C36: Beginner | D36: 34 | E36: Claude knowledge | F36: TODAY, NOW and DATE | G36: Which functions give you the current date, the current date and time, or a date you build from year, month and day? | H36: TODAY = टुडे, NOW = नाउ, DATE = डेट | I36: Date and time functions | J36: Very high | K36: 5 | L36: Excel stores a date as a serial number, counting days from 1 January 1900 in the default system. These functions give you that number in a safe way, and the cell format shows it as a date. | M36: To type a date that never changes, use Ctrl+; for the date and Ctrl+Shift+; for the time. | N36: TODAY and NOW need empty brackets, like =TODAY(). Without brackets you get #NAME?. | O36: A calendar on the wall flips by itself every midnight and shows today. DATE is you writing a day on the calendar yourself with year, month and day. | P36: A wall calendar whose page flips every midnight, with a clock stuck to the corner showing the time. | Q36: A calm feeling that the sheet is always up to date without extra work. | R36: TODAY gives today's date, NOW gives today's date with the time, and DATE makes a date from year, month and day. | S36: आज की तारीख, अभी की तारीख और समय, और साल-महीना-दिन से तारीख बनाना | T36: A1: =DATE(2024,3,5) A2: =A1+30 A3: =TODAY() A4: =NOW() | U36: A1 shows 05-03-2024 (format dd-mm-yyyy) A2 shows 04-04-2024 A3 shows the date of the day you open the file A4 shows that date and the current time | V36: DATE takes year, month and day and returns a real date that Excel can calculate with. Adding a number to a date moves it forward by that many days. TODAY and NOW update every time the sheet recalculates or is opened. | W36: TODAY() aaj ki date deta hai aur NOW() date ke saath abhi ka time bhi. DATE(saal, mahina, din) se aap apni date bana sakte ho. Date me number jodne se din aage badhte hain. | X36: Like a wall clock that keeps updating on its own, while DATE is a note you write once. | Y36: =TODAY() | =NOW() | =DATE(year, month, day) | Z36: TODAY() = no arguments, today's date | NOW() = no arguments, date and time | year = four-digit year | month = 1 to 12 | day = 1 to 31 | AA36: A1: =DATE(2024,8,15) | AB36: A1: =DATE(2025,12,31) A2: =TODAY() A3: =A1-A2 | AC36: A1: =NOW() Format the cell with Ctrl+1 > Custom > hh:mm to see only the time | AD36: =DATE(2024,14,1) month 14 rolls over and shows 01-02-2025 =DATE(2024,1,31)+1 shows 01-02-2024 =TODAY()+7 shows the date one week from today | AE36: TEXT, EDATE, NETWORKDAYS, IF | AF36: EDATE, EOMONTH, DATEDIF, WEEKDAY | AG36: Ctrl+; for a fixed date, Ctrl+Shift+; for a fixed time | AH36: TODAY, NOW, DATE, YEAR, MONTH, DAY, WEEKDAY | AI36: Due dates and days left | Age and service calculations | Time stamps in reports | AJ36: A: I want a cell that always shows how many days are left for the exam. | B: Put the exam date in A1 and write =A1-TODAY() in B1. It changes every day by itself. | AK36: ✗ TODAY() stays fixed at the day I typed it → ✓ TODAY() changes every day when the file is opened or recalculated, so use Ctrl+; if you want a fixed date | AL36: TODAY vs NOW: TODAY gives only the date, while NOW gives the date and the current time. | AM36: Do not use TODAY() for a record that must keep its original date, such as an invoice date. | AN36: A1: =TODAY | AO36: A1: =TODAY() | AP36: TODAY = date, NOW = date plus clock, DATE = you decide. | AQ36: A fee tracker uses =TODAY() to show how many days late each student is. | AR36: Interview: How can you enter a date that does not change when the file is reopened? | AS36: It is like a phone lock screen that always shows the current date and time. | AT36: A1: =DATE(2024,12,31)+1 The cell is formatted as dd-mm-yyyy. What does A1 show? | AU36: A) 31-12-2025 B) 01-01-2025 C) 32-12-2024 D) #VALUE! | AV36: B | AW36: Adding 1 to a date moves it to the next day, and the day after 31 December 2024 is 1 January 2025. | AX36: ____() shows the current date and updates every day → TODAY | AY36: Make a date 15 August 2024 using a formula, then show the date 10 days later in the next cell. | AZ36: A1: =DATE(2024,8,15) A2: =A1+10 | BA36: Write a formula that shows how many days are left until your next birthday date. | BB36: A1: =DATE(2024,1,31)+1 A1 is formatted as dd-mm-yyyy. What does A1 show? | BC36: 01-02-2024 | BD36: =IF(K36="","",REPT("★",K36)&REPT("☆",5-K36)&" ("&K36&"/5)") | BE36: =IF(S36="","","Meaning: "&S36&" = ______ (Answer: "&F36&")") | BF36: New
A37: XL-035 | B37: 08 Dates | C37: Intermediate | D37: 35 | E37: Claude knowledge | F37: DATEDIF, EDATE, EOMONTH and NETWORKDAYS | G37: Which functions find the years between two dates, move a date by months, find a month end, or count working days? | H37: DATEDIF = डेट-डिफ, EDATE = ई-डेट, EOMONTH = ई-ओ-मंथ, NETWORKDAYS = नेटवर्क-डेज़ | I37: Date functions | J37: Medium | K37: 4 | L37: These functions came from Lotus 1-2-3 and Excel add-ins. DATEDIF still works in Excel but is not listed in the function wizard, so you must type it. | M37: Give NETWORKDAYS a range of holiday dates as the third argument so that holidays are not counted. | N37: DATEDIF has no tooltip help while typing, so type the unit in quotes, like "Y". Start date must come before end date. | O37: A school clerk has four jobs. One counts completed years of a student, one moves the fee date by months, one finds the last day of the month, and one counts school days without Sundays. | P37: A clerk at a desk with a calendar, a stamp, a month-end red circle and a list of holidays. | Q37: Confidence that the due dates and ages in your sheet are correct. | R37: These four functions measure the gap between dates, move dates by months, find month ends, and count working days. | S37: तारीखों का अंतर निकालना, महीने आगे-पीछे करना, महीने का आखिरी दिन और कार्य दिवस गिनना | T37: A1: =DATE(2000,1,15) A2: =DATE(2024,3,10) B1: =DATEDIF(A1,A2,"Y") B2: =EDATE(A2,1) B3: =EOMONTH(A2,0) B4: =NETWORKDAYS(DATE(2024,3,4),DATE(2024,3,10)) | U37: B1 shows 24 B2 shows 10-04-2024 (format dd-mm-yyyy) B3 shows 31-03-2024 B4 shows 5 | V37: DATEDIF counts complete years ("Y"), months ("M") or days ("D") between a start and an end date. EDATE moves a date by whole months, and EOMONTH returns the last day of a month that many months away. NETWORKDAYS counts Monday to Friday between two dates, including both ends. | W37: DATEDIF poore saal, mahine ya din batata hai. EDATE date ko mahine se aage ya peeche karta hai. EOMONTH mahine ka aakhri din deta hai, aur NETWORKDAYS Saturday Sunday chhod kar kaam ke din ginta hai. | X37: Like a school diary: it knows your age in full years, the next fee date, the last day of the month and the number of school days. | Y37: =DATEDIF(start, end, unit) | =EDATE(start, months) | =EOMONTH(start, months) | =NETWORKDAYS(start, end, [holidays]) | Z37: unit = "Y" years, "M" months or "D" days | months = how many months to move, negative goes back | holidays = optional list of dates to skip | AA37: A1: =DATE(2000,1,15) A2: =DATE(2024,3,10) B1: =DATEDIF(A1,A2,"M") | AB37: A1: =DATE(2024,1,31) B1: =EDATE(A1,1) | AC37: A1: =DATE(2024,3,4) A2: =DATE(2024,3,10) A3: =DATE(2024,3,6) B1: =NETWORKDAYS(A1,A2,A3) | AD37: =EOMONTH(DATE(2024,2,10),0) shows 29-02-2024 =EOMONTH(DATE(2024,2,10),1) shows 31-03-2024 =EDATE(DATE(2024,3,10),-2) shows 10-01-2024 | AE37: DATE, TODAY, IF, TEXT | AF37: TODAY, DATE, WORKDAY, YEARFRAC | AG37: YEARFRAC, WORKDAY, simple subtraction like =A2-A1 for days | AH37: DATEDIF, EDATE, EOMONTH, NETWORKDAYS, WORKDAY, YEARFRAC | AI37: Age and service years | EMI and fee due dates | Project working days | AJ37: A: How do I find the age of a student from the birth date? | B: Use =DATEDIF(birth date, TODAY(), "Y"). It gives the completed years only. | AK37: ✗ NETWORKDAYS skips the start date and the end date → ✓ NETWORKDAYS counts both the start date and the end date if they are working days | AL37: NETWORKDAYS vs WORKDAY: NETWORKDAYS counts working days between two dates, while WORKDAY gives the date after a number of working days. | AM37: Do not put the later date first in DATEDIF, because it gives the #NUM! error. | AN37: A1: =DATE(2000,1,15) A2: =DATE(2024,3,10) B1: =DATEDIF(A2,A1,"Y") | AO37: A1: =DATE(2000,1,15) A2: =DATE(2024,3,10) B1: =DATEDIF(A1,A2,"Y") | AP37: DATEDIF = Difference, EDATE = Extra months, EOMONTH = End Of MONTH, NETWORKDAYS = Net work days. | AQ37: A HR sheet uses DATEDIF to show service years and NETWORKDAYS to count the working days of a leave. | AR37: Interview: How do you calculate the exact age in years from a date of birth? | AS37: It is like counting the working days left before a deadline on a calendar without Sundays. | AT37: =NETWORKDAYS(DATE(2024,3,1),DATE(2024,3,8)) is typed in a cell. Mar 1, 2024 is a Friday. What does it return? | AU37: A) 5 B) 6 C) 7 D) 8 | AV37: B | AW37: Friday 1 March counts, then Monday 4 to Friday 8 March gives 5 more days, so 1 + 5 = 6. | AX37: ____(A1,A2,"Y") counts the complete years between two dates → DATEDIF | AY37: Show the last day of the month for a date in A1 using a formula. | AZ37: A1: =DATE(2024,2,10) B1: =EOMONTH(A1,0) | BA37: Write a formula that counts your completed years of age from your own birth date. | BB37: A1: =DATE(2024,1,15) B1: =EOMONTH(A1,1) B1 is formatted as dd-mm-yyyy. What does it show? | BC37: 29-02-2024 | BD37: =IF(K37="","",REPT("★",K37)&REPT("☆",5-K37)&" ("&K37&"/5)") | BE37: =IF(S37="","","Meaning: "&S37&" = ______ (Answer: "&F37&")") | BF37: New
... A42: XL-040 | B42: 09 Analysis | C42: Advanced | D42: 40 | E42: Claude knowledge | F42: Power Query | G42: Which Data tab tool cleans and combines data with recorded steps that you can run again with one click? | H42: Power Query = पावर क्वेरी | I42: Data tool (Get & Transform) | J42: Medium | K42: 4 | L42: Microsoft made Power Query so that people could clean data without writing code. It started as an add-in for Excel 2010 and 2013, and it is built into Excel 2016 and later as Get & Transform on the Data tab. | M42: After you set up the steps once, new data only needs Data > Refresh All, not the same cleaning work again. | N42: These steps are for Windows Excel. Click Data tab > Get Data and choose a source. Mac Excel has Power Query too, but with fewer options. | O42: A cleaning robot watches you tidy one messy file and writes down every move in a notebook. Next month it opens the new messy file and repeats every move for you. | P42: A small robot with a notebook of steps and a pile of messy tables turning into one clean table. | Q42: Relief and freedom from repeating the same boring clean-up each month. | R42: Power Query imports data, cleans it with recorded steps, and loads the result into a sheet that you can refresh. | S42: डेटा लाना, साफ़ करना और हर बार एक क्लिक में दोबारा चलाना | T42: A1: Name A2: Asha A3: Ravi A4: Asha A5: Meena Steps: click any cell in A1:A5 > Data tab > From Table/Range > OK > select the Name column > Home tab > Remove Rows > Remove Duplicates > Close & Load | U42: A new sheet shows a table with three names: Asha, Ravi and Meena | V42: Power Query opens its own editor where each action becomes a step in the Applied Steps list on the right. When you choose Close & Load, the result is written to a sheet as a table. Your original data is not changed. | W42: Power Query me aap ek baar saaf karne ke steps banate ho, aur Excel unhe yaad rakhta hai. Agli baar naya data aaye to Refresh All dabao aur wahi saare steps dobara chal jate hain. | X42: Like a recipe card: you write the steps once and can cook the same dish again with new ingredients. | Y42: Data tab > Get Data (or From Table/Range, or From Text/CSV) > Power Query Editor > Close & Load | Z42: Source = where the data comes from | Applied Steps = the list of recorded actions | Transform = clean-up actions like Remove Duplicates | Close & Load = write the result to a sheet | Refresh All = run all steps again | AA42: Data tab > Get Data > From File > From Text/CSV > choose a CSV file > Load Result: the CSV rows appear in a new sheet as a table | AB42: A1: Name A2: Asha A3: Ravi A4: Asha Click a cell > Data > From Table/Range > select Name column > Remove Rows > Remove Duplicates > Close & Load Result: Asha and Ravi, one time each | AC42: Data tab > Get Data > Combine Queries > Append > choose two tables > OK > Close & Load Result: the rows of the second table are added below the first table in one list | AD42: Data tab > Refresh All (Ctrl+Alt+F5) runs every query again Home tab > Merge Queries joins two tables like a lookup Click the cross next to a step in Applied Steps to delete that step | AE42: Table (Ctrl+T), PivotTable, CSV files, Refresh All | AF42: PivotTable, Text to Columns, Table (Ctrl+T) | AG42: Manual clean-up, Text to Columns, Remove Duplicates on the Data tab, VBA macros | AH42: Power Query, Get & Transform, Applied Steps, Query, Refresh All, M language | AI42: Monthly CSV imports | Combining many files into one table | Cleaning exported data before a PivotTable | AJ42: A: Every month I get a new export and clean the same columns by hand. | B: Record the clean-up in Power Query once, and next month just click Refresh All. | AK42: ✗ Power Query changes my original data table → ✓ It reads the source and writes a new result table, so the original data stays as it was | AL42: Power Query vs a macro: Power Query records data-cleaning steps that refresh with new data, while a macro (VBA) records any clicks and keystrokes in Excel as code. | AM42: Do not edit the loaded result table by hand, because the next refresh will overwrite your changes. | AN42: Clean the new month's file by hand again, and then paste it over the old data every time | AO42: Load the file with Data > From Text/CSV, clean it in Power Query once, then use Data > Refresh All each month | AP42: Power Query = record the clean-up once, replay it forever. | AQ42: An accountant loads a bank CSV every month, removes blank rows, changes the date type and refreshes the same query. | AR42: Interview: How would you combine twelve monthly files with the same columns into one table in Excel? | AS42: It is like a washing machine program: you choose the steps once and press start every week. | AT42: A query already loads a CSV file. Next month the CSV file has new rows in the same place. What is the fastest way to bring them into the sheet? | AU42: A) Data tab > Refresh All B) Repeat all steps by hand C) Delete the query D) Press F9 | AV42: A | AW42: Refresh All runs the saved steps again on the changed source. F9 recalculates formulas but does not refresh a query. | AX42: In Power Query, the list of recorded actions on the right is called ____ Steps → Applied | AY42: Load a table into Power Query and remove duplicate names, then load it back to a sheet. | AZ42: Click a cell in the table > Data tab > From Table/Range > OK > select Name column > Home tab > Remove Rows > Remove Duplicates > Close & Load | BA42: Make a small list with repeated names and clean it with Power Query, then add one more name and refresh. | BB42: A1: Name, A2: Asha, A3: Ravi, A4: Asha, A5: Meena You load it in Power Query, remove duplicates on Name and click Close & Load. How many names are in the loaded table, not counting the heading? | BC42: 3 | BD42: =IF(K42="","",REPT("★",K42)&REPT("☆",5-K42)&" ("&K42&"/5)") | BE42: =IF(S42="","","Meaning: "&S42&" = ______ (Answer: "&F42&")") | BF42: New

Sheet Code card view
A1: Code concept (56-pt) · card view
A2: Card ID chuno ▸ | B2: XL-001
A4: FRONT · Recognition (pehchano)
A5: ID | B5: =INDEX('Code concept (56-pt) cards'!$A$3:$BN$42,MATCH($B$2,'Code concept (56-pt) cards'!$A$3:$A$42,0),MATCH("ID",'Code concept (56-pt) cards'!$A$2:$BN$2,0))&""
A6: Topic | B6: =INDEX('Code concept (56-pt) cards'!$A$3:$BN$42,MATCH($B$2,'Code concept (56-pt) cards'!$A$3:$A$42,0),MATCH("Topic",'Code concept (56-pt) cards'!$A$2:$BN$2,0))&""
A7: Level | B7: =INDEX('Code concept (56-pt) cards'!$A$3:$BN$42,MATCH($B$2,'Code concept (56-pt) cards'!$A$3:$A$42,0),MATCH("Level",'Code concept (56-pt) cards'!$A$2:$BN$2,0))&""
A8: Concept | B8: =INDEX('Code concept (56-pt) cards'!$A$3:$BN$42,MATCH($B$2,'Code concept (56-pt) cards'!$A$3:$A$42,0),MATCH("Concept",'Code concept (56-pt) cards'!$A$2:$BN$2,0))&""
A9: Recall cue | B9: =INDEX('Code concept (56-pt) cards'!$A$3:$BN$42,MATCH($B$2,'Code concept (56-pt) cards'!$A$3:$A$42,0),MATCH("Recall cue",'Code concept (56-pt) cards'!$A$2:$BN$2,0))&""
A10: Read aloud | B10: =INDEX('Code concept (56-pt) cards'!$A$3:$BN$42,MATCH($B$2,'Code concept (56-pt) cards'!$A$3:$A$42,0),MATCH("Read aloud",'Code concept (56-pt) cards'!$A$2:$BN$2,0))&""
A11: Type | B11: =INDEX('Code concept (56-pt) cards'!$A$3:$BN$42,MATCH($B$2,'Code concept (56-pt) cards'!$A$3:$A$42,0),MATCH("Type",'Code concept (56-pt) cards'!$A$2:$BN$2,0))&""
A12: How often used | B12: =INDEX('Code concept (56-pt) cards'!$A$3:$BN$42,MATCH($B$2,'Code concept (56-pt) cards'!$A$3:$A$42,0),MATCH("How often used",'Code concept (56-pt) cards'!$A$2:$BN$2,0))&""
A13: Importance (1-5) | B13: =INDEX('Code concept (56-pt) cards'!$A$3:$BN$42,MATCH($B$2,'Code concept (56-pt) cards'!$A$3:$A$42,0),MATCH("Importance (1-5)",'Code concept (56-pt) cards'!$A$2:$BN$2,0))&""
A14: Origin / why it exists | B14: =INDEX('Code concept (56-pt) cards'!$A$3:$BN$42,MATCH($B$2,'Code concept (56-pt) cards'!$A$3:$A$42,0),MATCH("Origin / why it exists",'Code concept (56-pt) cards'!$A$2:$BN$2,0))&""
A15: Pro tip | B15: =INDEX('Code concept (56-pt) cards'!$A$3:$BN$42,MATCH($B$2,'Code concept (56-pt) cards'!$A$3:$A$42,0),MATCH("Pro tip",'Code concept (56-pt) cards'!$A$2:$BN$2,0))&""
A16: Typing hint | B16: =INDEX('Code concept (56-pt) cards'!$A$3:$BN$42,MATCH($B$2,'Code concept (56-pt) cards'!$A$3:$A$42,0),MATCH("Typing hint",'Code concept (56-pt) cards'!$A$2:$BN$2,0))&""
A17: Memory story | B17: =INDEX('Code concept (56-pt) cards'!$A$3:$BN$42,MATCH($B$2,'Code concept (56-pt) cards'!$A$3:$A$42,0),MATCH("Memory story",'Code concept (56-pt) cards'!$A$2:$BN$2,0))&""
A18: Picture it | B18: =INDEX('Code concept (56-pt) cards'!$A$3:$BN$42,MATCH($B$2,'Code concept (56-pt) cards'!$A$3:$A$42,0),MATCH("Picture it",'Code concept (56-pt) cards'!$A$2:$BN$2,0))&""
A19: Emotion hook | B19: =INDEX('Code concept (56-pt) cards'!$A$3:$BN$42,MATCH($B$2,'Code concept (56-pt) cards'!$A$3:$A$42,0),MATCH("Emotion hook",'Code concept (56-pt) cards'!$A$2:$BN$2,0))&""
A20: Importance ★ | B20: =INDEX('Code concept (56-pt) cards'!$A$3:$BN$42,MATCH($B$2,'Code concept (56-pt) cards'!$A$3:$A$42,0),MATCH("Importance ★",'Code concept (56-pt) cards'!$A$2:$BN$2,0))&""
A21: BACK · Understanding (samjho)
A22: Meaning (short) | B22: =INDEX('Code concept (56-pt) cards'!$A$3:$BN$42,MATCH($B$2,'Code concept (56-pt) cards'!$A$3:$A$42,0),MATCH("Meaning (short)",'Code concept (56-pt) cards'!$A$2:$BN$2,0))&""
A23: Meaning in learner's language | B23: =INDEX('Code concept (56-pt) cards'!$A$3:$BN$42,MATCH($B$2,'Code concept (56-pt) cards'!$A$3:$A$42,0),MATCH("Meaning in learner's language",'Code concept (56-pt) cards'!$A$2:$BN$2,0))&""
A24: Code | B24: =INDEX('Code concept (56-pt) cards'!$A$3:$BN$42,MATCH($B$2,'Code concept (56-pt) cards'!$A$3:$A$42,0),MATCH("Code",'Code concept (56-pt) cards'!$A$2:$BN$2,0))&""
A25: Output | B25: =INDEX('Code concept (56-pt) cards'!$A$3:$BN$42,MATCH($B$2,'Code concept (56-pt) cards'!$A$3:$A$42,0),MATCH("Output",'Code concept (56-pt) cards'!$A$2:$BN$2,0))&""
A26: Explanation | B26: =INDEX('Code concept (56-pt) cards'!$A$3:$BN$42,MATCH($B$2,'Code concept (56-pt) cards'!$A$3:$A$42,0),MATCH("Explanation",'Code concept (56-pt) cards'!$A$2:$BN$2,0))&""
A27: Simple explanation (Hinglish) | B27: =INDEX('Code concept (56-pt) cards'!$A$3:$BN$42,MATCH($B$2,'Code concept (56-pt) cards'!$A$3:$A$42,0),MATCH("Simple explanation (Hinglish)",'Code concept (56-pt) cards'!$A$2:$BN$2,0))&""
A28: Real-life analogy | B28: =INDEX('Code concept (56-pt) cards'!$A$3:$BN$42,MATCH($B$2,'Code concept (56-pt) cards'!$A$3:$A$42,0),MATCH("Real-life analogy",'Code concept (56-pt) cards'!$A$2:$BN$2,0))&""
A29: Syntax pattern | B29: =INDEX('Code concept (56-pt) cards'!$A$3:$BN$42,MATCH($B$2,'Code concept (56-pt) cards'!$A$3:$A$42,0),MATCH("Syntax pattern",'Code concept (56-pt) cards'!$A$2:$BN$2,0))&""
A30: Anatomy | B30: =INDEX('Code concept (56-pt) cards'!$A$3:$BN$42,MATCH($B$2,'Code concept (56-pt) cards'!$A$3:$A$42,0),MATCH("Anatomy",'Code concept (56-pt) cards'!$A$2:$BN$2,0))&""
A31: Example 1 | B31: =INDEX('Code concept (56-pt) cards'!$A$3:$BN$42,MATCH($B$2,'Code concept (56-pt) cards'!$A$3:$A$42,0),MATCH("Example 1",'Code concept (56-pt) cards'!$A$2:$BN$2,0))&""
A32: Example 2 | B32: =INDEX('Code concept (56-pt) cards'!$A$3:$BN$42,MATCH($B$2,'Code concept (56-pt) cards'!$A$3:$A$42,0),MATCH("Example 2",'Code concept (56-pt) cards'!$A$2:$BN$2,0))&""
A33: Example 3 | B33: =INDEX('Code concept (56-pt) cards'!$A$3:$BN$42,MATCH($B$2,'Code concept (56-pt) cards'!$A$3:$A$42,0),MATCH("Example 3",'Code concept (56-pt) cards'!$A$2:$BN$2,0))&""
A34: Variation | B34: =INDEX('Code concept (56-pt) cards'!$A$3:$BN$42,MATCH($B$2,'Code concept (56-pt) cards'!$A$3:$A$42,0),MATCH("Variation",'Code concept (56-pt) cards'!$A$2:$BN$2,0))&""
A35: Used with | B35: =INDEX('Code concept (56-pt) cards'!$A$3:$BN$42,MATCH($B$2,'Code concept (56-pt) cards'!$A$3:$A$42,0),MATCH("Used with",'Code concept (56-pt) cards'!$A$2:$BN$2,0))&""
A36: Related concepts | B36: =INDEX('Code concept (56-pt) cards'!$A$3:$BN$42,MATCH($B$2,'Code concept (56-pt) cards'!$A$3:$A$42,0),MATCH("Related concepts",'Code concept (56-pt) cards'!$A$2:$BN$2,0))&""
A37: Alternatives | B37: =INDEX('Code concept (56-pt) cards'!$A$3:$BN$42,MATCH($B$2,'Code concept (56-pt) cards'!$A$3:$A$42,0),MATCH("Alternatives",'Code concept (56-pt) cards'!$A$2:$BN$2,0))&""
A38: Family / group | B38: =INDEX('Code concept (56-pt) cards'!$A$3:$BN$42,MATCH($B$2,'Code concept (56-pt) cards'!$A$3:$A$42,0),MATCH("Family / group",'Code concept (56-pt) cards'!$A$2:$BN$2,0))&""
A39: Where it is used | B39: =INDEX('Code concept (56-pt) cards'!$A$3:$BN$42,MATCH($B$2,'Code concept (56-pt) cards'!$A$3:$A$42,0),MATCH("Where it is used",'Code concept (56-pt) cards'!$A$2:$BN$2,0))&""
A40: Mini conversation | B40: =INDEX('Code concept (56-pt) cards'!$A$3:$BN$42,MATCH($B$2,'Code concept (56-pt) cards'!$A$3:$A$42,0),MATCH("Mini conversation",'Code concept (56-pt) cards'!$A$2:$BN$2,0))&""
A41: Common mistake | B41: =INDEX('Code concept (56-pt) cards'!$A$3:$BN$42,MATCH($B$2,'Code concept (56-pt) cards'!$A$3:$A$42,0),MATCH("Common mistake",'Code concept (56-pt) cards'!$A$2:$BN$2,0))&""
A42: Commonly confused with | B42: =INDEX('Code concept (56-pt) cards'!$A$3:$BN$42,MATCH($B$2,'Code concept (56-pt) cards'!$A$3:$A$42,0),MATCH("Commonly confused with",'Code concept (56-pt) cards'!$A$2:$BN$2,0))&""
A43: Avoid / don't | B43: =INDEX('Code concept (56-pt) cards'!$A$3:$BN$42,MATCH($B$2,'Code concept (56-pt) cards'!$A$3:$A$42,0),MATCH("Avoid / don't",'Code concept (56-pt) cards'!$A$2:$BN$2,0))&""
A44: Wrong code | B44: =INDEX('Code concept (56-pt) cards'!$A$3:$BN$42,MATCH($B$2,'Code concept (56-pt) cards'!$A$3:$A$42,0),MATCH("Wrong code",'Code concept (56-pt) cards'!$A$2:$BN$2,0))&""
A45: Right code | B45: =INDEX('Code concept (56-pt) cards'!$A$3:$BN$42,MATCH($B$2,'Code concept (56-pt) cards'!$A$3:$A$42,0),MATCH("Right code",'Code concept (56-pt) cards'!$A$2:$BN$2,0))&""
A46: Memory trick | B46: =INDEX('Code concept (56-pt) cards'!$A$3:$BN$42,MATCH($B$2,'Code concept (56-pt) cards'!$A$3:$A$42,0),MATCH("Memory trick",'Code concept (56-pt) cards'!$A$2:$BN$2,0))&""
A47: Real life: project / work | B47: =INDEX('Code concept (56-pt) cards'!$A$3:$BN$42,MATCH($B$2,'Code concept (56-pt) cards'!$A$3:$A$42,0),MATCH("Real life: project / work",'Code concept (56-pt) cards'!$A$2:$BN$2,0))&""
A48: Real life: interview / exam | B48: =INDEX('Code concept (56-pt) cards'!$A$3:$BN$42,MATCH($B$2,'Code concept (56-pt) cards'!$A$3:$A$42,0),MATCH("Real life: interview / exam",'Code concept (56-pt) cards'!$A$2:$BN$2,0))&""
A49: Real life: daily life | B49: =INDEX('Code concept (56-pt) cards'!$A$3:$BN$42,MATCH($B$2,'Code concept (56-pt) cards'!$A$3:$A$42,0),MATCH("Real life: daily life",'Code concept (56-pt) cards'!$A$2:$BN$2,0))&""
A50: PRACTICE · Khud karo
A51: MCQ question | B51: =INDEX('Code concept (56-pt) cards'!$A$3:$BN$42,MATCH($B$2,'Code concept (56-pt) cards'!$A$3:$A$42,0),MATCH("MCQ question",'Code concept (56-pt) cards'!$A$2:$BN$2,0))&""
A52: MCQ options | B52: =INDEX('Code concept (56-pt) cards'!$A$3:$BN$42,MATCH($B$2,'Code concept (56-pt) cards'!$A$3:$A$42,0),MATCH("MCQ options",'Code concept (56-pt) cards'!$A$2:$BN$2,0))&""
A53: MCQ answer | B53: =INDEX('Code concept (56-pt) cards'!$A$3:$BN$42,MATCH($B$2,'Code concept (56-pt) cards'!$A$3:$A$42,0),MATCH("MCQ answer",'Code concept (56-pt) cards'!$A$2:$BN$2,0))&""
A54: Why that answer | B54: =INDEX('Code concept (56-pt) cards'!$A$3:$BN$42,MATCH($B$2,'Code concept (56-pt) cards'!$A$3:$A$42,0),MATCH("Why that answer",'Code concept (56-pt) cards'!$A$2:$BN$2,0))&""
A55: Fill the blank | B55: =INDEX('Code concept (56-pt) cards'!$A$3:$BN$42,MATCH($B$2,'Code concept (56-pt) cards'!$A$3:$A$42,0),MATCH("Fill the blank",'Code concept (56-pt) cards'!$A$2:$BN$2,0))&""
A56: Task in learner's language | B56: =INDEX('Code concept (56-pt) cards'!$A$3:$BN$42,MATCH($B$2,'Code concept (56-pt) cards'!$A$3:$A$42,0),MATCH("Task in learner's language",'Code concept (56-pt) cards'!$A$2:$BN$2,0))&""
A57: Task answer | B57: =INDEX('Code concept (56-pt) cards'!$A$3:$BN$42,MATCH($B$2,'Code concept (56-pt) cards'!$A$3:$A$42,0),MATCH("Task answer",'Code concept (56-pt) cards'!$A$2:$BN$2,0))&""
A58: Write your own | B58: =INDEX('Code concept (56-pt) cards'!$A$3:$BN$42,MATCH($B$2,'Code concept (56-pt) cards'!$A$3:$A$42,0),MATCH("Write your own",'Code concept (56-pt) cards'!$A$2:$BN$2,0))&""
A59: Practice question | B59: =INDEX('Code concept (56-pt) cards'!$A$3:$BN$42,MATCH($B$2,'Code concept (56-pt) cards'!$A$3:$A$42,0),MATCH("Practice question",'Code concept (56-pt) cards'!$A$2:$BN$2,0))&""
A60: Practice answer | B60: =INDEX('Code concept (56-pt) cards'!$A$3:$BN$42,MATCH($B$2,'Code concept (56-pt) cards'!$A$3:$A$42,0),MATCH("Practice answer",'Code concept (56-pt) cards'!$A$2:$BN$2,0))&""
A61: Quick recall (reverse) | B61: =INDEX('Code concept (56-pt) cards'!$A$3:$BN$42,MATCH($B$2,'Code concept (56-pt) cards'!$A$3:$A$42,0),MATCH("Quick recall (reverse)",'Code concept (56-pt) cards'!$A$2:$BN$2,0))&""

Sheet Anki Import
A1: Front | B1: Back | C1: Tags
A2: Cells, ranges and cell references How does Excel name one box on the sheet, and how do you point to a whole block of boxes in a formula? A1: 10 A2: 20 A3: 30 B1: =SUM(A1:A3) | B2: MEANING (SHORT): A cell is one box on the sheet, and a range is a block of cells. MEANING IN LEARNER'S LANGUAGE: सेल = शीट का एक खाना; रेंज = कई खानों का समूह CODE: A1: 10 A2: 20 A3: 30 B1: =SUM(A1:A3) OUTPUT: 60 EXPLANATION: A cell address is the column letter followed by the row number. A range uses a colon between its first and last cell, so A1:A3 means A1, A2 and A3. Formulas use these addresses so the answer updates when the numbers change. SIMPLE EXPLANATION (HINGLISH): Har khane ka ek address hota hai, jaise A1. Kai khane ek saath lene hon to colon lagate hain, jaise A1:A3. Formula me address likhne se number badalne par answer khud badal jata hai. REAL-LIFE ANALOGY: Like a cinema seat number: row and seat together tell you exactly one seat, and a seat block is a group of neighbouring seats. SYNTAX PATTERN: =FUNCTION(first_cell:last_cell) ANATOMY: A = column letter | 1 = row number | A1 = one cell | A1:A3 = range from A1 down to A3 EXAMPLE 1: A1: 10 B1: =A1 (shows 10, B1 just points to one cell) EXAMPLE 2: A1: 10 A2: 20 A3: 30 B1: =SUM(A1:A3) (shows 60, a range down one column) EXAMPLE 3: A1: 5 A2: 10 B1: 15 B2: 20 C1: =SUM(A1:B2) (shows 50, a block across two columns) VARIATION: =SUM(A1,A3) adds only A1 and A3 (comma picks separate cells) =SUM(A:A) adds the whole column A Name Box: type D10 and press Enter to jump to D10 USED WITH: SUM, AVERAGE, Name Box, formulas RELATED CONCEPTS: Worksheet, Workbook, Named range, Table ALTERNATIVES: Named range, Excel Table column reference FAMILY / GROUP: cell, range, row, column, address, selection WHERE IT IS USED: Budgets and totals | Marks sheets | Any formula you write MINI CONVERSATION: A: My total shows 0, what did I do wrong? | B: Check your range; you may have typed A1:A2 instead of A1:A3 and missed a row. COMMON MISTAKE: ✗ A1:A3 means only the two cells A1 and A3 → ✓ A1:A3 means every cell from A1 through A3, including A2 COMMONLY CONFUSED WITH: A1:A3 vs A1,A3: the colon takes the whole block, the comma takes only the cells you name. AVOID / DON'T: Do not type numbers into a formula when the cell address can be used, or the answer will not update. WRONG CODE: A1: 10 A2: 20 A3: 30 B1: =SUM(A1,A3) RIGHT CODE: A1: 10 A2: 20 A3: 30 B1: =SUM(A1:A3) MEMORY TRICK: Colon = continues through all cells; comma = counts only the ones named. REAL LIFE: PROJECT / WORK: A school clerk sums the marks of one student by pointing a formula at the row range of that student. REAL LIFE: INTERVIEW / EXAM: Interview question: What is the difference between a cell reference and a range, and which symbol makes a range? REAL LIFE: DAILY LIFE: It is like telling a friend your flat number instead of saying the whole street, and a floor range instead of one flat. | C2: 01_Basics_&_Cells_Beginner_XL-001
A3: Data types: text, number, date Why can a cell that looks like a number refuse to add up, and what does Excel secretly store behind a date? A1: 100 A2: '100 (typed with an apostrophe, so it is text) B1: =ISNUMBER(A1) B2: =ISNUMBER(A2) | B3: MEANING (SHORT): Excel stores each entry as text, a number or a date, and treats them differently. MEANING IN LEARNER'S LANGUAGE: टेक्स्ट = शब्द, नंबर = संख्या, डेट = तारीख CODE: A1: 100 A2: '100 (typed with an apostrophe, so it is text) B1: =ISNUMBER(A1) B2: =ISNUMBER(A2) OUTPUT: B1 shows TRUE and B2 shows FALSE EXPLANATION: ISNUMBER checks if a cell holds a real number. A1 is a number, but A2 was stored as text because of the apostrophe, even though it looks the same. Dates are numbers too: Excel counts days from 1 January 1900, and 1 January 2024 is stored as 45292. SIMPLE EXPLANATION (HINGLISH): Excel teen cheez alag rakhta hai: text, number aur date. Text ke andar 100 likha ho to wo jodne me nahi aata. Date asal me ek number hai jo din ginta hai. REAL-LIFE ANALOGY: Like a bank counter with separate windows for cash, cheques and letters, each handled by different rules. SYNTAX PATTERN: =ISNUMBER(cell) | =ISTEXT(cell) ANATOMY: ISNUMBER = test function | cell = what to check | result = TRUE or FALSE EXAMPLE 1: A1: Asha B1: =ISTEXT(A1) (shows TRUE, a word is text) EXAMPLE 2: A1: 100 A2: '100 B1: =SUM(A1:A2) (shows 100, SUM skips the text one) EXAMPLE 3: A1: =DATE(2024,1,1) A2: =DATE(2024,3,1) B1: =A2-A1 (cell format General, shows 60 days) VARIATION: Format cell as General to see the date serial number, for example 45292 =VALUE(A2) converts text like "100" into the number 100 Data tab > Text to Columns > Finish converts a column of text numbers USED WITH: ISNUMBER, ISTEXT, VALUE, Format Cells RELATED CONCEPTS: Number format, Text to Columns, Date serial number, VALUE ALTERNATIVES: VALUE function, Text to Columns, multiply by 1 FAMILY / GROUP: text, number, date, time, logical, error value WHERE IT IS USED: Importing data from other systems | Cleaning mark lists | Date calculations like due dates MINI CONVERSATION: A: My SUM ignores some numbers in the column, why? | B: They are probably stored as text; look for left-aligned values and convert them. COMMON MISTAKE: ✗ Anything that looks like a number is a number → ✓ A value can look like 100 but be stored as text, and then SUM ignores it COMMONLY CONFUSED WITH: Text 100 vs number 100: text looks the same but is ignored by SUM and sorts like a word. AVOID / DON'T: Do not type numbers with extra spaces or apostrophes if you need to calculate with them. WRONG CODE: A1: 100 A2: '100 A3: 50 B1: =SUM(A1:A3) (expecting 250) RIGHT CODE: A1: 100 A2: '100 A3: 50 B2: =VALUE(A2) B1: =SUM(A1,B2,A3) (shows 250) MEMORY TRICK: Left = Letters (text), Right = Right numbers; this is the default alignment. REAL LIFE: PROJECT / WORK: A sales analyst imports a CSV and converts text numbers so that totals match the source report. REAL LIFE: INTERVIEW / EXAM: Interview question: Why does SUM give the wrong total when some numbers are stored as text? REAL LIFE: DAILY LIFE: It is like a shopkeeper who counts only real notes and puts photocopies of notes aside. | C3: 01_Basics_&_Cells_Beginner_XL-002
A4: AutoFill and the fill handle Which tiny square at a cell's corner lets you drag a pattern or formula down a column? A1: 1 A2: 2 Select A1:A2, drag the fill handle down to A5 | B4: MEANING (SHORT): AutoFill copies or continues a pattern by dragging the fill handle. MEANING IN LEARNER'S LANGUAGE: ऑटोफ़िल = खींचकर पैटर्न या फ़ॉर्मूला अपने आप भरना CODE: A1: 1 A2: 2 Select A1:A2, drag the fill handle down to A5 OUTPUT: A3 shows 3, A4 shows 4, A5 shows 5 EXPLANATION: Excel reads the first two values to find the step, here +1, and continues it. For text such as day names it continues the built-in list. For formulas it copies the formula and moves the relative references. SIMPLE EXPLANATION (HINGLISH): Do cell select karke handle kheenchoge to Excel pattern samajh kar aage bhar deta hai. Ek hi number ho to wo copy ho jata hai. Formula ho to wo bhi neeche copy hota hai. REAL-LIFE ANALOGY: Like showing a child 2, 4 and then saying carry on; the child continues 6, 8, 10 by the same rule. SYNTAX PATTERN: Select cells > drag the fill handle (bottom-right square) ANATOMY: Selected cells = the pattern | fill handle = small square | drag direction = where the pattern continues EXAMPLE 1: A1: 1 A2: 2 Select A1:A2, drag the handle to A5 (A5 shows 5, a number series) EXAMPLE 2: A1: Mon Drag the handle down to A3 (A2 shows Tue, A3 shows Wed, a text list) EXAMPLE 3: A1: 5 A2: 7 A3: 9 B1: =A1*2 Double-click the handle of B1 (B2 shows 14, B3 shows 18, a formula copy) VARIATION: A single number such as 5 is copied, not counted, when you drag Hold Ctrl while dragging a single number to make it count up (Windows) Click the small Auto Fill Options button after dragging to choose Copy Cells or Fill Series USED WITH: Fill series, relative references, Flash Fill, Ctrl+D RELATED CONCEPTS: Relative reference, Custom lists, Ctrl+D, Flash Fill ALTERNATIVES: Ctrl+D to fill down, Home tab > Fill > Series FAMILY / GROUP: AutoFill, fill handle, fill series, fill down, fill right, series WHERE IT IS USED: Serial numbers on a list | Dates and months across columns | Copying one formula to every row MINI CONVERSATION: A: I typed 1 and dragged but I got 1, 1, 1; why? | B: A single number is copied, so enter 1 and 2 first and drag both cells. COMMON MISTAKE: ✗ Dragging one number always counts up, 1, 2, 3 → ✓ A single number is copied; give two cells to show the step, or hold Ctrl while dragging COMMONLY CONFUSED WITH: Fill handle vs Ctrl+D: the handle drags to any distance and pattern, Ctrl+D copies the cell above into the selected cells. AVOID / DON'T: Do not drag blindly over a long list when double-clicking the fill handle does the work in one move. WRONG CODE: A1: 1 Drag the handle down to A5 (expecting 1, 2, 3, 4, 5) RIGHT CODE: A1: 1 A2: 2 Select A1:A2 and drag the handle down to A5 MEMORY TRICK: Two cells show the step; one cell shows only copy. REAL LIFE: PROJECT / WORK: An office assistant numbers 200 employee rows by dragging the handle instead of typing every number. REAL LIFE: INTERVIEW / EXAM: Interview question: How do you quickly copy a formula down 500 rows without dragging? REAL LIFE: DAILY LIFE: It is like a teacher writing the first two roll numbers and asking the class monitor to continue the list. | C4: 01_Basics_&_Cells_Beginner_XL-003
A5: Flash Fill Which feature watches one example you type and then completes the whole column without a formula? A1: Asha Rao A2: Sita Devi B1: Asha (typed by you) Click B2, press Ctrl+E | B5: MEANING (SHORT): Flash Fill copies a pattern you typed once to the other rows. MEANING IN LEARNER'S LANGUAGE: फ़्लैश फ़िल = एक उदाहरण देखकर बाकी पंक्तियाँ अपने आप भरना CODE: A1: Asha Rao A2: Sita Devi B1: Asha (typed by you) Click B2, press Ctrl+E OUTPUT: B2 shows Sita EXPLANATION: Excel compares your typed example with the cell beside it and finds the pattern, here the first word. It then fills the rest of the column using that pattern. The result is plain text, not a formula, so it will not update later. SIMPLE EXPLANATION (HINGLISH): Pehli row me jo chahiye wo khud likho, phir Ctrl+E dabao. Excel pattern pehchan kar baaki sab bhar deta hai. Ye formula nahi hai, sirf text hai. REAL-LIFE ANALOGY: Like showing a tailor one sample shirt, then asking him to stitch the rest in exactly the same style. SYNTAX PATTERN: Type first example > Ctrl+E (or Data tab > Flash Fill) ANATOMY: Source column = the data | typed example = the pattern | Ctrl+E = apply to all rows EXAMPLE 1: A1: Asha Rao A2: Sita Devi B1: Asha Click B2, press Ctrl+E (B2 shows Sita, a split) EXAMPLE 2: A1: Asha B1: Rao C1: Asha Rao (typed) Click C2, press Ctrl+E (joins first and last name for each row) EXAMPLE 3: A1: 9876543210 B1: 98765-43210 (typed) Click B2, press Ctrl+E (adds a dash in the same place for all rows) VARIATION: Data tab > Flash Fill does the same as Ctrl+E File > Options > Advanced > Automatically Flash Fill turns the live suggestion on or off If the grey preview appears while you type, press Enter to accept it USED WITH: Text to Columns, LEFT, MID, CONCAT RELATED CONCEPTS: Text to Columns, LEFT and RIGHT, TEXTJOIN, AutoFill ALTERNATIVES: Text to Columns, LEFT/MID/RIGHT formulas, TEXTSPLIT in Microsoft 365 FAMILY / GROUP: Flash Fill, pattern, split, join, extract, clean WHERE IT IS USED: Splitting full names | Fixing phone number format | Making email IDs from names MINI CONVERSATION: A: I have full names in one column, can I get only first names fast? | B: Type the first name once next to it and press Ctrl+E. COMMON MISTAKE: ✗ Flash Fill creates a formula that updates when the data changes → ✓ Flash Fill writes fixed values, so you must run it again after the source changes COMMONLY CONFUSED WITH: Flash Fill vs AutoFill: Flash Fill learns a text pattern from an example, while AutoFill continues a number or list series. AVOID / DON'T: Do not trust Flash Fill blindly on messy data; always scan the results for wrong rows. WRONG CODE: A1: Asha Rao A2: Sita Devi Select B2 and press Ctrl+E with B1 left empty RIGHT CODE: A1: Asha Rao A2: Sita Devi B1: Asha (typed) Click B2, press Ctrl+E MEMORY TRICK: Type one, press Ctrl+E, check all. REAL LIFE: PROJECT / WORK: A data entry person splits 1,000 full names into first and last name columns in a few seconds. REAL LIFE: INTERVIEW / EXAM: Interview question: How can you split a name column without writing a formula? REAL LIFE: DAILY LIFE: It is like showing a friend one correctly written address label and asking him to copy the style on the rest. | C5: 01_Basics_&_Cells_Beginner_XL-004
A6: Relative vs absolute references ($) Why does a copied formula sometimes point to the wrong cell, and what sign pins a cell in place? A2: 200 A3: 300 B1: 0.1 (rate) C2: =A2*$B$1 C3: =A3*$B$1 | B6: MEANING (SHORT): A relative reference moves when copied; an absolute reference with dollar signs stays fixed. MEANING IN LEARNER'S LANGUAGE: रिलेटिव = कॉपी करने पर बदलता है; एब्सोल्यूट ($) = जगह पर टिका रहता है CODE: A2: 200 A3: 300 B1: 0.1 (rate) C2: =A2*$B$1 C3: =A3*$B$1 OUTPUT: C2 shows 20 and C3 shows 30 EXPLANATION: When C2 is copied down, A2 becomes A3 because it is relative. $B$1 stays B1 because both its column and row are locked. This lets every row use the same rate cell. SIMPLE EXPLANATION (HINGLISH): Normal reference formula ke saath neeche khisakta hai. Dollar lagane se wo cell wahi rukta hai. Isliye rate wale cell par $ lagate hain. REAL-LIFE ANALOGY: Like asking each student to check the person next to them (relative), but also asking everyone to look at one fixed notice board (absolute). SYNTAX PATTERN: A1 (relative) | $A$1 (absolute) | A$1 or $A1 (mixed) ANATOMY: $ before the letter = lock the column | $ before the number = lock the row | no $ = free to move EXAMPLE 1: A2: 200 A3: 300 C2: =A2*2 (copied to C3 it becomes =A3*2 and shows 600, relative) EXAMPLE 2: A2: 200 A3: 300 B1: 0.1 C2: =A2*$B$1 (copied to C3 it stays $B$1 and shows 30, absolute) EXAMPLE 3: A2: 2 A3: 3 B1: 4 C1: 5 B2: =$A2*B$1 (shows 8; copied to C3 it becomes =$A3*C$1 and shows 15, mixed) VARIATION: F4 once makes $A$1, twice makes A$1, three times makes $A1, four times gives A1 again Named range, for example Rate, works like an absolute reference Copying a formula right changes the column letter; copying down changes the row number USED WITH: AutoFill, SUM, VLOOKUP, percentage calculations RELATED CONCEPTS: AutoFill, Named range, Mixed reference, F4 key ALTERNATIVES: Named range, Excel Table structured references FAMILY / GROUP: relative, absolute, mixed, anchor, lock, F4 WHERE IT IS USED: Applying one tax or discount rate to a price list | Multiplication tables | Lookup tables that must not shift MINI CONVERSATION: A: Only my first row is right after I drag the formula down; the rest show zero. | B: Your rate cell moved; press F4 to lock it as $B$1. COMMON MISTAKE: ✗ A copied formula always points to the same cells as the original → ✓ A normal reference shifts when copied; only the ones with $ stay fixed COMMONLY CONFUSED WITH: B1 vs $B$1: B1 shifts when copied, $B$1 never shifts. AVOID / DON'T: Do not copy a formula that uses a fixed rate cell without first adding the dollar signs. WRONG CODE: B1: 10 A2: 200 A3: 300 C2: =A2*B1 C3 (copied) becomes =A3*B2 and shows 0 RIGHT CODE: B1: 10 A2: 200 A3: 300 C2: =A2*$B$1 C3 (copied) stays =A3*$B$1 and shows 3000 MEMORY TRICK: Dollar = Done moving; no dollar means the cell can wander. REAL LIFE: PROJECT / WORK: A finance analyst applies one GST rate cell to hundreds of price rows using $ in the formula. REAL LIFE: INTERVIEW / EXAM: Interview question: What does $A$1 mean, and when would you use it instead of A1? REAL LIFE: DAILY LIFE: It is like fixing one price tag to a shelf so that it does not move while the other items change places. | C6: 01_Basics_&_Cells_Beginner_XL-005
A7: SUM and AutoSum Which function adds a block of numbers, and what shortcut types it for you? A1: 10 A2: 20 A3: 30 A4: =SUM(A1:A3) | B7: MEANING (SHORT): SUM adds all the numbers in the cells you give it. MEANING IN LEARNER'S LANGUAGE: SUM = जोड़ना, सारी संख्याओं का कुल CODE: A1: 10 A2: 20 A3: 30 A4: =SUM(A1:A3) OUTPUT: 60 EXPLANATION: SUM adds every number in the range. It ignores text and empty cells in the range. AutoSum, on the Home tab or with Alt+=, writes the SUM formula and guesses the range for you. SIMPLE EXPLANATION (HINGLISH): SUM sab number jod deta hai. Text ya khali cell ho to use chhod deta hai. Alt+= dabane se Excel khud formula likh deta hai. REAL-LIFE ANALOGY: Like emptying all small piles of money on a table into one big pile and counting that pile. SYNTAX PATTERN: =SUM(number1, [number2], ...) ANATOMY: = starts a formula | SUM = function name | ( ) = brackets | A1:A3 = numbers to add EXAMPLE 1: A1: 10 A2: 20 A3: 30 A4: =SUM(A1:A3) (shows 60, a simple range) EXAMPLE 2: A1: 10 A2: 20 A3: 30 B1: =SUM(A1:A3,5) (shows 65, a range plus a typed number) EXAMPLE 3: A1: 10 A2: n/a A3: 30 B1: =SUM(A1:A3) (shows 40, the text n/a is ignored) VARIATION: =SUM(A:A) adds the whole column A Select A4 under the numbers and press Alt+= then Enter (Windows) for AutoSum Home tab > Editing group > AutoSum button (the sigma sign) does the same USED WITH: AVERAGE, SUMIF, AutoSum, Alt+= RELATED CONCEPTS: SUMIF, SUMIFS, AVERAGE, COUNT ALTERNATIVES: Plus signs like =A1+A2+A3, the status bar total, SUMIF for conditions FAMILY / GROUP: SUM, SUMIF, SUMIFS, SUMPRODUCT, SUBTOTAL, AutoSum WHERE IT IS USED: Monthly expense totals | Marks totals | Sales reports MINI CONVERSATION: A: How do I add the whole column quickly? | B: Click the empty cell below it and press Alt+=, then Enter. COMMON MISTAKE: ✗ SUM will turn text like "five" into 5 → ✓ SUM ignores text in a range, so type real numbers COMMONLY CONFUSED WITH: SUM vs SUBTOTAL: SUM adds everything in the range, while SUBTOTAL can skip rows hidden by a filter. AVOID / DON'T: Do not add a long column with plus signs when one SUM range can do it. WRONG CODE: A1: 10 A2: 20 A3: 30 A4: SUM(A1:A3) RIGHT CODE: A1: 10 A2: 20 A3: 30 A4: =SUM(A1:A3) MEMORY TRICK: SUM = Stack Up Many numbers. REAL LIFE: PROJECT / WORK: An accounts assistant totals daily sales in a month column with one SUM formula. REAL LIFE: INTERVIEW / EXAM: Interview question: How do you add a column of numbers quickly, and what does SUM do with text? REAL LIFE: DAILY LIFE: It is like adding up all the bills on a monthly grocery list. | C7: 02_Basic_Functions_Beginner_XL-006
A8: AVERAGE, MIN and MAX Which three functions give the typical, smallest and biggest number of a list? A1: 70 A2: 80 A3: 90 A4: 60 B1: =AVERAGE(A1:A4) B2: =MIN(A1:A4) B3: =MAX(A1:A4) | B8: MEANING (SHORT): AVERAGE gives the mean, MIN the lowest and MAX the highest value. MEANING IN LEARNER'S LANGUAGE: एवरेज = औसत, MIN = सबसे छोटा, MAX = सबसे बड़ा CODE: A1: 70 A2: 80 A3: 90 A4: 60 B1: =AVERAGE(A1:A4) B2: =MIN(A1:A4) B3: =MAX(A1:A4) OUTPUT: B1 shows 75, B2 shows 60, B3 shows 90 EXPLANATION: AVERAGE adds the numbers and divides by how many numbers there are: (70+80+90+60)/4 = 75. MIN finds the lowest, which is 60, and MAX finds the highest, which is 90. All three ignore text and empty cells in a range. SIMPLE EXPLANATION (HINGLISH): AVERAGE sab jodkar number ginti se bhaag deta hai. MIN sabse chhota aur MAX sabse bada number batata hai. Khali ya text cell ginti me nahi aate. REAL-LIFE ANALOGY: Like checking a class: the shortest student, the tallest student and the typical height of all students. SYNTAX PATTERN: =AVERAGE(range) | =MIN(range) | =MAX(range) ANATOMY: AVERAGE, MIN, MAX = function names | range = cells to look at | brackets = hold the range EXAMPLE 1: A1: 70 A2: 80 A3: 90 A4: 60 B1: =AVERAGE(A1:A4) (shows 75, the mean) EXAMPLE 2: A1: 70 A2: 80 A3: 90 B1: =MAX(A1:A3,100) (shows 100, a typed number joins the range) EXAMPLE 3: A1: -5 A2: 3 A3: 0 B1: =MIN(A1:A3) (shows -5, negatives count too) VARIATION: =AVERAGE(A1:A4) skips blank cells but counts zero =LARGE(A1:A4,2) gives the second biggest number Status bar at the bottom shows Average, Count and Sum for selected cells USED WITH: SUM, COUNT, IF, LARGE, SMALL RELATED CONCEPTS: MEDIAN, LARGE, SMALL, COUNT ALTERNATIVES: MEDIAN, LARGE and SMALL, PivotTable summaries FAMILY / GROUP: AVERAGE, AVERAGEIF, MIN, MAX, MEDIAN, LARGE WHERE IT IS USED: Class marks analysis | Price comparison | Sales performance reports MINI CONVERSATION: A: My class average looks too low, why? | B: Check whether absent students were typed as 0, because zero is counted but blank is not. COMMON MISTAKE: ✗ AVERAGE ignores zero values like blanks → ✓ AVERAGE counts a typed 0 as a number, but skips empty cells COMMONLY CONFUSED WITH: AVERAGE vs MEDIAN: AVERAGE is the sum divided by the count, MEDIAN is the middle value when sorted. AVOID / DON'T: Do not type 0 for missing marks if the average must skip them; leave the cell blank. WRONG CODE: A1: 70 A2: 80 A3: 90 B1: =AVG(A1:A3) RIGHT CODE: A1: 70 A2: 80 A3: 90 B1: =AVERAGE(A1:A3) MEMORY TRICK: MIN is little, MAX is big, AVERAGE is the middle ground. REAL LIFE: PROJECT / WORK: A teacher finds the highest, lowest and average score of a class test in three cells. REAL LIFE: INTERVIEW / EXAM: Interview question: What is the difference between AVERAGE and MEDIAN, and how does a zero affect AVERAGE? REAL LIFE: DAILY LIFE: It is like checking the cheapest, costliest and usual price of tomatoes in the market. | C8: 02_Basic_Functions_Beginner_XL-007
A9: COUNT, COUNTA and COUNTBLANK Which functions count only numbers, count every filled cell, or count the empty ones? A1: 10 A2: Asha A3: (empty) A4: 25 B1: =COUNT(A1:A4) B2: =COUNTA(A1:A4) B3: =COUNTBLANK(A1:A4) | B9: MEANING (SHORT): COUNT counts numbers, COUNTA counts any filled cell and COUNTBLANK counts empty cells. MEANING IN LEARNER'S LANGUAGE: COUNT = सिर्फ़ संख्याएँ गिनो, COUNTA = भरे हुए सारे खाने, COUNTBLANK = खाली खाने CODE: A1: 10 A2: Asha A3: (empty) A4: 25 B1: =COUNT(A1:A4) B2: =COUNTA(A1:A4) B3: =COUNTBLANK(A1:A4) OUTPUT: B1 shows 2, B2 shows 3, B3 shows 1 EXPLANATION: COUNT counts only numbers (10 and 25), so it gives 2. COUNTA counts every cell that holds something, here 10, Asha and 25, so it gives 3. COUNTBLANK counts the single empty cell A3, and it also counts cells that hold a formula returning empty text. SIMPLE EXPLANATION (HINGLISH): COUNT sirf number ginta hai. COUNTA jo bhi likha ho wo sab ginta hai. COUNTBLANK khali khane ginta hai. REAL-LIFE ANALOGY: Like counting only the ticket numbers, then every person on the bus, then the empty seats. SYNTAX PATTERN: =COUNT(range) | =COUNTA(range) | =COUNTBLANK(range) ANATOMY: COUNT = numbers only | COUNTA = anything filled | COUNTBLANK = empty cells | range = where to look EXAMPLE 1: A1: 10 A2: Asha A3: 25 B1: =COUNT(A1:A3) (shows 2, numbers only) EXAMPLE 2: A1: Ravi A2: Sita A3: Amit B1: =COUNTA(A1:A3) (shows 3, names are counted) EXAMPLE 3: B1: P B2: (empty) B3: P B4: (empty) C1: =COUNTBLANK(B1:B4) (shows 2, empty attendance rows) VARIATION: =COUNTA(A:A)-1 counts the entries in a column after removing a header row =COUNTIF(A1:A10,"P") counts only cells equal to P =ROWS(A1:A10)-COUNTA(A1:A10) also gives the empty cells count USED WITH: COUNTIF, SUM, IF, ISBLANK RELATED CONCEPTS: COUNTIF, COUNTIFS, ISBLANK, ROWS ALTERNATIVES: COUNTIF, status bar Count, PivotTable count FAMILY / GROUP: COUNT, COUNTA, COUNTBLANK, COUNTIF, COUNTIFS, ROWS WHERE IT IS USED: Attendance sheets | Survey responses | Checking missing data in a form MINI CONVERSATION: A: I need to know how many students submitted their name. | B: Use COUNTA on the name column; COUNT would give zero since names are text. COMMON MISTAKE: ✗ COUNT counts every filled cell → ✓ COUNT counts only numbers; use COUNTA to count text and numbers together COMMONLY CONFUSED WITH: COUNT vs COUNTA: COUNT counts numbers only, COUNTA counts any non-empty cell including text. AVOID / DON'T: Do not use COUNT on a column of names, because it will return 0. WRONG CODE: A1: Ravi A2: Sita A3: Amit B1: =COUNT(A1:A3) (expecting 3) RIGHT CODE: A1: Ravi A2: Sita A3: Amit B1: =COUNTA(A1:A3) MEMORY TRICK: A in COUNTA = All entries; COUNT alone = numbers only. REAL LIFE: PROJECT / WORK: A coordinator counts how many feedback forms are still blank using COUNTBLANK. REAL LIFE: INTERVIEW / EXAM: Interview question: What is the difference between COUNT and COUNTA, and how do you count empty cells? REAL LIFE: DAILY LIFE: It is like counting how many seats on a train are taken and how many are still free. | C9: 02_Basic_Functions_Beginner_XL-008
A10: ROUND, ROUNDUP and ROUNDDOWN Which three functions change a number to fewer digits, rounding normally, always up or always down? A1: 7.456 B1: =ROUND(A1,2) B2: =ROUNDUP(A1,2) B3: =ROUNDDOWN(A1,2) | B10: MEANING (SHORT): These functions change the stored value to a chosen number of digits. MEANING IN LEARNER'S LANGUAGE: ROUND = पास की पूर्ण संख्या पर, ROUNDUP = हमेशा ऊपर, ROUNDDOWN = हमेशा नीचे CODE: A1: 7.456 B1: =ROUND(A1,2) B2: =ROUNDUP(A1,2) B3: =ROUNDDOWN(A1,2) OUTPUT: B1 shows 7.46, B2 shows 7.46, B3 shows 7.45 EXPLANATION: ROUND looks at the next digit, 6, and rounds up to 7.46. ROUNDUP always moves away from zero, so it also gives 7.46. ROUNDDOWN always cuts toward zero, so it gives 7.45. The second number is how many decimal places to keep. SIMPLE EXPLANATION (HINGLISH): ROUND paas wali value par le jata hai. ROUNDUP hamesha upar le jata hai aur ROUNDDOWN hamesha neeche. Doosra number batata hai kitne decimal rakhne hain. REAL-LIFE ANALOGY: Like deciding the bus fare: round to the nearest rupee, always charge up, or always drop the paise. SYNTAX PATTERN: =ROUND(number, num_digits) ANATOMY: number = value or cell | num_digits = decimals to keep | negative digits = round tens, hundreds EXAMPLE 1: A1: 2.5 B1: =ROUND(A1,0) (shows 3, a half rounds away from zero) EXAMPLE 2: A1: 1234 B1: =ROUND(A1,-2) (shows 1200, a negative digits value rounds to hundreds) EXAMPLE 3: A1: 9.99 B1: =ROUNDDOWN(A1,0) (shows 9, the decimals are cut off) VARIATION: =ROUNDUP(4.01,0) gives 5 =ROUNDDOWN(-3.7,0) gives -3 because it moves toward zero =INT(7.9) gives 7 and always goes to the lower whole number USED WITH: SUM, IF, percentage formulas, currency RELATED CONCEPTS: INT, TRUNC, CEILING, FLOOR ALTERNATIVES: INT, TRUNC, Number format with fewer decimals, MROUND FAMILY / GROUP: ROUND, ROUNDUP, ROUNDDOWN, INT, TRUNC, MROUND WHERE IT IS USED: Bills and invoices | Tax and interest calculations | Marks converted to whole numbers MINI CONVERSATION: A: I formatted the cell to two decimals, but my total is off by a paisa. | B: Formatting only changes the display; use ROUND to change the actual value. COMMON MISTAKE: ✗ Formatting a cell to 2 decimals also rounds the stored number → ✓ Format only changes how it looks; ROUND changes the stored value COMMONLY CONFUSED WITH: ROUNDDOWN vs INT: for negative numbers ROUNDDOWN moves toward zero, while INT moves to the lower whole number. AVOID / DON'T: Do not rely on cell formatting when the rounded value must be used in later formulas. WRONG CODE: A1: 7.456 B1: =ROUND(A1) (expecting 7.46) RIGHT CODE: A1: 7.456 B1: =ROUND(A1,2) MEMORY TRICK: ROUND is Regular, UP is Upwards always, DOWN is Down always. REAL LIFE: PROJECT / WORK: A billing clerk rounds each line item to two decimals so that the invoice total matches the bank amount. REAL LIFE: INTERVIEW / EXAM: Interview question: What is the difference between formatting to two decimals and using ROUND? REAL LIFE: DAILY LIFE: It is like a shopkeeper rounding the bill to the nearest rupee when no small change is available. | C10: 02_Basic_Functions_Beginner_XL-009
A11: Number formats (currency, date, percent) How can the same stored value appear as money, as a percentage or as a calendar date? A1: 0.25 Select A1, press Ctrl+Shift+5 (Home tab > Number group > %) | B11: MEANING (SHORT): A number format changes how a value looks without changing the value itself. MEANING IN LEARNER'S LANGUAGE: नंबर फ़ॉर्मेट = वही संख्या अलग रूप में दिखाना (पैसा, प्रतिशत, तारीख) CODE: A1: 0.25 Select A1, press Ctrl+Shift+5 (Home tab > Number group > %) OUTPUT: A1 shows 25% EXPLANATION: The number format changes only the display. The stored value of A1 is still 0.25, and Percentage format multiplies it by 100 for display and adds the % sign. Dates are stored as serial numbers, so Date format turns 45292 into a calendar date. SIMPLE EXPLANATION (HINGLISH): Number format sirf dikhane ka tareeka badalta hai, asli value wahi rehti hai. 0.25 ko percent format dene par 25% dikhta hai. Date bhi asal me ek number hai jise date jaisa dikhaya jata hai. REAL-LIFE ANALOGY: Like a person who stays the same but wears different clothes for office, a wedding or a gym. SYNTAX PATTERN: Ctrl+1 > Number tab > choose Category (Currency, Percentage, Date) ANATOMY: Category = type of format | Decimal places = digits shown | Symbol = currency sign EXAMPLE 1: A1: 1234.5 Select A1, press Ctrl+Shift+4 (shows $1,234.50 with US English settings, a currency format) EXAMPLE 2: A1: 0.25 Select A1, press Ctrl+Shift+5 (shows 25%, a percent format) EXAMPLE 3: A1: 45292 Select A1, press Ctrl+Shift+3 (shows 1-Jan-24 with US English settings, a date format) VARIATION: Ctrl+1 > Currency lets you choose the symbol such as the rupee Home tab > Increase Decimal or Decrease Decimal changes the digits shown Typing 25% directly in an empty cell stores 0.25 with Percentage format USED WITH: ROUND, TEXT, Format Cells, Home tab RELATED CONCEPTS: Format Cells, ROUND, TEXT function, Date serial number ALTERNATIVES: TEXT function, Accounting format, Custom number formats FAMILY / GROUP: General, Number, Currency, Accounting, Percentage, Date WHERE IT IS USED: Invoices and price lists | Growth and discount percentages | Date columns in schedules MINI CONVERSATION: A: I typed 0.5 but I want to show 50%. Should I type 50 instead? | B: No, keep 0.5 and apply the Percentage format. COMMON MISTAKE: ✗ Applying the Percentage format to 5 changes it into 5% → ✓ It shows 500%, because the format multiplies the stored value by 100 COMMONLY CONFUSED WITH: Number format vs ROUND: a format changes only how the value looks, ROUND changes the stored value. AVOID / DON'T: Do not type the currency symbol by hand when a Currency format can add it for you. WRONG CODE: A1: 5 Select A1 and apply Percentage format (expecting 5%) RIGHT CODE: A1: 0.05 Select A1 and press Ctrl+Shift+5 (shows 5%) MEMORY TRICK: Shift+4 is the dollar key, Shift+5 is the percent key. REAL LIFE: PROJECT / WORK: A finance assistant formats a price column as currency and a growth column as percent before sending a report. REAL LIFE: INTERVIEW / EXAM: Interview question: If you format 0.25 as a percentage, what is stored in the cell? REAL LIFE: DAILY LIFE: It is like the same weight shown in kilograms on one scale and in grams on another. | C11: 03_Formatting_&_Organising_Beginner_XL-010
A12: Sort Which Excel feature puts rows in order, such as A to Z or smallest to largest, without retyping anything? A1: Name B1: Marks A2: Ravi B2: 72 A3: Asha B3: 90 A4: Meena B4: 65 Steps: click B2 > Data tab > Sort Largest to Smallest | B12: MEANING (SHORT): Sort rearranges the rows of a table in order based on the values in one or more columns. MEANING IN LEARNER'S LANGUAGE: डेटा को क्रम में लगाना (A से Z या छोटे से बड़े) CODE: A1: Name B1: Marks A2: Ravi B2: 72 A3: Asha B3: 90 A4: Meena B4: 65 Steps: click B2 > Data tab > Sort Largest to Smallest OUTPUT: Rows become: Asha 90, Ravi 72, Meena 65 (each name stays with its own marks) EXPLANATION: Sort reorders whole rows, not just the column you clicked, as long as Excel sees your data as one table. The header row stays on top when Excel detects headers. You can sort text A to Z, numbers small to large, or dates old to new. SIMPLE EXPLANATION (HINGLISH): Sort ka matlab hai list ko order me lagana. Ek cell par click karo, Data tab me Sort dabao, aur poori row apne data ke saath move hoti hai. REAL-LIFE ANALOGY: Like arranging books on a shelf by their title: every book moves to a new spot, but each book stays in one piece. SYNTAX PATTERN: Data tab > Sort A to Z / Sort Z to A, or Data tab > Sort for the full dialog ANATOMY: Data tab = where the buttons live | Sort A to Z = smallest or alphabetical first | Sort Z to A = largest or reverse alphabetical first | Sort dialog = choose column, order and extra levels EXAMPLE 1: A1: Name A2: Ravi A3: Asha A4: Meena Steps: click A2 > Data tab > Sort A to Z Result: Asha, Meena, Ravi EXAMPLE 2: A1: Class, B1: Marks (class A and B mixed) Steps: Data tab > Sort > Sort by Class (A to Z) > Add Level > Then by Marks (Largest to Smallest) > OK Result: classes grouped, and highest marks first inside each class EXAMPLE 3: Select only column B (Marks) and click Sort Smallest to Largest Excel asks: Expand the selection or Continue with the current selection Choose Expand the selection so names move with the marks VARIATION: Data tab > Sort > Add Level (sort by two columns) Data tab > Sort > My data has headers (tick when row 1 is headings) Data tab > Sort > Order: Custom List... (for Low, Medium, High) USED WITH: Filter, Excel Tables, Freeze Panes, Conditional Formatting RELATED CONCEPTS: Filter, SORT function, Custom Lists, Excel Tables ALTERNATIVES: SORT function (Microsoft 365 or Excel 2021 or later), Filter button drop-down sort options FAMILY / GROUP: Sort, Filter, Group, Rank, Order WHERE IT IS USED: Ranking students by marks | Arranging a customer list A to Z | Putting dates in order before a report MINI CONVERSATION: A: My marks list is all mixed up and I need the topper first. | B: Click any cell in the Marks column, then use Data tab > Sort Largest to Smallest. COMMON MISTAKE: ✗ Sorting one column changes only that column's order → ✓ If you select only one column and choose Continue with the current selection, the other columns do not move and the rows no longer match; pick Expand the selection COMMONLY CONFUSED WITH: Sort vs Filter: Sort changes the order of all rows, while Filter only hides rows that do not match and keeps the order. AVOID / DON'T: Do not select a single column in the middle of a table and sort it alone, because the rows will no longer match. WRONG CODE: Select only B2:B4 > Data tab > Sort Smallest to Largest > Continue with the current selection RIGHT CODE: Click one cell inside the table (for example B2) > Data tab > Sort Smallest to Largest (or choose Expand the selection) MEMORY TRICK: Sort = Same rows Stay together, they only change order. REAL LIFE: PROJECT / WORK: A teacher sorts the class result sheet by total marks so the top ten students are at the top of the report. REAL LIFE: INTERVIEW / EXAM: Interviewer asks: How do you sort a table by two columns, such as Department and then Salary? REAL LIFE: DAILY LIFE: Arranging contacts in your phone by name so you can find a friend quickly. | C12: 03_Formatting_&_Organising_Beginner_XL-011
... A41: Power Query Which Data tab tool cleans and combines data with recorded steps that you can run again with one click? A1: Name A2: Asha A3: Ravi A4: Asha A5: Meena Steps: click any cell in A1:A5 > Data tab > From Table/Range > OK > select the Name column > Home tab > Remove Rows > Remove Duplicates > Close & Load | B41: MEANING (SHORT): Power Query imports data, cleans it with recorded steps, and loads the result into a sheet that you can refresh. MEANING IN LEARNER'S LANGUAGE: डेटा लाना, साफ़ करना और हर बार एक क्लिक में दोबारा चलाना CODE: A1: Name A2: Asha A3: Ravi A4: Asha A5: Meena Steps: click any cell in A1:A5 > Data tab > From Table/Range > OK > select the Name column > Home tab > Remove Rows > Remove Duplicates > Close & Load OUTPUT: A new sheet shows a table with three names: Asha, Ravi and Meena EXPLANATION: Power Query opens its own editor where each action becomes a step in the Applied Steps list on the right. When you choose Close & Load, the result is written to a sheet as a table. Your original data is not changed. SIMPLE EXPLANATION (HINGLISH): Power Query me aap ek baar saaf karne ke steps banate ho, aur Excel unhe yaad rakhta hai. Agli baar naya data aaye to Refresh All dabao aur wahi saare steps dobara chal jate hain. REAL-LIFE ANALOGY: Like a recipe card: you write the steps once and can cook the same dish again with new ingredients. SYNTAX PATTERN: Data tab > Get Data (or From Table/Range, or From Text/CSV) > Power Query Editor > Close & Load ANATOMY: Source = where the data comes from | Applied Steps = the list of recorded actions | Transform = clean-up actions like Remove Duplicates | Close & Load = write the result to a sheet | Refresh All = run all steps again EXAMPLE 1: Data tab > Get Data > From File > From Text/CSV > choose a CSV file > Load Result: the CSV rows appear in a new sheet as a table EXAMPLE 2: A1: Name A2: Asha A3: Ravi A4: Asha Click a cell > Data > From Table/Range > select Name column > Remove Rows > Remove Duplicates > Close & Load Result: Asha and Ravi, one time each EXAMPLE 3: Data tab > Get Data > Combine Queries > Append > choose two tables > OK > Close & Load Result: the rows of the second table are added below the first table in one list VARIATION: Data tab > Refresh All (Ctrl+Alt+F5) runs every query again Home tab > Merge Queries joins two tables like a lookup Click the cross next to a step in Applied Steps to delete that step USED WITH: Table (Ctrl+T), PivotTable, CSV files, Refresh All RELATED CONCEPTS: PivotTable, Text to Columns, Table (Ctrl+T) ALTERNATIVES: Manual clean-up, Text to Columns, Remove Duplicates on the Data tab, VBA macros FAMILY / GROUP: Power Query, Get & Transform, Applied Steps, Query, Refresh All, M language WHERE IT IS USED: Monthly CSV imports | Combining many files into one table | Cleaning exported data before a PivotTable MINI CONVERSATION: A: Every month I get a new export and clean the same columns by hand. | B: Record the clean-up in Power Query once, and next month just click Refresh All. COMMON MISTAKE: ✗ Power Query changes my original data table → ✓ It reads the source and writes a new result table, so the original data stays as it was COMMONLY CONFUSED WITH: Power Query vs a macro: Power Query records data-cleaning steps that refresh with new data, while a macro (VBA) records any clicks and keystrokes in Excel as code. AVOID / DON'T: Do not edit the loaded result table by hand, because the next refresh will overwrite your changes. WRONG CODE: Clean the new month's file by hand again, and then paste it over the old data every time RIGHT CODE: Load the file with Data > From Text/CSV, clean it in Power Query once, then use Data > Refresh All each month MEMORY TRICK: Power Query = record the clean-up once, replay it forever. REAL LIFE: PROJECT / WORK: An accountant loads a bank CSV every month, removes blank rows, changes the date type and refreshes the same query. REAL LIFE: INTERVIEW / EXAM: Interview: How would you combine twelve monthly files with the same columns into one table in Excel? REAL LIFE: DAILY LIFE: It is like a washing machine program: you choose the steps once and press start every week. | C41: 09_Analysis_Advanced_XL-040

Sheet Anki Quiz
A1: Front | B1: Back | C1: Tags
A2: MCQ: A sheet has A1 = 4, A2 = 6, A3 = 8 and A4 = 10. What does =SUM(A2:A4) return? A) 18 B) 24 C) 28 D) 30 FILL: The address of the cell in column C and row 3 is ____ HINDI TO TASK: Write a formula that adds the numbers in cells B2 down to B6. PRACTICE QUESTION: A1: 4 A2: 6 A3: 8 A4: 10 B1: =SUM(A2:A4) What does B1 show? | B2: MCQ answer: B A2:A4 covers A2, A3 and A4, so 6 + 8 + 10 = 24; 28 would include A1 only by mistake, and 30 is a different total. Fill answer: C3 Task answer: B7: =SUM(B2:B6) Practice answer: 24 | C2: 01_Basics_&_Cells_Beginner_XL-001_quiz
A3: MCQ: A cell shows 2500 on the left side of the cell, and SUM leaves it out. What is the most likely reason? A) It is stored as text B) It is formatted as currency C) It is stored as a date D) The column is too narrow FILL: Excel stores the date 1 January 2024 internally as the number ____ HINDI TO TASK: Write a formula that tells whether cell A1 holds a number. PRACTICE QUESTION: A1: 50 A2: '50 (text) A3: 50 B1: =SUM(A1:A3) What does B1 show? | B3: MCQ answer: A Numbers align right by default and SUM skips text; currency or date formats do not make SUM skip a value. Fill answer: 45292 Task answer: B1: =ISNUMBER(A1) Practice answer: 100 | C3: 01_Basics_&_Cells_Beginner_XL-002_quiz
A4: MCQ: A1 contains 5 and nothing else. You drag the fill handle from A1 down to A3 without pressing any key. What does A3 show? A) 3 B) 5 C) 7 D) 15 FILL: The small square at the bottom-right corner of a selected cell is called the ____ HINDI TO TASK: Fill the numbers 10, 20, 30, 40 in column A using only two typed cells. PRACTICE QUESTION: A1: 10 A2: 20 You select A1:A2 and drag the fill handle down to A4. What does A4 show? | B4: MCQ answer: B One plain number is copied, so A2 and A3 both show 5; counting needs two example cells or the Ctrl key. Fill answer: fill handle Task answer: A1: 10 A2: 20 Select A1:A2 and drag the fill handle down to A4 Practice answer: 40 | C4: 01_Basics_&_Cells_Beginner_XL-003_quiz
A5: MCQ: You used Flash Fill to get first names in column B. Later you change the name in A2. What happens to the value in B2? A) It updates by itself B) It turns into an error C) It stays as it was D) It is deleted FILL: The Windows shortcut for Flash Fill is Ctrl + ____ HINDI TO TASK: Column A has full names. Get only the first name in column B using Flash Fill. PRACTICE QUESTION: A1: Ravi Kumar A2: Sita Devi You type Ravi in B1, click B2 and press Ctrl+E. What does B2 show? | B5: MCQ answer: C Flash Fill pastes fixed values, not formulas, so B2 does not follow A2 afterwards. Fill answer: E Task answer: B1: type the first name by hand Click B2 and press Ctrl+E Practice answer: Sita | C5: 01_Basics_&_Cells_Beginner_XL-004_quiz
A6: MCQ: C2 holds =A2*B1. You copy C2 down to C3. What does C3 contain? A) =A3*B1 B) =A3*B2 C) =A2*B2 D) =A3*$B$1 FILL: To lock both the column and row of B1 in a formula, write ____ HINDI TO TASK: Price is in A2:A4 and the discount rate is in D1. Write the formula for C2 so it can be copied down. PRACTICE QUESTION: A1: 5 B2: 10 B3: 20 C2: =B2*$A$1 You copy C2 to C3. What does C3 show? | B6: MCQ answer: B Without dollar signs both references move down by one row, so A2 becomes A3 and B1 becomes B2. Fill answer: $B$1 Task answer: C2: =A2*$D$1 Practice answer: 100 | C6: 01_Basics_&_Cells_Beginner_XL-005_quiz
A7: MCQ: A1 = 2, A2 holds the text '3 (typed with an apostrophe) and A3 = 4. What does =SUM(A1:A3) show? A) 9 B) 6 C) #VALUE! D) 2 FILL: The Windows shortcut for AutoSum is Alt + ____ HINDI TO TASK: Add the numbers in A1 to A2 and also B2 in one formula. PRACTICE QUESTION: A1: 12 A2: 8 B1: 5 B2: 15 C1: =SUM(A1:A2,B2) What does C1 show? | B7: MCQ answer: B SUM skips text inside a range, so only 2 and 4 are added; 9 would count the text as 3. Fill answer: = Task answer: C1: =SUM(A1:A2,B2) Practice answer: 35 | C7: 02_Basic_Functions_Beginner_XL-006_quiz
A8: MCQ: Cells A1, A2, A3 hold 50, 0 (typed zero) and 100. What does =AVERAGE(A1:A3) show? A) 75 B) 50 C) 150 D) 0 FILL: The function that returns the biggest number in a range is ____ HINDI TO TASK: Find the lowest mark in cells A1 to A5 using a formula. PRACTICE QUESTION: A1: 4 A2: 8 A3: (empty) A4: 12 B1: =AVERAGE(A1:A4) What does B1 show? | B8: MCQ answer: B The zero counts as a value, so the total 150 is divided by 3 giving 50; 75 would ignore the zero. Fill answer: MAX Task answer: B1: =MIN(A1:A5) Practice answer: 8 | C8: 02_Basic_Functions_Beginner_XL-007_quiz
A9: MCQ: A1 = 5, A2 = Amit, A3 is empty and A4 = 9. What does =COUNT(A1:A4) return? A) 4 B) 3 C) 2 D) 1 FILL: The function that counts empty cells in a range is ____ HINDI TO TASK: Count how many cells from A1 to A10 contain anything at all. PRACTICE QUESTION: A1: 7 A2: hello A3: (empty) A4: 3 A5: (empty) B1: =COUNTA(A1:A5)-COUNT(A1:A5) What does B1 show? | B9: MCQ answer: C COUNT counts only numbers, so 5 and 9 give 2; 3 would be COUNTA, which also counts the name. Fill answer: COUNTBLANK Task answer: B1: =COUNTA(A1:A10) Practice answer: 1 | C9: 02_Basic_Functions_Beginner_XL-008_quiz
A10: MCQ: What does the formula =ROUNDDOWN(-3.7,0) return? A) -4 B) -3 C) -3.7 D) 0 FILL: =ROUND(1234,-2) gives ____ HINDI TO TASK: Round the number in A1 to one decimal place and always upwards. PRACTICE QUESTION: A1: 15.249 B1: =ROUNDUP(A1,1) What does B1 show? | B10: MCQ answer: B ROUNDDOWN moves toward zero, so -3.7 becomes -3; -4 would be ROUNDUP, which moves away from zero. Fill answer: 1200 Task answer: B1: =ROUNDUP(A1,1) Practice answer: 15.3 | C10: 02_Basic_Functions_Beginner_XL-009_quiz
A11: MCQ: You type 25% directly into an empty cell. What value does Excel store in that cell? A) 25 B) 0.25 C) 2.5 D) 0.025 FILL: The Windows shortcut to apply Percentage format is Ctrl+Shift+____ HINDI TO TASK: Make the number 1234.5 in cell A1 appear as currency with two decimals. PRACTICE QUESTION: A1: 0.07 Select A1 and press Ctrl+Shift+5. What does A1 show? | B11: MCQ answer: B Excel stores a percent as a fraction of 1, so 25% is 0.25; the % sign is only how it is displayed. Fill answer: 5 Task answer: Select A1 and press Ctrl+Shift+4 Practice answer: 7% | C11: 03_Formatting_&_Organising_Beginner_XL-010_quiz
A12: MCQ: You select only column B (Marks) in a Name and Marks table and sort it, choosing Continue with the current selection. What happens to the names in column A? A) They move together with the marks B) They stay where they were, so names no longer match marks C) They are sorted A to Z as well D) Excel deletes them FILL: To keep names with their marks, choose ____ the selection when Excel asks HINDI TO TASK: Make a small list of three items with prices and put it in order from the lowest price to the highest. PRACTICE QUESTION: A1: Item, B1: Price. A2: Pen 20, A3: Book 50, A4: Ink 5. You click B2 and use Data tab > Sort Smallest to Largest. In what order do the items appear from row 2 to row 4? | B12: MCQ answer: B Continue with the current selection sorts only the selected cells, so column A is untouched and the rows no longer match. Fill answer: Expand Task answer: A1: Item B1: Price A2: Pen B2: 20 A3: Book B3: 50 A4: Ink B4: 5 Steps: click B2 > Data tab > Sort Smallest to Largest Result: Ink 5, Pen 20, Book 50 Practice answer: Ink, Pen, Book (prices 5, 20, 50) | C12: 03_Formatting_&_Organising_Beginner_XL-011_quiz
... A41: MCQ: A query already loads a CSV file. Next month the CSV file has new rows in the same place. What is the fastest way to bring them into the sheet? A) Data tab > Refresh All B) Repeat all steps by hand C) Delete the query D) Press F9 FILL: In Power Query, the list of recorded actions on the right is called ____ Steps HINDI TO TASK: Load a table into Power Query and remove duplicate names, then load it back to a sheet. PRACTICE QUESTION: A1: Name, A2: Asha, A3: Ravi, A4: Asha, A5: Meena You load it in Power Query, remove duplicates on Name and click Close & Load. How many names are in the loaded table, not counting the heading? | B41: MCQ answer: A Refresh All runs the saved steps again on the changed source. F9 recalculates formulas but does not refresh a query. Fill answer: Applied Task answer: Click a cell in the table > Data tab > From Table/Range > OK > select Name column > Home tab > Remove Rows > Remove Duplicates > Close & Load Practice answer: 3 | C41: 09_Analysis_Advanced_XL-040_quiz

Sheet Summary
A1: Cards by type
A2: Code concept (56-pt) | B2: 40
A4: Cards by topic
A5: 03 Formatting & Organising | B5: 9
A6: 01 Basics & Cells | B6: 5
A7: 04 Logic | B7: 5
A8: 07 Text | B8: 5
A9: 09 Analysis | B9: 5
A10: 02 Basic Functions | B10: 4
A11: 06 Lookup | B11: 3
A12: 05 Conditional Maths | B12: 2
A13: 08 Dates | B13: 2
A15: Cards by level
A16: Beginner | B16: 18
A17: Intermediate | B17: 18
A18: Advanced | B18: 4
A20: Cards by source
A21: Claude knowledge | B21: 40
A23: Error check
A24: 0 errors, 0 warnings
