Workbook

Sheet Read Me
A1: CI/CD – Beginner to Advanced Flashcards
A2: Subject: CI/CD and GitHub Actions · Learner: Self learner, English · Cards: 40
A3: Source: Claude knowledge
A5: How to study a card
A6: 1. Read Side 1 only. Try to say the meaning, answer or formula out loud before looking further.
A7: 2. Check yourself against Side 2. Read the examples and the common mistake.
A8: 3. Do the practice on Side 3 without looking back. Then mark Status: New → Learning → Known.
A9: 4. Review on days 1, 3, 7, 15, 30, 60 after first study: write the date or ✓ in that day's column.
A10: Got it wrong on a review? Start that card's days again from Day 1.
A11: 5. Follow 'Study order': prerequisites come first, then easy to hard.
A13: Colours
A14: Shaded cells were added by Claude, not taken from your own book or notes. Check them against a trusted source,
A15: and mark the card 'Fix' in the OK / Fix column if anything is wrong. Unshaded cells came from your source.

Sheet Code concept (56-pt) cards
A1: Card | F1: Side 1 · Recognition | R1: Side 2 · Understanding | AT1: Side 3 · Real life & Practice | BD1: Auto | BF1: My review
A2: ID | B2: Topic | C2: Level | D2: Study order | E2: Source | F2: Concept | G2: Recall cue | H2: Read aloud | I2: Type | J2: How often used | K2: Importance (1-5) | L2: Origin / why it exists | M2: Pro tip | N2: Typing hint | O2: Memory story | P2: Picture it | Q2: Emotion hook | R2: Meaning (short) | S2: Meaning in learner's language | T2: Code | U2: Output | V2: Explanation | W2: Simple explanation (Hinglish) | X2: Real-life analogy | Y2: Syntax pattern | Z2: Anatomy | AA2: Example 1 | AB2: Example 2 | AC2: Example 3 | AD2: Variation | AE2: Used with | AF2: Related concepts | AG2: Alternatives | AH2: Family / group | AI2: Where it is used | AJ2: Mini conversation | AK2: Common mistake | AL2: Commonly confused with | AM2: Avoid / don't | AN2: Wrong code | AO2: Right code | AP2: Memory trick | AQ2: Real life: project / work | AR2: Real life: interview / exam | AS2: Real life: daily life | AT2: MCQ question | AU2: MCQ options | AV2: MCQ answer | AW2: Why that answer | AX2: Fill the blank | AY2: Try it yourself | AZ2: Task answer | BA2: Write your own | BB2: Practice question | BC2: Practice answer | BD2: Importance ★ | BE2: Quick recall (reverse) | BF2: Status | BG2: Day 1 | BH2: Day 3 | BI2: Day 7 | BJ2: Day 15 | BK2: Day 30 | BL2: Day 60 | BM2: OK / Fix | BN2: My note
A3: CICD-007 | B3: 02 GitHub Actions | C3: Beginner | D3: 7 | E3: Claude knowledge | F3: Workflow file | G3: Which YAML file in your repository defines an automated GitHub Actions process? | I3: GitHub Actions concept | J3: Very high | K3: 5 | L3: Automation needs to live with the code and be reviewed like code, so GitHub reads workflow definitions from a folder in the repository. | M3: Keep workflows small and named clearly, one purpose per file. | O3: The workflow file is a recipe card stored in the cookbook beside the code. | P3: A YAML file under .github/workflows triggering a run. | Q3: The thrill of your first green check. | R3: A workflow is a YAML file in .github/workflows that names its triggers and the jobs to run. | T3: name: CI on: pull_request: push: branches: [main] jobs: test: runs-on: ubuntu-latest steps: - uses: actions/checkout@v4 - run: npm test | U3: On each pull request and each push to main, a runner starts, checks out the code and runs the tests. | V3: The file must be inside .github/workflows and end in .yml or .yaml. The on key lists triggers, and jobs defines the work. Each job runs on a runner named by runs-on. Steps either run shell commands with run or use a packaged action with uses. Results appear in the Actions tab and on the pull request. | W3: Write a YAML file with a trigger and jobs, commit it, and GitHub runs it for you. | X3: It is a recipe card kept in the cookbook beside the code. | Y3: name: / on: / jobs: <id>: runs-on: / steps: | Z3: name = label | on = triggers | jobs = work units | runs-on = machine | steps = commands | AA3: on: workflow_dispatch | AB3: on: { schedule: [{ cron: "0 2 * * *" }] } | AC3: on: { push: { tags: ["v*"] } } | AD3: on: [push, pull_request] // shorthand for two triggers | AE3: runners, secrets, actions, branch protection | AF3: jobs and steps, runners, triggers, reusable workflows | AG3: GitLab CI files | Jenkinsfiles | AI3: Testing | Building | Deploying | AJ3: A: Nothing runs after my push. | B: The file must be in .github/workflows. | AK3: ✗ A workflow file can live anywhere in the repo → ✓ It must be inside .github/workflows to be detected | AL3: Workflow vs job: a workflow is the whole file, a job is one unit of work inside it. | AM3: Do not use tabs in YAML. | AN3: .github/workflow/ci.yml | AO3: .github/workflows/ci.yml | AP3: Folder name ends with an s. | AQ3: Adding a first workflow that ran the unit tests on every pull request. | AR3: An interviewer may ask: Where do GitHub Actions workflows live? | AS3: It is like a recipe card kept beside the code. | AT3: Which folder holds workflow files? | AU3: A) .actions B) .github/workflows C) .github/workflow D) workflows | AV3: B | AW3: GitHub only reads workflows from .github/workflows. | AX3: The key that lists the events that start a workflow is ____ → on | AY3: Write a trigger that runs on pull requests. | AZ3: on: pull_request: | BA3: Create a workflow that runs echo hello on every push. | BB3: What file extensions can a workflow use? | BC3: .yml or .yaml | BD3: =IF(K3="","",REPT("★",K3)&REPT("☆",5-K3)&" ("&K3&"/5)") | BE3: =IF(S3="","","Meaning: "&S3&" = ______ (Answer: "&F3&")") | BF3: New
A4: CICD-008 | B4: 02 GitHub Actions | C4: Beginner | D4: 8 | E4: Claude knowledge | F4: Jobs and steps | G4: How are the work units inside a workflow organised and ordered? | I4: GitHub Actions concept | J4: Very high | K4: 5 | L4: One long script is hard to read and reuse, so work is split into jobs, which hold ordered steps. | M4: Use needs to chain jobs, otherwise they run at the same time. | O4: Jobs are workstations, and steps are the tasks done at each one. | P4: Two job boxes with an arrow between them and steps inside. | Q4: The tidy feeling of a clear pipeline layout. | R4: A job is a group of steps that run on one runner, and jobs run in parallel unless one declares needs on another. | T4: jobs: build: runs-on: ubuntu-latest steps: - uses: actions/checkout@v4 - run: make build deploy: needs: build runs-on: ubuntu-latest steps: - run: echo deploying | U4: The build job runs first, and the deploy job starts only after it succeeds. | V4: Every job gets a fresh runner, so files do not carry over between jobs unless you upload and download artifacts. Steps inside a job run in order and share the file system. A failing step stops the job. Use if conditions to run a step only in some cases. Job outputs can pass small values to later jobs. | W4: Jobs run on separate machines, steps run in order inside a job, and needs links jobs. | X4: Jobs are workstations, and steps are the tasks done at each one. | Y4: jobs: <id>: needs: [other] steps: - run: command | Z4: jobs = units of work | needs = dependency | steps = ordered tasks | if = condition | AA4: needs: [lint, test] | AB4: if: github.ref == 'refs/heads/main' | AC4: outputs: version: ${{ steps.v.outputs.version }} | AD4: continue-on-error: true // let one step fail without stopping the job | AE4: artifacts, outputs, conditions | AF4: workflow file, runners, artifacts, matrix | AG4: Stages in other CI tools | AI4: Multi-stage pipelines | Parallel testing | Releases | AJ4: A: The deploy job cannot find my build output. | B: Jobs do not share files, so upload and download an artifact. | AK4: ✗ Jobs in one workflow share the same file system → ✓ Each job runs on its own fresh runner | AL4: needs vs steps order: needs orders jobs, steps order tasks inside a job. | AM4: Do not assume files from one job exist in the next. | AN4: deploy: runs-on: ubuntu-latest # runs at the same time as build | AO4: deploy: needs: build runs-on: ubuntu-latest | AP4: Needs chains jobs, steps stay in a job. | AQ4: Splitting lint, test and deploy into chained jobs so failures showed up clearly. | AR4: An interviewer may ask: How do you make one job wait for another? | AS4: It is like workstations with ordered tasks at each. | AT4: How do you make a job wait for another job? | AU4: A) after B) wait C) depends D) needs | AV4: D | AW4: The needs key declares job dependencies. | AX4: Jobs run in ____ by default unless chained → parallel | AY4: Make the deploy job wait for the test job. | AZ4: deploy: needs: test | BA4: Write two jobs where the second runs only if the first passes. | BB4: Do two jobs share a file system? | BC4: No, each job has its own runner. | BD4: =IF(K4="","",REPT("★",K4)&REPT("☆",5-K4)&" ("&K4&"/5)") | BE4: =IF(S4="","","Meaning: "&S4&" = ______ (Answer: "&F4&")") | BF4: New
A5: CICD-009 | B5: 02 GitHub Actions | C5: Beginner | D5: 9 | E5: Claude knowledge | F5: Runners | G5: Which machines actually execute the jobs of a workflow? | I5: GitHub Actions concept | J5: High | K5: 4 | L5: Jobs need computers to run on, so GitHub offers hosted machines and lets you register your own. | M5: Pin a specific runner image version if a new image could break your build. | O5: A runner is the worker who walks up to your job card and does it. | P5: A job card going to a machine labelled ubuntu-latest. | Q5: The ease of a clean machine for every run. | R5: A runner is a machine that runs a job, either GitHub-hosted with a fresh virtual machine each time, or self-hosted on your own infrastructure. | T5: jobs: test: runs-on: ubuntu-latest mac-build: runs-on: macos-14 internal: runs-on: [self-hosted, linux] | U5: Three jobs go to a hosted Linux machine, a hosted macOS machine and one of your own Linux runners. | V5: Hosted runners start clean for each job and include common tools. Minutes are free or paid depending on the plan, and macOS costs more than Linux. Self-hosted runners suit private networks or special hardware, but you must secure and update them. Labels in runs-on choose which runner is used. | W5: Choose hosted runners for convenience and self-hosted ones for private access or special hardware. | X5: A runner is the worker who picks up your job card and does it. | Y5: runs-on: ubuntu-latest | runs-on: [self-hosted, label] | Z5: ubuntu-latest = hosted Linux | macos-14 = hosted Mac | self-hosted = your machine | labels = selectors | AA5: runs-on: ubuntu-22.04 | AB5: runs-on: windows-latest | AC5: runs-on: [self-hosted, gpu] | AD5: runs-on: ubuntu-latest-4-cores // a larger hosted runner | AE5: matrix, caching, cost | AF5: workflow file, matrix builds, self-hosted runners, caching | AG5: Other CI agents | AI5: All workflows | Cross-platform builds | Private networks | AJ5: A: The job needs our internal database. | B: Use a self-hosted runner inside the network. | AK5: ✗ Hosted runners keep files between runs → ✓ Each job starts on a fresh machine | AL5: Hosted vs self-hosted: hosted are managed by GitHub, self-hosted are managed by you. | AM5: Do not use self-hosted runners for public repositories without protection. | AN5: runs-on: ubuntu | AO5: runs-on: ubuntu-latest | AP5: Latest label picks the current image. | AQ5: Using a self-hosted runner so tests could reach a customer's private test database. | AR5: An interviewer may ask: When would you use a self-hosted runner? | AS5: It is like a worker who picks up each job card. | AT5: What starts fresh for every hosted job? | AU5: A) The branch B) The repository C) The secrets D) The runner machine | AV5: D | AW5: Hosted runners are new virtual machines per job. | AX5: The key that picks the machine for a job is ____ → runs-on | AY5: Run a job on a hosted Windows machine. | AZ5: runs-on: windows-latest | BA5: Write a runs-on value for a self-hosted Linux runner with a GPU. | BB5: Why do self-hosted runners need extra care? | BC5: You must secure and update them, and untrusted code could run on them. | BD5: =IF(K5="","",REPT("★",K5)&REPT("☆",5-K5)&" ("&K5&"/5)") | BE5: =IF(S5="","","Meaning: "&S5&" = ______ (Answer: "&F5&")") | BF5: New
A6: CICD-010 | B6: 02 GitHub Actions | C6: Intermediate | D6: 10 | E6: Claude knowledge | F6: Matrix builds | G6: Which feature runs the same job across several versions or systems automatically? | I6: GitHub Actions concept | J6: High | K6: 4 | L6: Libraries must work on many versions, so repeating a job by hand for each combination was replaced by a matrix. | M6: Use exclude to skip combinations that are not supported, and fail-fast to stop early. | O6: A matrix is a grid of test tubes, each holding one combination. | P6: A grid of versions against operating systems with green ticks. | Q6: The confidence of testing many versions at once. | R6: A matrix strategy creates one job for each combination of the listed values, and runs them in parallel. | T6: jobs: test: runs-on: ${{ matrix.os }} strategy: matrix: os: [ubuntu-latest, windows-latest] python: ["3.11", "3.12"] steps: - uses: actions/setup-python@v5 with: python-version: ${{ matrix.python }} | U6: Four jobs run, one for each operating system and Python version combination. | V6: Values are read with the matrix context, such as matrix.os. Two lists of two values produce four jobs. The exclude key removes combinations, and include adds special ones. By default fail-fast cancels the other jobs when one fails, which can be turned off. Each matrix job counts towards the concurrency and minutes used. | W6: List the versions and systems once, and Actions makes a job for each combination. | X6: It is a grid of test tubes, each holding one combination. | Y6: strategy: matrix: key: [values] | Z6: strategy = how to run | matrix = lists | exclude = remove combos | fail-fast = stop on first failure | AA6: matrix: node: [20, 22, 24] | AB6: exclude: [{ os: windows-latest, python: "3.11" }] | AC6: fail-fast: false | AD6: max-parallel: 2 // limit simultaneous jobs | AE6: runners, caching, setup actions | AF6: runners, jobs and steps, caching, quality gates | AG6: Separate hand-written jobs | AI6: Libraries | Cross-platform apps | Compatibility tests | AJ6: A: Do we support Python 3.11 and 3.12? | B: The matrix tests both on every pull request. | AK6: ✗ Matrix jobs run one after the other → ✓ They run in parallel, within your concurrency limits | AL6: Matrix vs needs: a matrix repeats a job, needs orders different jobs. | AM6: Do not make a huge matrix that burns minutes without need. | AN6: python-version: 3.10 | AO6: python-version: "3.10" | AP6: Quote versions so 3.10 stays 3.10. | AQ6: Testing a customer library against three Python versions with one matrix. | AR6: An interviewer may ask: How would you test on several versions? | AS6: It is like a grid of test tubes. | AT6: Two operating systems and three versions give how many jobs? | AU6: A) 3 B) 6 C) 5 D) 2 | AV6: B | AW6: Two times three combinations are created. | AX6: The key that removes a combination from the grid is ____ → exclude | AY6: Test on Node 20 and 22. | AZ6: strategy: matrix: node: [20, 22] | BA6: Add a matrix of two operating systems to a test job. | BB6: What does fail-fast do? | BC6: It cancels other matrix jobs when one fails. | BD6: =IF(K6="","",REPT("★",K6)&REPT("☆",5-K6)&" ("&K6&"/5)") | BE6: =IF(S6="","","Meaning: "&S6&" = ______ (Answer: "&F6&")") | BF6: New
A7: CICD-011 | B7: 02 GitHub Actions | C7: Intermediate | D7: 11 | E7: Claude knowledge | F7: Caching dependencies | G7: How do you avoid downloading the same packages on every run? | I7: GitHub Actions concept | J7: High | K7: 4 | L7: Installing dependencies is often the slowest step, so Actions can save and restore folders between runs. | M7: Key the cache on a hash of the lockfile so it refreshes only when dependencies change. | O7: A cache is a lunch box packed once and reused all week. | P7: A package folder saved after one run and restored in the next. | Q7: The joy of a build that drops from five minutes to one. | R7: The cache action stores files under a key and restores them in later runs when the key matches. | T7: - uses: actions/cache@v4 with: path: ~/.npm key: npm-${{ hashFiles('package-lock.json') }} restore-keys: npm- | U7: The first run saves the npm cache, and later runs with the same lockfile restore it in seconds. | V7: The key must change when the contents should change, which is why a hash of the lockfile is used. restore-keys gives a fallback prefix when there is no exact match. Caches belong to a branch scope, so feature branches can read the main branch cache. Caches that are not accessed for a while are removed, and there is a total size limit per repository. Many setup actions have a built-in cache option. | W7: Cache the package folder with a key built from the lockfile. | X7: A cache is a lunch box packed once and reused all week. | Y7: uses: actions/cache@v4 with: path, key, restore-keys | Z7: path = what to save | key = exact match | restore-keys = fallback prefixes | AA7: uses: actions/setup-node@v4 with: { node-version: 22, cache: npm } | AB7: key: pip-${{ hashFiles('requirements.txt') }} | AC7: path: ~/.cache/pip | AD7: enableCrossOsArchive: true // share a cache between systems | AE7: setup actions, matrix, lockfiles | AF7: runners, jobs and steps, build artifacts, matrix builds | AG7: Docker layer cache | AI7: Slow installs | Large projects | Cost saving | AJ7: A: Every run reinstalls everything. | B: Add a cache keyed on the lockfile. | AK7: ✗ A cache and an artifact are the same thing → ✓ A cache speeds up repeated work, an artifact passes results to people or later jobs | AL7: Cache vs artifact: caches are for speed, artifacts are for results. | AM7: Do not cache secrets or build outputs that must be fresh. | AN7: key: npm-cache | AO7: key: npm-${{ hashFiles('package-lock.json') }} | AP7: Hash the lockfile to refresh the cache. | AQ7: Cutting build time by caching pip downloads keyed on the requirements file. | AR7: An interviewer may ask: How do you speed up a slow dependency install? | AS7: It is like a lunch box packed once. | AT7: Why include a lockfile hash in the key? | AU7: A) It deletes old runs B) It encrypts the cache C) The cache refreshes when dependencies change D) It speeds the network | AV7: C | AW7: A new hash makes a new key and a fresh cache. | AX7: A fallback prefix for a partial cache match is set with ____-keys → restore | AY7: Cache the pip folder using the requirements file as key. | AZ7: - uses: actions/cache@v4 with: path: ~/.cache/pip key: pip-${{ hashFiles('requirements.txt') }} | BA7: Write a cache step for a Node project using npm. | BB7: Why can feature branches use the main branch cache? | BC7: Caches from the default branch are readable by other branches. | BD7: =IF(K7="","",REPT("★",K7)&REPT("☆",5-K7)&" ("&K7&"/5)") | BE7: =IF(S7="","","Meaning: "&S7&" = ______ (Answer: "&F7&")") | BF7: New
A8: CICD-012 | B8: 02 GitHub Actions | C8: Intermediate | D8: 12 | E8: Claude knowledge | F8: Artifacts in workflows | G8: How do you keep files from one job and pass them to another or download them later? | I8: GitHub Actions concept | J8: High | K8: 4 | L8: Jobs run on separate machines, so results must be uploaded and downloaded explicitly. | M8: Set a short retention for large artifacts to save storage. | O8: An artifact is a parcel posted from one workstation to another. | P8: A box uploaded after build and downloaded before deploy. | Q8: The relief when the deploy job finally finds the build output. | R8: upload-artifact stores files from a job, and download-artifact retrieves them in a later job or lets you download them from the run page. | T8: - uses: actions/upload-artifact@v4 with: name: dist path: dist/ retention-days: 7 # later job - uses: actions/download-artifact@v4 with: name: dist | U8: The dist folder is stored for seven days and appears again in the later job. | V8: Artifacts are attached to the workflow run. They are useful for build outputs, test reports and logs. Unlike a cache, an artifact is meant for results, and it can be downloaded by people with access. Names must be unique within a run when using version 4. Large artifacts cost storage, so set retention. | W8: Upload at the end of a job, download at the start of the next. | X8: It is a parcel posted from one workstation to another. | Y8: actions/upload-artifact@v4 with: name, path, retention-days | Z8: name = label | path = files | retention-days = how long kept | AA8: name: coverage-report | AB8: path: | dist/ reports/ | AC8: if: always() // upload even when the tests fail | AD8: if-no-files-found: error // fail if nothing matched | AE8: needs, build jobs, test reports | AF8: jobs and steps, caching, build artifacts, reports | AG8: Container registries for images | AI8: Passing builds | Test reports | Debugging | AJ8: A: Tests failed and I cannot see the report. | B: Upload it with if: always() so it exists on failure. | AK8: ✗ Artifacts are shared automatically between jobs → ✓ You must upload and download them explicitly | AL8: Artifact vs cache: artifacts carry results, caches speed up repeated work. | AM8: Do not upload secrets inside artifacts. | AN8: - uses: actions/upload-artifact@v4 with: name: dist # path is missing, so the step fails | AO8: - uses: actions/upload-artifact@v4 with: name: dist path: dist/ | AP8: Always name the parcel you upload. | AQ8: Uploading test reports even on failure so reviewers could inspect them. | AR8: An interviewer may ask: How do you pass files between jobs? | AS8: It is like posting a parcel between workstations. | AT8: Which condition uploads a report even when tests fail? | AU8: A) always() B) never() C) success() D) once() | AV8: A | AW8: always() runs the step regardless of earlier failures. | AX8: How long a file is stored is set by ____-days → retention | AY8: Upload the reports folder under the name reports. | AZ8: - uses: actions/upload-artifact@v4 with: name: reports path: reports/ | BA8: Add a step that uploads a coverage report even on failure. | BB8: Why set retention-days? | BC8: To save storage by deleting old artifacts. | BD8: =IF(K8="","",REPT("★",K8)&REPT("☆",5-K8)&" ("&K8&"/5)") | BE8: =IF(S8="","","Meaning: "&S8&" = ______ (Answer: "&F8&")") | BF8: New
A9: CICD-013 | B9: 02 GitHub Actions | C9: Intermediate | D9: 13 | E9: Claude knowledge | F9: Secrets in workflows | G9: How do you give a workflow a password or token without putting it in the code? | I9: GitHub Actions concept | J9: Very high | K9: 5 | L9: Credentials in a repository leak, so GitHub stores encrypted secrets and injects them only into runs. | M9: Prefer short-lived tokens through OIDC over stored long-lived secrets. | O9: A secret is a sealed envelope handed to the job only when it runs. | P9: A key icon feeding a masked value into a step. | Q9: The peace of keeping tokens out of the code. | R9: Repository, environment and organisation secrets are encrypted values that workflows read with the secrets context, and logs mask them. | T9: steps: - run: ./deploy.sh env: API_TOKEN: ${{ secrets.API_TOKEN }} | U9: The script receives the token as an environment variable, and the log shows *** instead of the value. | V9: Secrets are set in repository settings and cannot be read back. They are not passed to workflows triggered from forks by default. Masking only hides exact values, so printing a transformed secret may reveal it. Environment secrets are available only to jobs that use that environment. Scope each secret as narrowly as you can. | W9: Store the value in settings, read it with the secrets context, and never print it. | X9: A secret is a sealed envelope handed to the job only when it runs. | Y9: ${{ secrets.NAME }} | Z9: secrets = context | NAME = secret name | env = pass to a step | AA9: password: ${{ secrets.DB_PASSWORD }} | AB9: gh secret set API_TOKEN | AC9: environment: production // unlocks environment secrets | AD9: with: token: ${{ secrets.GITHUB_TOKEN }} // the built-in short-lived token | AE9: environments, OIDC, least privilege | AF9: environments and approvals, OIDC, permissions, secret scanning | AG9: OIDC | External secret managers | AI9: Deployments | API calls | Registries | AJ9: A: Can I echo the token to debug? | B: No, never print secrets, even masked ones. | AK9: ✗ Masking makes it safe to print secrets in logs → ✓ Masking is a safety net, and printing secrets is still dangerous | AL9: Secret vs variable: secrets are encrypted and masked, variables are plain configuration. | AM9: Do not pass secrets to workflows that run untrusted code. | AN9: env: API_TOKEN: abc123 | AO9: env: API_TOKEN: ${{ secrets.API_TOKEN }} | AP9: Never print, never commit, always scope. | AQ9: Moving a registry password from a script into an environment secret. | AR9: An interviewer may ask: How do you handle credentials in GitHub Actions? | AS9: It is like a sealed envelope handed over at run time. | AT9: How do you read a secret named TOKEN in a workflow? | AU9: A) The secrets context written with double braces B) A plain text file C) The repository README D) A bare dollar variable only | AV9: A | AW9: The secrets context exposes stored secrets to steps. | AX9: Secret values in logs are replaced with ____ → *** | AY9: Pass the secret API_TOKEN to a step as an environment variable. | AZ9: env: API_TOKEN: ${{ secrets.API_TOKEN }} | BA9: Write a step that uses a database password from secrets. | BB9: Are secrets passed to workflows from forks by default? | BC9: No, they are withheld for safety. | BD9: =IF(K9="","",REPT("★",K9)&REPT("☆",5-K9)&" ("&K9&"/5)") | BE9: =IF(S9="","","Meaning: "&S9&" = ______ (Answer: "&F9&")") | BF9: New
A10: CICD-014 | B10: 02 GitHub Actions | C10: Advanced | D10: 14 | E10: Claude knowledge | F10: Environments and approvals | G10: How do you protect a deployment target with rules and a required reviewer? | I10: GitHub Actions concept | J10: High | K10: 5 | L10: Production deployments need a human check and their own secrets, so GitHub lets you define protected environments. | M10: Give each environment its own secrets, and require approval only for production. | O10: An environment is a locked gate with a guard who asks for a signature. | P10: A job stopping at a gate until a reviewer clicks approve. | Q10: The assurance that nothing reaches production by accident. | R10: An environment is a named deployment target in repository settings that can require reviewers, wait timers, branch limits and its own secrets. | T10: jobs: deploy: runs-on: ubuntu-latest environment: name: production url: https://app.example.com steps: - run: ./deploy.sh | U10: The job pauses until a required reviewer approves, then runs with the production secrets. | V10: Protection rules are configured in settings, not in the YAML. The job waits for approval before any step runs. Deployment history is recorded for each environment. Branch rules can allow only main to deploy to production. This gives delivery with a manual gate, as opposed to full deployment. | W10: Name the environment in the job, and set reviewers and secrets in settings. | X10: It is a locked gate with a guard who asks for a signature. | Y10: environment: name: production url: ... | Z10: environment = target name | url = link shown in UI | rules = set in settings | AA10: environment: staging | AB10: environment: { name: production } | AC10: concurrency: production // one deployment at a time | AD10: environment: ${{ inputs.target }} // choose at run time | AE10: secrets, reviewers, branches | AF10: environments, secrets in workflows, deployment strategies, permissions | AG10: Manual release scripts | AI10: Production deploys | Compliance | Staging | AJ10: A: Can anyone deploy to production? | B: No, it needs a reviewer to approve. | AK10: ✗ Approval rules are written in the workflow YAML → ✓ They are configured in the environment's settings | AL10: Environment secret vs repository secret: environment secrets are only for jobs using that environment. | AM10: Do not let feature branches deploy to production. | AN10: deploy: environment: prod # a typo here silently creates a new, unprotected environment | AO10: deploy: environment: production | AP10: Rules live in settings, name lives in YAML. | AQ10: Adding a production environment with a required approver after a bad release. | AR10: An interviewer may ask: How do you add a manual approval to a deployment? | AS10: It is like a gate with a guard. | AT10: Where are required reviewers configured? | AU10: A) In the Dockerfile B) In the README C) In the environment settings D) In package.json | AV10: C | AW10: Environment protection rules are managed in repository settings. | AX10: A named deployment target in GitHub is called an ____ → environment | AY10: Make a job deploy to the production environment. | AZ10: environment: production | BA10: Write a deploy job that targets staging with a URL. | BB10: What does a required reviewer do? | BC10: They must approve before the job runs. | BD10: =IF(K10="","",REPT("★",K10)&REPT("☆",5-K10)&" ("&K10&"/5)") | BE10: =IF(S10="","","Meaning: "&S10&" = ______ (Answer: "&F10&")") | BF10: New
A11: CICD-015 | B11: 02 GitHub Actions | C11: Advanced | D11: 15 | E11: Claude knowledge | F11: Reusable workflows | G11: How do you share one workflow across many repositories or jobs? | I11: GitHub Actions concept | J11: Medium | K11: 4 | L11: Copying the same steps into every repository leads to drift, so a workflow can be called like a function. | M11: Pin the called workflow to a tag or commit, not a moving branch. | O11: A reusable workflow is a shared recipe that other kitchens can cook from. | P11: Many callers pointing to one central workflow file. | Q11: The satisfaction of fixing something once for every repository. | R11: A reusable workflow uses the workflow_call trigger, so other workflows can call it with inputs and secrets. | T11: # .github/workflows/test.yml on: workflow_call: inputs: node: { type: string, default: "20" } # caller jobs: ci: uses: acme/shared/.github/workflows/test.yml@v1 with: { node: "22" } | U11: The caller runs the shared test workflow with Node 22 without copying any steps. | V11: The called workflow defines inputs and secrets under workflow_call. The caller uses the uses key at the job level with a path and a version. Secrets can be passed explicitly or inherited. Outputs can return values. A composite action is another reuse option, for sharing steps instead of whole jobs. | W11: Write the workflow once with workflow_call, and call it from other workflows with inputs. | X11: It is a shared recipe that other kitchens can cook from. | Y11: on: workflow_call: | uses: owner/repo/.github/workflows/file.yml@ref | Z11: workflow_call = makes it callable | inputs = parameters | uses = call it | @ref = version | AA11: secrets: inherit | AB11: uses: ./.github/workflows/test.yml | AC11: outputs: image: ${{ jobs.build.outputs.image }} | AD11: uses: acme/actions/setup@v2 // reuse steps with a composite action | AE11: versions, inputs, organisations | AF11: workflow file, jobs and steps, pinning actions, permissions | AG11: Composite actions | Copy and paste | AI11: Organisations | Many repositories | Standard pipelines | AJ11: A: Twenty repositories have slightly different test workflows. | B: Move it into one reusable workflow. | AK11: ✗ A reusable workflow is the same as a composite action → ✓ A workflow reuses whole jobs, and a composite action reuses steps | AL11: Reusable workflow vs composite action: jobs versus steps. | AM11: Do not call a shared workflow from a moving branch name. | AN11: uses: acme/shared/.github/workflows/test.yml@main | AO11: uses: acme/shared/.github/workflows/test.yml@v1 | AP11: Version your shared workflows like software. | AQ11: Replacing twelve copied test workflows with one reusable workflow. | AR11: An interviewer may ask: How would you standardise CI across many repositories? | AS11: It is like a shared recipe for many kitchens. | AT11: Which trigger makes a workflow callable? | AU11: A) schedule B) release C) push D) workflow_call | AV11: D | AW11: workflow_call lets other workflows invoke it. | AX11: A callable workflow declares its parameters as ____ → inputs | AY11: Call the shared workflow test.yml at version v1 from the acme/shared repo. | AZ11: jobs: ci: uses: acme/shared/.github/workflows/test.yml@v1 | BA11: Add an input called node to a reusable workflow. | BB11: What is the difference between a reusable workflow and a composite action? | BC11: A reusable workflow shares whole jobs, a composite action shares steps. | BD11: =IF(K11="","",REPT("★",K11)&REPT("☆",5-K11)&" ("&K11&"/5)") | BE11: =IF(S11="","","Meaning: "&S11&" = ______ (Answer: "&F11&")") | BF11: New
A12: CICD-016 | B12: 02 GitHub Actions | C12: Advanced | D12: 16 | E12: Claude knowledge | F12: Workflow permissions | G12: How do you limit what the built-in GITHUB_TOKEN can do in a workflow? | I12: GitHub Actions concept | J12: High | K12: 5 | L12: A token with write access everywhere makes a compromised step dangerous, so permissions can be limited per workflow and job. | M12: Start with read-only and add only the scopes a job needs. | O12: Permissions are the keys on a keyring, and you hand over only the ones needed. | P12: A token with a short list of scopes ticked. | Q12: The security of a token that can do very little. | R12: The permissions key sets the scopes of GITHUB_TOKEN, such as contents, pull-requests or packages, as read, write or none. | T12: permissions: contents: read jobs: release: runs-on: ubuntu-latest permissions: contents: write packages: write steps: - uses: actions/checkout@v4 | U12: Every job gets read-only access to contents, except the release job, which can also write contents and packages. | V12: When permissions is set, any scope you do not list becomes none. A workflow-level setting applies to every job unless a job overrides it. The repository default can also be set to read-only in settings. For OIDC to a cloud, a job needs id-token write. Least privilege here limits the damage from a malicious or buggy action. | W12: Set permissions at the top to read, then raise them only on the jobs that need more. | X12: Permissions are keys on a keyring, and you hand over only the ones needed. | Y12: permissions: scope: read|write|none | Z12: contents = repository files | packages = registry | id-token = OIDC | pull-requests = PR comments | AA12: permissions: read-all | AB12: permissions: { id-token: write, contents: read } | AC12: permissions: {} | AD12: permissions: write-all // avoid, grants everything | AE12: GITHUB_TOKEN, OIDC, least privilege | AF12: secrets in workflows, OIDC to the cloud, pinning actions, least privilege tokens | AG12: Fine-grained personal tokens | AI12: Security hardening | Releases | Cloud deployment | AJ12: A: A third-party action has write access to our repo. | B: Set permissions to read at the top. | AK12: ✗ The default token permissions are always minimal → ✓ Older repositories may default to broad write access, so set them explicitly | AL12: Permissions vs secrets: permissions limit the built-in token, secrets are stored values you add. | AM12: Do not grant write-all to any job. | AN12: permissions: write-all | AO12: permissions: contents: read | AP12: Read at the top, write only where needed. | AQ12: Setting read-only permissions workflow-wide after a third-party action review. | AR12: An interviewer may ask: How do you secure the GITHUB_TOKEN? | AS12: It is like handing over only the keys needed. | AT12: What happens to scopes you do not list once permissions is set? | AU12: A) They become read B) They become none C) They stay write D) They are ignored | AV12: B | AW12: Unlisted scopes are set to no access. | AX12: Cloud sign-in through OIDC needs the scope ____ write → id-token | AY12: Make a workflow read-only for repository contents. | AZ12: permissions: contents: read | BA12: Give a release job write access to packages only. | BB12: Why set permissions explicitly? | BC12: Defaults may be broad, and least privilege limits damage from a bad step. | BD12: =IF(K12="","",REPT("★",K12)&REPT("☆",5-K12)&" ("&K12&"/5)") | BE12: =IF(S12="","","Meaning: "&S12&" = ______ (Answer: "&F12&")") | BF12: New
A13: CICD-032 | B13: 05 Security and Scale | C13: Advanced | D13: 32 | E13: Claude knowledge | F13: OIDC to the cloud | G13: How can a workflow sign in to a cloud account without any stored key? | I13: Security practice | J13: High | K13: 5 | L13: Stored cloud keys in secrets leak and never expire, so workflows now prove their identity with a short-lived signed token. | M13: Restrict the cloud role to your repository and branch in its trust policy. | O13: OIDC is showing a signed visitor badge at the door instead of carrying a permanent key. | P13: A workflow exchanging a signed token for temporary cloud credentials. | Q13: The relief of deleting the last stored cloud key. | R13: With OpenID Connect, the workflow requests a signed identity token from GitHub, and the cloud exchanges it for temporary credentials for a role it trusts. | T13: permissions: id-token: write contents: read steps: - uses: aws-actions/configure-aws-credentials@v4 with: role-to-assume: arn:aws:iam::123456789012:role/deploy aws-region: ap-south-1 | U13: The job receives temporary credentials for the deploy role, and no long-lived key is stored anywhere. | V13: The cloud role has a trust policy that names GitHub as the identity provider and limits which repository, branch or environment may assume it. The token contains claims about the repository and ref. The workflow needs the id-token write permission. Credentials are short-lived, by default about an hour with the AWS action, so a leak is much less harmful. Azure and GCP offer similar federation. | W13: Trust GitHub in the cloud, limit the role by repository, and let the workflow request temporary access. | X13: It is like showing a signed visitor badge instead of carrying a permanent key. | Y13: permissions: id-token: write | role-to-assume: <role> | Z13: id-token = lets the job request a token | trust policy = who may assume | role = what they may do | AA13: sub: repo:acme/api:ref:refs/heads/main | AB13: role-to-assume: arn:aws:iam::123456789012:role/deploy | AC13: audience: sts.amazonaws.com | AD13: azure/login with client-id and tenant-id // the same idea on Azure | AE13: IAM roles, permissions, environments | AF13: workflow permissions, secrets in workflows, temporary credentials, least privilege tokens | AG13: Stored access keys | AI13: Cloud deployments | Container pushes | Infrastructure pipelines | AJ13: A: Where is the AWS key stored for the pipeline? | B: Nowhere, it uses OIDC and a role. | AK13: ✗ OIDC removes the need to limit the role → ✓ The trust policy must still restrict which repository and branch can use it | AL13: OIDC vs stored secret: OIDC gives temporary access, a secret is a long-lived value. | AM13: Do not trust every repository in the organisation with a powerful role. | AN13: permissions: contents: read # no id-token, so OIDC fails | AO13: permissions: id-token: write contents: read | AP13: Badge at the door, no key in pocket. | AQ13: Replacing a stored deployment key with OIDC and a role limited to the main branch. | AR13: An interviewer may ask: How do you avoid storing cloud credentials in CI? | AS13: It is like a signed visitor badge instead of a permanent key. | AT13: Which permission does a job need to request an OIDC token? | AU13: A) contents: write B) actions: none C) packages: read D) id-token: write | AV13: D | AW13: The id-token write scope allows token requests. | AX13: The cloud checks a ____ policy to see who may assume the role → trust | AY13: Allow a job to request an OIDC token. | AZ13: permissions: id-token: write | BA13: Describe what the trust policy should restrict. | BB13: Why are OIDC credentials safer than stored keys? | BC13: They are temporary and no long-lived secret exists. | BD13: =IF(K13="","",REPT("★",K13)&REPT("☆",5-K13)&" ("&K13&"/5)") | BE13: =IF(S13="","","Meaning: "&S13&" = ______ (Answer: "&F13&")") | BF13: New
A14: CICD-033 | B14: 05 Security and Scale | C14: Advanced | D14: 33 | E14: Claude knowledge | F14: Pinning actions | G14: How do you stop a third-party action from changing under you? | I14: Security practice | J14: High | K14: 5 | L14: A moving tag can be replaced by an attacker or a bad release, so workflows should point at an exact immutable version. | M14: Pin third-party actions to a full commit hash, and let a bot propose updates. | O14: Pinning is writing the exact serial number instead of the product name. | P14: An action reference ending in a long commit hash. | Q14: The assurance that code does not change silently. | R14: Pinning means referencing an action by a full commit SHA rather than a tag or branch, so its code cannot change without your knowledge. | T14: - uses: actions/checkout@b4ffde65f46336ab88eb53be808477a3936bae11 # v4.1.1 - uses: some-org/deploy-action@5e1c2a8b9d0f3a4b6c7d8e9f0a1b2c3d4e5f6a7b | U14: The workflow always runs the exact reviewed code, and a version comment shows the human-readable tag. | V14: Tags such as v1 can be moved by the action author, so a compromised maintainer account can change what your pipeline runs. A full commit hash is immutable. Bots such as Dependabot can open pull requests to update pinned hashes. Actions from the official organisation carry lower risk but pinning is still wise for critical pipelines. Review what an action does before use. | W14: Use full commit hashes for third-party actions, and update them through reviewed pull requests. | X14: Pinning is writing the exact serial number instead of the product name. | Y14: uses: owner/action@<full-commit-sha> | Z14: owner/action = which action | @sha = exact version | comment = human label | AA14: uses: actions/setup-node@60edb5dd545a775178f52524783378180af0d1f8 # v4.0.2 | AB14: Dependabot updating github-actions weekly | AC14: uses: ./.github/actions/local-step | AD14: uses: owner/action@v1 // convenient but movable | AE14: Dependabot, code review, permissions | AF14: workflow permissions, secret scanning, reusable workflows, supply chain | AG14: Vendoring or forking the action | AI14: Security hardening | Regulated pipelines | Shared workflows | AJ14: A: An action we use was compromised. | B: Pinned hashes would have protected us from the new code. | AK14: ✗ A version tag such as v4 can never change → ✓ Tags can be moved, and only a commit hash is immutable | AL14: Tag vs commit hash: a tag is a movable label, a hash identifies fixed code. | AM14: Do not use branch names such as main for third-party actions. | AN14: uses: some-org/deploy-action@main | AO14: uses: some-org/deploy-action@5e1c2a8b9d0f3a4b6c7d8e9f0a1b2c3d4e5f6a7b | AP14: Pin the hash, not the nickname. | AQ14: Pinning all third-party actions after a supply chain scare, with weekly update pull requests. | AR14: An interviewer may ask: How do you defend against a compromised GitHub Action? | AS14: It is like writing the exact serial number. | AT14: Which reference is immutable? | AU14: A) The word latest B) A full commit SHA C) A branch name D) A tag name | AV14: B | AW14: A hash identifies exact content. | AX14: A bot that proposes pinned updates is called ____ → Dependabot | AY14: Pin an action to a commit hash instead of a tag. | AZ14: uses: some-org/deploy-action@5e1c2a8b9d0f3a4b6c7d8e9f0a1b2c3d4e5f6a7b | BA14: Explain how you would keep pinned versions up to date. | BB14: Why can a tag be unsafe? | BC14: The author can move it to different code. | BD14: =IF(K14="","",REPT("★",K14)&REPT("☆",5-K14)&" ("&K14&"/5)") | BE14: =IF(S14="","","Meaning: "&S14&" = ______ (Answer: "&F14&")") | BF14: New

Sheet Code card view
A1: Code concept (56-pt) · card view
A2: Card ID chuno ▸ | B2: CICD-007
A4: FRONT · Recognition (pehchano)
A5: ID | B5: =INDEX('Code concept (56-pt) cards'!$A$3:$BN$14,MATCH($B$2,'Code concept (56-pt) cards'!$A$3:$A$14,0),MATCH("ID",'Code concept (56-pt) cards'!$A$2:$BN$2,0))&""
A6: Topic | B6: =INDEX('Code concept (56-pt) cards'!$A$3:$BN$14,MATCH($B$2,'Code concept (56-pt) cards'!$A$3:$A$14,0),MATCH("Topic",'Code concept (56-pt) cards'!$A$2:$BN$2,0))&""
A7: Level | B7: =INDEX('Code concept (56-pt) cards'!$A$3:$BN$14,MATCH($B$2,'Code concept (56-pt) cards'!$A$3:$A$14,0),MATCH("Level",'Code concept (56-pt) cards'!$A$2:$BN$2,0))&""
A8: Concept | B8: =INDEX('Code concept (56-pt) cards'!$A$3:$BN$14,MATCH($B$2,'Code concept (56-pt) cards'!$A$3:$A$14,0),MATCH("Concept",'Code concept (56-pt) cards'!$A$2:$BN$2,0))&""
A9: Recall cue | B9: =INDEX('Code concept (56-pt) cards'!$A$3:$BN$14,MATCH($B$2,'Code concept (56-pt) cards'!$A$3:$A$14,0),MATCH("Recall cue",'Code concept (56-pt) cards'!$A$2:$BN$2,0))&""
A10: Read aloud | B10: =INDEX('Code concept (56-pt) cards'!$A$3:$BN$14,MATCH($B$2,'Code concept (56-pt) cards'!$A$3:$A$14,0),MATCH("Read aloud",'Code concept (56-pt) cards'!$A$2:$BN$2,0))&""
A11: Type | B11: =INDEX('Code concept (56-pt) cards'!$A$3:$BN$14,MATCH($B$2,'Code concept (56-pt) cards'!$A$3:$A$14,0),MATCH("Type",'Code concept (56-pt) cards'!$A$2:$BN$2,0))&""
A12: How often used | B12: =INDEX('Code concept (56-pt) cards'!$A$3:$BN$14,MATCH($B$2,'Code concept (56-pt) cards'!$A$3:$A$14,0),MATCH("How often used",'Code concept (56-pt) cards'!$A$2:$BN$2,0))&""
A13: Importance (1-5) | B13: =INDEX('Code concept (56-pt) cards'!$A$3:$BN$14,MATCH($B$2,'Code concept (56-pt) cards'!$A$3:$A$14,0),MATCH("Importance (1-5)",'Code concept (56-pt) cards'!$A$2:$BN$2,0))&""
A14: Origin / why it exists | B14: =INDEX('Code concept (56-pt) cards'!$A$3:$BN$14,MATCH($B$2,'Code concept (56-pt) cards'!$A$3:$A$14,0),MATCH("Origin / why it exists",'Code concept (56-pt) cards'!$A$2:$BN$2,0))&""
A15: Pro tip | B15: =INDEX('Code concept (56-pt) cards'!$A$3:$BN$14,MATCH($B$2,'Code concept (56-pt) cards'!$A$3:$A$14,0),MATCH("Pro tip",'Code concept (56-pt) cards'!$A$2:$BN$2,0))&""
A16: Typing hint | B16: =INDEX('Code concept (56-pt) cards'!$A$3:$BN$14,MATCH($B$2,'Code concept (56-pt) cards'!$A$3:$A$14,0),MATCH("Typing hint",'Code concept (56-pt) cards'!$A$2:$BN$2,0))&""
A17: Memory story | B17: =INDEX('Code concept (56-pt) cards'!$A$3:$BN$14,MATCH($B$2,'Code concept (56-pt) cards'!$A$3:$A$14,0),MATCH("Memory story",'Code concept (56-pt) cards'!$A$2:$BN$2,0))&""
A18: Picture it | B18: =INDEX('Code concept (56-pt) cards'!$A$3:$BN$14,MATCH($B$2,'Code concept (56-pt) cards'!$A$3:$A$14,0),MATCH("Picture it",'Code concept (56-pt) cards'!$A$2:$BN$2,0))&""
A19: Emotion hook | B19: =INDEX('Code concept (56-pt) cards'!$A$3:$BN$14,MATCH($B$2,'Code concept (56-pt) cards'!$A$3:$A$14,0),MATCH("Emotion hook",'Code concept (56-pt) cards'!$A$2:$BN$2,0))&""
A20: Importance ★ | B20: =INDEX('Code concept (56-pt) cards'!$A$3:$BN$14,MATCH($B$2,'Code concept (56-pt) cards'!$A$3:$A$14,0),MATCH("Importance ★",'Code concept (56-pt) cards'!$A$2:$BN$2,0))&""
A21: BACK · Understanding (samjho)
A22: Meaning (short) | B22: =INDEX('Code concept (56-pt) cards'!$A$3:$BN$14,MATCH($B$2,'Code concept (56-pt) cards'!$A$3:$A$14,0),MATCH("Meaning (short)",'Code concept (56-pt) cards'!$A$2:$BN$2,0))&""
A23: Meaning in learner's language | B23: =INDEX('Code concept (56-pt) cards'!$A$3:$BN$14,MATCH($B$2,'Code concept (56-pt) cards'!$A$3:$A$14,0),MATCH("Meaning in learner's language",'Code concept (56-pt) cards'!$A$2:$BN$2,0))&""
A24: Code | B24: =INDEX('Code concept (56-pt) cards'!$A$3:$BN$14,MATCH($B$2,'Code concept (56-pt) cards'!$A$3:$A$14,0),MATCH("Code",'Code concept (56-pt) cards'!$A$2:$BN$2,0))&""
A25: Output | B25: =INDEX('Code concept (56-pt) cards'!$A$3:$BN$14,MATCH($B$2,'Code concept (56-pt) cards'!$A$3:$A$14,0),MATCH("Output",'Code concept (56-pt) cards'!$A$2:$BN$2,0))&""
A26: Explanation | B26: =INDEX('Code concept (56-pt) cards'!$A$3:$BN$14,MATCH($B$2,'Code concept (56-pt) cards'!$A$3:$A$14,0),MATCH("Explanation",'Code concept (56-pt) cards'!$A$2:$BN$2,0))&""
A27: Simple explanation (Hinglish) | B27: =INDEX('Code concept (56-pt) cards'!$A$3:$BN$14,MATCH($B$2,'Code concept (56-pt) cards'!$A$3:$A$14,0),MATCH("Simple explanation (Hinglish)",'Code concept (56-pt) cards'!$A$2:$BN$2,0))&""
A28: Real-life analogy | B28: =INDEX('Code concept (56-pt) cards'!$A$3:$BN$14,MATCH($B$2,'Code concept (56-pt) cards'!$A$3:$A$14,0),MATCH("Real-life analogy",'Code concept (56-pt) cards'!$A$2:$BN$2,0))&""
A29: Syntax pattern | B29: =INDEX('Code concept (56-pt) cards'!$A$3:$BN$14,MATCH($B$2,'Code concept (56-pt) cards'!$A$3:$A$14,0),MATCH("Syntax pattern",'Code concept (56-pt) cards'!$A$2:$BN$2,0))&""
A30: Anatomy | B30: =INDEX('Code concept (56-pt) cards'!$A$3:$BN$14,MATCH($B$2,'Code concept (56-pt) cards'!$A$3:$A$14,0),MATCH("Anatomy",'Code concept (56-pt) cards'!$A$2:$BN$2,0))&""
A31: Example 1 | B31: =INDEX('Code concept (56-pt) cards'!$A$3:$BN$14,MATCH($B$2,'Code concept (56-pt) cards'!$A$3:$A$14,0),MATCH("Example 1",'Code concept (56-pt) cards'!$A$2:$BN$2,0))&""
A32: Example 2 | B32: =INDEX('Code concept (56-pt) cards'!$A$3:$BN$14,MATCH($B$2,'Code concept (56-pt) cards'!$A$3:$A$14,0),MATCH("Example 2",'Code concept (56-pt) cards'!$A$2:$BN$2,0))&""
A33: Example 3 | B33: =INDEX('Code concept (56-pt) cards'!$A$3:$BN$14,MATCH($B$2,'Code concept (56-pt) cards'!$A$3:$A$14,0),MATCH("Example 3",'Code concept (56-pt) cards'!$A$2:$BN$2,0))&""
A34: Variation | B34: =INDEX('Code concept (56-pt) cards'!$A$3:$BN$14,MATCH($B$2,'Code concept (56-pt) cards'!$A$3:$A$14,0),MATCH("Variation",'Code concept (56-pt) cards'!$A$2:$BN$2,0))&""
A35: Used with | B35: =INDEX('Code concept (56-pt) cards'!$A$3:$BN$14,MATCH($B$2,'Code concept (56-pt) cards'!$A$3:$A$14,0),MATCH("Used with",'Code concept (56-pt) cards'!$A$2:$BN$2,0))&""
A36: Related concepts | B36: =INDEX('Code concept (56-pt) cards'!$A$3:$BN$14,MATCH($B$2,'Code concept (56-pt) cards'!$A$3:$A$14,0),MATCH("Related concepts",'Code concept (56-pt) cards'!$A$2:$BN$2,0))&""
A37: Alternatives | B37: =INDEX('Code concept (56-pt) cards'!$A$3:$BN$14,MATCH($B$2,'Code concept (56-pt) cards'!$A$3:$A$14,0),MATCH("Alternatives",'Code concept (56-pt) cards'!$A$2:$BN$2,0))&""
A38: Family / group | B38: =INDEX('Code concept (56-pt) cards'!$A$3:$BN$14,MATCH($B$2,'Code concept (56-pt) cards'!$A$3:$A$14,0),MATCH("Family / group",'Code concept (56-pt) cards'!$A$2:$BN$2,0))&""
A39: Where it is used | B39: =INDEX('Code concept (56-pt) cards'!$A$3:$BN$14,MATCH($B$2,'Code concept (56-pt) cards'!$A$3:$A$14,0),MATCH("Where it is used",'Code concept (56-pt) cards'!$A$2:$BN$2,0))&""
A40: Mini conversation | B40: =INDEX('Code concept (56-pt) cards'!$A$3:$BN$14,MATCH($B$2,'Code concept (56-pt) cards'!$A$3:$A$14,0),MATCH("Mini conversation",'Code concept (56-pt) cards'!$A$2:$BN$2,0))&""
A41: Common mistake | B41: =INDEX('Code concept (56-pt) cards'!$A$3:$BN$14,MATCH($B$2,'Code concept (56-pt) cards'!$A$3:$A$14,0),MATCH("Common mistake",'Code concept (56-pt) cards'!$A$2:$BN$2,0))&""
A42: Commonly confused with | B42: =INDEX('Code concept (56-pt) cards'!$A$3:$BN$14,MATCH($B$2,'Code concept (56-pt) cards'!$A$3:$A$14,0),MATCH("Commonly confused with",'Code concept (56-pt) cards'!$A$2:$BN$2,0))&""
A43: Avoid / don't | B43: =INDEX('Code concept (56-pt) cards'!$A$3:$BN$14,MATCH($B$2,'Code concept (56-pt) cards'!$A$3:$A$14,0),MATCH("Avoid / don't",'Code concept (56-pt) cards'!$A$2:$BN$2,0))&""
A44: Wrong code | B44: =INDEX('Code concept (56-pt) cards'!$A$3:$BN$14,MATCH($B$2,'Code concept (56-pt) cards'!$A$3:$A$14,0),MATCH("Wrong code",'Code concept (56-pt) cards'!$A$2:$BN$2,0))&""
A45: Right code | B45: =INDEX('Code concept (56-pt) cards'!$A$3:$BN$14,MATCH($B$2,'Code concept (56-pt) cards'!$A$3:$A$14,0),MATCH("Right code",'Code concept (56-pt) cards'!$A$2:$BN$2,0))&""
A46: Memory trick | B46: =INDEX('Code concept (56-pt) cards'!$A$3:$BN$14,MATCH($B$2,'Code concept (56-pt) cards'!$A$3:$A$14,0),MATCH("Memory trick",'Code concept (56-pt) cards'!$A$2:$BN$2,0))&""
A47: Real life: project / work | B47: =INDEX('Code concept (56-pt) cards'!$A$3:$BN$14,MATCH($B$2,'Code concept (56-pt) cards'!$A$3:$A$14,0),MATCH("Real life: project / work",'Code concept (56-pt) cards'!$A$2:$BN$2,0))&""
A48: Real life: interview / exam | B48: =INDEX('Code concept (56-pt) cards'!$A$3:$BN$14,MATCH($B$2,'Code concept (56-pt) cards'!$A$3:$A$14,0),MATCH("Real life: interview / exam",'Code concept (56-pt) cards'!$A$2:$BN$2,0))&""
A49: Real life: daily life | B49: =INDEX('Code concept (56-pt) cards'!$A$3:$BN$14,MATCH($B$2,'Code concept (56-pt) cards'!$A$3:$A$14,0),MATCH("Real life: daily life",'Code concept (56-pt) cards'!$A$2:$BN$2,0))&""
A50: PRACTICE · Khud karo
A51: MCQ question | B51: =INDEX('Code concept (56-pt) cards'!$A$3:$BN$14,MATCH($B$2,'Code concept (56-pt) cards'!$A$3:$A$14,0),MATCH("MCQ question",'Code concept (56-pt) cards'!$A$2:$BN$2,0))&""
A52: MCQ options | B52: =INDEX('Code concept (56-pt) cards'!$A$3:$BN$14,MATCH($B$2,'Code concept (56-pt) cards'!$A$3:$A$14,0),MATCH("MCQ options",'Code concept (56-pt) cards'!$A$2:$BN$2,0))&""
A53: MCQ answer | B53: =INDEX('Code concept (56-pt) cards'!$A$3:$BN$14,MATCH($B$2,'Code concept (56-pt) cards'!$A$3:$A$14,0),MATCH("MCQ answer",'Code concept (56-pt) cards'!$A$2:$BN$2,0))&""
A54: Why that answer | B54: =INDEX('Code concept (56-pt) cards'!$A$3:$BN$14,MATCH($B$2,'Code concept (56-pt) cards'!$A$3:$A$14,0),MATCH("Why that answer",'Code concept (56-pt) cards'!$A$2:$BN$2,0))&""
A55: Fill the blank | B55: =INDEX('Code concept (56-pt) cards'!$A$3:$BN$14,MATCH($B$2,'Code concept (56-pt) cards'!$A$3:$A$14,0),MATCH("Fill the blank",'Code concept (56-pt) cards'!$A$2:$BN$2,0))&""
A56: Try it yourself | B56: =INDEX('Code concept (56-pt) cards'!$A$3:$BN$14,MATCH($B$2,'Code concept (56-pt) cards'!$A$3:$A$14,0),MATCH("Try it yourself",'Code concept (56-pt) cards'!$A$2:$BN$2,0))&""
A57: Task answer | B57: =INDEX('Code concept (56-pt) cards'!$A$3:$BN$14,MATCH($B$2,'Code concept (56-pt) cards'!$A$3:$A$14,0),MATCH("Task answer",'Code concept (56-pt) cards'!$A$2:$BN$2,0))&""
A58: Write your own | B58: =INDEX('Code concept (56-pt) cards'!$A$3:$BN$14,MATCH($B$2,'Code concept (56-pt) cards'!$A$3:$A$14,0),MATCH("Write your own",'Code concept (56-pt) cards'!$A$2:$BN$2,0))&""
A59: Practice question | B59: =INDEX('Code concept (56-pt) cards'!$A$3:$BN$14,MATCH($B$2,'Code concept (56-pt) cards'!$A$3:$A$14,0),MATCH("Practice question",'Code concept (56-pt) cards'!$A$2:$BN$2,0))&""
A60: Practice answer | B60: =INDEX('Code concept (56-pt) cards'!$A$3:$BN$14,MATCH($B$2,'Code concept (56-pt) cards'!$A$3:$A$14,0),MATCH("Practice answer",'Code concept (56-pt) cards'!$A$2:$BN$2,0))&""
A61: Quick recall (reverse) | B61: =INDEX('Code concept (56-pt) cards'!$A$3:$BN$14,MATCH($B$2,'Code concept (56-pt) cards'!$A$3:$A$14,0),MATCH("Quick recall (reverse)",'Code concept (56-pt) cards'!$A$2:$BN$2,0))&""

Sheet Topic (56-pt) cards
A1: Card | F1: Side 1 · Recognition | P1: Side 2 · Understanding | AJ1: Side 3 · Real life & Practice | AR1: Auto | AT1: My review
A2: ID | B2: Topic | C2: Level | D2: Study order | E2: Source | F2: Term / topic | G2: Recall cue | H2: Category | I2: How often used | J2: Importance (1-5) | K2: Origin / why it exists | L2: Pro tip | M2: Memory story | N2: Picture it | O2: Emotion hook | P2: Definition (simple) | Q2: Meaning in learner's language | R2: How / why it works | S2: Simple explanation (Hinglish) | T2: Real-life analogy | U2: Formula / rule | V2: Example 1 | W2: Example 2 | X2: Example 3 | Y2: Related concepts | Z2: Family / group | AA2: Where it is used | AB2: Mini conversation | AC2: Common mistake | AD2: Don't confuse with | AE2: Avoid / don't | AF2: Memory trick | AG2: Real life: project / work | AH2: Real life: interview / exam | AI2: Real life: daily life | AJ2: MCQ question | AK2: MCQ options | AL2: MCQ answer | AM2: Why that answer | AN2: Fill the blank | AO2: Apply it | AP2: Explain it yourself | AQ2: Write your own | AR2: Importance ★ | AS2: Quick recall (reverse) | AT2: Status | AU2: Day 1 | AV2: Day 3 | AW2: Day 7 | AX2: Day 15 | AY2: Day 30 | AZ2: Day 60 | BA2: OK / Fix | BB2: My note
A3: CICD-001 | B3: 01 Ideas | C3: Beginner | D3: 1 | E3: Claude knowledge | F3: CI vs continuous delivery vs continuous deployment | G3: Which three practices differ in how far automation goes between a code change and production? | H3: Core concept | I3: Very high | J3: 5 | K3: Teams that merged code only occasionally suffered painful, risky releases, so they began integrating, testing and releasing in small automatic steps. | L3: Say which one you mean, because many people use CI/CD as one word for all three. | M3: CI checks the ingredients, delivery plates the dish, and deployment serves it without asking the manager. | N3: A pipeline arrow with three marked stopping points along it. | O3: The calm of small releases instead of one terrifying big one. | P3: Continuous integration merges and tests code often, continuous delivery keeps every build ready to release with a manual approval, and continuous deployment releases every passing build automatically. | R3: CI builds and tests each change soon after it is pushed. Continuous delivery adds an automated path to a release-ready package, but a person decides when to ship. Continuous deployment removes that decision, so every change that passes goes live. The difference is the human approval at the end. Strong tests are the price of full automation. | S3: CI tests every change, delivery makes it ready to ship, deployment ships it for you. | T3: CI checks the ingredients, delivery plates the dish, and deployment serves it without asking the manager. | U3: CI = test often. Delivery = ready to release. Deployment = released automatically. | V3: A pull request that runs the test suite automatically. | W3: A build that waits for a manager to click approve before going live. | X3: A change that goes live minutes after merging with no clicks. | Y3: pipeline stages, triggers, environments, approvals | Z3: integration, delivery, deployment, pipeline, automation | AA3: Software teams | Customer projects | Release planning | AB3: A: Do we ship every merge automatically? | B: Only after a manual approval, so that is delivery, not deployment. | AC3: ✗ Continuous delivery and continuous deployment are the same thing → ✓ Delivery needs a human approval to release, while deployment does not | AD3: Delivery vs deployment: delivery waits for a human decision, deployment does not. | AE3: Do not automate releases before the tests can be trusted. | AF3: Test often, ready always, release automatically. | AG3: Moving a customer integration from monthly manual releases to a tested pipeline with approval. | AH3: An interviewer may ask: What is the difference between continuous delivery and continuous deployment? | AI3: It is like checking ingredients, plating a dish and serving it. | AJ3: What is the main difference between delivery and deployment? | AK3: A) There is no difference B) A person approves the release in delivery C) Deployment has no code D) Delivery has no tests | AL3: B | AM3: Deployment ships automatically, while delivery waits for approval. | AN3: Merging and testing code often is called continuous ____ → integration | AO3: Every passing change must go live with no clicks. Which practice is this? → Continuous deployment | AP3: Explain the three practices in three lines. | AQ3: Decide which one fits a bank and which one fits a small web shop. | AR3: =IF(J3="","",REPT("★",J3)&REPT("☆",5-J3)&" ("&J3&"/5)") | AS3: =IF(Q3="","","Meaning: "&Q3&" = ______ (Answer: "&F3&")") | AT3: New
A4: CICD-002 | B4: 01 Ideas | C4: Beginner | D4: 2 | E4: Claude knowledge | F4: Pipeline stages | G4: Which ordered steps does code pass through between a commit and a running release? | H4: Core concept | I4: Very high | J4: 5 | K4: Teams repeated the same manual steps for every release, so they wrote those steps down as an ordered, automatic pipeline. | L4: Put the fastest checks first so a broken change fails in seconds, not minutes. | M4: A pipeline is a factory conveyor belt where each station inspects the product before it moves on. | N4: Boxes labelled build, test, scan, package and deploy joined by arrows. | O4: The satisfaction of watching every stage turn green. | P4: A pipeline is an automated sequence of stages, such as build, test, scan, package and deploy, where each stage runs only if the one before it succeeded. | R4: A stage groups jobs that do one kind of work. Failure stops the pipeline, so bad changes do not reach later stages. Stages can run in parallel when they do not depend on each other. The pipeline definition is stored as code in the repository. Short feedback time is a key quality of a good pipeline. | S4: A pipeline runs build, test, scan and deploy in order, and stops at the first failure. | T4: It is a factory conveyor belt where each station inspects the product before it moves on. | U4: Commit → build → test → scan → package → deploy, stop on failure. | V4: A pipeline that lints code first and fails in ten seconds. | W4: Unit tests and security scans running side by side. | X4: A deploy stage that runs only on the main branch. | Y4: triggers, build artifacts, environments, quality gates | Z4: stage, job, step, gate, artifact | AA4: Every CI system | Release automation | Reviews | AB4: A: The deploy ran even though tests failed. | B: The stages were not chained, so add a dependency. | AC4: ✗ A pipeline only needs one big script that does everything → ✓ Separate stages give clear feedback, parallel work and reuse | AD4: Stage vs job: a stage is a phase of the pipeline, a job is one unit of work inside it. | AE4: Do not put slow tests before quick linting. | AF4: Fast checks first, slow checks later. | AG4: Reordering stages so lint and unit tests failed fast before the slow integration tests. | AH4: An interviewer may ask: What stages would you put in a pipeline? | AI4: It is like a conveyor belt with an inspector at each station. | AJ4: What happens when an early stage fails? | AK4: A) The code deploys B) They all run anyway C) Later stages do not run D) The repo is deleted | AL4: C | AM4: Stages depend on the success of the one before. | AN4: Where the pipeline is defined as code in the repo is a ____ file → workflow | AO4: Linting takes ten seconds and integration tests take ten minutes. Which goes first? → Linting | AP4: Explain pipeline stages in three lines. | AQ4: Draw a pipeline for a Python API with five stages. | AR4: =IF(J4="","",REPT("★",J4)&REPT("☆",5-J4)&" ("&J4&"/5)") | AS4: =IF(Q4="","","Meaning: "&Q4&" = ______ (Answer: "&F4&")") | AT4: New
A5: CICD-003 | B5: 01 Ideas | C5: Beginner | D5: 3 | E5: Claude knowledge | F5: Triggers | G5: Which events start a pipeline run automatically? | H5: Core concept | I5: Very high | J5: 4 | K5: Nobody wants to start a build by hand every time, so pipelines listen for events such as pushes and pull requests. | L5: Run tests on pull requests and deploy only on merges to the main branch. | M5: A trigger is the doorbell that wakes the pipeline. | N5: An event arrow, such as a push, pointing at a pipeline box. | O5: The ease of builds starting on their own. | P5: A trigger is an event, such as a push, a pull request, a tag, a schedule or a manual click, that starts a pipeline. | R5: Triggers can be filtered by branch, path or tag. A path filter avoids running backend tests when only documentation changed. Scheduled triggers run nightly jobs. Manual triggers allow on-demand deployments or maintenance. Webhooks from other systems can also start runs. Pull request triggers run on code from a fork with fewer permissions. | S5: Choose which events start the pipeline, and filter them so only relevant changes run it. | T5: It is the doorbell that wakes the pipeline. | U5: Event + filter = when the pipeline runs. | V5: Running tests on every pull request. | W5: Deploying only when a version tag is pushed. | X5: A nightly scheduled data refresh. | Y5: GitHub Actions workflows, branches, environments, schedules | Z5: event, push, pull request, schedule, webhook | AA5: Workflow design | Cost control | Release automation | AB5: A: Why did docs changes run the whole test suite? | B: There is no path filter on the trigger. | AC5: ✗ Pipelines can only start when code is pushed → ✓ They can also start on schedules, tags, manual clicks and webhooks | AD5: Push trigger vs pull request trigger: one runs on pushed commits, the other on proposed merges. | AE5: Do not trigger expensive jobs for every small docs change. | AF5: Events start it, filters narrow it. | AG5: Adding path filters so documentation edits no longer ran heavy integration tests. | AH5: An interviewer may ask: When should a deployment run? | AI5: It is like a doorbell that wakes the pipeline. | AJ5: Which trigger suits a nightly job? | AK5: A) A star B) A push C) A comment D) A schedule | AL5: D | AM5: Scheduled triggers run at set times. | AN5: A trigger that starts only for chosen branches uses a branch ____ → filter | AO5: You want deployments only for version tags. Which trigger? → A tag push | AP5: Explain triggers in three lines. | AQ5: List three triggers and what each is good for. | AR5: =IF(J5="","",REPT("★",J5)&REPT("☆",5-J5)&" ("&J5&"/5)") | AS5: =IF(Q5="","","Meaning: "&Q5&" = ______ (Answer: "&F5&")") | AT5: New
A6: CICD-004 | B6: 01 Ideas | C6: Beginner | D6: 4 | E6: Claude knowledge | F6: Build artifacts | G6: Which outputs of a build are saved and passed to later stages or releases? | H6: Core concept | I6: High | J6: 4 | K6: Rebuilding the same code in every stage risks differences, so one build is saved and reused through the pipeline. | L6: Build once, then deploy that same artifact to every environment. | M6: An artifact is the sealed box that travels down the line instead of being rebuilt at each station. | N6: A sealed package moving through test and production stages. | O6: The trust of shipping exactly what was tested. | P6: A build artifact is a file or package produced by a build, such as a container image, a zip or a wheel, that is stored and promoted through later stages. | R6: Artifacts include binaries, images, test reports and coverage files. They are stored in an artifact repository or container registry, and versioned, usually with the commit hash. Promoting the same artifact from test to production ensures that what was tested is what ships. Artifacts should be immutable, meaning never changed after creation. | S6: Build once, store the result with a version, and deploy the same thing everywhere. | T6: It is a sealed box that travels down the line instead of being rebuilt at each station. | U6: Build once, version it, promote it unchanged. | V6: A container image tagged with the commit hash. | W6: A test report uploaded for download. | X6: A Python package published to a private index. | Y6: registries, environments, release tagging, caching | Z6: artifact, package, image, version, immutable | AA6: Releases | Rollbacks | Auditing | AB6: A: The production build behaves differently from staging. | B: It was rebuilt, so promote the tested artifact instead. | AC6: ✗ Rebuilding for each environment is safer → ✓ Rebuilding can introduce differences, so promote the same artifact | AD6: Artifact vs source code: the artifact is the built result, the source is the input. | AE6: Do not overwrite a published artifact version. | AF6: Build once, promote many times. | AG6: Promoting one tagged image from staging to production to avoid environment surprises. | AH6: An interviewer may ask: Why build only once in a pipeline? | AI6: It is like a sealed box passed down the line. | AJ6: Why promote the same artifact between environments? | AK6: A) What was tested is exactly what ships B) It saves disk space only C) It avoids logging D) It removes tests | AL6: A | AM6: A rebuilt artifact may differ from the tested one. | AN6: An artifact that is never changed after creation is called ____ → immutable | AO6: Staging works but production fails after a rebuild. What should you change? → Promote the same artifact | AP6: Explain build artifacts in three lines. | AQ6: List four artifacts a pipeline for a web API might produce. | AR6: =IF(J6="","",REPT("★",J6)&REPT("☆",5-J6)&" ("&J6&"/5)") | AS6: =IF(Q6="","","Meaning: "&Q6&" = ______ (Answer: "&F6&")") | AT6: New
A7: CICD-005 | B7: 01 Ideas | C7: Intermediate | D7: 5 | E7: Claude knowledge | F7: Environments | G7: Which separate places do changes pass through before reaching real users? | H7: Core concept | I7: Very high | J7: 4 | K7: Testing directly on live systems is dangerous, so teams set up copies of the system where changes are tried safely first. | L7: Keep staging as similar to production as you can afford. | M7: Environments are rehearsal rooms before the stage performance. | N7: Three boxes labelled dev, staging and production linked by arrows. | O7: The comfort of finding bugs before customers do. | P7: Environments are separate deployments of the same application, such as development, staging and production, each with its own configuration and data. | R7: Development is for quick changes, staging mirrors production for final checks, and production serves real users. Configuration, such as database addresses and keys, differs by environment and is kept outside the code. Production data should not be copied to lower environments without masking. Protected environments can require approvals. | S7: Try changes in dev and staging, then release to production with the same artifact and different settings. | T7: Environments are rehearsal rooms before the stage performance. | U7: Same artifact, different configuration per environment. | V7: A staging database that is a masked copy of production. | W7: A production environment that requires approval before deploying. | X7: A temporary preview environment per pull request. | Y7: build artifacts, configuration, approvals, secrets | Z7: dev, staging, production, configuration, promotion | AA7: Release flow | Testing | Customer projects | AB7: A: Can I test on production? | B: No, test on staging, which mirrors it. | AC7: ✗ Staging does not need to resemble production → ✓ The closer it is, the more bugs it catches before release | AD7: Staging vs production: staging is a rehearsal copy, production serves real users. | AE7: Do not copy raw personal data into test environments. | AF7: Rehearse in staging, perform in production. | AG7: Adding a staging environment that caught a configuration bug before a customer launch. | AH7: An interviewer may ask: Why do you need a staging environment? | AI7: It is like a rehearsal room before the stage. | AJ7: What should differ between environments? | AK7: A) Configuration such as addresses and keys B) The code version C) The tests D) The language | AL7: A | AM7: The same artifact runs with environment-specific settings. | AN7: Moving a build from staging to production is called ____ → promotion | AO7: You need to catch config bugs before release. What do you add? → A staging environment | AP7: Explain environments in three lines. | AQ7: List what should differ between staging and production. | AR7: =IF(J7="","",REPT("★",J7)&REPT("☆",5-J7)&" ("&J7&"/5)") | AS7: =IF(Q7="","","Meaning: "&Q7&" = ______ (Answer: "&F7&")") | AT7: New
A8: CICD-006 | B8: 01 Ideas | C8: Advanced | D8: 6 | E8: Claude knowledge | F8: DORA metrics | G8: Which four measures describe how well a team delivers software? | H8: Core concept | I8: Medium | J8: 3 | K8: Research on thousands of teams found a small set of measures that separate high performers from the rest. | L8: Use the metrics to find bottlenecks, not to rank individual people. | M8: DORA metrics are the four dials on a delivery dashboard. | N8: Four dials: frequency, lead time, failure rate and recovery time. | O8: The motivation of watching your numbers improve. | P8: The DORA metrics are deployment frequency, lead time for changes, change failure rate, failed deployment recovery time (formerly time to restore service) and, in newer guidance, rework rate. | R8: Deployment frequency shows how often you release. Lead time measures the time from commit to production. Change failure rate is the share of releases causing a problem. Failed deployment recovery time (formerly time to restore) measures how fast you recover. Fast and stable go together, because small, frequent changes are easier to test and fix. Numbers can be gamed if used as targets for people. | S8: Measure how often, how fast, how safely and how quickly you recover. | T8: They are four dials on a delivery dashboard. | U8: Speed (frequency, lead time) + stability (failure rate, restore time). | V8: Deploying several times a day with a lead time under an hour. | W8: A rollback fixing a bad release in ten minutes. | X8: A change failure rate of five percent. | Y8: pipeline stages, rollbacks, monitoring, small batches | Z8: frequency, lead time, failure rate, recovery, delivery | AA8: Team reviews | Improvement plans | Engineering reports | AB8: A: How do we know the pipeline improved things? | B: Compare lead time and failure rate before and after. | AC8: ✗ Releasing faster always means lower quality → ✓ Small frequent releases often improve stability | AD8: Speed vs stability metrics: frequency and lead time measure speed, failure rate and restore time measure stability. | AE8: Do not use DORA numbers to rank individuals. | AF8: Two for speed, two for stability. | AG8: Tracking lead time to show the customer that the new pipeline cut release time. | AH8: An interviewer may ask: What are the DORA metrics? | AI8: It is like four dials on a dashboard. | AJ8: Which metric measures time from commit to production? | AK8: A) Change failure rate B) Deployment frequency C) Lead time for changes D) Failed deployment recovery time | AL8: C | AM8: Lead time covers the span from commit to release. | AN8: The share of releases that cause problems is the change ____ rate → failure | AO8: You want to know how quickly you recover from incidents. Which metric? → Failed deployment recovery time | AP8: Explain the four DORA metrics in three lines. | AQ8: Write how you would measure lead time in your own pipeline. | AR8: =IF(J8="","",REPT("★",J8)&REPT("☆",5-J8)&" ("&J8&"/5)") | AS8: =IF(Q8="","","Meaning: "&Q8&" = ______ (Answer: "&F8&")") | AT8: New
A9: CICD-017 | B9: 03 Quality Gates | C9: Beginner | D9: 17 | E9: Claude knowledge | F9: Unit and integration tests in CI | G9: Which two kinds of automatic tests check small parts and connected parts of a system? | H9: Core concept | I9: Very high | J9: 5 | K9: Manual testing could not keep up with frequent releases, so tests were written as code that the pipeline runs on every change. | L9: Keep most tests as fast unit tests, with fewer slower integration tests on top. | M9: Unit tests check each brick, and integration tests check that the wall stands. | N9: A pyramid with many small unit tests at the base and few large tests at the top. | O9: The confidence of a green test run before merging. | P9: Unit tests check one small piece of code in isolation, and integration tests check that several parts, such as code and a database, work together. | R9: Unit tests run in milliseconds and pinpoint the broken function. Integration tests are slower, because they start real dependencies such as a database container, but they catch wiring mistakes. In CI the database is often started as a service container. A good suite has many unit tests and fewer integration tests. A failing test must block the merge. | S9: Run fast unit tests first, then integration tests, and block the merge if either fails. | T9: Unit tests check each brick, and integration tests check that the wall stands. | U9: Many fast unit tests + fewer slower integration tests. | V9: A test of one function that adds two prices. | W9: A test that saves a record to a real test database. | X9: A job starting a database service container before tests. | Y9: pipeline stages, required checks, flaky tests, coverage | Z9: unit, integration, test pyramid, mock, fixture | AA9: Every pipeline | Pull requests | Customer code | AB9: A: The tests pass locally but fail in CI. | B: CI uses a fresh database, so check the setup. | AC9: ✗ More integration tests are always better than unit tests → ✓ They are slower and harder to debug, so keep most tests small | AD9: Unit vs integration test: unit checks one piece alone, integration checks pieces together. | AE9: Do not let a failing test pass by skipping it. | AF9: Many bricks, a few walls. | AG9: Adding a database service container so integration tests ran in the pipeline. | AH9: An interviewer may ask: What is the test pyramid? | AI9: It is like checking each brick and then the wall. | AJ9: Which tests are usually the fastest? | AK9: A) Load tests B) Manual tests C) Unit tests D) Integration tests | AL9: C | AM9: Unit tests avoid real dependencies. | AN9: A shape with many small tests at the base is the test ____ → pyramid | AO9: You must test code against a real database in CI. Which test type? → An integration test | AP9: Explain unit and integration tests in three lines. | AQ9: List two unit tests and one integration test for a login page. | AR9: =IF(J9="","",REPT("★",J9)&REPT("☆",5-J9)&" ("&J9&"/5)") | AS9: =IF(Q9="","","Meaning: "&Q9&" = ______ (Answer: "&F9&")") | AT9: New
A10: CICD-018 | B10: 03 Quality Gates | C10: Beginner | D10: 18 | E10: Claude knowledge | F10: Linting and formatting | G10: Which automatic checks find style problems and likely mistakes before tests run? | H10: Core concept | I10: Very high | J10: 4 | K10: Teams argued about style in reviews, so tools were introduced to check and fix it automatically. | L10: Run the formatter in a pre-commit hook and the linter in CI. | M10: A linter is a proofreader that marks mistakes, and a formatter retypes the page neatly. | N10: A code file with red marks beside suspicious lines. | O10: The relief of never arguing about commas again. | P10: Linting analyses code for likely bugs and rule violations, and formatting rewrites code into one consistent style. | R10: Linters such as ESLint or Ruff catch unused variables, risky patterns and some bugs without running the code. Formatters such as Prettier or Black change layout only. In CI the formatter runs in check mode and fails if files would change. Running these first gives feedback in seconds. Rules should be agreed by the team and stored in the repository. | S10: Lint to find mistakes, format for consistent style, and fail the pipeline fast. | T10: A linter is a proofreader, and a formatter retypes the page neatly. | U10: Lint = find problems. Format = make style uniform. | V10: ESLint flagging an unused variable. | W10: A check mode run that fails if code is unformatted. | X10: A pre-commit hook that formats files before a commit. | Y10: pipeline stages, required checks, code review, pre-commit hooks | Z10: lint, format, rule, style, check | AA10: Pull requests | Pre-commit hooks | Team standards | AB10: A: Reviews are full of style comments. | B: Add a formatter check in CI. | AC10: ✗ Linting and formatting do the same job → ✓ Linting finds problems, and formatting only changes layout | AD10: Linter vs formatter: one reports risky code, the other rewrites style. | AE10: Do not disable lint rules just to get a green build. | AF10: Lint finds, format fixes style. | AG10: Adding lint and format checks that cut style comments in reviews. | AH10: An interviewer may ask: Why run linting first in a pipeline? | AI10: It is like a proofreader marking a page. | AJ10: Which tool changes only code layout? | AK10: A) A formatter B) A scanner C) A compiler D) A linter | AL10: A | AM10: Formatters rewrite style without changing behaviour. | AN10: Running a formatter without changing files is called check ____ → mode | AO10: Reviews waste time on style. What do you add? → A formatter check | AP10: Explain linting and formatting in three lines. | AQ10: Choose a linter and a formatter for a Python project. | AR10: =IF(J10="","",REPT("★",J10)&REPT("☆",5-J10)&" ("&J10&"/5)") | AS10: =IF(Q10="","","Meaning: "&Q10&" = ______ (Answer: "&F10&")") | AT10: New
A11: CICD-019 | B11: 03 Quality Gates | C11: Intermediate | D11: 19 | E11: Claude knowledge | F11: Security scans in CI | G11: Which automatic scans look for vulnerable dependencies, leaked secrets and risky code? | H11: Core concept | I11: High | J11: 5 | K11: Security reviews at the end of a project were slow and late, so scans were moved into the pipeline to catch problems early. | L11: Fail the build only on serious, fixable findings so the team does not learn to ignore alerts. | M11: Scans are airport security checks placed before the boarding gate. | N11: A pipeline with a scanner stage before packaging. | O11: The reassurance of finding a flaw before release. | P11: Security scans in CI include dependency scanning, secret scanning, static code analysis and image scanning, each checking a different risk. | R11: Dependency scanning compares packages with databases of known vulnerabilities. Secret scanning looks for leaked keys. Static analysis reads code for risky patterns, such as SQL built from user input. Image scanning checks container layers. Findings should have severity and owners. Too many false alarms cause alert fatigue, so tune the rules. | S11: Scan dependencies, secrets, code and images in the pipeline, and block only what matters. | T11: Scans are airport security checks before the boarding gate. | U11: Dependencies + secrets + code + images. | V11: A dependency scan failing on a critical vulnerability with a fix. | W11: A secret scan blocking a pushed API key. | X11: A static analysis tool flagging an injection risk. | Y11: quality gates, secret scanning, container scanning, least privilege | Z11: SAST, dependency, vulnerability, severity, false positive | AA11: Pull requests | Release gates | Compliance | AB11: A: The scan found forty issues. | B: Start with critical ones that have a fix. | AC11: ✗ If the scanner is quiet, the code is secure → ✓ Scanners find known patterns only, and reviews and design still matter | AD11: SAST vs dependency scan: SAST reads your code, dependency scanning checks other people's packages. | AE11: Do not ignore alerts because there are too many. | AF11: Block what matters, tune what nags. | AG11: Adding a dependency scan that blocked a critical vulnerable library before release. | AH11: An interviewer may ask: What security checks belong in a pipeline? | AI11: It is like airport security before boarding. | AJ11: Which scan finds known vulnerable packages? | AK11: A) Caching B) Dependency scanning C) Formatting D) Tagging | AL11: B | AM11: It compares packages to vulnerability databases. | AN11: Too many false alarms cause alert ____ → fatigue | AO11: You need to catch a pushed API key. Which scan? → Secret scanning | AP11: Explain the security scans in three lines. | AQ11: Choose which findings should fail a build. | AR11: =IF(J11="","",REPT("★",J11)&REPT("☆",5-J11)&" ("&J11&"/5)") | AS11: =IF(Q11="","","Meaning: "&Q11&" = ______ (Answer: "&F11&")") | AT11: New
A12: CICD-020 | B12: 03 Quality Gates | C12: Intermediate | D12: 20 | E12: Claude knowledge | F12: Code coverage | G12: Which measure shows how much of the code the tests actually run? | H12: Core concept | I12: High | J12: 3 | K12: Teams needed a rough idea of untested areas, so tools record which lines run during the tests. | L12: Use coverage to find untested risky code, not as a number to chase. | M12: Coverage is a highlighter showing which pages of the book the tests actually read. | N12: Code lines painted green when tested and red when not. | O12: The curiosity of finding an untested corner. | P12: Code coverage is the percentage of lines, branches or functions that run during the test suite. | R12: A report highlights lines never executed. Coverage shows what is not tested, but not how well the tested lines are checked. A test with no assertions can reach one hundred percent. Teams often set a minimum gate, such as eighty percent, and require that new code is covered. Chasing a high number can produce poor tests. | S12: Use coverage to find gaps, set a sensible minimum, and focus on meaningful tests. | T12: Coverage is a highlighter showing which pages the tests read. | U12: Coverage = executed lines ÷ total lines. It shows gaps, not quality. | V12: A report showing an error branch never tested. | W12: A gate requiring new code to have eighty percent coverage. | X12: A test with no checks inflating the number. | Y12: unit tests, required checks, flaky tests, reviews | Z12: coverage, line, branch, threshold, report | AA12: Quality gates | Reviews | Reports | AB12: A: Coverage is ninety percent, so we are safe. | B: Not necessarily, the tests may check little. | AC12: ✗ High coverage guarantees good tests → ✓ It only shows code was run, not that it was checked properly | AD12: Line vs branch coverage: lines count statements run, branches count decisions covered. | AE12: Do not write empty tests to raise the percentage. | AF12: Coverage shows gaps, not quality. | AG12: Using a coverage report to find an untested payment error path. | AH12: An interviewer may ask: Is one hundred percent coverage a good goal? | AI12: It is like a highlighter on read pages. | AJ12: What does coverage measure? | AK12: A) How many bugs exist B) How big the repo is C) How fast tests are D) How much code the tests run | AL12: D | AM12: It counts executed code in the tests. | AN12: A minimum coverage value that fails the build is a ____ → threshold | AO12: A team chases one hundred percent with empty tests. What is wrong? → The tests do not check anything | AP12: Explain code coverage in three lines. | AQ12: Decide a coverage rule for new code. | AR12: =IF(J12="","",REPT("★",J12)&REPT("☆",5-J12)&" ("&J12&"/5)") | AS12: =IF(Q12="","","Meaning: "&Q12&" = ______ (Answer: "&F12&")") | AT12: New
A13: CICD-021 | B13: 03 Quality Gates | C13: Intermediate | D13: 21 | E13: Claude knowledge | F13: Required checks and branch protection | G13: Which settings stop a pull request from merging until the checks pass? | H13: Core concept | I13: Very high | J13: 5 | K13: Checks that can be ignored are just suggestions, so repositories can require them before code reaches the main branch. | L13: Require checks, a review and an up-to-date branch on main. | M13: Branch protection is a turnstile that opens only with a valid ticket. | N13: A merge button greyed out with a list of pending checks. | O13: The safety of a protected main branch. | P13: Branch protection rules require status checks, reviews and other conditions before changes can be merged into a protected branch. | R13: You choose which checks are required, how many approvals are needed and whether force pushes are blocked. Rules can require the branch to be up to date before merging. Administrators can be included in the rules. A required check must report success. A check that never runs, for example because of a path filter, stays pending and blocks the merge, so design for that. Rulesets provide a newer way to manage rules across repositories. | S13: Protect main, require the pipeline and a review, and block direct pushes. | T13: Branch protection is a turnstile that opens only with a valid ticket. | U13: Required checks + review + no force push. | V13: A rule requiring the test and lint jobs to pass. | W13: A rule requiring one approving review. | X13: Blocking force pushes to main. | Y13: pull requests, quality gates, code owners, rulesets | Z13: protection, required check, review, ruleset, merge | AA13: Main branches | Teams | Compliance | AB13: A: Someone pushed a broken change to main. | B: Turn on branch protection and required checks. | AC13: ✗ Admins should be exempt from branch protection → ✓ Including admins avoids accidental bypasses | AD13: Required check vs optional check: required ones block merging, optional ones only inform. | AE13: Do not allow direct pushes to the main branch. | AF13: Checks plus review guard the main branch. | AG13: Enabling required checks so broken code could no longer be merged into main. | AH13: An interviewer may ask: How do you stop broken code reaching the main branch? | AI13: It is like a turnstile that opens only with a ticket. | AJ13: What does a required check do? | AK13: A) Deletes the branch B) Adds a tag C) Speeds up tests D) Blocks merging until it passes | AL13: D | AM13: A required check must succeed before the merge. | AN13: Rules that guard the main branch are called branch ____ → protection | AO13: Broken code was pushed straight to main. What should you enable? → Branch protection | AP13: Explain required checks in three lines. | AQ13: Write the protection rules you would set on main. | AR13: =IF(J13="","",REPT("★",J13)&REPT("☆",5-J13)&" ("&J13&"/5)") | AS13: =IF(Q13="","","Meaning: "&Q13&" = ______ (Answer: "&F13&")") | AT13: New
A14: CICD-022 | B14: 03 Quality Gates | C14: Intermediate | D14: 22 | E14: Claude knowledge | F14: Flaky tests | G14: Which tests pass and fail randomly without any change in the code? | H14: Core concept | I14: High | J14: 4 | K14: As suites grew, some tests started failing at random because of timing or shared state, wasting everyone's time. | L14: Find the cause, since rerunning until green hides a real problem. | M14: A flaky test is a smoke alarm that rings for no reason, so people stop trusting it. | N14: A test history showing green and red runs on the same code. | O14: The frustration of a pipeline that fails for no reason. | P14: A flaky test is one that gives different results on the same code, usually because of timing, order, shared data or external services. | R14: Common causes are sleeps instead of waiting for a condition, tests that depend on each other, random data, clock use and network calls. Flakiness trains people to ignore failures, which is dangerous. Quarantining a test temporarily is acceptable only with an owner and a deadline. Fix by isolating data, controlling time and mocking external services. | S14: Find why the result changes, fix the cause, and never train the team to rerun and ignore. | T14: It is a smoke alarm that rings for no reason. | U14: Same code, different result = a bug in the test or system. | V14: A test that fails when run after another test. | W14: A test using real time that fails near midnight. | X14: A test calling a real web service. | Y14: unit tests, required checks, retries, test isolation | Z14: flaky, intermittent, isolation, timing, mock | AA14: Test suites | Pipelines | Reliability work | AB14: A: Just rerun it, it always passes the second time. | B: Then it is flaky, so let us find the cause. | AC14: ✗ Rerunning a failed test until it passes is a fix → ✓ It hides the problem, which may be a real race condition | AD14: Flaky vs failing test: a failing test fails every time, a flaky test fails sometimes. | AE14: Do not add automatic retries to hide flakiness permanently. | AF14: Random failure means find the cause. | AG14: Replacing fixed sleeps with waits on a condition to remove random failures. | AH14: An interviewer may ask: How do you handle flaky tests? | AI14: It is like a smoke alarm that rings for nothing. | AJ14: Which is a common cause of flakiness? | AK14: A) Fixed sleeps and shared state B) Isolated data C) Clear assertions D) Small tests | AL14: A | AM14: Timing and shared state change results between runs. | AN14: Results that change without code changes are called ____ → flaky | AO14: A test fails near midnight only. What is a likely cause? → It depends on the clock | AP14: Explain flaky tests in three lines. | AQ14: List three causes and a fix for each. | AR14: =IF(J14="","",REPT("★",J14)&REPT("☆",5-J14)&" ("&J14&"/5)") | AS14: =IF(Q14="","","Meaning: "&Q14&" = ______ (Answer: "&F14&")") | AT14: New
... A30: CICD-040 | B30: 06 Mapping | C30: Intermediate | D30: 40 | E30: Claude knowledge | F30: Choosing a CI/CD tool | G30: Which questions decide the CI/CD tool for a customer? | H30: Reference | I30: Medium | J30: 4 | K30: Every customer already has code, clouds and habits, so the best tool depends on context rather than fame. | L30: Use the tool next to the code unless a requirement says otherwise. | M30: Choosing a tool is choosing a vehicle for the road, not for the brochure. | N30: A checklist with hosting, security, cost and skills. | O30: The clarity of a decision based on facts. | P30: Choosing a CI/CD tool means weighing where the code lives, security and compliance needs, private network access, cost and team skills. | R30: Ask where the repository is hosted, whether jobs must reach private systems, and who maintains the servers. Check compliance needs, such as audit logs and approvals. Consider cost in minutes and in staff time. Migrating pipelines has its own cost, so avoid it without a clear gain. Prefer standard, portable steps such as scripts and containers. | S30: Start from where the code lives and what the customer must keep private, then compare cost and skills. | T30: It is choosing a vehicle for the road, not for the brochure. | U30: Code location + security + network + cost + skills. | V30: A GitHub repository with Actions as the natural choice. | W30: A bank needing self-hosted runners in a private network. | X30: A team keeping Jenkins because migration is costly. | Y30: Jenkins, GitLab CI, Azure Pipelines, self-hosted runners | Z30: requirements, hosting, compliance, portability, cost | AA30: Proposals | Migrations | Platform decisions | AB30: A: Which CI tool should we use? | B: The one next to the code, unless security rules say otherwise. | AC30: ✗ The newest CI tool is always the best choice → ✓ The best tool fits the customer's code, rules and skills | AD30: Hosted vs self-hosted: hosted is simpler, self-hosted gives control and private access. | AE30: Do not migrate pipelines without a clear benefit. | AF30: Fit the customer, not the fashion. | AG30: Recommending Actions for a GitHub customer while keeping private test runners. | AH30: An interviewer may ask: How would you choose a CI tool? | AI30: It is like choosing a vehicle for the road. | AJ30: What should usually decide the tool? | AK30: A) Where the code lives and the customer's needs B) Personal taste C) Random choice D) The logo | AL30: A | AM30: Context decides, since tools share the same ideas. | AN30: Steps written as scripts are more ____ between tools → portable | AO30: A customer's code is on GitHub and jobs need no private access. What tool? → GitHub Actions | AP30: Explain how to choose a CI/CD tool in three lines. | AQ30: Write five questions to ask a customer about CI/CD. | AR30: =IF(J30="","",REPT("★",J30)&REPT("☆",5-J30)&" ("&J30&"/5)") | AS30: =IF(Q30="","","Meaning: "&Q30&" = ______ (Answer: "&F30&")") | AT30: New

Sheet Topic card view
A1: Topic (56-pt) · card view
A2: Card ID chuno ▸ | B2: CICD-001
A4: FRONT · Recognition (pehchano)
A5: ID | B5: =INDEX('Topic (56-pt) cards'!$A$3:$BB$30,MATCH($B$2,'Topic (56-pt) cards'!$A$3:$A$30,0),MATCH("ID",'Topic (56-pt) cards'!$A$2:$BB$2,0))&""
A6: Topic | B6: =INDEX('Topic (56-pt) cards'!$A$3:$BB$30,MATCH($B$2,'Topic (56-pt) cards'!$A$3:$A$30,0),MATCH("Topic",'Topic (56-pt) cards'!$A$2:$BB$2,0))&""
A7: Level | B7: =INDEX('Topic (56-pt) cards'!$A$3:$BB$30,MATCH($B$2,'Topic (56-pt) cards'!$A$3:$A$30,0),MATCH("Level",'Topic (56-pt) cards'!$A$2:$BB$2,0))&""
A8: Term / topic | B8: =INDEX('Topic (56-pt) cards'!$A$3:$BB$30,MATCH($B$2,'Topic (56-pt) cards'!$A$3:$A$30,0),MATCH("Term / topic",'Topic (56-pt) cards'!$A$2:$BB$2,0))&""
A9: Recall cue | B9: =INDEX('Topic (56-pt) cards'!$A$3:$BB$30,MATCH($B$2,'Topic (56-pt) cards'!$A$3:$A$30,0),MATCH("Recall cue",'Topic (56-pt) cards'!$A$2:$BB$2,0))&""
A10: Category | B10: =INDEX('Topic (56-pt) cards'!$A$3:$BB$30,MATCH($B$2,'Topic (56-pt) cards'!$A$3:$A$30,0),MATCH("Category",'Topic (56-pt) cards'!$A$2:$BB$2,0))&""
A11: How often used | B11: =INDEX('Topic (56-pt) cards'!$A$3:$BB$30,MATCH($B$2,'Topic (56-pt) cards'!$A$3:$A$30,0),MATCH("How often used",'Topic (56-pt) cards'!$A$2:$BB$2,0))&""
A12: Importance (1-5) | B12: =INDEX('Topic (56-pt) cards'!$A$3:$BB$30,MATCH($B$2,'Topic (56-pt) cards'!$A$3:$A$30,0),MATCH("Importance (1-5)",'Topic (56-pt) cards'!$A$2:$BB$2,0))&""
A13: Origin / why it exists | B13: =INDEX('Topic (56-pt) cards'!$A$3:$BB$30,MATCH($B$2,'Topic (56-pt) cards'!$A$3:$A$30,0),MATCH("Origin / why it exists",'Topic (56-pt) cards'!$A$2:$BB$2,0))&""
A14: Pro tip | B14: =INDEX('Topic (56-pt) cards'!$A$3:$BB$30,MATCH($B$2,'Topic (56-pt) cards'!$A$3:$A$30,0),MATCH("Pro tip",'Topic (56-pt) cards'!$A$2:$BB$2,0))&""
A15: Memory story | B15: =INDEX('Topic (56-pt) cards'!$A$3:$BB$30,MATCH($B$2,'Topic (56-pt) cards'!$A$3:$A$30,0),MATCH("Memory story",'Topic (56-pt) cards'!$A$2:$BB$2,0))&""
A16: Picture it | B16: =INDEX('Topic (56-pt) cards'!$A$3:$BB$30,MATCH($B$2,'Topic (56-pt) cards'!$A$3:$A$30,0),MATCH("Picture it",'Topic (56-pt) cards'!$A$2:$BB$2,0))&""
A17: Emotion hook | B17: =INDEX('Topic (56-pt) cards'!$A$3:$BB$30,MATCH($B$2,'Topic (56-pt) cards'!$A$3:$A$30,0),MATCH("Emotion hook",'Topic (56-pt) cards'!$A$2:$BB$2,0))&""
A18: Importance ★ | B18: =INDEX('Topic (56-pt) cards'!$A$3:$BB$30,MATCH($B$2,'Topic (56-pt) cards'!$A$3:$A$30,0),MATCH("Importance ★",'Topic (56-pt) cards'!$A$2:$BB$2,0))&""
A19: BACK · Understanding (samjho)
A20: Definition (simple) | B20: =INDEX('Topic (56-pt) cards'!$A$3:$BB$30,MATCH($B$2,'Topic (56-pt) cards'!$A$3:$A$30,0),MATCH("Definition (simple)",'Topic (56-pt) cards'!$A$2:$BB$2,0))&""
A21: Meaning in learner's language | B21: =INDEX('Topic (56-pt) cards'!$A$3:$BB$30,MATCH($B$2,'Topic (56-pt) cards'!$A$3:$A$30,0),MATCH("Meaning in learner's language",'Topic (56-pt) cards'!$A$2:$BB$2,0))&""
A22: How / why it works | B22: =INDEX('Topic (56-pt) cards'!$A$3:$BB$30,MATCH($B$2,'Topic (56-pt) cards'!$A$3:$A$30,0),MATCH("How / why it works",'Topic (56-pt) cards'!$A$2:$BB$2,0))&""
A23: Simple explanation (Hinglish) | B23: =INDEX('Topic (56-pt) cards'!$A$3:$BB$30,MATCH($B$2,'Topic (56-pt) cards'!$A$3:$A$30,0),MATCH("Simple explanation (Hinglish)",'Topic (56-pt) cards'!$A$2:$BB$2,0))&""
A24: Real-life analogy | B24: =INDEX('Topic (56-pt) cards'!$A$3:$BB$30,MATCH($B$2,'Topic (56-pt) cards'!$A$3:$A$30,0),MATCH("Real-life analogy",'Topic (56-pt) cards'!$A$2:$BB$2,0))&""
A25: Formula / rule | B25: =INDEX('Topic (56-pt) cards'!$A$3:$BB$30,MATCH($B$2,'Topic (56-pt) cards'!$A$3:$A$30,0),MATCH("Formula / rule",'Topic (56-pt) cards'!$A$2:$BB$2,0))&""
A26: Example 1 | B26: =INDEX('Topic (56-pt) cards'!$A$3:$BB$30,MATCH($B$2,'Topic (56-pt) cards'!$A$3:$A$30,0),MATCH("Example 1",'Topic (56-pt) cards'!$A$2:$BB$2,0))&""
A27: Example 2 | B27: =INDEX('Topic (56-pt) cards'!$A$3:$BB$30,MATCH($B$2,'Topic (56-pt) cards'!$A$3:$A$30,0),MATCH("Example 2",'Topic (56-pt) cards'!$A$2:$BB$2,0))&""
A28: Example 3 | B28: =INDEX('Topic (56-pt) cards'!$A$3:$BB$30,MATCH($B$2,'Topic (56-pt) cards'!$A$3:$A$30,0),MATCH("Example 3",'Topic (56-pt) cards'!$A$2:$BB$2,0))&""
A29: Related concepts | B29: =INDEX('Topic (56-pt) cards'!$A$3:$BB$30,MATCH($B$2,'Topic (56-pt) cards'!$A$3:$A$30,0),MATCH("Related concepts",'Topic (56-pt) cards'!$A$2:$BB$2,0))&""
A30: Family / group | B30: =INDEX('Topic (56-pt) cards'!$A$3:$BB$30,MATCH($B$2,'Topic (56-pt) cards'!$A$3:$A$30,0),MATCH("Family / group",'Topic (56-pt) cards'!$A$2:$BB$2,0))&""
A31: Where it is used | B31: =INDEX('Topic (56-pt) cards'!$A$3:$BB$30,MATCH($B$2,'Topic (56-pt) cards'!$A$3:$A$30,0),MATCH("Where it is used",'Topic (56-pt) cards'!$A$2:$BB$2,0))&""
A32: Mini conversation | B32: =INDEX('Topic (56-pt) cards'!$A$3:$BB$30,MATCH($B$2,'Topic (56-pt) cards'!$A$3:$A$30,0),MATCH("Mini conversation",'Topic (56-pt) cards'!$A$2:$BB$2,0))&""
A33: Common mistake | B33: =INDEX('Topic (56-pt) cards'!$A$3:$BB$30,MATCH($B$2,'Topic (56-pt) cards'!$A$3:$A$30,0),MATCH("Common mistake",'Topic (56-pt) cards'!$A$2:$BB$2,0))&""
A34: Don't confuse with | B34: =INDEX('Topic (56-pt) cards'!$A$3:$BB$30,MATCH($B$2,'Topic (56-pt) cards'!$A$3:$A$30,0),MATCH("Don't confuse with",'Topic (56-pt) cards'!$A$2:$BB$2,0))&""
A35: Avoid / don't | B35: =INDEX('Topic (56-pt) cards'!$A$3:$BB$30,MATCH($B$2,'Topic (56-pt) cards'!$A$3:$A$30,0),MATCH("Avoid / don't",'Topic (56-pt) cards'!$A$2:$BB$2,0))&""
A36: Memory trick | B36: =INDEX('Topic (56-pt) cards'!$A$3:$BB$30,MATCH($B$2,'Topic (56-pt) cards'!$A$3:$A$30,0),MATCH("Memory trick",'Topic (56-pt) cards'!$A$2:$BB$2,0))&""
A37: Real life: project / work | B37: =INDEX('Topic (56-pt) cards'!$A$3:$BB$30,MATCH($B$2,'Topic (56-pt) cards'!$A$3:$A$30,0),MATCH("Real life: project / work",'Topic (56-pt) cards'!$A$2:$BB$2,0))&""
A38: Real life: interview / exam | B38: =INDEX('Topic (56-pt) cards'!$A$3:$BB$30,MATCH($B$2,'Topic (56-pt) cards'!$A$3:$A$30,0),MATCH("Real life: interview / exam",'Topic (56-pt) cards'!$A$2:$BB$2,0))&""
A39: Real life: daily life | B39: =INDEX('Topic (56-pt) cards'!$A$3:$BB$30,MATCH($B$2,'Topic (56-pt) cards'!$A$3:$A$30,0),MATCH("Real life: daily life",'Topic (56-pt) cards'!$A$2:$BB$2,0))&""
A40: PRACTICE · Khud karo
A41: MCQ question | B41: =INDEX('Topic (56-pt) cards'!$A$3:$BB$30,MATCH($B$2,'Topic (56-pt) cards'!$A$3:$A$30,0),MATCH("MCQ question",'Topic (56-pt) cards'!$A$2:$BB$2,0))&""
A42: MCQ options | B42: =INDEX('Topic (56-pt) cards'!$A$3:$BB$30,MATCH($B$2,'Topic (56-pt) cards'!$A$3:$A$30,0),MATCH("MCQ options",'Topic (56-pt) cards'!$A$2:$BB$2,0))&""
A43: MCQ answer | B43: =INDEX('Topic (56-pt) cards'!$A$3:$BB$30,MATCH($B$2,'Topic (56-pt) cards'!$A$3:$A$30,0),MATCH("MCQ answer",'Topic (56-pt) cards'!$A$2:$BB$2,0))&""
A44: Why that answer | B44: =INDEX('Topic (56-pt) cards'!$A$3:$BB$30,MATCH($B$2,'Topic (56-pt) cards'!$A$3:$A$30,0),MATCH("Why that answer",'Topic (56-pt) cards'!$A$2:$BB$2,0))&""
A45: Fill the blank | B45: =INDEX('Topic (56-pt) cards'!$A$3:$BB$30,MATCH($B$2,'Topic (56-pt) cards'!$A$3:$A$30,0),MATCH("Fill the blank",'Topic (56-pt) cards'!$A$2:$BB$2,0))&""
A46: Apply it | B46: =INDEX('Topic (56-pt) cards'!$A$3:$BB$30,MATCH($B$2,'Topic (56-pt) cards'!$A$3:$A$30,0),MATCH("Apply it",'Topic (56-pt) cards'!$A$2:$BB$2,0))&""
A47: Explain it yourself | B47: =INDEX('Topic (56-pt) cards'!$A$3:$BB$30,MATCH($B$2,'Topic (56-pt) cards'!$A$3:$A$30,0),MATCH("Explain it yourself",'Topic (56-pt) cards'!$A$2:$BB$2,0))&""
A48: Write your own | B48: =INDEX('Topic (56-pt) cards'!$A$3:$BB$30,MATCH($B$2,'Topic (56-pt) cards'!$A$3:$A$30,0),MATCH("Write your own",'Topic (56-pt) cards'!$A$2:$BB$2,0))&""
A49: Quick recall (reverse) | B49: =INDEX('Topic (56-pt) cards'!$A$3:$BB$30,MATCH($B$2,'Topic (56-pt) cards'!$A$3:$A$30,0),MATCH("Quick recall (reverse)",'Topic (56-pt) cards'!$A$2:$BB$2,0))&""

Sheet Anki Import
A1: Front | B1: Back | C1: Tags
A2: CI vs continuous delivery vs continuous deployment Which three practices differ in how far automation goes between a code change and production? | B2: DEFINITION (SIMPLE): Continuous integration merges and tests code often, continuous delivery keeps every build ready to release with a manual approval, and continuous deployment releases every passing build automatically. HOW / WHY IT WORKS: CI builds and tests each change soon after it is pushed. Continuous delivery adds an automated path to a release-ready package, but a person decides when to ship. Continuous deployment removes that decision, so every change that passes goes live. The difference is the human approval at the end. Strong tests are the price of full automation. SIMPLE EXPLANATION (HINGLISH): CI tests every change, delivery makes it ready to ship, deployment ships it for you. REAL-LIFE ANALOGY: CI checks the ingredients, delivery plates the dish, and deployment serves it without asking the manager. FORMULA / RULE: CI = test often. Delivery = ready to release. Deployment = released automatically. EXAMPLE 1: A pull request that runs the test suite automatically. EXAMPLE 2: A build that waits for a manager to click approve before going live. EXAMPLE 3: A change that goes live minutes after merging with no clicks. RELATED CONCEPTS: pipeline stages, triggers, environments, approvals FAMILY / GROUP: integration, delivery, deployment, pipeline, automation WHERE IT IS USED: Software teams | Customer projects | Release planning MINI CONVERSATION: A: Do we ship every merge automatically? | B: Only after a manual approval, so that is delivery, not deployment. COMMON MISTAKE: ✗ Continuous delivery and continuous deployment are the same thing → ✓ Delivery needs a human approval to release, while deployment does not DON'T CONFUSE WITH: Delivery vs deployment: delivery waits for a human decision, deployment does not. AVOID / DON'T: Do not automate releases before the tests can be trusted. MEMORY TRICK: Test often, ready always, release automatically. REAL LIFE: PROJECT / WORK: Moving a customer integration from monthly manual releases to a tested pipeline with approval. REAL LIFE: INTERVIEW / EXAM: An interviewer may ask: What is the difference between continuous delivery and continuous deployment? REAL LIFE: DAILY LIFE: It is like checking ingredients, plating a dish and serving it. | C2: 01_Ideas_Beginner_CICD-001
A3: Pipeline stages Which ordered steps does code pass through between a commit and a running release? | B3: DEFINITION (SIMPLE): A pipeline is an automated sequence of stages, such as build, test, scan, package and deploy, where each stage runs only if the one before it succeeded. HOW / WHY IT WORKS: A stage groups jobs that do one kind of work. Failure stops the pipeline, so bad changes do not reach later stages. Stages can run in parallel when they do not depend on each other. The pipeline definition is stored as code in the repository. Short feedback time is a key quality of a good pipeline. SIMPLE EXPLANATION (HINGLISH): A pipeline runs build, test, scan and deploy in order, and stops at the first failure. REAL-LIFE ANALOGY: It is a factory conveyor belt where each station inspects the product before it moves on. FORMULA / RULE: Commit → build → test → scan → package → deploy, stop on failure. EXAMPLE 1: A pipeline that lints code first and fails in ten seconds. EXAMPLE 2: Unit tests and security scans running side by side. EXAMPLE 3: A deploy stage that runs only on the main branch. RELATED CONCEPTS: triggers, build artifacts, environments, quality gates FAMILY / GROUP: stage, job, step, gate, artifact WHERE IT IS USED: Every CI system | Release automation | Reviews MINI CONVERSATION: A: The deploy ran even though tests failed. | B: The stages were not chained, so add a dependency. COMMON MISTAKE: ✗ A pipeline only needs one big script that does everything → ✓ Separate stages give clear feedback, parallel work and reuse DON'T CONFUSE WITH: Stage vs job: a stage is a phase of the pipeline, a job is one unit of work inside it. AVOID / DON'T: Do not put slow tests before quick linting. MEMORY TRICK: Fast checks first, slow checks later. REAL LIFE: PROJECT / WORK: Reordering stages so lint and unit tests failed fast before the slow integration tests. REAL LIFE: INTERVIEW / EXAM: An interviewer may ask: What stages would you put in a pipeline? REAL LIFE: DAILY LIFE: It is like a conveyor belt with an inspector at each station. | C3: 01_Ideas_Beginner_CICD-002
A4: Triggers Which events start a pipeline run automatically? | B4: DEFINITION (SIMPLE): A trigger is an event, such as a push, a pull request, a tag, a schedule or a manual click, that starts a pipeline. HOW / WHY IT WORKS: Triggers can be filtered by branch, path or tag. A path filter avoids running backend tests when only documentation changed. Scheduled triggers run nightly jobs. Manual triggers allow on-demand deployments or maintenance. Webhooks from other systems can also start runs. Pull request triggers run on code from a fork with fewer permissions. SIMPLE EXPLANATION (HINGLISH): Choose which events start the pipeline, and filter them so only relevant changes run it. REAL-LIFE ANALOGY: It is the doorbell that wakes the pipeline. FORMULA / RULE: Event + filter = when the pipeline runs. EXAMPLE 1: Running tests on every pull request. EXAMPLE 2: Deploying only when a version tag is pushed. EXAMPLE 3: A nightly scheduled data refresh. RELATED CONCEPTS: GitHub Actions workflows, branches, environments, schedules FAMILY / GROUP: event, push, pull request, schedule, webhook WHERE IT IS USED: Workflow design | Cost control | Release automation MINI CONVERSATION: A: Why did docs changes run the whole test suite? | B: There is no path filter on the trigger. COMMON MISTAKE: ✗ Pipelines can only start when code is pushed → ✓ They can also start on schedules, tags, manual clicks and webhooks DON'T CONFUSE WITH: Push trigger vs pull request trigger: one runs on pushed commits, the other on proposed merges. AVOID / DON'T: Do not trigger expensive jobs for every small docs change. MEMORY TRICK: Events start it, filters narrow it. REAL LIFE: PROJECT / WORK: Adding path filters so documentation edits no longer ran heavy integration tests. REAL LIFE: INTERVIEW / EXAM: An interviewer may ask: When should a deployment run? REAL LIFE: DAILY LIFE: It is like a doorbell that wakes the pipeline. | C4: 01_Ideas_Beginner_CICD-003
A5: Build artifacts Which outputs of a build are saved and passed to later stages or releases? | B5: DEFINITION (SIMPLE): A build artifact is a file or package produced by a build, such as a container image, a zip or a wheel, that is stored and promoted through later stages. HOW / WHY IT WORKS: Artifacts include binaries, images, test reports and coverage files. They are stored in an artifact repository or container registry, and versioned, usually with the commit hash. Promoting the same artifact from test to production ensures that what was tested is what ships. Artifacts should be immutable, meaning never changed after creation. SIMPLE EXPLANATION (HINGLISH): Build once, store the result with a version, and deploy the same thing everywhere. REAL-LIFE ANALOGY: It is a sealed box that travels down the line instead of being rebuilt at each station. FORMULA / RULE: Build once, version it, promote it unchanged. EXAMPLE 1: A container image tagged with the commit hash. EXAMPLE 2: A test report uploaded for download. EXAMPLE 3: A Python package published to a private index. RELATED CONCEPTS: registries, environments, release tagging, caching FAMILY / GROUP: artifact, package, image, version, immutable WHERE IT IS USED: Releases | Rollbacks | Auditing MINI CONVERSATION: A: The production build behaves differently from staging. | B: It was rebuilt, so promote the tested artifact instead. COMMON MISTAKE: ✗ Rebuilding for each environment is safer → ✓ Rebuilding can introduce differences, so promote the same artifact DON'T CONFUSE WITH: Artifact vs source code: the artifact is the built result, the source is the input. AVOID / DON'T: Do not overwrite a published artifact version. MEMORY TRICK: Build once, promote many times. REAL LIFE: PROJECT / WORK: Promoting one tagged image from staging to production to avoid environment surprises. REAL LIFE: INTERVIEW / EXAM: An interviewer may ask: Why build only once in a pipeline? REAL LIFE: DAILY LIFE: It is like a sealed box passed down the line. | C5: 01_Ideas_Beginner_CICD-004
A6: Environments Which separate places do changes pass through before reaching real users? | B6: DEFINITION (SIMPLE): Environments are separate deployments of the same application, such as development, staging and production, each with its own configuration and data. HOW / WHY IT WORKS: Development is for quick changes, staging mirrors production for final checks, and production serves real users. Configuration, such as database addresses and keys, differs by environment and is kept outside the code. Production data should not be copied to lower environments without masking. Protected environments can require approvals. SIMPLE EXPLANATION (HINGLISH): Try changes in dev and staging, then release to production with the same artifact and different settings. REAL-LIFE ANALOGY: Environments are rehearsal rooms before the stage performance. FORMULA / RULE: Same artifact, different configuration per environment. EXAMPLE 1: A staging database that is a masked copy of production. EXAMPLE 2: A production environment that requires approval before deploying. EXAMPLE 3: A temporary preview environment per pull request. RELATED CONCEPTS: build artifacts, configuration, approvals, secrets FAMILY / GROUP: dev, staging, production, configuration, promotion WHERE IT IS USED: Release flow | Testing | Customer projects MINI CONVERSATION: A: Can I test on production? | B: No, test on staging, which mirrors it. COMMON MISTAKE: ✗ Staging does not need to resemble production → ✓ The closer it is, the more bugs it catches before release DON'T CONFUSE WITH: Staging vs production: staging is a rehearsal copy, production serves real users. AVOID / DON'T: Do not copy raw personal data into test environments. MEMORY TRICK: Rehearse in staging, perform in production. REAL LIFE: PROJECT / WORK: Adding a staging environment that caught a configuration bug before a customer launch. REAL LIFE: INTERVIEW / EXAM: An interviewer may ask: Why do you need a staging environment? REAL LIFE: DAILY LIFE: It is like a rehearsal room before the stage. | C6: 01_Ideas_Intermediate_CICD-005
A7: DORA metrics Which four measures describe how well a team delivers software? | B7: DEFINITION (SIMPLE): The DORA metrics are deployment frequency, lead time for changes, change failure rate, failed deployment recovery time (formerly time to restore service) and, in newer guidance, rework rate. HOW / WHY IT WORKS: Deployment frequency shows how often you release. Lead time measures the time from commit to production. Change failure rate is the share of releases causing a problem. Failed deployment recovery time (formerly time to restore) measures how fast you recover. Fast and stable go together, because small, frequent changes are easier to test and fix. Numbers can be gamed if used as targets for people. SIMPLE EXPLANATION (HINGLISH): Measure how often, how fast, how safely and how quickly you recover. REAL-LIFE ANALOGY: They are four dials on a delivery dashboard. FORMULA / RULE: Speed (frequency, lead time) + stability (failure rate, restore time). EXAMPLE 1: Deploying several times a day with a lead time under an hour. EXAMPLE 2: A rollback fixing a bad release in ten minutes. EXAMPLE 3: A change failure rate of five percent. RELATED CONCEPTS: pipeline stages, rollbacks, monitoring, small batches FAMILY / GROUP: frequency, lead time, failure rate, recovery, delivery WHERE IT IS USED: Team reviews | Improvement plans | Engineering reports MINI CONVERSATION: A: How do we know the pipeline improved things? | B: Compare lead time and failure rate before and after. COMMON MISTAKE: ✗ Releasing faster always means lower quality → ✓ Small frequent releases often improve stability DON'T CONFUSE WITH: Speed vs stability metrics: frequency and lead time measure speed, failure rate and restore time measure stability. AVOID / DON'T: Do not use DORA numbers to rank individuals. MEMORY TRICK: Two for speed, two for stability. REAL LIFE: PROJECT / WORK: Tracking lead time to show the customer that the new pipeline cut release time. REAL LIFE: INTERVIEW / EXAM: An interviewer may ask: What are the DORA metrics? REAL LIFE: DAILY LIFE: It is like four dials on a dashboard. | C7: 01_Ideas_Advanced_CICD-006
A8: Workflow file Which YAML file in your repository defines an automated GitHub Actions process? name: CI on: pull_request: push: branches: [main] jobs: test: runs-on: ubuntu-latest steps: - uses: actions/checkout@v4 - run: npm test | B8: MEANING (SHORT): A workflow is a YAML file in .github/workflows that names its triggers and the jobs to run. CODE: name: CI on: pull_request: push: branches: [main] jobs: test: runs-on: ubuntu-latest steps: - uses: actions/checkout@v4 - run: npm test OUTPUT: On each pull request and each push to main, a runner starts, checks out the code and runs the tests. EXPLANATION: The file must be inside .github/workflows and end in .yml or .yaml. The on key lists triggers, and jobs defines the work. Each job runs on a runner named by runs-on. Steps either run shell commands with run or use a packaged action with uses. Results appear in the Actions tab and on the pull request. SIMPLE EXPLANATION (HINGLISH): Write a YAML file with a trigger and jobs, commit it, and GitHub runs it for you. REAL-LIFE ANALOGY: It is a recipe card kept in the cookbook beside the code. SYNTAX PATTERN: name: / on: / jobs: <id>: runs-on: / steps: ANATOMY: name = label | on = triggers | jobs = work units | runs-on = machine | steps = commands EXAMPLE 1: on: workflow_dispatch EXAMPLE 2: on: { schedule: [{ cron: "0 2 * * *" }] } EXAMPLE 3: on: { push: { tags: ["v*"] } } VARIATION: on: [push, pull_request] // shorthand for two triggers USED WITH: runners, secrets, actions, branch protection RELATED CONCEPTS: jobs and steps, runners, triggers, reusable workflows ALTERNATIVES: GitLab CI files | Jenkinsfiles WHERE IT IS USED: Testing | Building | Deploying MINI CONVERSATION: A: Nothing runs after my push. | B: The file must be in .github/workflows. COMMON MISTAKE: ✗ A workflow file can live anywhere in the repo → ✓ It must be inside .github/workflows to be detected COMMONLY CONFUSED WITH: Workflow vs job: a workflow is the whole file, a job is one unit of work inside it. AVOID / DON'T: Do not use tabs in YAML. WRONG CODE: .github/workflow/ci.yml RIGHT CODE: .github/workflows/ci.yml MEMORY TRICK: Folder name ends with an s. REAL LIFE: PROJECT / WORK: Adding a first workflow that ran the unit tests on every pull request. REAL LIFE: INTERVIEW / EXAM: An interviewer may ask: Where do GitHub Actions workflows live? REAL LIFE: DAILY LIFE: It is like a recipe card kept beside the code. | C8: 02_GitHub_Actions_Beginner_CICD-007
A9: Jobs and steps How are the work units inside a workflow organised and ordered? jobs: build: runs-on: ubuntu-latest steps: - uses: actions/checkout@v4 - run: make build deploy: needs: build runs-on: ubuntu-latest steps: - run: echo deploying | B9: MEANING (SHORT): A job is a group of steps that run on one runner, and jobs run in parallel unless one declares needs on another. CODE: jobs: build: runs-on: ubuntu-latest steps: - uses: actions/checkout@v4 - run: make build deploy: needs: build runs-on: ubuntu-latest steps: - run: echo deploying OUTPUT: The build job runs first, and the deploy job starts only after it succeeds. EXPLANATION: Every job gets a fresh runner, so files do not carry over between jobs unless you upload and download artifacts. Steps inside a job run in order and share the file system. A failing step stops the job. Use if conditions to run a step only in some cases. Job outputs can pass small values to later jobs. SIMPLE EXPLANATION (HINGLISH): Jobs run on separate machines, steps run in order inside a job, and needs links jobs. REAL-LIFE ANALOGY: Jobs are workstations, and steps are the tasks done at each one. SYNTAX PATTERN: jobs: <id>: needs: [other] steps: - run: command ANATOMY: jobs = units of work | needs = dependency | steps = ordered tasks | if = condition EXAMPLE 1: needs: [lint, test] EXAMPLE 2: if: github.ref == 'refs/heads/main' EXAMPLE 3: outputs: version: ${{ steps.v.outputs.version }} VARIATION: continue-on-error: true // let one step fail without stopping the job USED WITH: artifacts, outputs, conditions RELATED CONCEPTS: workflow file, runners, artifacts, matrix ALTERNATIVES: Stages in other CI tools WHERE IT IS USED: Multi-stage pipelines | Parallel testing | Releases MINI CONVERSATION: A: The deploy job cannot find my build output. | B: Jobs do not share files, so upload and download an artifact. COMMON MISTAKE: ✗ Jobs in one workflow share the same file system → ✓ Each job runs on its own fresh runner COMMONLY CONFUSED WITH: needs vs steps order: needs orders jobs, steps order tasks inside a job. AVOID / DON'T: Do not assume files from one job exist in the next. WRONG CODE: deploy: runs-on: ubuntu-latest # runs at the same time as build RIGHT CODE: deploy: needs: build runs-on: ubuntu-latest MEMORY TRICK: Needs chains jobs, steps stay in a job. REAL LIFE: PROJECT / WORK: Splitting lint, test and deploy into chained jobs so failures showed up clearly. REAL LIFE: INTERVIEW / EXAM: An interviewer may ask: How do you make one job wait for another? REAL LIFE: DAILY LIFE: It is like workstations with ordered tasks at each. | C9: 02_GitHub_Actions_Beginner_CICD-008
A10: Runners Which machines actually execute the jobs of a workflow? jobs: test: runs-on: ubuntu-latest mac-build: runs-on: macos-14 internal: runs-on: [self-hosted, linux] | B10: MEANING (SHORT): A runner is a machine that runs a job, either GitHub-hosted with a fresh virtual machine each time, or self-hosted on your own infrastructure. CODE: jobs: test: runs-on: ubuntu-latest mac-build: runs-on: macos-14 internal: runs-on: [self-hosted, linux] OUTPUT: Three jobs go to a hosted Linux machine, a hosted macOS machine and one of your own Linux runners. EXPLANATION: Hosted runners start clean for each job and include common tools. Minutes are free or paid depending on the plan, and macOS costs more than Linux. Self-hosted runners suit private networks or special hardware, but you must secure and update them. Labels in runs-on choose which runner is used. SIMPLE EXPLANATION (HINGLISH): Choose hosted runners for convenience and self-hosted ones for private access or special hardware. REAL-LIFE ANALOGY: A runner is the worker who picks up your job card and does it. SYNTAX PATTERN: runs-on: ubuntu-latest | runs-on: [self-hosted, label] ANATOMY: ubuntu-latest = hosted Linux | macos-14 = hosted Mac | self-hosted = your machine | labels = selectors EXAMPLE 1: runs-on: ubuntu-22.04 EXAMPLE 2: runs-on: windows-latest EXAMPLE 3: runs-on: [self-hosted, gpu] VARIATION: runs-on: ubuntu-latest-4-cores // a larger hosted runner USED WITH: matrix, caching, cost RELATED CONCEPTS: workflow file, matrix builds, self-hosted runners, caching ALTERNATIVES: Other CI agents WHERE IT IS USED: All workflows | Cross-platform builds | Private networks MINI CONVERSATION: A: The job needs our internal database. | B: Use a self-hosted runner inside the network. COMMON MISTAKE: ✗ Hosted runners keep files between runs → ✓ Each job starts on a fresh machine COMMONLY CONFUSED WITH: Hosted vs self-hosted: hosted are managed by GitHub, self-hosted are managed by you. AVOID / DON'T: Do not use self-hosted runners for public repositories without protection. WRONG CODE: runs-on: ubuntu RIGHT CODE: runs-on: ubuntu-latest MEMORY TRICK: Latest label picks the current image. REAL LIFE: PROJECT / WORK: Using a self-hosted runner so tests could reach a customer's private test database. REAL LIFE: INTERVIEW / EXAM: An interviewer may ask: When would you use a self-hosted runner? REAL LIFE: DAILY LIFE: It is like a worker who picks up each job card. | C10: 02_GitHub_Actions_Beginner_CICD-009
A11: Matrix builds Which feature runs the same job across several versions or systems automatically? jobs: test: runs-on: ${{ matrix.os }} strategy: matrix: os: [ubuntu-latest, windows-latest] python: ["3.11", "3.12"] steps: - uses: actions/setup-python@v5 with: python-version: ${{ matrix.python }} | B11: MEANING (SHORT): A matrix strategy creates one job for each combination of the listed values, and runs them in parallel. CODE: jobs: test: runs-on: ${{ matrix.os }} strategy: matrix: os: [ubuntu-latest, windows-latest] python: ["3.11", "3.12"] steps: - uses: actions/setup-python@v5 with: python-version: ${{ matrix.python }} OUTPUT: Four jobs run, one for each operating system and Python version combination. EXPLANATION: Values are read with the matrix context, such as matrix.os. Two lists of two values produce four jobs. The exclude key removes combinations, and include adds special ones. By default fail-fast cancels the other jobs when one fails, which can be turned off. Each matrix job counts towards the concurrency and minutes used. SIMPLE EXPLANATION (HINGLISH): List the versions and systems once, and Actions makes a job for each combination. REAL-LIFE ANALOGY: It is a grid of test tubes, each holding one combination. SYNTAX PATTERN: strategy: matrix: key: [values] ANATOMY: strategy = how to run | matrix = lists | exclude = remove combos | fail-fast = stop on first failure EXAMPLE 1: matrix: node: [20, 22, 24] EXAMPLE 2: exclude: [{ os: windows-latest, python: "3.11" }] EXAMPLE 3: fail-fast: false VARIATION: max-parallel: 2 // limit simultaneous jobs USED WITH: runners, caching, setup actions RELATED CONCEPTS: runners, jobs and steps, caching, quality gates ALTERNATIVES: Separate hand-written jobs WHERE IT IS USED: Libraries | Cross-platform apps | Compatibility tests MINI CONVERSATION: A: Do we support Python 3.11 and 3.12? | B: The matrix tests both on every pull request. COMMON MISTAKE: ✗ Matrix jobs run one after the other → ✓ They run in parallel, within your concurrency limits COMMONLY CONFUSED WITH: Matrix vs needs: a matrix repeats a job, needs orders different jobs. AVOID / DON'T: Do not make a huge matrix that burns minutes without need. WRONG CODE: python-version: 3.10 RIGHT CODE: python-version: "3.10" MEMORY TRICK: Quote versions so 3.10 stays 3.10. REAL LIFE: PROJECT / WORK: Testing a customer library against three Python versions with one matrix. REAL LIFE: INTERVIEW / EXAM: An interviewer may ask: How would you test on several versions? REAL LIFE: DAILY LIFE: It is like a grid of test tubes. | C11: 02_GitHub_Actions_Intermediate_CICD-010
A12: Caching dependencies How do you avoid downloading the same packages on every run? - uses: actions/cache@v4 with: path: ~/.npm key: npm-${{ hashFiles('package-lock.json') }} restore-keys: npm- | B12: MEANING (SHORT): The cache action stores files under a key and restores them in later runs when the key matches. CODE: - uses: actions/cache@v4 with: path: ~/.npm key: npm-${{ hashFiles('package-lock.json') }} restore-keys: npm- OUTPUT: The first run saves the npm cache, and later runs with the same lockfile restore it in seconds. EXPLANATION: The key must change when the contents should change, which is why a hash of the lockfile is used. restore-keys gives a fallback prefix when there is no exact match. Caches belong to a branch scope, so feature branches can read the main branch cache. Caches that are not accessed for a while are removed, and there is a total size limit per repository. Many setup actions have a built-in cache option. SIMPLE EXPLANATION (HINGLISH): Cache the package folder with a key built from the lockfile. REAL-LIFE ANALOGY: A cache is a lunch box packed once and reused all week. SYNTAX PATTERN: uses: actions/cache@v4 with: path, key, restore-keys ANATOMY: path = what to save | key = exact match | restore-keys = fallback prefixes EXAMPLE 1: uses: actions/setup-node@v4 with: { node-version: 22, cache: npm } EXAMPLE 2: key: pip-${{ hashFiles('requirements.txt') }} EXAMPLE 3: path: ~/.cache/pip VARIATION: enableCrossOsArchive: true // share a cache between systems USED WITH: setup actions, matrix, lockfiles RELATED CONCEPTS: runners, jobs and steps, build artifacts, matrix builds ALTERNATIVES: Docker layer cache WHERE IT IS USED: Slow installs | Large projects | Cost saving MINI CONVERSATION: A: Every run reinstalls everything. | B: Add a cache keyed on the lockfile. COMMON MISTAKE: ✗ A cache and an artifact are the same thing → ✓ A cache speeds up repeated work, an artifact passes results to people or later jobs COMMONLY CONFUSED WITH: Cache vs artifact: caches are for speed, artifacts are for results. AVOID / DON'T: Do not cache secrets or build outputs that must be fresh. WRONG CODE: key: npm-cache RIGHT CODE: key: npm-${{ hashFiles('package-lock.json') }} MEMORY TRICK: Hash the lockfile to refresh the cache. REAL LIFE: PROJECT / WORK: Cutting build time by caching pip downloads keyed on the requirements file. REAL LIFE: INTERVIEW / EXAM: An interviewer may ask: How do you speed up a slow dependency install? REAL LIFE: DAILY LIFE: It is like a lunch box packed once. | C12: 02_GitHub_Actions_Intermediate_CICD-011
... A41: Choosing a CI/CD tool Which questions decide the CI/CD tool for a customer? | B41: DEFINITION (SIMPLE): Choosing a CI/CD tool means weighing where the code lives, security and compliance needs, private network access, cost and team skills. HOW / WHY IT WORKS: Ask where the repository is hosted, whether jobs must reach private systems, and who maintains the servers. Check compliance needs, such as audit logs and approvals. Consider cost in minutes and in staff time. Migrating pipelines has its own cost, so avoid it without a clear gain. Prefer standard, portable steps such as scripts and containers. SIMPLE EXPLANATION (HINGLISH): Start from where the code lives and what the customer must keep private, then compare cost and skills. REAL-LIFE ANALOGY: It is choosing a vehicle for the road, not for the brochure. FORMULA / RULE: Code location + security + network + cost + skills. EXAMPLE 1: A GitHub repository with Actions as the natural choice. EXAMPLE 2: A bank needing self-hosted runners in a private network. EXAMPLE 3: A team keeping Jenkins because migration is costly. RELATED CONCEPTS: Jenkins, GitLab CI, Azure Pipelines, self-hosted runners FAMILY / GROUP: requirements, hosting, compliance, portability, cost WHERE IT IS USED: Proposals | Migrations | Platform decisions MINI CONVERSATION: A: Which CI tool should we use? | B: The one next to the code, unless security rules say otherwise. COMMON MISTAKE: ✗ The newest CI tool is always the best choice → ✓ The best tool fits the customer's code, rules and skills DON'T CONFUSE WITH: Hosted vs self-hosted: hosted is simpler, self-hosted gives control and private access. AVOID / DON'T: Do not migrate pipelines without a clear benefit. MEMORY TRICK: Fit the customer, not the fashion. REAL LIFE: PROJECT / WORK: Recommending Actions for a GitHub customer while keeping private test runners. REAL LIFE: INTERVIEW / EXAM: An interviewer may ask: How would you choose a CI tool? REAL LIFE: DAILY LIFE: It is like choosing a vehicle for the road. | C41: 06_Mapping_Intermediate_CICD-040

Sheet Anki Quiz
A1: Front | B1: Back | C1: Tags
A2: MCQ: What is the main difference between delivery and deployment? A) There is no difference B) A person approves the release in delivery C) Deployment has no code D) Delivery has no tests FILL: Merging and testing code often is called continuous ____ APPLY: Every passing change must go live with no clicks. Which practice is this? | B2: MCQ answer: B Deployment ships automatically, while delivery waits for approval. Fill answer: integration Apply: Continuous deployment | C2: 01_Ideas_Beginner_CICD-001_quiz
A3: MCQ: What happens when an early stage fails? A) The code deploys B) They all run anyway C) Later stages do not run D) The repo is deleted FILL: Where the pipeline is defined as code in the repo is a ____ file APPLY: Linting takes ten seconds and integration tests take ten minutes. Which goes first? | B3: MCQ answer: C Stages depend on the success of the one before. Fill answer: workflow Apply: Linting | C3: 01_Ideas_Beginner_CICD-002_quiz
A4: MCQ: Which trigger suits a nightly job? A) A star B) A push C) A comment D) A schedule FILL: A trigger that starts only for chosen branches uses a branch ____ APPLY: You want deployments only for version tags. Which trigger? | B4: MCQ answer: D Scheduled triggers run at set times. Fill answer: filter Apply: A tag push | C4: 01_Ideas_Beginner_CICD-003_quiz
A5: MCQ: Why promote the same artifact between environments? A) What was tested is exactly what ships B) It saves disk space only C) It avoids logging D) It removes tests FILL: An artifact that is never changed after creation is called ____ APPLY: Staging works but production fails after a rebuild. What should you change? | B5: MCQ answer: A A rebuilt artifact may differ from the tested one. Fill answer: immutable Apply: Promote the same artifact | C5: 01_Ideas_Beginner_CICD-004_quiz
A6: MCQ: What should differ between environments? A) Configuration such as addresses and keys B) The code version C) The tests D) The language FILL: Moving a build from staging to production is called ____ APPLY: You need to catch config bugs before release. What do you add? | B6: MCQ answer: A The same artifact runs with environment-specific settings. Fill answer: promotion Apply: A staging environment | C6: 01_Ideas_Intermediate_CICD-005_quiz
A7: MCQ: Which metric measures time from commit to production? A) Change failure rate B) Deployment frequency C) Lead time for changes D) Failed deployment recovery time FILL: The share of releases that cause problems is the change ____ rate APPLY: You want to know how quickly you recover from incidents. Which metric? | B7: MCQ answer: C Lead time covers the span from commit to release. Fill answer: failure Apply: Failed deployment recovery time | C7: 01_Ideas_Advanced_CICD-006_quiz
A8: MCQ: Which folder holds workflow files? A) .actions B) .github/workflows C) .github/workflow D) workflows FILL: The key that lists the events that start a workflow is ____ HINDI TO TASK: Write a trigger that runs on pull requests. PRACTICE QUESTION: What file extensions can a workflow use? | B8: MCQ answer: B GitHub only reads workflows from .github/workflows. Fill answer: on Task answer: on: pull_request: Practice answer: .yml or .yaml | C8: 02_GitHub_Actions_Beginner_CICD-007_quiz
A9: MCQ: How do you make a job wait for another job? A) after B) wait C) depends D) needs FILL: Jobs run in ____ by default unless chained HINDI TO TASK: Make the deploy job wait for the test job. PRACTICE QUESTION: Do two jobs share a file system? | B9: MCQ answer: D The needs key declares job dependencies. Fill answer: parallel Task answer: deploy: needs: test Practice answer: No, each job has its own runner. | C9: 02_GitHub_Actions_Beginner_CICD-008_quiz
A10: MCQ: What starts fresh for every hosted job? A) The branch B) The repository C) The secrets D) The runner machine FILL: The key that picks the machine for a job is ____ HINDI TO TASK: Run a job on a hosted Windows machine. PRACTICE QUESTION: Why do self-hosted runners need extra care? | B10: MCQ answer: D Hosted runners are new virtual machines per job. Fill answer: runs-on Task answer: runs-on: windows-latest Practice answer: You must secure and update them, and untrusted code could run on them. | C10: 02_GitHub_Actions_Beginner_CICD-009_quiz
A11: MCQ: Two operating systems and three versions give how many jobs? A) 3 B) 6 C) 5 D) 2 FILL: The key that removes a combination from the grid is ____ HINDI TO TASK: Test on Node 20 and 22. PRACTICE QUESTION: What does fail-fast do? | B11: MCQ answer: B Two times three combinations are created. Fill answer: exclude Task answer: strategy: matrix: node: [20, 22] Practice answer: It cancels other matrix jobs when one fails. | C11: 02_GitHub_Actions_Intermediate_CICD-010_quiz
A12: MCQ: Why include a lockfile hash in the key? A) It deletes old runs B) It encrypts the cache C) The cache refreshes when dependencies change D) It speeds the network FILL: A fallback prefix for a partial cache match is set with ____-keys HINDI TO TASK: Cache the pip folder using the requirements file as key. PRACTICE QUESTION: Why can feature branches use the main branch cache? | B12: MCQ answer: C A new hash makes a new key and a fresh cache. Fill answer: restore Task answer: - uses: actions/cache@v4 with: path: ~/.cache/pip key: pip-${{ hashFiles('requirements.txt') }} Practice answer: Caches from the default branch are readable by other branches. | C12: 02_GitHub_Actions_Intermediate_CICD-011_quiz
... A41: MCQ: What should usually decide the tool? A) Where the code lives and the customer's needs B) Personal taste C) Random choice D) The logo FILL: Steps written as scripts are more ____ between tools APPLY: A customer's code is on GitHub and jobs need no private access. What tool? | B41: MCQ answer: A Context decides, since tools share the same ideas. Fill answer: portable Apply: GitHub Actions | C41: 06_Mapping_Intermediate_CICD-040_quiz

Sheet Summary
A1: Cards by type
A2: Topic (56-pt) | B2: 28
A3: Code concept (56-pt) | B3: 12
A5: Cards by topic
A6: 02 GitHub Actions | B6: 10
A7: 04 Deployment | B7: 9
A8: 01 Ideas | B8: 6
A9: 03 Quality Gates | B9: 6
A10: 05 Security and Scale | B10: 5
A11: 06 Mapping | B11: 4
A13: Cards by level
A14: Intermediate | B14: 17
A15: Beginner | B15: 13
A16: Advanced | B16: 10
A18: Cards by source
A19: Claude knowledge | B19: 40
A21: Error check
A22: 0 errors, 0 warnings
