Workbook

Sheet Read Me
A1: EduSarthi — Customer Support English cards
A2: 180 cards: Voice, Chat and Email × Basic, Intermediate, Advanced × 20 cards. In every group of 20: 14 'Say it' cards (what the agent says or writes) and 6 'Understand it' cards (what the customer says, what it means, and what to say next).
A3: Every card has the same 56 fields on three sides, like every EduSarthi card: Side 1 Recognition · Side 2 Meaning & use · Side 3 Practice. The 'Field guide' sheet explains each field.
A4: How to study
A5: 1. Open 'Card View' and pick a card ID in the yellow cell (B3). 2. Read Side 1 and answer 'Recall first' before you look further. 3. Read Side 2. 4. Do every task on Side 3 out loud or in writing. 5. Voice and chat cards: record yourself. Email cards: write the reply and send it as text or a photo for audit. 6. In the card's sheet (Voice, Chat or Email), fill in your review columns. 7. Review again on days 1 · 3 · 7 · 15 · 30 · 60.
A6: Cells you fill in
A7: Only the yellow cells: Card View B3 (the card ID) and the 'MY REVIEW' columns at the right of the Voice, Chat and Email sheets — Status (pick Known / Unknown / Learning / Fix), Day 1 … Day 60 (the date you reviewed), My remark. Example: Status = Learning · Day 1 = 14 Oct · Day 3 = 17 Oct · My remark = 'I keep saying "one minute" instead of a real time'. The 'Summary' sheet counts your Known cards automatically.
A8: Placeholders
A9: [Company] stands for the company name. Names, order numbers, amounts and dates in the examples are made up.
A10: Status: DRAFT
A11: Every line was written by Claude from public customer-service guidance (see 'Sources') and checked twice (a script plus two rounds of independent review). It still needs a check by a verified teacher before students use it. Indian-English phrases such as 'revert' or 'prepone' are taught as switches for international customers, not as mistakes.

Sheet Card View
A1: Card View — pick a card ID in the yellow cell
A3: Card ID | B3: CSV-B-001
A5: CARD
A6: ID | B6: =IFERROR(INDEX(Voice!$A:$A,MATCH($B$3,Voice!$A:$A,0)),IFERROR(INDEX(Chat!$A:$A,MATCH($B$3,Chat!$A:$A,0)),IFERROR(INDEX(Email!$A:$A,MATCH($B$3,Email!$A:$A,0)),""))) -> CSV-B-001
A7: Channel | B7: =IFERROR(INDEX(Voice!$B:$B,MATCH($B$3,Voice!$A:$A,0)),IFERROR(INDEX(Chat!$B:$B,MATCH($B$3,Chat!$A:$A,0)),IFERROR(INDEX(Email!$B:$B,MATCH($B$3,Email!$A:$A,0)),""))) -> Voice
A8: Level | B8: =IFERROR(INDEX(Voice!$C:$C,MATCH($B$3,Voice!$A:$A,0)),IFERROR(INDEX(Chat!$C:$C,MATCH($B$3,Chat!$A:$A,0)),IFERROR(INDEX(Email!$C:$C,MATCH($B$3,Email!$A:$A,0)),""))) -> Basic
A9: CEFR | B9: =IFERROR(INDEX(Voice!$D:$D,MATCH($B$3,Voice!$A:$A,0)),IFERROR(INDEX(Chat!$D:$D,MATCH($B$3,Chat!$A:$A,0)),IFERROR(INDEX(Email!$D:$D,MATCH($B$3,Email!$A:$A,0)),""))) -> A2
A10: Kind | B10: =IFERROR(INDEX(Voice!$E:$E,MATCH($B$3,Voice!$A:$A,0)),IFERROR(INDEX(Chat!$E:$E,MATCH($B$3,Chat!$A:$A,0)),IFERROR(INDEX(Email!$E:$E,MATCH($B$3,Email!$A:$A,0)),""))) -> Say it
A11: Stage | B11: =IFERROR(INDEX(Voice!$F:$F,MATCH($B$3,Voice!$A:$A,0)),IFERROR(INDEX(Chat!$F:$F,MATCH($B$3,Chat!$A:$A,0)),IFERROR(INDEX(Email!$F:$F,MATCH($B$3,Email!$A:$A,0)),""))) -> Opening
A13: SIDE 1 · RECOGNITION
A14: Sentence | B14: =IFERROR(INDEX(Voice!$G:$G,MATCH($B$3,Voice!$A:$A,0)),IFERROR(INDEX(Chat!$G:$G,MATCH($B$3,Chat!$A:$A,0)),IFERROR(INDEX(Email!$G:$G,MATCH($B$3,Email!$A:$A,0)),""))) -> Thank you for calling [Company]. This is Priya. How can I help you today?
A15: Who says it | B15: =IFERROR(INDEX(Voice!$H:$H,MATCH($B$3,Voice!$A:$A,0)),IFERROR(INDEX(Chat!$H:$H,MATCH($B$3,Chat!$A:$A,0)),IFERROR(INDEX(Email!$H:$H,MATCH($B$3,Email!$A:$A,0)),""))) -> Agent
A16: Situation | B16: =IFERROR(INDEX(Voice!$I:$I,MATCH($B$3,Voice!$A:$A,0)),IFERROR(INDEX(Chat!$I:$I,MATCH($B$3,Chat!$A:$A,0)),IFERROR(INDEX(Email!$I:$I,MATCH($B$3,Email!$A:$A,0)),""))) -> The phone rings and you pick up the first call of your shift; you know nothing yet about the caller.
A17: Recall first | B17: =IFERROR(INDEX(Voice!$J:$J,MATCH($B$3,Voice!$A:$A,0)),IFERROR(INDEX(Chat!$J:$J,MATCH($B$3,Chat!$A:$A,0)),IFERROR(INDEX(Email!$J:$J,MATCH($B$3,Email!$A:$A,0)),""))) -> A new call connects. Which three things do you say in your first breath, and in what order?
A18: Say it like (stress) | B18: =IFERROR(INDEX(Voice!$K:$K,MATCH($B$3,Voice!$A:$A,0)),IFERROR(INDEX(Chat!$K:$K,MATCH($B$3,Chat!$A:$A,0)),IFERROR(INDEX(Email!$K:$K,MATCH($B$3,Email!$A:$A,0)),""))) -> THANK-you-for-CALL-ing-[COM-pa-ny] · this-is-PRI-ya · how-can-i-HELP-you-to-DAY
A19: Linking | B19: =IFERROR(INDEX(Voice!$L:$L,MATCH($B$3,Voice!$A:$A,0)),IFERROR(INDEX(Chat!$L:$L,MATCH($B$3,Chat!$A:$A,0)),IFERROR(INDEX(Email!$L:$L,MATCH($B$3,Email!$A:$A,0)),""))) -> thank_you → "thang-kyoo" · this_is → "thi-siz" · help_you → "hel-pyoo"
A20: Intonation & pace | B20: =IFERROR(INDEX(Voice!$M:$M,MATCH($B$3,Voice!$A:$A,0)),IFERROR(INDEX(Chat!$M:$M,MATCH($B$3,Chat!$A:$A,0)),IFERROR(INDEX(Email!$M:$M,MATCH($B$3,Email!$A:$A,0)),""))) -> Warm and steady on the greeting, with a short pause after the company name and again after your name. "How can I help you today?" is a wh- question, so let it fall gently at the end; do not rush it.
A21: Indian speaker tip | B21: =IFERROR(INDEX(Voice!$N:$N,MATCH($B$3,Voice!$A:$A,0)),IFERROR(INDEX(Chat!$N:$N,MATCH($B$3,Chat!$A:$A,0)),IFERROR(INDEX(Email!$N:$N,MATCH($B$3,Email!$A:$A,0)),""))) -> "Thank" and "this" both start with "th". For "thank", put the tongue tip lightly between the teeth and blow (not "tank"); for "this", use the same tongue position with voice (not "dis"). Minimal pairs: thin / tin (for "thank"), then / den (for "this").
A22: Register | B22: =IFERROR(INDEX(Voice!$O:$O,MATCH($B$3,Voice!$A:$A,0)),IFERROR(INDEX(Chat!$O:$O,MATCH($B$3,Chat!$A:$A,0)),IFERROR(INDEX(Email!$O:$O,MATCH($B$3,Email!$A:$A,0)),""))) -> Neutral
A23: Tone | B23: =IFERROR(INDEX(Voice!$P:$P,MATCH($B$3,Voice!$A:$A,0)),IFERROR(INDEX(Chat!$P:$P,MATCH($B$3,Chat!$A:$A,0)),IFERROR(INDEX(Email!$P:$P,MATCH($B$3,Email!$A:$A,0)),""))) -> Warm, welcoming, ready
A24: Importance (1-5) | B24: =IFERROR(INDEX(Voice!$Q:$Q,MATCH($B$3,Voice!$A:$A,0)),IFERROR(INDEX(Chat!$Q:$Q,MATCH($B$3,Chat!$A:$A,0)),IFERROR(INDEX(Email!$Q:$Q,MATCH($B$3,Email!$A:$A,0)),""))) -> 5
A25: Customer feels | B25: =IFERROR(INDEX(Voice!$R:$R,MATCH($B$3,Voice!$A:$A,0)),IFERROR(INDEX(Chat!$R:$R,MATCH($B$3,Chat!$A:$A,0)),IFERROR(INDEX(Email!$R:$R,MATCH($B$3,Email!$A:$A,0)),""))) -> Hopeful but unsure whether they have reached the right place.
A26: Memory hook | B26: =IFERROR(INDEX(Voice!$S:$S,MATCH($B$3,Voice!$A:$A,0)),IFERROR(INDEX(Chat!$S:$S,MATCH($B$3,Chat!$A:$A,0)),IFERROR(INDEX(Email!$S:$S,MATCH($B$3,Email!$A:$A,0)),""))) -> Think of opening a shop door: you thank them for coming in, show your name badge, then ask how you can help.
A28: SIDE 2 · MEANING & USE
A29: Hindi meaning | B29: =IFERROR(INDEX(Voice!$T:$T,MATCH($B$3,Voice!$A:$A,0)),IFERROR(INDEX(Chat!$T:$T,MATCH($B$3,Chat!$A:$A,0)),IFERROR(INDEX(Email!$T:$T,MATCH($B$3,Email!$A:$A,0)),""))) -> [Company] को कॉल करने के लिए धन्यवाद। मेरा नाम प्रिया है। आज मैं आपकी क्या मदद कर सकता/सकती हूँ?
A30: Hindi (Roman) | B30: =IFERROR(INDEX(Voice!$U:$U,MATCH($B$3,Voice!$A:$A,0)),IFERROR(INDEX(Chat!$U:$U,MATCH($B$3,Chat!$A:$A,0)),IFERROR(INDEX(Email!$U:$U,MATCH($B$3,Email!$A:$A,0)),""))) -> [Company] ko call karne ke liye dhanyavaad. Mera naam Priya hai. Aaj main aapki kya madad kar sakta/sakti hoon?
A31: In simple English | B31: =IFERROR(INDEX(Voice!$V:$V,MATCH($B$3,Voice!$A:$A,0)),IFERROR(INDEX(Chat!$V:$V,MATCH($B$3,Chat!$A:$A,0)),IFERROR(INDEX(Email!$V:$V,MATCH($B$3,Email!$A:$A,0)),""))) -> Thanks for phoning this company. My name is Priya. What would you like help with?
A32: Why it works | B32: =IFERROR(INDEX(Voice!$W:$W,MATCH($B$3,Voice!$A:$A,0)),IFERROR(INDEX(Chat!$W:$W,MATCH($B$3,Chat!$A:$A,0)),IFERROR(INDEX(Email!$W:$W,MATCH($B$3,Email!$A:$A,0)),""))) -> In one breath the caller learns they reached the right company, hears a real person's name, and is invited to explain. "How can I help" assumes you will help, which sounds far more willing than "What is your problem?"
A33: Key chunk | B33: =IFERROR(INDEX(Voice!$X:$X,MATCH($B$3,Voice!$A:$A,0)),IFERROR(INDEX(Chat!$X:$X,MATCH($B$3,Chat!$A:$A,0)),IFERROR(INDEX(Email!$X:$X,MATCH($B$3,Email!$A:$A,0)),""))) -> How can I help you ___?
A34: Grammar pattern | B34: =IFERROR(INDEX(Voice!$Y:$Y,MATCH($B$3,Voice!$A:$A,0)),IFERROR(INDEX(Chat!$Y:$Y,MATCH($B$3,Chat!$A:$A,0)),IFERROR(INDEX(Email!$Y:$Y,MATCH($B$3,Email!$A:$A,0)),""))) -> Thank you for + verb-ing · This is + name · How can I + base verb …?
A35: Grammar in one line | B35: =IFERROR(INDEX(Voice!$Z:$Z,MATCH($B$3,Voice!$A:$A,0)),IFERROR(INDEX(Chat!$Z:$Z,MATCH($B$3,Chat!$A:$A,0)),IFERROR(INDEX(Email!$Z:$Z,MATCH($B$3,Email!$A:$A,0)),""))) -> After "Thank you for", use the -ing form: "for calling", not "for call".
A36: Tone note | B36: =IFERROR(INDEX(Voice!$AA:$AA,MATCH($B$3,Voice!$A:$A,0)),IFERROR(INDEX(Chat!$AA:$AA,MATCH($B$3,Chat!$A:$A,0)),IFERROR(INDEX(Email!$AA:$AA,MATCH($B$3,Email!$A:$A,0)),""))) -> Saying your name makes you a person, not a machine. A flat, fast "Hello, tell me" sounds like you want the call to end quickly.
A37: Watch out | B37: =IFERROR(INDEX(Voice!$AB:$AB,MATCH($B$3,Voice!$A:$A,0)),IFERROR(INDEX(Chat!$AB:$AB,MATCH($B$3,Chat!$A:$A,0)),IFERROR(INDEX(Email!$AB:$AB,MATCH($B$3,Email!$A:$A,0)),""))) -> ✗ Thank you for calling to [Company]. I am Priya. How I can help you? → ✓ Thank you for calling [Company]. This is Priya. How can I help you today?
A38: Don't say | B38: =IFERROR(INDEX(Voice!$AC:$AC,MATCH($B$3,Voice!$A:$A,0)),IFERROR(INDEX(Chat!$AC:$AC,MATCH($B$3,Chat!$A:$A,0)),IFERROR(INDEX(Email!$AC:$AC,MATCH($B$3,Email!$A:$A,0)),""))) -> "Hello, tell me." — it skips the company name and your name, and sounds like an order.
A39: Positive swap | B39: =IFERROR(INDEX(Voice!$AD:$AD,MATCH($B$3,Voice!$A:$A,0)),IFERROR(INDEX(Chat!$AD:$AD,MATCH($B$3,Chat!$A:$A,0)),IFERROR(INDEX(Email!$AD:$AD,MATCH($B$3,Email!$A:$A,0)),""))) -> Instead of "Yes, tell me your problem", say "How can I help you today?"
A40: Another way 1 | B40: =IFERROR(INDEX(Voice!$AE:$AE,MATCH($B$3,Voice!$A:$A,0)),IFERROR(INDEX(Chat!$AE:$AE,MATCH($B$3,Chat!$A:$A,0)),IFERROR(INDEX(Email!$AE:$AE,MATCH($B$3,Email!$A:$A,0)),""))) -> Good morning, you're through to [Company]. My name is Priya. How can I help?
A41: Another way 2 | B41: =IFERROR(INDEX(Voice!$AF:$AF,MATCH($B$3,Voice!$A:$A,0)),IFERROR(INDEX(Chat!$AF:$AF,MATCH($B$3,Chat!$A:$A,0)),IFERROR(INDEX(Email!$AF:$AF,MATCH($B$3,Email!$A:$A,0)),""))) -> Hi, thanks for calling [Company]. Priya speaking. What can I do for you today?
A42: More formal | B42: =IFERROR(INDEX(Voice!$AG:$AG,MATCH($B$3,Voice!$A:$A,0)),IFERROR(INDEX(Chat!$AG:$AG,MATCH($B$3,Chat!$A:$A,0)),IFERROR(INDEX(Email!$AG:$AG,MATCH($B$3,Email!$A:$A,0)),""))) -> Good afternoon, and thank you for calling [Company]. My name is Priya. How may I assist you today?
A43: Ask next | B43: =IFERROR(INDEX(Voice!$AH:$AH,MATCH($B$3,Voice!$A:$A,0)),IFERROR(INDEX(Chat!$AH:$AH,MATCH($B$3,Chat!$A:$A,0)),IFERROR(INDEX(Email!$AH:$AH,MATCH($B$3,Email!$A:$A,0)),""))) -> Sure, I can look into that. Could I start with your name, please?
A44: Replies you may hear | B44: =IFERROR(INDEX(Voice!$AI:$AI,MATCH($B$3,Voice!$A:$A,0)),IFERROR(INDEX(Chat!$AI:$AI,MATCH($B$3,Chat!$A:$A,0)),IFERROR(INDEX(Email!$AI:$AI,MATCH($B$3,Email!$A:$A,0)),""))) -> Hi, I'm calling about my order. · Is this the billing team? · My internet has stopped working.
A45: If the customer pushes back | B45: =IFERROR(INDEX(Voice!$AJ:$AJ,MATCH($B$3,Voice!$A:$A,0)),IFERROR(INDEX(Chat!$AJ:$AJ,MATCH($B$3,Chat!$A:$A,0)),IFERROR(INDEX(Email!$AJ:$AJ,MATCH($B$3,Email!$A:$A,0)),""))) -> Customer: "Is this a real person? I've been waiting ages." → Agent: "Yes, I'm Priya, a real person, and I'm sorry about the wait. How can I help you today?"
A46: Indian English vs international | B46: =IFERROR(INDEX(Voice!$AK:$AK,MATCH($B$3,Voice!$A:$A,0)),IFERROR(INDEX(Chat!$AK:$AK,MATCH($B$3,Chat!$A:$A,0)),IFERROR(INDEX(Email!$AK:$AK,MATCH($B$3,Email!$A:$A,0)),""))) -> Many Indian agents say "Myself Priya" or open with "Yes, tell me". International callers may not expect these; they expect "This is Priya" or "My name is Priya", with the company name first.
A47: On other channels | B47: =IFERROR(INDEX(Voice!$AL:$AL,MATCH($B$3,Voice!$A:$A,0)),IFERROR(INDEX(Chat!$AL:$AL,MATCH($B$3,Chat!$A:$A,0)),IFERROR(INDEX(Email!$AL:$AL,MATCH($B$3,Email!$A:$A,0)),""))) -> Chat: "Hi, I'm Priya from [Company]. How can I help today?" Email: greet the customer by name and get to the point; no phone-style opening.
A48: When not to use | B48: =IFERROR(INDEX(Voice!$AM:$AM,MATCH($B$3,Voice!$A:$A,0)),IFERROR(INDEX(Chat!$AM:$AM,MATCH($B$3,Chat!$A:$A,0)),IFERROR(INDEX(Email!$AM:$AM,MATCH($B$3,Email!$A:$A,0)),""))) -> When you call the customer back, do not say "Thank you for calling"; say "Hi, this is Priya from [Company], returning your call."
A49: Mini conversation | B49: =IFERROR(INDEX(Voice!$AN:$AN,MATCH($B$3,Voice!$A:$A,0)),IFERROR(INDEX(Chat!$AN:$AN,MATCH($B$3,Chat!$A:$A,0)),IFERROR(INDEX(Email!$AN:$AN,MATCH($B$3,Email!$A:$A,0)),""))) -> Customer: Hello? | Agent: Thank you for calling [Company]. This is Priya. How can I help you today? | Customer: Hi, my parcel hasn't arrived. | Agent: I'm sorry to hear that. Could I have your order number, please?
A50: Best-practice rule | B50: =IFERROR(INDEX(Voice!$AO:$AO,MATCH($B$3,Voice!$A:$A,0)),IFERROR(INDEX(Chat!$AO:$AO,MATCH($B$3,Chat!$A:$A,0)),IFERROR(INDEX(Email!$AO:$AO,MATCH($B$3,Email!$A:$A,0)),""))) -> Open with thanks, the company name and an offer of help, and give your own name.
A52: SIDE 3 · PRACTICE
A53: Fill the blank | B53: =IFERROR(INDEX(Voice!$AP:$AP,MATCH($B$3,Voice!$A:$A,0)),IFERROR(INDEX(Chat!$AP:$AP,MATCH($B$3,Chat!$A:$A,0)),IFERROR(INDEX(Email!$AP:$AP,MATCH($B$3,Email!$A:$A,0)),""))) -> Thank you ____ calling [Company]. This is Priya. How can I help you today?
A54: Fill answer | B54: =IFERROR(INDEX(Voice!$AQ:$AQ,MATCH($B$3,Voice!$A:$A,0)),IFERROR(INDEX(Chat!$AQ:$AQ,MATCH($B$3,Chat!$A:$A,0)),IFERROR(INDEX(Email!$AQ:$AQ,MATCH($B$3,Email!$A:$A,0)),""))) -> for
A55: MCQ question | B55: =IFERROR(INDEX(Voice!$AR:$AR,MATCH($B$3,Voice!$A:$A,0)),IFERROR(INDEX(Chat!$AR:$AR,MATCH($B$3,Chat!$A:$A,0)),IFERROR(INDEX(Email!$AR:$AR,MATCH($B$3,Email!$A:$A,0)),""))) -> A call has just connected. Which opening is the most welcoming and complete?
A56: MCQ options | B56: =IFERROR(INDEX(Voice!$AS:$AS,MATCH($B$3,Voice!$A:$A,0)),IFERROR(INDEX(Chat!$AS:$AS,MATCH($B$3,Chat!$A:$A,0)),IFERROR(INDEX(Email!$AS:$AS,MATCH($B$3,Email!$A:$A,0)),""))) -> A) Good morning, [Company] customer service. Yes, please tell me your problem. | B) Hello, [Company] customer service, Priya here. What is the problem today? | C) Thank you for calling [Company]. This is Priya. How can I help you today? | D) Hello, this is [Company]. Please give me your name and order number.
A57: MCQ answer | B57: =IFERROR(INDEX(Voice!$AT:$AT,MATCH($B$3,Voice!$A:$A,0)),IFERROR(INDEX(Chat!$AT:$AT,MATCH($B$3,Chat!$A:$A,0)),IFERROR(INDEX(Email!$AT:$AT,MATCH($B$3,Email!$A:$A,0)),""))) -> C
A58: Why that answer | B58: =IFERROR(INDEX(Voice!$AU:$AU,MATCH($B$3,Voice!$A:$A,0)),IFERROR(INDEX(Chat!$AU:$AU,MATCH($B$3,Chat!$A:$A,0)),IFERROR(INDEX(Email!$AU:$AU,MATCH($B$3,Email!$A:$A,0)),""))) -> C thanks the caller and gives the company, your name and an offer of help. A and B ask for "the problem" bluntly, and D starts with a demand for details and skips your name.
A59: Put in order | B59: =IFERROR(INDEX(Voice!$AV:$AV,MATCH($B$3,Voice!$A:$A,0)),IFERROR(INDEX(Chat!$AV:$AV,MATCH($B$3,Chat!$A:$A,0)),IFERROR(INDEX(Email!$AV:$AV,MATCH($B$3,Email!$A:$A,0)),""))) -> help / today / I / can / How / you
A60: Order answer | B60: =IFERROR(INDEX(Voice!$AW:$AW,MATCH($B$3,Voice!$A:$A,0)),IFERROR(INDEX(Chat!$AW:$AW,MATCH($B$3,Chat!$A:$A,0)),IFERROR(INDEX(Email!$AW:$AW,MATCH($B$3,Email!$A:$A,0)),""))) -> How can I help you today
A61: Say it in English | B61: =IFERROR(INDEX(Voice!$AX:$AX,MATCH($B$3,Voice!$A:$A,0)),IFERROR(INDEX(Chat!$AX:$AX,MATCH($B$3,Chat!$A:$A,0)),IFERROR(INDEX(Email!$AX:$AX,MATCH($B$3,Email!$A:$A,0)),""))) -> [Company] ko call karne ke liye shukriya, mera naam Rahul hai. Main aaj aapki kya madad kar sakta hoon?
A62: English answer | B62: =IFERROR(INDEX(Voice!$AY:$AY,MATCH($B$3,Voice!$A:$A,0)),IFERROR(INDEX(Chat!$AY:$AY,MATCH($B$3,Chat!$A:$A,0)),IFERROR(INDEX(Email!$AY:$AY,MATCH($B$3,Email!$A:$A,0)),""))) -> Thank you for calling [Company]. This is Rahul. How can I help you today?
A63: Customer says next | B63: =IFERROR(INDEX(Voice!$AZ:$AZ,MATCH($B$3,Voice!$A:$A,0)),IFERROR(INDEX(Chat!$AZ:$AZ,MATCH($B$3,Chat!$A:$A,0)),IFERROR(INDEX(Email!$AZ:$AZ,MATCH($B$3,Email!$A:$A,0)),""))) -> Hi, I'm calling because I was charged twice.
A64: Model reply | B64: =IFERROR(INDEX(Voice!$BA:$BA,MATCH($B$3,Voice!$A:$A,0)),IFERROR(INDEX(Chat!$BA:$BA,MATCH($B$3,Chat!$A:$A,0)),IFERROR(INDEX(Email!$BA:$BA,MATCH($B$3,Email!$A:$A,0)),""))) -> I'm sorry you've been charged twice. I'll look into it for you. Could I have your name, please?
A65: Role-play task | B65: =IFERROR(INDEX(Voice!$BB:$BB,MATCH($B$3,Voice!$A:$A,0)),IFERROR(INDEX(Chat!$BB:$BB,MATCH($B$3,Chat!$A:$A,0)),IFERROR(INDEX(Email!$BB:$BB,MATCH($B$3,Email!$A:$A,0)),""))) -> Partner A phones [Company] about a late delivery. Partner B answers with thanks, the company name, their own name and an offer of help, then asks for A's name.
A66: Record / write for audit | B66: =IFERROR(INDEX(Voice!$BC:$BC,MATCH($B$3,Voice!$A:$A,0)),IFERROR(INDEX(Chat!$BC:$BC,MATCH($B$3,Chat!$A:$A,0)),IFERROR(INDEX(Email!$BC:$BC,MATCH($B$3,Email!$A:$A,0)),""))) -> Record your full opening three times: once normally, once smiling, once slowly. Submit the one that sounds the warmest.
A67: Self-check | B67: =IFERROR(INDEX(Voice!$BD:$BD,MATCH($B$3,Voice!$A:$A,0)),IFERROR(INDEX(Chat!$BD:$BD,MATCH($B$3,Chat!$A:$A,0)),IFERROR(INDEX(Email!$BD:$BD,MATCH($B$3,Email!$A:$A,0)),""))) -> Did you say the company name and your own name? · Did "today" fall at the end? · Did "thank" start with a soft "th", not "t"?
A69: MY REVIEW (fill it in on the Voice / Chat / Email sheet)
A70: Status | B70: =IFERROR(IF(INDEX(Voice!$BE:$BE,MATCH($B$3,Voice!$A:$A,0))="","",INDEX(Voice!$BE:$BE,MATCH($B$3,Voice!$A:$A,0))),IFERROR(IF(INDEX(Chat!$BE:$BE,MATCH($B$3,Chat!$A:$A,0))="","",INDEX(Chat!$BE:$BE,MATCH($B$3,Chat!$A:$A,0))),IFERROR(IF(INDEX(Email!$BE:$BE,MATCH($B$3,Email!$A:$A,0))="","",INDEX(Email!$BE:$BE,MATCH($B$3,Email!$A:$A,0))),"")))
A71: Day 1 | B71: =IFERROR(IF(INDEX(Voice!$BF:$BF,MATCH($B$3,Voice!$A:$A,0))="","",INDEX(Voice!$BF:$BF,MATCH($B$3,Voice!$A:$A,0))),IFERROR(IF(INDEX(Chat!$BF:$BF,MATCH($B$3,Chat!$A:$A,0))="","",INDEX(Chat!$BF:$BF,MATCH($B$3,Chat!$A:$A,0))),IFERROR(IF(INDEX(Email!$BF:$BF,MATCH($B$3,Email!$A:$A,0))="","",INDEX(Email!$BF:$BF,MATCH($B$3,Email!$A:$A,0))),"")))
A72: Day 3 | B72: =IFERROR(IF(INDEX(Voice!$BG:$BG,MATCH($B$3,Voice!$A:$A,0))="","",INDEX(Voice!$BG:$BG,MATCH($B$3,Voice!$A:$A,0))),IFERROR(IF(INDEX(Chat!$BG:$BG,MATCH($B$3,Chat!$A:$A,0))="","",INDEX(Chat!$BG:$BG,MATCH($B$3,Chat!$A:$A,0))),IFERROR(IF(INDEX(Email!$BG:$BG,MATCH($B$3,Email!$A:$A,0))="","",INDEX(Email!$BG:$BG,MATCH($B$3,Email!$A:$A,0))),"")))
A73: Day 7 | B73: =IFERROR(IF(INDEX(Voice!$BH:$BH,MATCH($B$3,Voice!$A:$A,0))="","",INDEX(Voice!$BH:$BH,MATCH($B$3,Voice!$A:$A,0))),IFERROR(IF(INDEX(Chat!$BH:$BH,MATCH($B$3,Chat!$A:$A,0))="","",INDEX(Chat!$BH:$BH,MATCH($B$3,Chat!$A:$A,0))),IFERROR(IF(INDEX(Email!$BH:$BH,MATCH($B$3,Email!$A:$A,0))="","",INDEX(Email!$BH:$BH,MATCH($B$3,Email!$A:$A,0))),"")))
A74: Day 15 | B74: =IFERROR(IF(INDEX(Voice!$BI:$BI,MATCH($B$3,Voice!$A:$A,0))="","",INDEX(Voice!$BI:$BI,MATCH($B$3,Voice!$A:$A,0))),IFERROR(IF(INDEX(Chat!$BI:$BI,MATCH($B$3,Chat!$A:$A,0))="","",INDEX(Chat!$BI:$BI,MATCH($B$3,Chat!$A:$A,0))),IFERROR(IF(INDEX(Email!$BI:$BI,MATCH($B$3,Email!$A:$A,0))="","",INDEX(Email!$BI:$BI,MATCH($B$3,Email!$A:$A,0))),"")))
A75: Day 30 | B75: =IFERROR(IF(INDEX(Voice!$BJ:$BJ,MATCH($B$3,Voice!$A:$A,0))="","",INDEX(Voice!$BJ:$BJ,MATCH($B$3,Voice!$A:$A,0))),IFERROR(IF(INDEX(Chat!$BJ:$BJ,MATCH($B$3,Chat!$A:$A,0))="","",INDEX(Chat!$BJ:$BJ,MATCH($B$3,Chat!$A:$A,0))),IFERROR(IF(INDEX(Email!$BJ:$BJ,MATCH($B$3,Email!$A:$A,0))="","",INDEX(Email!$BJ:$BJ,MATCH($B$3,Email!$A:$A,0))),"")))
A76: Day 60 | B76: =IFERROR(IF(INDEX(Voice!$BK:$BK,MATCH($B$3,Voice!$A:$A,0))="","",INDEX(Voice!$BK:$BK,MATCH($B$3,Voice!$A:$A,0))),IFERROR(IF(INDEX(Chat!$BK:$BK,MATCH($B$3,Chat!$A:$A,0))="","",INDEX(Chat!$BK:$BK,MATCH($B$3,Chat!$A:$A,0))),IFERROR(IF(INDEX(Email!$BK:$BK,MATCH($B$3,Email!$A:$A,0))="","",INDEX(Email!$BK:$BK,MATCH($B$3,Email!$A:$A,0))),"")))
A77: My remark | B77: =IFERROR(IF(INDEX(Voice!$BL:$BL,MATCH($B$3,Voice!$A:$A,0))="","",INDEX(Voice!$BL:$BL,MATCH($B$3,Voice!$A:$A,0))),IFERROR(IF(INDEX(Chat!$BL:$BL,MATCH($B$3,Chat!$A:$A,0))="","",INDEX(Chat!$BL:$BL,MATCH($B$3,Chat!$A:$A,0))),IFERROR(IF(INDEX(Email!$BL:$BL,MATCH($B$3,Email!$A:$A,0))="","",INDEX(Email!$BL:$BL,MATCH($B$3,Email!$A:$A,0))),"")))

Sheet Voice
A1: CARD | G1: SIDE 1 · RECOGNITION | T1: SIDE 2 · MEANING & USE | AP1: SIDE 3 · PRACTICE | BE1: MY REVIEW (fill in)
A2: ID | B2: Channel | C2: Level | D2: CEFR | E2: Kind | F2: Stage | G2: Sentence | H2: Who says it | I2: Situation | J2: Recall first | K2: Say it like (stress) | L2: Linking | M2: Intonation & pace | N2: Indian speaker tip | O2: Register | P2: Tone | Q2: Importance (1-5) | R2: Customer feels | S2: Memory hook | T2: Hindi meaning | U2: Hindi (Roman) | V2: In simple English | W2: Why it works | X2: Key chunk | Y2: Grammar pattern | Z2: Grammar in one line | AA2: Tone note | AB2: Watch out | AC2: Don't say | AD2: Positive swap | AE2: Another way 1 | AF2: Another way 2 | AG2: More formal | AH2: Ask next | AI2: Replies you may hear | AJ2: If the customer pushes back | AK2: Indian English vs international | AL2: On other channels | AM2: When not to use | AN2: Mini conversation | AO2: Best-practice rule | AP2: Fill the blank | AQ2: Fill answer | AR2: MCQ question | AS2: MCQ options | AT2: MCQ answer | AU2: Why that answer | AV2: Put in order | AW2: Order answer | AX2: Say it in English | AY2: English answer | AZ2: Customer says next | BA2: Model reply | BB2: Role-play task | BC2: Record / write for audit | BD2: Self-check | BE2: Status | BF2: Day 1 | BG2: Day 3 | BH2: Day 7 | BI2: Day 15 | BJ2: Day 30 | BK2: Day 60 | BL2: My remark
A3: CSV-B-001 | B3: Voice | C3: Basic | D3: A2 | E3: Say it | F3: Opening | G3: Thank you for calling [Company]. This is Priya. How can I help you today? | H3: Agent | I3: The phone rings and you pick up the first call of your shift; you know nothing yet about the caller. | J3: A new call connects. Which three things do you say in your first breath, and in what order? | K3: THANK-you-for-CALL-ing-[COM-pa-ny] · this-is-PRI-ya · how-can-i-HELP-you-to-DAY | L3: thank_you → "thang-kyoo" · this_is → "thi-siz" · help_you → "hel-pyoo" | M3: Warm and steady on the greeting, with a short pause after the company name and again after your name. "How can I help you today?" is a wh- question, so let it fall gently at the end; do not rush it. | N3: "Thank" and "this" both start with "th". For "thank", put the tongue tip lightly between the teeth and blow (not "tank"); for "this", use the same tongue position with voice (not "dis"). Minimal pairs: thin / tin (for "thank"), then / den (for "this"). | O3: Neutral | P3: Warm, welcoming, ready | Q3: 5 | R3: Hopeful but unsure whether they have reached the right place. | S3: Think of opening a shop door: you thank them for coming in, show your name badge, then ask how you can help. | T3: [Company] को कॉल करने के लिए धन्यवाद। मेरा नाम प्रिया है। आज मैं आपकी क्या मदद कर सकता/सकती हूँ? | U3: [Company] ko call karne ke liye dhanyavaad. Mera naam Priya hai. Aaj main aapki kya madad kar sakta/sakti hoon? | V3: Thanks for phoning this company. My name is Priya. What would you like help with? | W3: In one breath the caller learns they reached the right company, hears a real person's name, and is invited to explain. "How can I help" assumes you will help, which sounds far more willing than "What is your problem?" | X3: How can I help you ___? | Y3: Thank you for + verb-ing · This is + name · How can I + base verb …? | Z3: After "Thank you for", use the -ing form: "for calling", not "for call". | AA3: Saying your name makes you a person, not a machine. A flat, fast "Hello, tell me" sounds like you want the call to end quickly. | AB3: ✗ Thank you for calling to [Company]. I am Priya. How I can help you? → ✓ Thank you for calling [Company]. This is Priya. How can I help you today? | AC3: "Hello, tell me." — it skips the company name and your name, and sounds like an order. | AD3: Instead of "Yes, tell me your problem", say "How can I help you today?" | AE3: Good morning, you're through to [Company]. My name is Priya. How can I help? | AF3: Hi, thanks for calling [Company]. Priya speaking. What can I do for you today? | AG3: Good afternoon, and thank you for calling [Company]. My name is Priya. How may I assist you today? | AH3: Sure, I can look into that. Could I start with your name, please? | AI3: Hi, I'm calling about my order. · Is this the billing team? · My internet has stopped working. | AJ3: Customer: "Is this a real person? I've been waiting ages." → Agent: "Yes, I'm Priya, a real person, and I'm sorry about the wait. How can I help you today?" | AK3: Many Indian agents say "Myself Priya" or open with "Yes, tell me". International callers may not expect these; they expect "This is Priya" or "My name is Priya", with the company name first. | AL3: Chat: "Hi, I'm Priya from [Company]. How can I help today?" Email: greet the customer by name and get to the point; no phone-style opening. | AM3: When you call the customer back, do not say "Thank you for calling"; say "Hi, this is Priya from [Company], returning your call." | AN3: Customer: Hello? | Agent: Thank you for calling [Company]. This is Priya. How can I help you today? | Customer: Hi, my parcel hasn't arrived. | Agent: I'm sorry to hear that. Could I have your order number, please? | AO3: Open with thanks, the company name and an offer of help, and give your own name. | AP3: Thank you ____ calling [Company]. This is Priya. How can I help you today? | AQ3: for | AR3: A call has just connected. Which opening is the most welcoming and complete? | AS3: A) Good morning, [Company] customer service. Yes, please tell me your problem. | B) Hello, [Company] customer service, Priya here. What is the problem today? | C) Thank you for calling [Company]. This is Priya. How can I help you today? | D) Hello, this is [Company]. Please give me your name and order number. | AT3: C | AU3: C thanks the caller and gives the company, your name and an offer of help. A and B ask for "the problem" bluntly, and D starts with a demand for details and skips your name. | AV3: help / today / I / can / How / you | AW3: How can I help you today | AX3: [Company] ko call karne ke liye shukriya, mera naam Rahul hai. Main aaj aapki kya madad kar sakta hoon? | AY3: Thank you for calling [Company]. This is Rahul. How can I help you today? | AZ3: Hi, I'm calling because I was charged twice. | BA3: I'm sorry you've been charged twice. I'll look into it for you. Could I have your name, please? | BB3: Partner A phones [Company] about a late delivery. Partner B answers with thanks, the company name, their own name and an offer of help, then asks for A's name. | BC3: Record your full opening three times: once normally, once smiling, once slowly. Submit the one that sounds the warmest. | BD3: Did you say the company name and your own name? · Did "today" fall at the end? · Did "thank" start with a soft "th", not "t"?
A4: CSV-B-002 | B4: Voice | C4: Basic | D4: A2 | E4: Say it | F4: Verify | G4: Could I have your full name, please? | H4: Agent | I4: The caller has said they need help with a refund, and you need their name to find their account. | J4: You need to know who you are speaking to. How do you ask without sounding like a police officer? | K4: could-i-HAVE · your-FULL-NAME · PLEASE | L4: could_I → "cu-dai" · have_your → "ha-vyor" · full_name → "ful-naym" (short "u" as in "put", not "fool"; no pause between the words) | M4: A polite request shaped like a yes/no question, so rise slightly on "please?". Slow down on "full name" so it is heard clearly. | N4: "Have" ends in a real /v/: top teeth touch the lower lip, not "haw" or "hab". Practise the pair vest / west so "have" does not slide into a w-sound. | O4: Neutral | P4: Polite, simple request | Q4: 5 | R4: Neutral and ready to give details, but wants the call to move fast. | S4: Imagine holding out an open hand for a business card: "Could I have…" asks for it, it does not grab. | T4: क्या मुझे आपका पूरा नाम मिल सकता है? | U4: Kya mujhe aapka poora naam mil sakta hai? | V4: Please tell me your first name and your surname. | W4: "Could I have" is a soft, standard request that international callers hear every day. Asking for the full name up front saves a second question later when two accounts share a first name. | X4: Could I have your ___, please? | Y4: Could + I + have + your + noun, please? | Z4: "Could I have…?" asks to receive something; it is softer than "Give me…" or "Tell me…". | AA4: The question form and "please" make it polite. "Name?" or "Tell your name" sounds like a form being filled in, not a person helping. | AB4: ✗ Can you tell your full name? → ✓ Could I have your full name, please? | AC4: "Tell me your good name." — "good name" echoes Hindi "shubh naam"; international callers may find it odd, and it sounds like an order. | AD4: Instead of "Tell me your name", say "Could I have your full name, please?" | AE4: Can I take your name, please? | AF4: Who am I speaking with today? | AG4: Before we go further, could you give me your full name as it appears on the account? | AH4: Thank you, Ms Okafor. Could you spell your surname for me, please? | AI4: It's James Walker. · Sarah, Sarah Jones. · Why do you need my name? | AJ4: Customer: "Why do you need my name? Just fix it." → Agent: "I understand you want this sorted quickly. I need your name to find your account, so I can see exactly what happened." | AK4: "Your good name" and "May I know your name?" are common Indian English forms. International callers may not expect them; switch to "Could I have your name?" or "Who am I speaking with?" | AL4: Chat: "Could I have your full name, please?" works as is. Email: the name is usually in the signature, so do not ask; use it in your greeting. | AM4: Do not ask again if the caller already gave their name in the first sentence; use it instead: "Thanks, Mr Walker." | AN4: Customer: I need help with a refund. | Agent: Sure. Could I have your full name, please? | Customer: It's Anna Brooks. | Agent: Thank you, Ms Brooks. Let me find your account. | AO4: Verification: ask only for what you need, and state the purpose when the caller asks why. | AP4: Could I have your full name, ____ (starts with p)? | AQ4: please | AR4: Which way of asking for the caller's name sounds most natural to an international customer? | AS4: A) Please tell me your name quickly. | B) Could I have your full name, please? | C) What is your name? I need it now. | D) First give your name, then I will help. | AT4: B | AU4: B is a soft, standard request. A and C are orders, and D sets a condition instead of asking. | AV4: name / I / your / please / Could / full / have | AW4: Could I have your full name please | AX4: Kya main aapka poora naam jaan sakti hoon? | AY4: Could I have your full name, please? | AZ4: It's Daniel O'Brien. | BA4: Thank you, Mr O'Brien. Let me check the spelling: O, apostrophe, B-R-I-E-N. Is that right? | BB4: Partner A calls to change a delivery address. Partner B asks for A's full name, repeats it back, and asks A to spell the surname. | BC4: Record yourself asking for the caller's name, then thanking them by name, as if the caller said "Anna Brooks". | BD4: Did your voice rise a little on "please?" · Did you ask with "Could I have..." rather than "Tell me"? · Did "have" end in a clear "v"?
A5: CSV-B-003 | B5: Voice | C5: Basic | D5: B1 | E5: Say it | F5: Verify | G5: To protect your account, could you confirm your registered mobile number or email address? | H5: Agent | I5: Before you can discuss a billing question, you must check that the caller is the account holder. | J5: Before sharing any account details, you must check who the caller is. What reason do you give first, and what do you ask for? | K5: to-pro-TECT-your-ac-COUNT · could-you-con-FIRM · your-REG-is-tered-MO-bile-NUM-ber · or-E-mail-ad-DRESS | L5: protect_your → "pro-tek-chor" · confirm_your → "con-fur-myor" · email_address → "ee-may-la-dress" | M5: Keep your voice level, or rise a little, after "account" and pause, so the caller hears that the request is still coming. In "mobile number or email address", rise on "number" and fall on "address" to show there are two choices. | N5: Final clusters: "protect" ends in "-kt" and "registered" ends in "-rd". Say pro-TEKT and REJ-is-terd with the last sound clear; dropping it ("pro-tek", "REJ-is-ter") makes the words harder to catch on a phone line. | O5: Neutral | P5: Calm, reassuring, clear | Q5: 5 | R5: Slightly impatient, and may wonder why they must prove who they are. | S5: A bank locker needs two keys: first show why (to keep it safe), then ask for the second key (their number). | T5: आपके अकाउंट की सुरक्षा के लिए, क्या आप अपना रजिस्टर्ड मोबाइल नंबर या ईमेल पता कन्फ़र्म कर सकते हैं? | U5: Aapke account ki suraksha ke liye, kya aap apna registered mobile number ya email address confirm kar sakte hain? | V5: So that nobody else can use your account, please tell me the phone number or email linked to it. | W5: Putting the reason first turns a check into something done for the customer, not against them. Offering two options lets them use whichever one they remember. | X5: To protect your account, could you confirm your ___? | Y5: To + base verb (purpose), could + you + confirm + noun? | Z5: "To protect…" at the start explains why; it means "so that I can protect…". | AA5: The reason makes it feel like care, not suspicion. "Give your number first, then I'll talk" sounds like you think they are lying. | AB5: ✗ For protect your account, could you confirm registered mobile number or email? → ✓ To protect your account, could you confirm your registered mobile number or email address? | AC5: "I can't tell you anything until you verify." — it sounds like a threat and gives no reason the caller cares about. | AD5: Instead of "I can't help without verification", say "To protect your account, could you confirm your registered mobile number or email address?" | AE5: For your security, could you tell me the mobile number on the account? | AF5: Just so I know I'm speaking with the account holder, could you confirm your email address? | AG5: To keep your account secure, could you please confirm the mobile number or email address registered with us? | AH5: Thank you, that matches. Now, how can I help with your bill today? | AI5: It's 07700 900123. · Which email, my work one or my personal one? · I don't remember which number I used. | AJ5: Customer: "I've already given this to the last agent!" → Agent: "I'm sorry to ask again. We check on every call to keep your account safe. Your email address works too, if that's easier." | AK5: "May I know your registered mobile number?" is common on Indian calls. It is grammatical, but international callers may not expect it; they more often hear "Could you confirm…?" or "Could you tell me…?" | AL5: Chat: same wording, but never ask for a full card number, PIN, password or one-time code (OTP). Email: ask the customer to reply from the email address registered on the account. | AM5: Do not use it if the caller only wants general information, such as opening hours, which needs no account access. | AN5: Customer: I want to check my last bill. | Agent: To protect your account, could you confirm your registered mobile number or email address? | Customer: It's lucy.grant@example.com. | Agent: Thank you, that matches. Let me open your bill. | AO5: Verification: state the purpose ("To protect your account…") and ask only for what you need. | AP5: ____ protect your account, could you confirm your registered mobile number or email address? | AQ5: To | AR5: You must verify the caller before discussing their bill. Which line explains the check best? | AS5: A) Before I tell you anything, you will have to prove you are the account holder. | B) To protect your account, could you confirm your registered mobile number or email address? | C) I can't discuss your bill until you give me your registered mobile number or email address. | D) It is company rule, so could you please confirm your registered mobile number or email? | AT5: B | AU5: B gives a reason the customer cares about. A sounds like a threat, C refuses until the customer complies, and D hides behind "company rule" instead of explaining why. | AV5: account / your / protect / To / could / confirm / you / email / your / address | AW5: To protect your account could you confirm your email address | AX5: Aapke account ki suraksha ke liye, kya aap apna registered email address confirm kar sakte hain? | AY5: To protect your account, could you confirm your registered email address? | AZ5: Why do you need that? I'm the account holder. | BA5: I understand, and I'm sorry for the extra step. It's a quick check we do on every call, so nobody else can get into your account. | BB5: Partner A calls about a high phone bill. Partner B explains the reason for the check, asks for the registered mobile number or email, confirms it matches, then asks how to help. | BC5: Record the verification line, then the line you say when the number matches, then the line you say when it does not match. | BD5: Did you give the reason before the request? · Did "address" fall at the end to show a choice? · Did you say the final "t" in "protect"?
A6: CSV-B-004 | B6: Voice | C6: Basic | D6: A2 | E6: Say it | F6: Listen & clarify | G6: I'm sorry, I didn't catch that. Could you say it again, please? | H6: Agent | I6: The caller said their order number quickly and you missed two of the digits. | J6: You missed part of what the caller said. How do you ask them to repeat it without blaming them? | K6: i'm-SOR-ry · i-DID-n't-CATCH-that · could-you-SAY-it-a-GAIN · PLEASE | L6: sorry_I → "sor-ree-yai" (a small "y" joins the two vowels) · didn't_catch → "didn-catch" · say_it_again → "say-yi-ta-gen" | M6: Gentle fall on "catch that", a short pause, then a rise on "please?". Keep the voice soft so it sounds like your miss, not theirs. | N6: "That" starts with a voiced "th": put the tongue tip between the teeth and add voice. Saying "dat" is a common habit because Hindi has no English-style "th" and uses a "d" or "t" instead; practise then / den. | O6: Neutral | P6: Apologetic, polite request | Q6: 5 | R6: Mildly impatient, and may feel they already spoke clearly. | S6: Their words were a ball thrown to you and you did not catch it: say sorry, then ask them to throw it once more. | T6: माफ़ कीजिए, मैं ठीक से सुन नहीं पाया/पाई। क्या आप फिर से बता सकते हैं? | U6: Maaf kijiye, main theek se sun nahin paaya/paayi. Kya aap phir se bata sakte hain? | V6: Sorry, I missed what you said. Please say it one more time. | W6: "I didn't catch that" puts the miss on you, not on the caller's accent or speed. A guessed digit leads to the wrong order later, so asking is always better than guessing. | X6: I didn't catch ___. Could you say it again, please? | Y6: I + didn't + catch + that · Could + you + say + it + again, please? | Z6: "Catch" here means "hear and understand"; use the past "didn't catch" because the words were already said. | AA6: Apologising first makes it your problem. "What?" or "Repeat" sounds rude, and "You are not clear" blames the caller. | AB6: ✗ Sorry, I am not understanding. Say again please. → ✓ I'm sorry, I didn't catch that. Could you say it again, please? | AC6: "Speak properly, I can't understand you." — it blames the caller and can sound like you are judging their accent. | AD6: Instead of "You are not audible", say "I'm sorry, I didn't catch that. Could you say it again, please?" | AE6: Sorry, could you repeat the last part, please? | AF6: I missed the last two digits. Could you read them out again? | AG6: I do apologise, I didn't quite catch that. Would you mind repeating it, please? | AH6: Thank you. So that's 4 8 1 7 2. Is that right? | AI6: Sure, it's 4 8 1 7 2. · Which part did you miss? · I just said it! | AJ6: Customer: "I just said it!" → Agent: "I know, and I'm sorry. I want to get the number exactly right so I find the correct order." | AK6: "Repeat once more" and "You are not audible" are common on Indian calls. International callers may hear them as abrupt or formal; "I didn't catch that" is the softer, more expected form. | AL6: Chat: hearing is not the issue, but you can ask "Could you check that number again? I can't find it." Email: ask for the missing detail in one clear question. | AM6: Do not ask a third time in the same way; ask the caller to spell it or read it slowly, digit by digit. | AN6: Customer: My order number is four-eight-one-something-two. | Agent: I'm sorry, I didn't catch that. Could you say it again, please? | Customer: Four, eight, one, seven, two. | Agent: Thank you. That's 4 8 1 7 2. Let me find it. | AO6: Ask politely for a repeat ("I'm sorry, could you please repeat that?") rather than guess. | AP6: I'm ____ (starts with s), I didn't catch that. Could you say it again, please? | AQ6: sorry | AR6: You missed part of the caller's account number. Which response is best? | AS6: A) Your voice is not clear. Please say the number again, and slowly. | B) I'm sorry, I didn't catch that. Could you say it again, please? | C) I think I got most of it, so I'll carry on with the number I heard. | D) Could you speak louder and slower? You are going too fast for me. | AT6: B | AU6: B apologises and asks politely. C risks opening the wrong account, and A and D put the blame on the caller. | AV6: again / Could / say / it / you / please | AW6: Could you say it again please | AX6: Maaf kijiye, main sun nahin paaya. Kya aap phir se bata sakte hain? | AY6: I'm sorry, I didn't catch that. Could you say it again, please? | AZ6: Sure. It's 4 8 1 7 2. | BA6: Thank you, that's much clearer. I've got all five digits now, so let me find your order. | BB6: Partner A reads a five-digit order number quickly and swallows one digit. Partner B asks for a repeat politely, then reads the full number back to confirm. | BC6: Record yourself asking for a repeat, then reading back the number 4 8 1 7 2 slowly, digit by digit. | BD6: Did you say sorry before asking? · Did you avoid "repeat" as a one-word order? · Did "that" start with a soft "th", not "d"?
A7: CSV-B-005 | B7: Voice | C7: Basic | D7: A2 | E7: Say it | F7: Listen & clarify | G7: Could you spell your email address for me, please? | H7: Agent | I7: The caller has given an unusual email address, and you need it exactly right to send a refund receipt. | J7: The caller's email has an unusual name in it. What do you ask so that you type it exactly right? | K7: could-you-SPELL · your-E-mail-ad-DRESS · for-ME · PLEASE | L7: spell_your → "spel-yor" · email_address → "ee-may-la-dress" · for_me → "fer-mee" | M7: One smooth question, rising on "please?". While they spell, say "Yes" or "Got it" after each group so they know you are with them. | N7: "Spell" starts with an s-cluster: say "spell" straight away, not "ispell" or "su-pell". Some speakers add a vowel before s-clusters (as in "iskul" for school); keep the "s" and "p" together. | O7: Neutral | P7: Careful, polite request | Q7: 4 | R7: Patient, but may be tired of spelling their email on every call. | S7: Picture the letters dropping one by one into your keyboard like coins: one wrong coin and the email bounces. | T7: क्या आप मेरे लिए अपना ईमेल पता स्पेल कर सकते हैं? | U7: Kya aap mere liye apna email address spell kar sakte hain? | V7: Please say the letters of your email one by one. | W7: Spelling stops mistakes with names that sound alike, like "Shaw" and "Shore". One wrong letter means the customer never gets the email and has to call back. | X7: Could you spell ___ for me, please? | Y7: Could + you + spell + noun + for me, please? | Z7: "Spell" means say each letter; "for me" makes the request personal and softer. | AA7: "For me, please" sounds like you want to get it right for them. "Spell it" on its own sounds like an order. | AB7: ✗ Please spelling your email address. → ✓ Could you spell your email address for me, please? | AC7: "Your email is not clear, spell it." — it blames the customer for a normal difficulty. | AD7: Instead of "Tell your email ID spelling", say "Could you spell your email address for me, please?" | AE7: Could you spell that for me, letter by letter? | AF7: Just to get it right, could you spell your email for me? | AG7: To make sure the receipt reaches you, would you mind spelling your email address for me? | AH7: Thank you. Let me read it back: r-o-s-s-k-a-y at example dot com. Is that right? | AI7: Sure, it's r-o-s-s-k-a-y at example dot com. · Is it the one on my account? · Didn't I give that already? | AJ7: Customer: "It's just my name, it's easy!" → Agent: "It is, and I want to be sure I don't mix up an 'e' and an 'i'. Spelling it now saves you a lost receipt." | AK7: "Email ID" is common in India; international callers usually say "email address" or just "email". Read it back with "at" and "dot", and use clear words for letters (B for Bravo) if needed. | AL7: Chat: no spelling needed; ask "Could you type your email here?" Email: you already have it, so do not ask. | AM7: Do not ask the caller to spell something already on your screen from verification; read it back and ask for a yes or no instead. | AN7: Customer: My email is rosskay at example dot com. | Agent: Could you spell your email address for me, please? | Customer: R-O-S-S-K-A-Y at example dot com. | Agent: Thank you. I have rosskay at example dot com. Is that right? | AO7: Ask callers to spell names and emails, then read them back. | AP7: Could you spell your email ____ for me, please? | AQ7: address | AR7: The caller's surname could be "Shaw" or "Shore". What is the best next step? | AS7: A) Type "Shaw" for now, because it is the more common spelling. | B) Ask, "Could you spell your surname for me, please?" | C) Say, "Sorry, your name is not clear. Please say it again." | D) Ask the caller to send their name by email later. | AT7: B | AU7: B removes the doubt politely. A is a guess that can put the wrong name on the account, C blames the caller, and D delays the fix and risks losing the detail. | AV7: email / spell / Could / for / you / me / your / address / please | AW7: Could you spell your email address for me please | AX7: Kya aap apne naam ki spelling bata sakte hain? | AY7: Could you spell your name for me, please? | AZ7: Sure. It's t-h-o-m-a-s dot r-e-e-d at example dot com. | BA7: Thank you. I have thomas dot reed at example dot com. Is that right? | BB7: Partner A has the email "lia.devane@example.com" and says it fast. Partner B asks A to spell it, reads it back with "dot" and "at", and confirms. | BC7: Record yourself asking for the spelling, then reading back the email "lia.devane at example dot com" letter by letter. | BD7: Did you say "spell" without an extra vowel at the start? · Did you read the email back? · Did you say "email address" in full?
A8: CSV-B-006 | B8: Voice | C8: Basic | D8: A2 | E8: Say it | F8: Hold & check | G8: Could you hold for about two minutes, please? I'll check your order. | H8: Agent | I8: The customer asked about their order and you need about two minutes to look it up in the system. | J8: You need a couple of minutes to look something up. What do you ask the caller first, and what do you promise them? | K8: could-you-HOLD · for-a-BOUT-two-MIN-utes · PLEASE · i'll-CHECK · your-OR-der | L8: could_you → "cud-joo" · hold_for → "hole-fer" · two_minutes → "too-MIN-its" | M8: Rising tone on "please?" because it is a real question. Short pause after it, then a falling, confident tone on "I'll check your order." | N8: Say "hold" with a long "oh" and a clear final "d"; do not drop it to "hol". "Minutes" is MIN-its, stress on the first part, with a clear final "s". | O8: Neutral | P8: Polite request, calm | Q8: 5 | R8: Patient but a little worried about how long this will take. | S8: Picture pressing a soft pause button on a remote: you ask before you press it, and you promise to press play again. | T8: क्या आप लगभग दो मिनट होल्ड कर सकते हैं? मैं आपका ऑर्डर देखता/देखती हूँ। | U8: Kya aap lagbhag do minute hold kar sakte hain? Main aapka order dekhta/dekhti hoon. | V8: Please stay on the line for about two minutes while I look at your order. | W8: It asks permission instead of giving an order, says why the caller is waiting and gives a real time. "A moment" is vague; "about two minutes" lets the caller decide. | X8: Could you ___, please? | Y8: Could + you + base verb + …, please? · I'll + base verb | Z8: "Could you" makes a polite request; "I'll" means you are deciding to do it now. | AA8: The question form lets the caller say yes. "Hold on" or "Wait" sounds like an order and can make a worried caller feel ignored. | AB8: ✗ Hold the line, I check it. → ✓ Could you hold for about two minutes, please? I'll check your order. | AC8: "Wait." or "Hold on." — it is an order, gives no reason, and the caller does not know if you are still there. | AD8: Instead of "Wait, I am checking", say "Could you hold for about two minutes, please? I'll check your order." | AE8: Would you mind holding for about two minutes while I look into this? | AF8: May I put you on hold for two or three minutes while I check your order? | AG8: Would it be all right if I placed you on hold for about two minutes while I review your account? | AH8: Thank you for holding. I can see your order — it was dispatched yesterday. | AI8: Sure, go ahead. · How long will it take? · Can't you just tell me now? | AJ8: Customer: "Can't you just tell me now?" → Agent: "I know you'd like it now, and I'll be quick. I need to check one detail so the answer is right. It will take about two minutes." | AK8: Many agents say "One minute, sir" and go silent. International callers expect a reason, a time, and a "thank you for holding" when you return. | AL8: Chat: "Let me check that for you. It'll take about two minutes." Email: not needed; say when you will reply instead. | AM8: Do not put an angry caller on hold right after they finish complaining; acknowledge their problem first. | AN8: Customer: My order still hasn't arrived. Can you check it? | Agent: Could you hold for about two minutes, please? I'll check your order. | Customer: Sure. | Agent: Thank you for holding. Your order was dispatched yesterday. | AO8: Ask permission before a hold, give the reason and a real time, and thank the caller first when you return. | AP8: Could you hold ____ about two minutes, please? I'll check your order. | AQ8: for | AR8: You need to check the order history. Which line puts the caller on hold in the most polite way? | AS8: A) You must hold the line now, because I need to check your order history. | B) Could you hold for about two minutes, please? I'll check your order. | C) Wait, please. I am checking your order now, so do not disconnect the call. | D) Hold on, sir, I will be back soon. I just need to look at a few things. | AT8: B | AU8: B asks permission, gives a reason and a real time. A and C are orders, and D gives no clear reason and no real time ("soon"). | AV8: hold / you / minutes / for / about / Could / two / please | AW8: Could you hold for about two minutes please | AX8: Kya aap lagbhag do minute hold kar sakte hain? Main aapka payment check karta hoon. | AY8: Could you hold for about two minutes, please? I'll check your payment. | AZ8: How long will it take? | BA8: About two minutes. If it's going to take longer, I'll come back and tell you before then. | BB8: Partner A calls about a missing parcel. Partner B asks to put A on hold, checks for two minutes, comes back, thanks A for holding and gives an update. | BC8: Record yourself saying the sentence, then the "Thank you for holding" line you would say when you return. | BD8: Did your voice rise on "please?" · Did you say why the caller is waiting? · Did you pronounce the final "d" in "hold"?
A9: CSV-B-007 | B9: Voice | C9: Basic | D9: A2 | E9: Say it | F9: Hold & check | G9: Thank you for holding, Ms Carter. I've found your order, and it's on its way. | H9: Agent | I9: You return to the line after a two-minute hold with the order update the caller asked for. | J9: You come back after putting someone on hold. What is the very first thing you say, before any information? | K9: THANK-you-for-HOLD-ing · ms-CAR-ter · i've-FOUND-your-OR-der · and-it's-ON-its-WAY | L9: thank_you → "thang-kyoo" · found_your → "foun-jor" · it's_on_its_way → "it-son-it-sway" | M9: Warm, slightly lifted energy on "Thank you for holding". Pause after the name. Falling, confident tone on "on its way". | N9: "Way" starts with a W: round your lips and keep the teeth off the lip; do not say "vay". Minimal pair: west / vest. Also keep the final "d" in "found" before "your". | O9: Neutral | P9: Grateful, warm, positive | Q9: 5 | R9: A little restless after waiting, and hoping for good news. | S9: Coming back from hold is like returning to a guest you left at the door: thank them first, then hand over the parcel. | T9: होल्ड करने के लिए धन्यवाद, मिस कार्टर। मुझे आपका ऑर्डर मिल गया है, और वह रास्ते में है। | U9: Hold karne ke liye dhanyavaad, Ms Carter. Mujhe aapka order mil gaya hai, aur woh raaste mein hai. | V9: Thanks for waiting. I found your order, and it is being delivered. | W9: Thanking first rewards the caller's patience and tells them you are back. Using their name and giving the news straight away ends the uncertainty of the wait. | X9: Thank you for holding, ___. I've found ___. | Y9: Thank you for + verb-ing · I've (I have) + past participle | Z9: "I've found" (present perfect) means you have just found it and the result matters now. | AA9: The thanks and the name make the wait feel respected. Coming back with "Hello? Yes, so…" sounds like you forgot about them. | AB9: ✗ Thank you for hold, Ms Carter. I am finding your order. → ✓ Thank you for holding, Ms Carter. I've found your order. | AC9: "Hello? Are you there? Yes, so your order…" — it skips the thanks and sounds disorganised. | AD9: Instead of "Sorry, I took long", say "Thank you for holding, Ms Carter. I've found your order." | AE9: Thanks so much for waiting, Ms Carter. I have an update for you. | AF9: Thank you for your patience, Ms Carter. Good news: your order has shipped. | AG9: Thank you very much for holding, Ms Carter. I have now located your order, and it is on its way to you. | AH9: It should reach you by Thursday. Would you like the tracking number? | AI9: Oh, great, thank you. · When will it arrive? · That took longer than two minutes. | AJ9: Customer: "That took a lot longer than two minutes." → Agent: "You're right, and I'm sorry it took longer. The good news is your order is on its way and should arrive by Thursday." | AK9: Some agents come back with "Yes ma'am, I have checked the same." International callers may not expect "the same"; they expect a clear "Thank you for holding", their name, then the news. | AL9: Chat: "Thanks for waiting, Ms Carter. I've found your order." Email: there is no hold; thank them for their patience only if your reply is late. | AM9: Do not come back with this if you have no update yet; say "Thank you for holding. I need about two more minutes. Is that all right?" | AN9: Customer: Sure, I'll hold. | Agent: Thank you for holding, Ms Carter. I've found your order, and it's on its way. | Customer: Great! When will it arrive? | Agent: It should reach you by Thursday. | AO9: Thank the caller first when you return from hold, before giving information. | AP9: Thank you for holding, Ms Carter. I've found your order, and it's on its ____. | AQ9: way | AR9: You come back after a two-minute hold. Which line should you say first? | AS9: A) Hello? Are you still there? I have your order details now. | B) Okay, I have checked your order and it is shipped now, Ms Carter. | C) Sorry, the system is very slow today. I found your order, finally. | D) Thank you for holding, Ms Carter. I've found your order. | AT9: D | AU9: D thanks the caller first and uses their name. B jumps straight to the news, C blames the system before thanking the caller, and A sounds as if you forgot them. | AV9: order / found / for / Thank / I've / holding / you / your | AW9: Thank you for holding I've found your order | AX9: Hold karne ke liye shukriya. Mujhe aapka payment mil gaya hai. | AY9: Thank you for holding. I've found your payment. | AZ9: Oh good. When will it get here? | BA9: The courier is due to deliver on Thursday. I can text you the tracking link if that helps. | BB9: Partner A waits on hold for an order update. Partner B returns, thanks A by name, gives the update and the delivery day, then offers the tracking number. | BC9: Record your return-from-hold line twice: once with good news, and once telling the caller you need two more minutes. | BD9: Did you thank the caller before giving news? · Did you use their name? · Did "way" start with rounded lips, not "v"?
A10: CSV-B-008 | B10: Voice | C10: Basic | D10: A2 | E10: Say it | F10: Apologise | G10: I'm sorry your parcel arrived late. I'll find out what happened right away. | H10: Agent | I10: The customer says their birthday gift arrived three days after the promised delivery date. | J10: A parcel came late. How do you apologise for the exact problem and show that you will act? | K10: i'm-SOR-ry · your-PAR-cel-a-RIVED-LATE · i'll-FIND-OUT · what-HAP-pened · right-a-WAY | L10: arrived_late → "a-rived-late" (touch the d, then release it into the l) · find_out → "fine-dout" · right_away → "ry-ta-way" | M10: Slow, low and sincere on "I'm sorry your parcel arrived late." Pause. Then a firmer, falling tone on "right away" to show action. | N10: "Arrived" and "happened" end in a final "d" after another consonant: say a-RIVED and HAP-pend, not "a-rive" and "hap-pen". The past tense lives in that last sound. | O10: Neutral | P10: Sincere, responsible, active | Q10: 5 | R10: Disappointed and annoyed that a promise was broken. | S10: A good apology has two hands: one says sorry for the exact thing, the other reaches out to fix it. | T10: मुझे खेद है कि आपका पार्सल देर से पहुँचा। मैं अभी पता करता/करती हूँ कि क्या हुआ। | U10: Mujhe khed hai ki aapka parcel der se pahuncha. Main abhi pata karta/karti hoon ki kya hua. | V10: I am sorry the package came late. I will check the reason now. | W10: It names the exact problem, which shows you listened, and pairs the apology with action. In Lewicki, Polin and Lount's 2016 study, taking responsibility ranked first and offering repair second among the parts of an apology; say "we" when the company is at fault: "I'm sorry we didn't deliver on time." | X10: I'm sorry ___. I'll ___ right away. | Y10: I'm sorry + (that) + clause · I'll + base verb | Z10: After "I'm sorry", add the exact problem as a full clause: "I'm sorry your parcel arrived late." | AA10: A specific apology sounds real. "Sorry for the inconvenience" sounds scripted, and "It's not my fault" sounds like you are defending yourself. | AB10: ✗ Sorry for your parcel delay, I will check what is the matter. → ✓ I'm sorry your parcel arrived late. I'll find out what happened right away. | AC10: "Sorry for the inconvenience caused." — it is vague and scripted, and says nothing about what you will do. | AD10: Instead of "That is the courier's fault, not ours", say "I'm sorry your parcel arrived late. I'll find out what happened right away." | AE10: I'm really sorry it came late, especially for a birthday. Let me check what went wrong. | AF10: I'm sorry we didn't deliver on time. I'll look into it now. | AG10: Please accept my apologies for the late delivery of your parcel. I will look into the cause immediately. | AH10: Could you give me your order number so I can check the delivery history? | AI10: Thank you, I appreciate that. · It was a birthday present, it's ruined now. · Sorry doesn't help me. | AJ10: Customer: "Sorry doesn't help me." → Agent: "You're right, saying sorry isn't enough. I'm checking the delivery record now so I can tell you what went wrong and what I can do to put it right." | AK10: "Sorry for the inconvenience caused" is a common line in Indian scripts. International customers often hear it as automatic; naming the actual problem sounds sincere. | AL10: Chat: "I'm sorry your parcel arrived late. I'll check what happened now." Email: apologise in the first line, then say what you did and what happens next. | AM10: Do not promise "right away" if the check needs another team and takes days; say when you will update the customer instead. | AN10: Customer: My parcel came three days late. | Agent: I'm sorry your parcel arrived late. I'll find out what happened right away. | Customer: Thank you. It was a gift. | Agent: That makes it even more disappointing. Could I have your order number, please? | AO10: Apologise specifically and take responsibility, then offer a fix (Lewicki, Polin & Lount, 2016). | AP10: I'm sorry your parcel arrived late. I'll find ____ what happened right away. | AQ10: out | AR10: A customer's parcel came three days late. Which apology works best? | AS10: A) Sorry for the inconvenience. We value your patience and will try to improve. | B) I understand, but the courier is responsible for the late delivery, not our company. | C) These things happen sometimes, so please be patient and wait for the next delivery. | D) I'm sorry your parcel arrived late. I'll find out what happened right away. | AT10: D | AU10: D names the problem and promises action. A is vague and sounds scripted, B pushes the blame onto someone else, and C brushes the problem off. | AV10: late / arrived / sorry / your / I'm / parcel | AW10: I'm sorry your parcel arrived late | AX10: Mujhe khed hai ki aapka refund der se aaya. Main abhi check karta hoon. | AY10: I'm sorry your refund came late. I'll check it right now. | AZ10: It was for my son's birthday. It's too late now. | BA10: I'm really sorry it missed his birthday. Let me check the order and see what I can do for you. | BB10: Partner A's parcel arrived three days late and missed a birthday. Partner B apologises for the exact problem, asks for the order number and says what they will check. | BC10: Record your apology, then the next line where you ask for the order number. Keep your voice slow and low on the apology. | BD10: Did you name the exact problem? · Did you say what you will do next? · Did you say the final "d" in "arrived"?
A11: CSV-B-009 | B11: Voice | C11: Basic | D11: B1 | E11: Say it | F11: Listen & clarify | G11: Let me make sure I have this right: you were charged twice for one order. Is that correct? | H11: Agent | I11: The caller has explained a long billing problem, and you want to check you understood before you act. | J11: The caller has just explained a long problem. How do you check your understanding before you start fixing anything? | K11: let-me-make-SURE · i-have-this-RIGHT · you-were-CHARGED-TWICE · for-ONE-OR-der · is-that-cor-RECT | L11: let_me → "lem-mee" · charged_twice → "charjd-twice" (a quick d, no extra vowel) · that_correct → "tha-cor-rect" (the t of "that" is barely heard) | M11: Fall on "right", then pause. Say the summary more slowly, with stress on "twice" and "one". Rise on "correct?" because it is a yes/no question. | N11: "Charged" ends in two sounds, "j" then "d": say "charjd". Dropping the "d" gives "charge", which sounds like the present tense. Also "this" has a voiced "th", not "dis". | O11: Neutral | P11: Careful, attentive, checking | Q11: 5 | R11: Frustrated, and keen to be understood before anything else happens. | S11: A tailor measures twice and cuts once: you check the problem before you cut into the fix. | T11: मैं पक्का कर लूँ कि मैंने सही समझा है: आपके एक ही ऑर्डर के लिए दो बार पैसे कट गए। क्या यह सही है? | U11: Main pakka kar loon ki maine sahi samjha hai: aapke ek hi order ke liye do baar paise kat gaye. Kya yeh sahi hai? | V11: I want to check I understood: you paid two times for one order. Yes? | W11: Saying the problem back shows you listened and lets the caller correct you early. Fixing the wrong problem wastes their time and makes them explain everything again. | X11: Let me make sure I have this right: ___. Is that correct? | Y11: Let me + base verb · you + were + past participle (passive) · Is that + adjective? | Z11: "You were charged" is passive: it says what happened to the caller without blaming anyone. | AA11: It sounds careful and respectful. "So what you are saying is…" in a flat voice can sound like you doubt them. | AB11: ✗ So you was charged twice for one order, right? → ✓ Let me make sure I have this right: you were charged twice for one order. Is that correct? | AC11: "Okay, okay, I understood." — said before the caller finishes, it sounds like you are not listening. | AD11: Instead of "Your problem is not clear", say "Let me make sure I have this right: you were charged twice for one order. Is that correct?" | AE11: So, just to check: you paid twice for a single order. Is that right? | AF11: Just to check, the money came out of your account twice for one order? | AG11: To be sure I have understood, you were charged twice for a single order. Have I got that right? | AH11: Thank you. Could you tell me the date of the order so I can find both payments? | AI11: Yes, exactly. · Not quite, it was two different orders. · Yes, and I want the money back today. | AJ11: Customer: "Why are you repeating it? I just told you!" → Agent: "I'm sorry, I know you've just explained it. I'm checking so I fix the right thing first time. You were charged twice, so I'll look at both payments now." | AK11: "You are telling that…" is a common Indian English pattern. International callers more often expect "So, you…" or "If I've understood correctly…", with a clear question at the end. | AL11: Chat: "Just to confirm: you were charged twice for one order?" Email: open with a one-line summary, such as "You were charged twice for order 55021." | AM11: Do not paraphrase a one-line request like "What are your opening hours?"; just answer it. | AN11: Customer: I ordered once but my card shows two payments. | Agent: Let me make sure I have this right: you were charged twice for one order. Is that correct? | Customer: Yes, that's it. | Agent: Thank you. Let me find both payments. | AO11: Paraphrase before solving: sum up what you heard, then ask a yes/no question so the caller can correct you. | AP11: Let me make ____ (starts with s) I have this right: you were charged twice for one order. | AQ11: sure | AR11: The caller has just explained a confusing billing problem. What should you do before you start fixing it? | AS11: A) Start the refund straight away, then explain what you did. | B) Say "Okay, okay, I understand" so they know you are listening. | C) Summarise the problem back to them and ask "Is that correct?" | D) Ask them to email all the details so you can read them properly. | AT11: C | AU11: C catches misunderstandings early. A may fix the wrong problem, B can sound as if you are not really listening, and D makes the caller do more work. | AV11: right / make / Let / have / sure / me / I / this | AW11: Let me make sure I have this right | AX11: Main confirm kar leti hoon: aapka parcel galat address par gaya, sahi? | AY11: Let me make sure I have this right: your parcel went to the wrong address. Is that correct? | AZ11: Not exactly. I was charged twice, but for two different amounts. | BA11: Thank you for correcting me. So there are two payments with different amounts. Let me look at both. | BB11: Partner A explains, at length, that a subscription renewed twice this month. Partner B listens without interrupting, sums up the problem in one sentence and asks "Is that correct?" | BC11: Record yourself summing up this problem to the customer in one sentence: they ordered a blue shirt and received a red one. Start with "Let me make sure I have this right" and say "you". | BD11: Did you sum up in one short sentence? · Did your voice rise on "correct?" · Did you say the final "d" in "charged"?
A12: CSV-B-010 | B12: Voice | C12: Basic | D12: A2 | E12: Say it | F12: Verify | G12: Could you read me your order number? You'll find it in your confirmation email. | H12: Agent | I12: The caller wants to know where their order is, and you need the order number to search for it. | J12: You need the caller's order reference to search. What do you ask, and how do you help them find it? | K12: could-you-READ-me · your-OR-der-NUM-ber · you'll-FIND-it · in-your-con-fir-MA-tion-E-mail | L12: read_me → "ree-mee" · find_it → "fine-dit" · confirmation_email → "con-fur-may-shun-ee-mayl" | M12: Rise on "number?". Pause. Then a falling, helpful tone on "confirmation email", said as a tip, not an order. | N12: "Number" has its stress on the first part, NUM-ber, with a weak "-ber"; do not give both parts equal beats. In "confirmation", the stress is on "MA" (con-fur-MAY-shun), not on "con". | O12: Neutral | P12: Helpful, guiding request | Q12: 5 | R12: Eager for an update, and maybe unsure where the number is. | S12: The order number is the key to the right locker, and you also tell them which pocket the key is in. | T12: क्या आप मुझे अपना ऑर्डर नंबर पढ़कर बता सकते हैं? यह आपको कन्फ़र्मेशन ईमेल में मिलेगा। | U12: Kya aap mujhe apna order number padhkar bata sakte hain? Yeh aapko confirmation email mein milega. | V12: Please tell me your order number. It is in the email we sent when you ordered. | W12: Saying where the number is saves the caller from searching and stops "I don't know it" from becoming a dead end. It shows you are thinking one step ahead for them. | X12: Could you read me your ___? You'll find it in ___. | Y12: Could + you + read + me + noun? · You'll + find + it + in + place | Z12: "You'll find it in…" is a friendly way to say where something is. | AA12: Giving the location helps the caller. "Order number?" alone sounds like a form, and "Give order ID first" sounds like a condition. | AB12: ✗ Could you read me your order number? You will found it in confirmation email. → ✓ Could you read me your order number? You'll find it in your confirmation email. | AC12: "Without order ID I can't do anything." — it blocks the caller and does not help them find the number. | AD12: Instead of "I can't check without the order number", say "Could you read me your order number? You'll find it in your confirmation email." | AE12: Do you have your order number handy? It starts with the letters SO. | AF12: If you have the confirmation email open, could you read me the order number? | AG12: Could you please give me your order number? It appears at the top of your order confirmation email. | AH12: Thank you. That's S O 5 5 0 2 1. Let me look that up. | AI12: Hang on, let me find it. · It's SO55021. · I deleted that email. | AJ12: Customer: "I deleted the email." → Agent: "That's fine. I can find your order with your email address or phone number instead." | AK12: "Order ID" and "then only I can check" are common Indian phrasing. International callers usually say "order number" and expect you to offer another way if they cannot find it. | AL12: Chat: "Could you share your order number? It's in your confirmation email." Email: ask for it only if it is not already in their message. | AM12: Do not ask for the order number if you already found the order during verification; confirm the order on your screen instead. | AN12: Customer: Where's my order? | Agent: Could you read me your order number? You'll find it in your confirmation email. | Customer: It's SO55021. | Agent: Thank you. Let me look that up for you. | AO12: Ask only for what you need, and make it easy for the customer to give it. | AP12: Could you read me your order number? You'll find it ____ your confirmation email. | AQ12: in | AR12: The caller is not sure where their order number is. What is the most helpful thing to say? | AS12: A) I can't check your order without the order number. Do you have it? | B) Could you read me your order number, please? I need it to find your order quickly. | C) Could you read me your order number? You'll find it in your confirmation email. | D) Please call us back when you have your order number, and we will help then. | AT12: C | AU12: C tells the caller where to look. A and D block them, and B asks for the number but does not help them find it. | AV12: number / read / your / Could / me / order / you | AW12: Could you read me your order number | AX12: Kya aap apna order number bata sakte hain? Woh aapke SMS mein hoga. | AY12: Could you tell me your order number? You'll find it in your text message. | AZ12: Which email do you mean? I get a lot of emails from you. | BA12: It's the one with the subject "Order confirmed". If you can't find it, I can search with your email address instead. | BB12: Partner A calls about a late order but cannot find the order number at first. Partner B says where to look and offers to search by email if A still cannot find it. | BC12: Record yourself asking for the order number, then the backup line you say if the caller has deleted the email. | BD12: Did you say where to find the number? · Did "number" have stress on the first part? · Did you offer a backup if they cannot find it?
A13: CSV-B-011 | B13: Voice | C13: Basic | D13: A2 | E13: Say it | F13: Opening | G13: Sure, I can help you with that. | H13: Agent | I13: The caller has just explained that they cannot log in to their account and sounds worried. | J13: A worried caller has just told you their problem. What short line tells them they are in the right place? | K13: SURE · i-can-HELP-you · with-THAT | L13: I_can → "eye-kn" (weak "can") · help_you → "hel-pyoo" · with_that → "wi-that" (one "th" sound) | M13: Bright on "Sure", then steady and falling on "that" to sound confident. Do not rise at the end, or it sounds like a question. | N13: In "with that", the "th" at the end of "with" and the start of "that" join into one soft voiced "th", tongue between the teeth; avoid "wit dat". | O13: Friendly | P13: Calm, confident reassurance | Q13: 5 | R13: Worried and unsure whether this call will solve anything. | S13: It is a friendly hand on the shoulder: seven short words that tell the caller they can relax now. | T13: ज़रूर, मैं इसमें आपकी मदद कर सकता/सकती हूँ। | U13: Zaroor, main ismein aapki madad kar sakta/sakti hoon. | V13: Yes, I am able to help with this problem. | W13: It answers the caller's real fear ("Will anyone fix this?") in one breath, before any questions. It promises help, not a result, so it stays honest. | X13: I can help you with ___. | Y13: I + can + help + you + with + noun | Z13: "Help you with" takes a thing: "help you with that", "help you with your login". | AA13: Short and warm sounds confident. "I will try" sounds unsure, and "That's not my department" sounds like you want to get rid of them. | AB13: ✗ I will try to help you for that. → ✓ Sure, I can help you with that. | AC13: "I'll try, but I'm not sure." — it makes a worried caller more worried. | AD13: Instead of "I'll try my best", say "Sure, I can help you with that." | AE13: Of course, I'm happy to help you with your login. | AF13: Don't worry, let's get you back into your account. | AG13: Certainly, I'd be glad to help you with that. | AH13: First, could you tell me the email address you use to log in? | AI13: Oh, thank goodness. · Great, thanks. · The last person said that too. | AJ13: Customer: "The last person said that too." → Agent: "I'm sorry it wasn't fixed then. I'll stay with you on this call and tell you each step as I do it." | AK13: "I will try my level best" is a common, kind phrase in India, but international callers may hear "try" as doubt. "I can help you with that" sounds more certain. | AL13: Chat: "Sure, I can help you with that." works as is. Email: "I can help with this" fits as the first line after the greeting. | AM13: Do not say it when the request belongs to another team; say "The billing team handles this. I'll transfer you and explain your case to them." | AN13: Customer: I can't log in and I need my invoice today. | Agent: Sure, I can help you with that. | Customer: Oh, good. | Agent: First, could you tell me the email address you use to log in? | AO13: Lead with what you can do; use "I can" and "I will", not "we'll try". | AP13: Sure, I can help you ____ that. | AQ13: with | AR13: A worried caller has just explained they are locked out. Which first reply builds the most confidence? | AS13: A) I'll try my best, but I can't promise that it will work today. | B) That's a very common problem. It happens to a lot of our customers. | C) Why did you lock yourself out? Did you forget your password? | D) Sure, I can help you with that. Let's get you back into your account. | AT13: D | AU13: D is certain and kind, and starts the fix. A sounds unsure, B does not say you will help, and C sounds like blame. | AV13: with / can / help / I / that / you | AW13: I can help you with that | AX13: Haan bilkul, main aapki ismein madad kar sakta hoon. | AY13: Sure, I can help you with that. | AZ13: Thank you. I've been trying for an hour. | BA13: I'm sorry it's taken so long. Let's fix it together now. | BB13: Partner A is stressed because they cannot reset a password before a meeting. Partner B reassures A in one line, then asks the first question needed to help. | BC13: Record the line three times: flat, too excited, and warm and calm. Submit the warm and calm one for audit. | BD13: Did your voice fall at the end, not rise? · Did you avoid "try"? · Did you follow it with a question that moves the call on?
A14: CSV-B-012 | B14: Voice | C14: Basic | D14: A2 | E14: Say it | F14: Listen & clarify | G14: Sorry, the line isn't very clear. Could you speak up a little, please? | H14: Agent | I14: The caller's voice keeps breaking up, and you can hear only half of each sentence. | J14: You can hear only half of what the caller says. How do you tell them, and what do you ask them to do? | K14: SOR-ry · the-LINE-is-n't-VER-y-CLEAR · could-you-SPEAK-UP · a-LIT-tle · PLEASE | L14: line_isn't → "lie-nizunt" · speak_up → "spee-kup" · a_little → "uh-lit-ul" | M14: A calm fall on "clear", so the caller knows the line is the problem, not them. Rise on "please?". Speak a little slower and louder yourself. | N14: In "very", the "v" needs your top teeth on your lower lip, not rounded lips (vest / west), so it is not heard as "wery". "Little" is LIT-ul, with a very weak second part. | O14: Neutral | P14: Calm, practical request | Q14: 4 | R14: Possibly unaware the line is bad, or frustrated by a weak signal. | S14: Blame the wire, never the caller: the line is the villain in this sentence. | T14: माफ़ कीजिए, लाइन साफ़ नहीं है। क्या आप थोड़ा ज़ोर से बोल सकते हैं? | U14: Maaf kijiye, line saaf nahin hai. Kya aap thoda zor se bol sakte hain? | V14: Sorry, the phone sound is bad. Please talk a bit louder. | W14: It blames the line, not the caller's voice or accent, and gives one easy action. If that fails, offering a callback stops both of you from struggling. | X14: Sorry, the line isn't very clear. Could you ___, please? | Y14: The line + isn't + very + adjective · Could + you + speak up? | Z14: "Speak up" is a phrasal verb that means "speak more loudly". | AA14: Naming the line keeps it neutral. "I can't hear you properly" or "Your voice is breaking" can sound like the caller is at fault. | AB14: ✗ Please speak loudly, line is not clear. → ✓ Sorry, the line isn't very clear. Could you speak up a little, please? | AC14: "Hello? Hello? Hello?" again and again — it sounds panicked and gives the caller nothing to do. | AD14: Instead of "Your voice is breaking", say "Sorry, the line isn't very clear. Could you speak up a little, please?" | AE14: I'm sorry, you're breaking up a little. Could you say that again? | AF14: The line's quite bad. Could I call you back on this number in a minute? | AG14: I'm afraid the line is unclear. Would it be all right if I called you back on the number ending 4417? | AH14: That's much better, thank you. You were saying your card was declined? | AI14: Is that better? · I'm on the train, sorry. · Can you call me back in ten minutes? | AJ14: Customer: "I can hear you fine!" → Agent: "I'm glad you can hear me. On my side the line is breaking up a little, so I want to be sure I don't miss anything." | AK14: "You are not audible" is a standard Indian office phrase. International callers rarely use it and may hear it as formal or blaming; "The line isn't very clear" sounds neutral. | AL14: Chat and email do not have this problem. If a chat keeps disconnecting, offer email: "If the chat drops, I'll email you the update." | AM14: Do not ask the caller to speak up if the line is fine and they are just quiet and upset; slow down and listen instead. | AN14: Customer: My card was … de… today. | Agent: Sorry, the line isn't very clear. Could you speak up a little, please? | Customer: Is that better? My card was declined today. | Agent: Much better, thank you. Let me check your card. | AO14: Tell the caller what is happening, and offer a callback instead of a long struggle. | AP14: Sorry, the line isn't very clear. Could you speak ____ a little, please? | AQ14: up | AR14: The caller's voice keeps cutting out. Which response is best first? | AS14: A) Sorry, your voice is breaking. Please speak loudly and clearly. | B) Hello? Hello? Can you hear me? Hello? I can't hear anything. | C) I'm afraid I cannot help you on this line. Please call us again later. | D) Sorry, the line isn't very clear. Could you speak up a little, please? | AT14: D | AU14: D blames the line and asks for one easy action. A blames the caller's voice, B gives the caller nothing to do, and C gives up before trying a callback. | AV14: up / you / Could / little / speak / a / please | AW14: Could you speak up a little please | AX14: Line kharab hai. Kya main aapko do minute mein call back kar sakta hoon? | AY14: The line is quite bad. Could I call you back in two minutes? | AZ14: Sorry, I'm on the train. Is that better? | BA14: Yes, that's much better, thank you. Let's carry on. | BB14: Partner A calls from a noisy train and the line keeps breaking. Partner B asks A to speak up, and when that fails, offers to call back on A's number in ten minutes. | BC14: Record the "speak up" line, then the callback offer you would make if the line does not improve. | BD14: Did you blame the line, not the caller? · Did you offer a callback if it stays bad? · Did "very" start with a clear "v", not "w"?
... A62: CSV-A-020 | B62: Voice | C62: Advanced | D62: C1 | E62: Understand it | F62: Difficult customer | G62: I'll take my business elsewhere. | H62: Customer | I62: A customer of six years is upset that their insurance premium rose without warning and says they will move to a competitor. | J62: A loyal customer says they will move to a competitor. What are they really telling you, and what is your first move? | K62: i'll TAKE my BIZ-nis else-WHERE | L62: take_my → "tay-kmy" (no gap between k and m) · my_business → "mai-BIZ-nis" · business_elsewhere → "biz-ni-sels-WAIR" (the s joins the e) | M62: Usually calm, slow and final, falling on "elsewhere"; a quiet delivery can mean the decision is close. A loud one may be a bargaining move. | N62: "Business" has two syllables, BIZ-nis, with a z sound, not "bi-zi-ness" in three beats. Listen for "elsewhere": British speakers stress the second part, els-WHERE (American speakers often say ELS-wair). | O62: Neutral | P62: Calm, final warning | Q62: 5 | R62: Disappointed, feeling unvalued after years of loyalty. | S62: A customer with one foot out of the door: you don't block the door, you ask what made them stand up. | T62: मैं किसी और कंपनी के पास चला/चली जाऊँगा/जाऊँगी। (मतलब: मुझे लगता है यहाँ मेरी कद्र नहीं है।) | U62: Main kisi aur company ke paas chala/chali jaaunga/jaaungi. (Matlab: mujhe lagta hai yahaan meri kadar nahin hai.) | V62: The customer means: "I will stop buying from you and use another company instead." | W62: It often signals that a loyal customer feels taken for granted and may still stay if someone listens. They need you to acknowledge their loyalty, ask what went wrong, and offer something real, without pressure. | X62: I'll take my ___ elsewhere. | Y62: I'll + take + my business + elsewhere (a decision made now) | Z62: "Business" here means "the money I spend with you", not a company the customer owns. | AA62: It is a serious warning, not an insult. Replying "Okay, that's your choice" sounds as if the customer does not matter. | AB62: ✗ Agent: Okay sir, it is your wish. → ✓ Agent: I'd be sorry to lose you after six years. Could you tell me what's changed? | AC62: "Okay, that's your decision, sir." — it lets a loyal customer walk away without even asking why. | AD62: Instead of "If you want to go, you can go", say "I'd be sorry to lose you. Could you tell me what's made you feel this way?" | AE62: You've been with us for six years, and I'd hate to lose you. Can you tell me what went wrong with the renewal? | AF62: I understand, and I'd like to see if I can fix this first. What would make you want to stay? | AG62: We greatly value your six years with us, and I would be sorry to lose you as a customer. Could you tell me what prompted this? | AH62: I'd be sorry to lose you after six years. Could you tell me what's changed, so I can see what I can do? | AI62: My premium went up by 3,000 rupees with no warning. · Nothing you say will change my mind. · Another company has offered me a better price. | AJ62: Customer: "Nothing you say will change my mind." → Agent: "That's completely your choice, and I'll help either way. If you're happy for me to, I can check whether the increase was a mistake; it will take two minutes." | AK62: Some learners may hear "business" and think the customer owns a company. In this phrase it simply means "my custom", and it is a common way to threaten to switch providers. | AL62: Chat: often "ill go to another company" or "switching provider"; acknowledge, then ask one question. Email: often the last line of a complaint; answer the complaint fully and mention their loyalty. | AM62: Do not keep trying to hold on to a customer who has clearly confirmed they want to leave; respect the decision and make leaving easy. | AN62: Customer: My premium's gone up again. I'll take my business elsewhere. | Agent: I'd be sorry to lose you after six years. Could you tell me what's changed, so I can see what I can do? | Customer: It went up by 3,000 rupees without any warning. | Agent: I'm sorry you weren't told in advance. Let me review the renewal now and see if a better plan fits you. | AO62: Listen, acknowledge, then act: one common version is LATTE (credited to Starbucks). | AP62: I'd be sorry to ____ you after six years. Could you tell me what's changed? | AQ62: lose | AR62: A long-time customer says, "I'll take my business elsewhere." What do they mean? | AS62: A) They are planning to open their own company somewhere else in the city. | B) They want to move their registered business address to another place. | C) They want to be transferred to the business team in another department. | D) They plan to stop using your company and buy from a competitor instead. | AT62: D | AU62: D is right: "take my business elsewhere" means spend money with another company. A and B are tempting because "business" often means a company, but here it means the customer's custom; C confuses it with a department. | AV62: what's / me / you / Could / changed / tell | AW62: Could you tell me what's changed | AX62: Aap chhe saal se hamare saath hain, mujhe aapko khona achha nahin lagega. Kya aap bata sakte hain kya badla? | AY62: You've been with us for six years, and I'd be sorry to lose you. Could you tell me what's changed? | AZ62: Another company has offered me a cheaper price. | BA62: Thank you for telling me. Let me review your plan now; if I can match that cover for less, I'll tell you before you decide. | BB62: Partner A, a customer for six years, is angry about a surprise premium increase and says they will switch. Partner B acknowledges their loyalty, asks what changed, and offers one real option without pressure. | BC62: Record your reply to the customer's line in a sincere voice, then record what you would say if they answer "Nothing will change my mind." | BD62: Did you understand "business" as the customer's custom? · Did you mention their loyalty? · Did you ask a question before offering anything?

Sheet Chat
A1: CARD | G1: SIDE 1 · RECOGNITION | T1: SIDE 2 · MEANING & USE | AP1: SIDE 3 · PRACTICE | BE1: MY REVIEW (fill in)
A2: ID | B2: Channel | C2: Level | D2: CEFR | E2: Kind | F2: Stage | G2: Sentence | H2: Who says it | I2: Situation | J2: Recall first | K2: Say it like (stress) | L2: Linking | M2: Intonation & pace | N2: Indian speaker tip | O2: Register | P2: Tone | Q2: Importance (1-5) | R2: Customer feels | S2: Memory hook | T2: Hindi meaning | U2: Hindi (Roman) | V2: In simple English | W2: Why it works | X2: Key chunk | Y2: Grammar pattern | Z2: Grammar in one line | AA2: Tone note | AB2: Watch out | AC2: Don't say | AD2: Positive swap | AE2: Another way 1 | AF2: Another way 2 | AG2: More formal | AH2: Ask next | AI2: Replies you may hear | AJ2: If the customer pushes back | AK2: Indian English vs international | AL2: On other channels | AM2: When not to use | AN2: Mini conversation | AO2: Best-practice rule | AP2: Fill the blank | AQ2: Fill answer | AR2: MCQ question | AS2: MCQ options | AT2: MCQ answer | AU2: Why that answer | AV2: Put in order | AW2: Order answer | AX2: Say it in English | AY2: English answer | AZ2: Customer says next | BA2: Model reply | BB2: Role-play task | BC2: Record / write for audit | BD2: Self-check | BE2: Status | BF2: Day 1 | BG2: Day 3 | BH2: Day 7 | BI2: Day 15 | BJ2: Day 30 | BK2: Day 60 | BL2: My remark
A3: CSC-B-001 | B3: Chat | C3: Basic | D3: A2 | E3: Say it | F3: Opening | G3: Hi, thanks for contacting [Company]. I'm Ananya. How can I help you today? | H3: Agent | I3: A new chat window opens on the website and you send the first message to the customer. | J3: A customer has just opened a chat with your company. What three things does your first message give them? | K3: HI · thanks-for-con-TACT-ing-[COM-pa-ny] · i'm-a-NAN-ya · how-can-i-HELP-you-to-DAY | L3: If read aloud: thanks_for → "thanks-fer" · help_you → "hel-pyoo" · I'm_Ananya → "ai-ma-NAN-ya" (the "m" joins the next vowel) | M3: If read aloud: a friendly lift on "Hi", a short pause after the company name, and a falling tone on "How can I help you today?" because it is a wh- question. | N3: If read aloud: "thanks" starts with a soft "th" (tongue lightly between the teeth), not a hard "t" as in "tanks". Keep the final "s". | O3: Friendly | P3: Warm, welcoming, ready to help | Q3: 5 | R3: Hopeful but unsure whether a real person is on the other side. | S3: Think of a shop door bell: hello, the shop's name, your name tag and "how can I help?", all in one ring. | T3: नमस्ते, [Company] से संपर्क करने के लिए धन्यवाद। मैं अनन्या हूँ। आज मैं आपकी कैसे मदद कर सकता/सकती हूँ? | U3: Namaste, [Company] se sampark karne ke liye dhanyavaad. Main Ananya hoon. Aaj main aapki kaise madad kar sakta/sakti hoon? | V3: Hello, thank you for writing to us. My name is Ananya. What do you need help with? | W3: It tells the customer a real person has joined, gives a name they can use, and ends with an open question so they can explain the problem in their own words. | X3: Hi, thanks for contacting ___. I'm ___. | Y3: Thanks + for + verb-ing · How + can + I + base verb + you …? | Z3: After "thanks for", use the -ing form: "thanks for contacting", not "thanks for contact". | AA3: "Hi" and "thanks" sound human and friendly. "Dear Customer, state your query" sounds like a robot and makes the customer write back coldly. | AB3: ✗ Hi, thanks for contact [Company]. How I can help you? → ✓ Hi, thanks for contacting [Company]. How can I help you today? | AC3: "Hello Dear Customer, please state your query." — it is cold, sounds automated and gives no name. | AD3: Instead of "State your query", say "How can I help you today?" | AE3: Hello and welcome to [Company]. My name's Ananya. What can I help you with? | AF3: Hi there, you're chatting with Ananya from [Company]. How can I help? | AG3: Good morning, and thank you for contacting [Company]. My name is Ananya. How may I help you today? | AH3: Thanks, Sarah. Could you share your order number so I can take a look? | AI3: Hi, my parcel hasn't arrived. · I want to change my delivery address. · is this a bot? | AJ3: Customer: "Is this a bot?" → Agent: "No, I'm Ananya, a real person on the [Company] support team. How can I help you today?" | AK3: Many Indian agents introduce themselves with "Myself Ananya"; international customers may not expect this, so switch to "I'm Ananya" or "My name's Ananya" in chat. | AL3: Voice: "Thank you for calling [Company]. This is Ananya." Email: "Hi Sarah, thanks for getting in touch," with your name in the sign-off. | AM3: Do not send the full greeting if a colleague has already greeted the customer and passed the chat to you; write "Hi Sarah, I'm Ananya from billing" instead. | AN3: Customer: hello | Agent: Hi, thanks for contacting [Company]. I'm Ananya. How can I help you today? | Customer: my parcel is late | Agent: I'm sorry it's late. Could you share your order number so I can check? | AO3: Chat: greet with your name, as you would on a call, and ask an open question. | AP3: Hi, thanks for ____ [Company]. I'm Ananya. How can I help you today? (Hint: the verb "contact") | AQ3: contacting | AR3: Which first chat message sounds the most natural to an international customer? | AS3: A) Hello. What is your problem? Please tell me your order number first. | B) Dear Customer, welcome to [Company]. Please state your query so we can help. | C) Hi, thanks for contacting [Company]. I'm Ananya. How can I help you today? | D) HELLO!! WELCOME TO [Company]!! HOW CAN I HELP YOU TODAY?? 😊 | AT3: C | AU3: C gives thanks, a name and an open question in plain English. A is blunt and asks for a number before offering help, B reads like a robot template, and D shouts in capitals. | AV3: help / today / can / How / you / I | AW3: How can I help you today | AX3: Namaste, main Ananya hoon. Bataiye, aaj main aapki kya madad kar sakti hoon? | AY3: Hi, I'm Ananya. How can I help you today? | AZ3: hi, my refund hasn't come yet | BA3: I'm sorry your refund hasn't arrived yet. Could you share your order number so I can check it for you? | BB3: Partner A opens a chat about a late parcel. Partner B sends the greeting with their own name and an open question, then asks for the order number in the next message. | BC3: Record yourself reading aloud the opening message you would send, with your own name, and then your reply when the customer writes "my parcel is late". | BD3: Did you say your own name with "I'm"? · Did you end with an open question? · Did you thank the customer for contacting you?
A4: CSC-B-002 | B4: Chat | C4: Basic | D4: A2 | E4: Say it | F4: Verify | G4: Could you type your order number here, please? It's in your confirmation email. | H4: Agent | I4: The customer says there is a problem with an order, and you need the number to find it. | J4: You need to find the customer's purchase in the system. What do you ask for, and where do you tell them to look? | K4: could-you-TYPE-your-OR-der-NUM-ber-HERE · PLEASE · it's-in-your-con-fir-MA-tion-E-mail | L4: If read aloud: could_you → "cud-joo" · it's_in → "it-sin" · confirmation_email → "con-fir-MAY-shu-nee-mail" | M4: If read aloud: rise on "please?" because it is a yes/no request, then a falling, helpful tone on the second sentence. | N4: If read aloud: say "order" as OR-der with the tongue just behind the top teeth for "d", not curled back; "confirmation" is con-fir-MA-tion, with the stress on MA. | O4: Neutral | P4: Polite request, helpful | Q4: 5 | R4: Wants a quick answer and may feel slightly impatient at being asked for details. | S4: The order number is the key to the locker; tell the customer which pocket the key is in: the confirmation email. | T4: क्या आप अपना ऑर्डर नंबर यहाँ टाइप कर सकते हैं? यह आपके कन्फ़र्मेशन ईमेल में है। | U4: Kya aap apna order number yahan type kar sakte hain? Yeh aapke confirmation email mein hai. | V4: Please write your order number in the chat. You can find it in the email we sent when you ordered. | W4: It asks politely and tells the customer exactly where to find the number, so they do not have to search or send another message asking where it is. | X4: Could you type your ___ here, please? | Y4: Could + you + base verb + object + here, please? · It's + in + place | Z4: "Could you…?" makes a soft request; "It's in…" tells someone where something is. | AA4: The question form and "please" make it a request. "Send order no." sounds like an order and uses shorthand, which looks careless in chat. | AB4: ✗ Could you type here your order number, please? → ✓ Could you type your order number here, please? | AC4: "Order ID?" — a two-word demand with no "please" feels cold and rushed in writing. | AD4: Instead of "You have to give the order number first", say "Could you type your order number here, please? It's in your confirmation email." | AE4: Could you share your order number, please? You'll see it in your confirmation email. | AF4: Could I have your order number, please? It starts with "ORD" and it's in the email we sent you. | AG4: Could you please provide your order number so that I can locate your order? You will find it in your order confirmation email. | AH4: Thank you. Let me look up order ORD-36571 now. | AI4: ORD-36571 · where do i find it? · i deleted the email | AJ4: Customer: "i deleted the email" → Agent: "That's fine. Could you give me the email address you ordered with instead? I can find the order that way." | AK4: "Please share me your order number" is common in Indian English; international customers may not expect "share me", so write "share your order number" or "send me your order number". | AL4: Voice: "Could you read me your order number?" Email: "Could you reply with your order number? It's in your confirmation email." | AM4: Do not ask for it if the customer has already typed it earlier in the chat; scroll up and use it. | AN4: Customer: my order hasn't come | Agent: I'm sorry about that. Could you type your order number here, please? It's in your confirmation email. | Customer: ORD-36571 | Agent: Thank you. Let me look that up now. | AO4: Verification: ask only for what you need, and make it easy for the customer to find. | AP4: Could you type your order number here, please? It's in your confirmation ____. (Hint: starts with "e") | AQ4: email | AR4: Which message asks for the order number in the clearest, most polite way? | AS4: A) You have to give me your order number first, then I can check your problem. | B) Order no. pls. It's in the confirmation email we sent you. | C) Could you type your order number here, please? It's in your confirmation email. | D) PLEASE TYPE YOUR ORDER NUMBER HERE. IT IS IN YOUR CONFIRMATION EMAIL. | AT4: C | AU4: C is polite and says where to look. A is an order ("You have to"), B uses shorthand ("no.", "pls"), and D is all capitals, which reads as shouting. | AV4: your / Could / here / type / number / you / order / please | AW4: Could you type your order number here please | AX4: Kya aap apna order number yahan likh sakte hain? Woh aapke email mein milega. | AY4: Could you type your order number here, please? You'll find it in your email. | AZ4: where do i find it? | BA4: It's in the email we sent when you placed the order. It starts with "ORD". | BB4: Partner A says their parcel has not arrived but gives no details. Partner B asks politely for the order number, says where to find it, and helps when A says they deleted the email. | BC4: Record yourself reading aloud the message you would send to ask for an order number, plus your reply when the customer cannot find it. | BD4: Did you use "Could you … please?" · Did you say where to find the number? · Did you avoid shorthand like "no." and "pls"?
A5: CSC-B-003 | B5: Chat | C5: Basic | D5: A2 | E5: Say it | F5: Hold & check | G5: Let me check that for you. One moment, please. | H5: Agent | I5: The customer has given their order number and you need a few seconds to look it up. | J5: You are about to look something up, and the customer will see no reply for a short time. What do you send first? | K5: let-me-CHECK-that-for-YOU · one-MO-ment · PLEASE | L5: If read aloud: let_me → "let-mee" (very light "t") · check_that → "chek-that" (touch the "k", then "th") · for_you → "fer-yoo" | M5: If read aloud: a falling, confident tone on "for you", a short pause, then a soft fall on "please". | N5: If read aloud: "that" starts with a voiced "th" (tongue lightly between the teeth), not "dat". "Moment" is MO-ment, with a clear final "t". | O5: Neutral | P5: Calm, reassuring | Q5: 5 | R5: Waiting and watching the screen, wondering whether anyone is working on it. | S5: A silent chat looks like an empty chair; this line puts a "back in a moment" sign on the chair. | T5: मैं आपके लिए यह चेक करता/करती हूँ। कृपया एक पल रुकिए। | U5: Main aapke liye yeh check karta/karti hoon. Kripya ek pal rukiye. | V5: I'm going to look at this for you now. Please wait a few seconds. | W5: In chat the customer cannot hear you typing, so silence looks like nobody is there. This tells them you are working on it and that the wait will be short. | X5: Let me ___ that for you. | Y5: Let + me + base verb + that + for you | Z5: "Let me…" offers to do something now; it sounds softer than "I will…". | AA5: "Let me" sounds helpful and active. "Wait" or "Hold" on its own sounds like an order and gives no reason. | AB5: ✗ Let me to check that for you, wait one minute. → ✓ Let me check that for you. One moment, please. | AC5: "Wait." — one word with no reason feels rude, and the customer does not know how long to wait. | AD5: Instead of "Wait, checking", say "Let me check that for you. One moment, please." | AE5: I'll look into that for you now. It'll take just a moment. | AF5: Thanks, Tom. Let me take a quick look at your order. | AG5: Thank you. Please allow me a moment while I check your order details. | AH5: Thanks for waiting. I can see your order, and it's out for delivery today. | AI5: ok · sure · how long will it take? | AJ5: Customer: "how long will it take?" → Agent: "About a minute. I'll update you as soon as I have the details." | AK5: "I am checking the same" is common in Indian English; international customers may not expect "the same" used this way, so name the thing ("your order") or say "that". | AL5: Voice: ask permission and give a real time: "Could you hold for about two minutes?" Email: not needed; say when you will reply instead. | AM5: Do not write "one moment" if the check will take more than a minute; give a real time instead, such as "about three minutes". | AN5: Customer: my order number is ORD-50927 | Agent: Thanks, Tom. Let me check that for you. One moment, please. | Customer: ok | Agent: Thanks for waiting. Your order is out for delivery today. | AO5: Chat: reply fast and never go silent; for a longer check, give a real time, not "a moment". | AP5: ____ me check that for you. One moment, please. | AQ5: Let | AR5: Your check will take a few minutes. Which message is best? | AS5: A) Let me check that for you. It'll only take a moment. | B) Let me check that for you. It'll take about three minutes. | C) Please wait. I'm checking your order now. Thank you. | D) Give me some time, please. I'll reply when I have it. | AT5: B | AU5: B gives a real time, which is right when the check will take a few minutes. A promises "a moment", which is misleading, and C and D give no time at all. | AV5: that / me / for / check / Let / you | AW5: Let me check that for you | AX5: Ek minute, main aapka order check karti hoon. | AY5: One moment, please. Let me check your order. | AZ5: ok thanks, waiting | BA5: Thank you, Tom. I'm still checking the delivery details, and I'll have your answer in about a minute. | BB5: Partner A asks where their order is. Partner B sends the "let me check" message, waits 30 seconds, then thanks A for waiting and gives the update. | BC5: Record yourself reading aloud the message you send before checking and the message you send when you come back with the answer. | BD5: Did you send a message before going quiet? · Did you give a real time if the check is long? · Did you thank the customer when you came back?
A6: CSC-B-004 | B6: Chat | C6: Basic | D6: A2 | E6: Say it | F6: Hold & check | G6: Thanks for waiting, James. Your parcel left our warehouse this morning. | H6: Agent | I6: You told the customer you would check, and you are now back with the answer after a short wait. | J6: You have just finished checking something while the customer waited. What do you write before you give the answer? | K6: THANKS-for-WAIT-ing-JAMES · your-PAR-cel-LEFT-our-WARE-house-this-MOR-ning | L6: If read aloud: thanks_for → "thanks-fer" · left_our → "lef-tower" · this_morning → "this-MOR-ning" | M6: If read aloud: a warm fall on "James", a tiny pause, then a clear, falling statement for the news. | N6: If read aloud: "warehouse" starts with a "w" (round the lips, no teeth on the lip) as in "west", not a "v" as in "vest". | O6: Friendly | P6: Grateful, clear update | Q6: 4 | R6: A little impatient after waiting and keen to hear the answer. | S6: Like a waiter coming back to the table: say "thanks for waiting" before you put the plate down. | T6: इंतज़ार करने के लिए धन्यवाद, जेम्स। आपका पार्सल आज सुबह हमारे गोदाम से निकल गया है। | U6: Intezaar karne ke liye dhanyavaad, James. Aapka parcel aaj subah hamare godaam se nikal gaya hai. | V6: Thank you for waiting. Your parcel was sent from our storage building this morning. | W6: Thanking first shows you noticed their time; then the news comes straight away in one clear line, so the customer does not have to wait or ask again. | X6: Thanks for waiting, ___. + the news | Y6: Thanks + for + verb-ing, name. · Subject + past simple + finished time | Z6: Use the past simple ("left") with a finished time like "this morning" or "yesterday". | AA6: Thanking sounds respectful. Jumping straight to the news with no thanks feels a little cold, and answering only "Yes, I checked" leaves the customer still waiting. | AB6: ✗ Thanks for waiting. Your parcel has left yesterday. → ✓ Thanks for waiting, James. Your parcel left our warehouse this morning. | AC6: "Yes, I checked." — it makes the customer ask again for the actual answer. | AD6: Instead of "Sorry for delay, I was busy", say "Thanks for waiting, James. Your parcel left our warehouse this morning." | AE6: Thanks for bearing with me, James. Your parcel was sent this morning. | AF6: Thanks for waiting! Good news: your order is on its way. | AG6: Thank you for waiting, Mr Brown. Your parcel was dispatched from our warehouse this morning. | AH6: Would you like me to send you the tracking link, so you can follow it? | AI6: great, when will it arrive? · ok thanks · why so late? | AJ6: Customer: "why so late?" → Agent: "I'm sorry it's taken longer than you expected. It's on its way now and should reach you by Thursday." | AK6: Indian-English scripts often say "Kindly bear with us" or "Thanks for being on hold" in chat; international customers may not expect these there, so switch to "Thanks for waiting" or "Thanks for bearing with me". | AL6: Voice: "Thank you for holding, James." Email: "Thanks for waiting while we looked into this," at the start of the reply. | AM6: Do not use a thank-you alone after a very long wait; add an apology, such as "Thanks for waiting, and I'm sorry that took so long." | AN6: Customer: where is my parcel? | Agent: Let me check that for you. One moment, please. | Customer: ok | Agent: Thanks for waiting, James. Your parcel left our warehouse this morning. | AO6: Thank the customer first when you return, then give the information. | AP6: ____ for waiting, James. Your parcel left our warehouse this morning. | AQ6: Thanks | AR6: You come back to the chat after checking. What should your first words be? | AS6: A) Thanks for waiting, James. Here's what I found. | B) Yes, I checked it. Do you need anything else? | C) Sorry, I was busy with another chat just now. | D) Your parcel left our warehouse this morning. | AT6: A | AU6: A thanks the customer first and then moves to the news. D gives the news but skips the thank-you, which feels cold. B gives no answer, and C makes the wait about you instead of the customer. | AV6: warehouse / Your / this / left / parcel / morning / our | AW6: Your parcel left our warehouse this morning | AX6: Intezaar ke liye shukriya. Aapka order kal bhej diya gaya tha. | AY6: Thanks for waiting. Your order was sent yesterday. | AZ6: great, when will it arrive? | BA6: It should reach you by Thursday. I'll send you the tracking link now. | BB6: Partner A asks about a parcel. Partner B says they will check, waits 20 seconds, then thanks A for waiting and gives the update with a delivery day. | BC6: Record yourself reading aloud your "thanks for waiting" message with the update, then your reply when the customer asks "why so late?". | BD6: Did you thank the customer before the news? · Did you give the actual answer in the same message? · Did you use the past simple with "this morning"?
A7: CSC-B-005 | B7: Chat | C7: Basic | D7: A2 | E7: Say it | F7: Apologise | G7: I'm sorry your order arrived damaged. I'll send you a replacement today. | H7: Agent | I7: The customer writes that her new lamp arrived broken, and your system shows a free replacement can go out today with no need to return the broken one. | J7: The customer's item came broken. What two things does a good short apology in chat contain? | K7: i'm-SOR-ry-your-OR-der-ar-RIVED-DAM-aged · i'll-SEND-you-a-re-PLACE-ment-to-DAY | L7: If read aloud: order_arrived → "or-de-ra-rived" · arrived_damaged → "a-rive-DAM-ijd" (the two "d" sounds join into one) · send_you → "sen-joo" | M7: If read aloud: a sincere, slightly slower fall on "damaged"; a firm, confident fall on "today". | N7: If read aloud: say the final sounds in "arrived" ("-vd") and "damaged" ("-jd") clearly; do not drop them to "arrive damage". | O7: Neutral | P7: Sincere, responsible, action-focused | Q7: 5 | R7: Disappointed and annoyed that they paid for something broken. | S7: Sorry is the bandage and the replacement is the medicine: one without the other heals nothing. | T7: मुझे खेद है कि आपका ऑर्डर टूटा हुआ पहुँचा। मैं आज ही आपको नया सामान भेज दूँगा/दूँगी। | U7: Mujhe khed hai ki aapka order toota hua pahuncha. Main aaj hi aapko naya saamaan bhej doonga/doongi. | V7: I apologise that your item came broken. I will send you a new one today. | W7: It names the exact problem, so the customer knows you read their message, and the second line offers a fix with a time, which matters more to them than the apology words. | X7: I'm sorry your ___. I'll ___. | Y7: I'm sorry + (that) + clause · I'll + base verb + time | Z7: After "I'm sorry" you can add a full sentence: "I'm sorry your order arrived damaged." | AA7: A specific apology sounds sincere. A vague "Sorry for the inconvenience" sounds copied and pasted, and with an upset customer it can feel cold. | AB7: ✗ I'm sorry for your order arrived damaged. → ✓ I'm sorry your order arrived damaged. I'll send you a replacement today. | AC7: "These things happen during delivery." — it sounds like an excuse and does not say what you will do. | AD7: Instead of "Sorry for the inconvenience caused", say "I'm sorry your order arrived damaged. I'll send you a replacement today." | AE7: I'm really sorry it reached you broken. I'll arrange a new one for you right away. | AF7: Sorry about the damaged item, Grace. I'm sending a replacement today. | AG7: I apologise that your order arrived damaged. I will arrange for a replacement to be dispatched today. | AH7: Could you send a photo of the damage? It helps our warehouse team stop this happening again. | AI7: thank you · do i need to send it back? · i need it by friday | AJ7: Customer: "this is the second time!" → Agent: "I'm sorry it has happened twice. I'll send the replacement today and add a note asking for extra packing." | AK7: "Sorry for the inconvenience caused" is very common in Indian support scripts; international customers often read it as a template, so name the actual problem instead. | AL7: Voice: the same words, said slowly and sincerely. Email: add the case number and the expected delivery date of the replacement. | AM7: Do not promise "today" if the replacement cannot go out today; give the real day instead. | AN7: Customer: my lamp came broken | Agent: I'm sorry your order arrived damaged. I'll send you a replacement today. | Customer: ok, when will it get here? | Agent: It should arrive by Saturday. I'll email you the tracking link today. | AO7: Apologise specifically, take responsibility and offer a fix; no emoji with a complaint. | AP7: I'm ____ your order arrived damaged. I'll send you a replacement today. | AQ7: sorry | AR7: Which apology works best in chat for a broken item? | AS7: A) Sorry for the inconvenience. We hope to see you again soon. | B) I'm sorry your order arrived damaged. I'll send you a replacement today. | C) I'm so sorry your order arrived damaged 😔 Please let me know how I can help. | D) Parcels sometimes get damaged in delivery, but I'll look into it for you. | AT7: B | AU7: B names the problem and gives a fix with a time. A is a vague template, C uses an emoji with a complaint and offers no fix, and D sounds like an excuse. | AV7: replacement / send / I'll / today / a / you | AW7: I'll send you a replacement today | AX7: Mujhe afsos hai ki aapka order toota hua aaya. Main aaj hi naya bhej deti hoon. | AY7: I'm sorry your order arrived broken. I'll send you a new one today. | AZ7: do i need to send the broken one back? | BA7: No, you don't need to send it back. You can keep it or recycle it. | BB7: Partner A writes that their new headphones arrived with a cracked case. Partner B apologises for that exact problem, offers a replacement with a time, and answers A's question about returning the broken pair. | BC7: Record yourself reading aloud your short apology message and the next message, where you ask for a photo of the damage. | BD7: Did you name the exact problem? · Did you offer a fix with a time? · Did you avoid a vague "sorry for the inconvenience" and emoji?
A8: CSC-B-006 | B8: Chat | C8: Basic | D8: A2 | E8: Say it | F8: Listen & clarify | G8: Could you send me a screenshot of the error message? It'll help me see exactly what's happening. | H8: Agent | I8: The customer says the app shows an error when they try to pay, but they cannot describe it clearly. | J8: The customer says "it shows some error" but cannot describe it. What do you ask them to send, and how do you explain why? | K8: could-you-SEND-me-a-SCREEN-shot · of-the-ER-ror-MES-sage · it'll-HELP-me-SEE-ex-ACT-ly-what's-HAP-pen-ing | L8: If read aloud: send_me → "sen-mee" · of_the_error → "uv-thee-ER-ror" · what's_happening → "wots-HAP-ning" | M8: If read aloud: rise on "message?" because it is a yes/no request; fall on "happening". | N8: If read aloud: "message" is MES-ij, two syllables with a soft "-ij" ending, not "mes-SAGE" with the stress at the end. | O8: Neutral | P8: Helpful, patient, curious | Q8: 4 | R8: Frustrated and a little confused by a technical problem. | S8: A screenshot is the patient's X-ray: the doctor sees in one look what ten lines of words cannot describe. | T8: क्या आप मुझे एरर मैसेज का स्क्रीनशॉट भेज सकते हैं? इससे मैं ठीक-ठीक देख पाऊँगा/पाऊँगी कि क्या हो रहा है। | U8: Kya aap mujhe error message ka screenshot bhej sakte hain? Isse main theek-theek dekh paoonga/paoongi ki kya ho raha hai. | V8: Please take a picture of your screen showing the error and send it to me, so I can understand the problem. | W8: It asks politely and gives the reason, so the customer sees the extra step helps them and is not just more work. | X8: Could you send me a ___ of ___? It'll help me ___. | Y8: Could + you + send + me + a + noun · It'll + help + me + base verb | Z8: After "help me", use the base verb: "help me see", not "help me seeing". | AA8: Giving a reason makes it a shared task. "Send screenshot" on its own sounds like a demand and can suggest you do not believe the customer. | AB8: ✗ Could you send me screenshot of error message? → ✓ Could you send me a screenshot of the error message? | AC8: "I can't help without a screenshot." — it puts the blame on the customer and sounds like a refusal. | AD8: Instead of "I can't help without a screenshot", say "Could you send me a screenshot of the error message? It'll help me see exactly what's happening." | AE8: Could you take a screenshot of what you see on the screen and send it here? | AF8: If you can, please send a screenshot of the error. That way I can find the cause faster. | AG8: Would you be able to send a screenshot of the error message? It will help me identify the problem more quickly. | AH8: Thank you, that helps. I can see the card was declined, so let's try another payment method. | AI8: how do i take a screenshot? · sent · it says payment failed | AJ8: Customer: "i already told you what it says, why a screenshot?" → Agent: "Thank you, and I'm sorry for the extra step. The screenshot shows me the exact wording, so I don't have to guess. It only takes a few seconds." | AK8: "Kindly share the screenshot of the same" is common in Indian English; international customers may not expect "of the same", so name the thing: "a screenshot of the error". | AL8: Voice: ask the caller to read the error message aloud, or offer to email them so they can reply with the screenshot. Email: "Could you reply with a screenshot of the error message?" | AM8: Do not ask for a screenshot of a screen that shows a full card number or password; ask the customer to describe it or cover those parts. | AN8: Customer: payment not working, some error | Agent: Could you send me a screenshot of the error message? It'll help me see exactly what's happening. | Customer: sent | Agent: Thank you. I can see the card was declined, so let's try another card. | AO8: Chat: ask with "Could you…?", give the reason for the extra step, and keep the message short. | AP8: Could you send me a ____ of the error message? It'll help me see exactly what's happening. (Hint: one word for a picture of your screen) | AQ8: screenshot | AR8: Why does the agent add "It'll help me see exactly what's happening"? | AS8: A) To make the message longer and sound more formal. | B) To give a reason, so the customer sees why the extra step helps. | C) To suggest that the customer caused the error themselves. | D) To promise the customer that the error will be fixed today. | AT8: B | AU8: B is right: a reason turns a demand into teamwork. C is the tempting wrong idea, because the line blames no one; A adds nothing for the customer, and D promises something the line never says. | AV8: screenshot / you / me / send / a / Could | AW8: Could you send me a screenshot | AX8: Kya aap error ka screenshot bhej sakte hain? Isse mujhe problem samajhne mein madad milegi. | AY8: Could you send me a screenshot of the error? It'll help me understand the problem. | AZ8: how do i take a screenshot? | BA8: On most phones, press the power and volume-down buttons together. If that doesn't work, tell me which phone you have, and I'll walk you through it. Then send the picture here. | BB8: Partner A says the app shows "some error" when they log in. Partner B asks for a screenshot with a reason, explains how to take one, and responds once A describes what the error says. | BC8: Record yourself reading aloud your screenshot request and the message explaining how to take a screenshot on a phone. | BD8: Did you say why you need the screenshot? · Did you name exactly what to send (the error message)? · Did your request start with "Could you"?
A9: CSC-B-007 | B9: Chat | C9: Basic | D9: A2 | E9: Say it | F9: Explain | G9: You can reset your password here: [Company].com/reset. Just open it and enter your email address. | H9: Agent | I9: The customer cannot log in, and you send them the password reset page. | J9: You are sending the customer a page where they can fix a login problem. What do you add so they know what to do on it? | K9: you-can-re-SET-your-PASS-word-HERE · just-O-pen-it · and-EN-ter-your-E-mail-ad-DRESS | L9: If read aloud: reset_your → "ree-set-cher" · open_it → "oh-pe-nit" · and_enter → "an-den-ter" | M9: If read aloud: steady and falling; pause briefly before and after the link, so each part is clear. | N9: If read aloud: in "password" the "w" is a rounded-lip sound, PASS-wurd, not "pass-vord" with teeth on the lip. | O9: Neutral | P9: Clear, simple instruction | Q9: 4 | R9: Locked out and slightly stressed about getting back into the account. | S9: A link without an instruction is a door with no handle; give one handle: "open it and enter your email". | T9: आप यहाँ अपना पासवर्ड रीसेट कर सकते हैं: [Company].com/reset। बस इसे खोलिए और अपना ईमेल पता डालिए। | U9: Aap yahan apna password reset kar sakte hain: [Company].com/reset. Bas ise kholiye aur apna email address daaliye. | V9: Here is the page to make a new password. Open it and type your email address. | W9: One link with one action is easy to follow on a phone. The customer knows exactly what to do next and does not need to come back and ask. | X9: You can ___ here: ___. Just ___. | Y9: You + can + base verb + here · Just + imperative + and + imperative | Z9: "Just" before a verb makes an instruction sound easy and friendly, not bossy. | AA9: "You can… here" sounds like help on offer. "You have to go through the link and do the process" sounds like a rule and does not say what the process is. | AB9: ✗ You can reset your password in this link. Just open and fill your email. → ✓ You can reset your password here: [Company].com/reset. Just open it and enter your email address. | AC9: "Go through the link." — it gives no instruction, so the customer opens the page and does not know what to do. | AD9: Instead of "You have to go through the below link", say "You can reset your password here: [Company].com/reset. Just open it and enter your email address." | AE9: Here's the reset page: [Company].com/reset. Enter your email address there, and we'll email you a link to choose a new password. | AF9: This link lets you set a new password: [Company].com/reset. Tap it and type your email address. | AG9: You can reset your password using this link: [Company].com/reset. Please open it and enter the email address linked to your account. | AH9: Let me know once you've done that, and I'll check that you can log in. | AI9: done · the link isn't opening · i didn't get any email | AJ9: Customer: "the link isn't opening" → Agent: "I'm sorry the link isn't opening. Could you copy it into your browser? If it still doesn't open, I'll send the reset email to you directly." | AK9: "Go through the below link and do the needful" is common in Indian business English; international customers may not expect it and find it vague, so say the one action they should take. | AL9: Voice: the caller cannot click anything on a call, so offer to send the link by SMS or email. Email: number the steps if there is more than one. | AM9: Do not send a link alone when the task has several steps; split it into short, numbered messages instead. | AN9: Customer: i forgot my password | Agent: You can reset your password here: [Company].com/reset. Just open it and enter your email address. | Customer: done, got the email | Agent: Great. Open that email and choose a new password, and you'll be able to log in. | AO9: Chat: short messages, one clear step at a time; number multi-step instructions. | AP9: You can reset your password here: [Company].com/reset. Just open it and ____ your email address. (Hint: starts with "e") | AQ9: enter | AR9: What makes a good chat message when you share a link? | AS9: A) The link on its own, so the message is as short as possible. | B) The link plus one clear action the customer should take. | C) The link plus a long explanation of how the system works. | D) The link plus five steps in one long paragraph of text. | AT9: B | AU9: B is right: one link with one clear action is easy to follow on a phone. A is tempting because it is short, but the customer may not know what to do; C and D bury the action in too much text. | AV9: email / your / open / enter / Just / address / and / it | AW9: Just open it and enter your email address | AX9: Bas is link ko kholiye aur apna email address daaliye. | AY9: Just open this link and enter your email address. | AZ9: i didn't get any email | BA9: Could you check your spam folder? If it isn't there, I'll send it again now. | BB9: Partner A cannot log in. Partner B sends the reset link with one clear instruction, then helps when A says the email has not arrived. | BC9: Record yourself reading aloud the link message you would send and your next message when the customer says no email arrived. | BD9: Did you give exactly one clear action with the link? · Did you say what the link is for ("reset your password")? · Is the message short enough to read on a phone?
A10: CSC-B-008 | B10: Chat | C10: Basic | D10: B1 | E10: Say it | F10: Verify | G10: Just to confirm, you'd like to change the delivery address to 14 Park Road, Pune? | H10: Agent | I10: The customer asked to change where their parcel goes, and you check the new address before you update it. | J10: Before you change an important detail, how do you check in one short message that you have understood it correctly? | K10: just-to-con-FIRM · you'd-LIKE-to-CHANGE-the-de-LIV-er-y-ad-DRESS · to-four-TEEN-PARK-ROAD-PU-ne | L10: If read aloud: just_to → "jus-tuh" · you'd_like → "yood-like" · change_the → "chainj-the" | M10: If read aloud: a rising tone at the end, because it is a yes/no check, even though the words look like a statement. | N10: If read aloud: "fourteen" is four-TEEN, with the stress at the end; "forty" is FOR-ty. Mixing them up changes the address. | O10: Neutral | P10: Careful, polite check | Q10: 5 | R10: Wants the change done quickly and correctly, and is a little anxious about mistakes. | S10: Measure twice, cut once: read the address back before you press save. | T10: बस पक्का करने के लिए, आप डिलीवरी का पता बदलकर 14 पार्क रोड, पुणे करना चाहते हैं? | U10: Bas pakka karne ke liye, aap delivery ka pata badalkar 14 Park Road, Pune karna chahte hain? | V10: I want to check: is the new delivery address 14 Park Road, Pune? | W10: Repeating the exact detail lets the customer catch a mistake before it costs them a lost parcel, and it shows you read their message carefully. | X10: Just to confirm, you'd like to ___? | Y10: Just to confirm, + you'd like + to + base verb …? | Z10: A statement with a question mark asks "Is this right?"; "you'd like" is a polite form of "you want". | AA10: "Just to confirm" sounds careful, not doubtful. "Are you sure?" can sound as if you think the customer is wrong. | AB10: ✗ Just to confirm, you want that I change the address? → ✓ Just to confirm, you'd like to change the delivery address to 14 Park Road, Pune? | AC10: "Are you sure about the address?" — it sounds as if you doubt the customer instead of checking your own understanding. | AD10: Instead of "Are you sure it's correct?", say "Just to confirm, you'd like to change the delivery address to 14 Park Road, Pune?" | AE10: Can I check: the new address is 14 Park Road, Pune. Is that right? | AF10: So the parcel should now go to 14 Park Road, Pune. Have I got that right? | AG10: Could you confirm that you would like the delivery address changed to 14 Park Road, Pune? | AH10: Thanks. Should I add a flat number or landmark to help the courier find it? | AI10: yes thats right · no, it's 41 not 14 · yes, and add flat 2B | AJ10: Customer: "yes, I already said that!" → Agent: "Sorry to double-check, Imran. I just wanted to be sure your parcel goes to the right place. It's updated now." | AK10: "You want that I change…" copies the Hindi "chahte hain ki…" pattern; international customers may not expect it, so write "you'd like me to change…" or "you'd like to change…". | AL10: Voice: say numbers slowly, digit by digit: "one-four Park Road". Email: put the new address on its own line so it is easy to check. | AM10: Do not confirm every small detail in a short chat; save it for things that are costly to get wrong, such as addresses, amounts and dates. | AN10: Customer: can you send it to 14 Park Road, Pune instead | Agent: Just to confirm, you'd like to change the delivery address to 14 Park Road, Pune? | Customer: yes | Agent: Thanks. I've updated it, and you'll get a confirmation email shortly. | AO10: Paraphrase before acting: repeat the key detail so the customer can correct you. | AP10: Just to confirm, you'd like to change the delivery ____ to 14 Park Road, Pune? | AQ10: address | AR10: The customer writes "please send it to 14 Park Road, Pune instead". What is the best next message? | AS10: A) Done! I've changed your delivery address to 14 Park Road, Pune. | B) Are you sure that is the right address? 14 Park Road, Pune? | C) Just to confirm, you'd like the parcel sent to 14 Park Road, Pune? | D) Could you type the whole address again from the beginning, please? | AT10: C | AU10: C repeats the detail so the customer can catch an error. B is tempting as a check, but it sounds as if you doubt them. A changes the address without checking, and D makes the customer do the work again. | AV10: confirm / like / Just / you'd / to / change / to / the / address | AW10: Just to confirm you'd like to change the address | AX10: Bas confirm karne ke liye, aap payment ki date badalkar 5 March karna chahte hain? | AY10: Just to confirm, you'd like to change the payment date to 5 March? | AZ10: no, it's 41 not 14 | BA10: Thanks for catching that. So it's 41 Park Road, Pune. Is that right? | BB10: Partner A asks to change the delivery address and types it with one digit unclear. Partner B confirms the detail, A corrects it, and B confirms the corrected address before updating it. | BC10: Record yourself reading aloud your confirm message with a full address, using a rising tone at the end. | BD10: Did you repeat the exact detail? · Did you use "you'd like to" instead of "you want that"? · Did you wait for a yes before changing it?
A11: CSC-B-009 | B11: Chat | C11: Basic | D11: A2 | E11: Say it | F11: Hold & check | G11: Are you still there, Sarah? I'm here whenever you're ready. | H11: Agent | I11: The customer has not replied for a few minutes after you asked them a question. | J11: The customer has gone quiet for several minutes. What friendly message do you send before you think about closing the chat? | K11: are-you-STILL-THERE-SA-rah · i'm-HERE · when-EV-er-you're-READ-y | L11: If read aloud: are_you → "ar-yoo" · still_there → "stil-there" · whenever_you're → "wen-ev-er-yor" | M11: If read aloud: rise on "there?" because it is a yes/no question, then a soft, warm fall on "ready". | N11: If read aloud: "there" starts with a voiced "th" (tongue between the teeth), not "dare"; "whenever" begins with a rounded-lip "w", not a "v". | O11: Friendly | P11: Patient, friendly check-in | Q11: 4 | R11: Probably busy or distracted, perhaps looking for a document, and not annoyed. | S11: A gentle knock on the door, not a bang: "Still there? I'm here when you're ready." | T11: सारा, क्या आप अभी भी चैट पर हैं? जब भी आप तैयार हों, मैं यहीं हूँ। | U11: Sarah, kya aap abhi bhi chat par hain? Jab bhi aap taiyaar hon, main yahin hoon. | V11: Are you still in the chat? Take your time; I'm waiting for you. | W11: It checks politely without pressure and tells the customer they have not lost their place, so they can come back without starting again. | X11: Are you still there, ___? I'm here whenever ___. | Y11: Are + you + still + there? · whenever + you're + adjective | Z11: "Still" means "continuing from before"; "whenever" means "at any time that". | AA11: The second sentence removes pressure. "Hello?? Are you there??" with many question marks sounds impatient. | AB11: ✗ Hello? Are you there or not? → ✓ Are you still there, Sarah? I'm here whenever you're ready. | AC11: "If you don't reply, I will close the chat." as the first check-in — it sounds like a threat; warn only after a friendly check-in. | AD11: Instead of "No response from your side", say "Are you still there, Sarah? I'm here whenever you're ready." | AE11: Just checking in, Sarah. Take your time; I'm still here. | AF11: Hi Sarah, are you still with me? There's no rush. | AG11: I just wanted to check whether you are still there. I'm happy to wait while you find the details. | AH11: I haven't heard back, so I'll close this chat in two minutes. If you still need help, just reply here and I'll keep it open. | AI11: sorry, here · yes, looking for the receipt · 2 min | AJ11: Customer: "stop rushing me" → Agent: "Sorry, Sarah, I didn't mean to rush you. Take all the time you need; I'll wait." | AK11: "No response from your side" is common in Indian support scripts; international customers may read it as blame, so a friendly question works better. | AL11: Voice: "Hello, are you still there?" after a few seconds of silence. Email: not used; send a follow-up email later instead. | AM11: Do not send it seconds after your own message; give the customer a real gap first, as they may be typing or looking something up. | AN11: Customer: one sec, finding my receipt | Agent: (four minutes later) Are you still there, Sarah? I'm here whenever you're ready. | Customer: sorry, here it is: ORD-55102 | Agent: Thanks, Sarah. Let me check that now. | AO11: Ending a chat: if the customer goes silent, check in, then warn, then close politely. | AP11: Are you ____ there, Sarah? I'm here whenever you're ready. | AQ11: still | AR11: A customer has not replied for four minutes. What is the best first step? | AS11: A) Close the chat now, because the customer has probably left. | B) Send a friendly check-in and say you are still there. | C) Send "Hello?? Are you there??" so the customer sees it quickly. | D) Write "If you don't reply, the chat will close" straight away. | AT11: B | AU11: B follows best practice: check in first, then warn, then close. D is tempting, but it skips the friendly check-in and sounds like a threat; A closes too early and C sounds impatient. | AV11: ready / here / you're / I'm / whenever | AW11: I'm here whenever you're ready | AX11: Kya aap abhi bhi chat par hain? Koi jaldi nahin hai. | AY11: Are you still there? There's no rush. | AZ11: sorry, my phone rang. here now | BA11: No worries, Sarah. Could you send me the order number when you have it? | BB11: Partner B asks for an order number, and Partner A goes silent. B sends a friendly check-in, then a polite warning, and A comes back just before the chat closes. | BC11: Record yourself reading aloud your check-in message, then the polite warning you would send two minutes later if there is still no reply. | BD11: Did you check in before warning? · Did you remove pressure with "whenever you're ready"? · Did you avoid capitals and extra question marks?
A12: CSC-B-010 | B12: Chat | C12: Basic | D12: A2 | E12: Say it | F12: Close | G12: You're welcome, Sarah. Thanks for chatting with us, and have a great evening! | H12: Agent | I12: The issue is solved, and the customer has written "thanks, bye". | J12: The customer thanks you and says goodbye after the problem is fixed. How do you return the goodbye in one message? | K12: you're-WEL-come-SA-rah · THANKS-for-CHAT-ting-with-us · and-have-a-GREAT-EVE-ning | L12: If read aloud: thanks_for → "thanks-fer" · with_us → "wi-thus" · have_a → "ha-vuh" | M12: If read aloud: a warm fall on "Sarah", then a bright, slightly higher pitch on "great evening" before the final fall. | N12: If read aloud: "with" ends in a soft "th", not a "t" ("wit"); "evening" is EEV-ning, two syllables, not "ee-ve-ning". | O12: Friendly | P12: Warm, grateful goodbye | Q12: 4 | R12: Relieved and satisfied, and ready to leave the chat. | S12: The customer waved goodbye; wave back with three fingers: "you're welcome", "thanks", "have a great evening". | T12: धन्यवाद की कोई बात नहीं, सारा। हमसे चैट करने के लिए धन्यवाद, आपकी शाम अच्छी हो! | U12: Dhanyavaad ki koi baat nahin, Sarah. Humse chat karne ke liye dhanyavaad, aapki shaam acchi ho! | V12: No need to thank me. Thank you for talking to us. Enjoy your evening! | W12: It answers the customer's thanks, thanks them back and says goodbye, so the chat ends warmly instead of stopping suddenly. | X12: You're welcome, ___. Thanks for ___, and have a great ___! | Y12: You're welcome · Thanks + for + verb-ing · Have + a + adjective + noun | Z12: "Have a great evening" is a wish, not an order, even though it starts with a verb. | AA12: "You're welcome" is the safe, polite reply to thanks. Saying nothing and closing the window feels cold after a good chat. | AB12: ✗ You welcome, Sarah. Thanks for chat with us. → ✓ You're welcome, Sarah. Thanks for chatting with us. | AC12: "Chat is being closed." — it is a system message, not a goodbye, and ends a good chat coldly. | AD12: Instead of "Closing the chat now", say "You're welcome, Sarah. Thanks for chatting with us, and have a great evening!" | AE12: My pleasure, Sarah! Thanks for getting in touch, and have a lovely evening. | AF12: Glad I could help! Take care, Sarah. | AG12: You're very welcome. Thank you for contacting [Company], and have a pleasant evening. | AH12: If anything else comes up, just message us again any time. Take care, Sarah! | AI12: bye · thanks again · you too | AJ12: Customer: "actually, one more thing" → Agent: "Of course, Sarah. What else can I help with?" | AK12: Many Indian English speakers reply to "thank you" with "Welcome"; international customers may not expect this and usually hear "You're welcome" or "My pleasure". | AL12: Voice: "You're welcome, Mr Lee. Have a great evening." Email: end with "Best regards" and your name. | AM12: Do not use it while the issue is still open; first tell the customer the next step and when they will hear from you. | AN12: Customer: that worked, thanks! bye | Agent: You're welcome, Sarah. Thanks for chatting with us, and have a great evening! | Customer: you too | Agent: Thank you, Sarah. Take care! | AO12: Ending a chat: return the customer's goodbye; "You're welcome" is the safe default reply to thanks. | AP12: You're ____, Sarah. Thanks for chatting with us, and have a great evening! | AQ12: welcome | AR12: The customer writes "thanks so much, bye!" Which reply is the most natural for an international customer? | AS12: A) This chat is now closed. Please rate your experience with us in the survey. | B) YOU'RE WELCOME!! THANKS FOR CHATTING WITH US. HAVE A GREAT EVENING!! | C) No problem, Sarah! Is there anything else I can help you with before I close the chat? | D) You're welcome, Sarah. Thanks for chatting with us, and have a great evening! | AT12: D | AU12: D returns the thanks and the goodbye. A sounds like a system message, B shouts in capitals, and C asks a new question when the customer is already leaving. | AV12: chatting / us / Thanks / with / for | AW12: Thanks for chatting with us | AX12: Humse chat karne ke liye shukriya. Aapki shaam acchi ho! | AY12: Thanks for chatting with us. Have a great evening! | AZ12: you too, thanks! | BA12: Thanks, Sarah. Bye for now! | BB12: Partner A's refund problem has been solved, and A writes "thanks, bye". Partner B returns the thanks and the goodbye; then A adds "one more thing", and B answers before closing again. | BC12: Record yourself reading aloud your goodbye message, then your reply if the customer suddenly writes "actually, one more thing". | BD12: Did you say "You're welcome" in full, with the customer's name? · Did you thank the customer for chatting? · Did you close only after the issue was solved?
A13: CSC-B-011 | B13: Chat | C13: Basic | D13: A2 | E13: Say it | F13: Close | G13: I'm glad that's sorted. Is there anything else I can help you with today? | H13: Agent | I13: You have fixed the customer's problem, and they have confirmed that it works. | J13: The customer confirms the fix worked. What do you say about the fix, and what do you ask before you close? | K13: i'm-GLAD-that's-SORT-ed · is-there-AN-y-thing-ELSE · i-can-HELP-you-with-to-DAY | L13: If read aloud: that's_sorted → "that-SORT-ed" (the two "s" sounds join) · anything_else → "en-ee-thing-els" (the "ng" flows into "else", with no hard g) · help_you → "hel-pyoo" | M13: If read aloud: a warm fall on "sorted"; a rise on "today?" because it is a yes/no question. | N13: If read aloud: "anything" ends in "-thing" with the tongue between the teeth, not "any-ting"; "else" ends in a clear "s", not "el-se". | O13: Friendly | P13: Warm, open, helpful | Q13: 5 | R13: Pleased the problem is fixed and perhaps ready to leave. | S13: Close the first door ("glad that's sorted") before you open the next one ("anything else?"). | T13: मुझे खुशी है कि यह ठीक हो गया। क्या आज मैं आपकी किसी और चीज़ में मदद कर सकता/सकती हूँ? | U13: Mujhe khushi hai ki yeh theek ho gaya. Kya aaj main aapki kisi aur cheez mein madad kar sakta/sakti hoon? | V13: Good, the problem is fixed. Do you need help with something else? | W13: It first confirms the problem is solved, then gives the customer a clear chance to raise another issue before the chat ends. | X13: Is there anything else I can help you with ___? | Y13: Is + there + anything + else + (that) + I + can + base verb …? | Z13: Use "anything" in questions ("anything else?") and "something" in offers ("something to drink?"). | AA13: Asking after the fix sounds caring. Asking it before the problem is solved sounds as if you want to end the chat. | AB13: ✗ Is there anything else I can help you today? → ✓ Is there anything else I can help you with today? | AC13: "Anything else?" while the problem is still open — it suggests the issue is finished when it is not. | AD13: Instead of "Any other query?", say "I'm glad that's sorted. Is there anything else I can help you with today?" | AE13: Great, that's working now. Can I help with anything else? | AF13: Happy to hear that's fixed! Is there anything else you need today? | AG13: I'm pleased the issue is resolved. Is there anything else I can assist you with today? | AH13: If it stops working again, Kiran, just message us here and we'll pick it up. | AI13: no that's all, thanks · yes, one more thing · nope | AJ13: Customer: "yes, actually, my last bill looks wrong too" → Agent: "Of course. Could you tell me which amount looks wrong? I'll check it now." | AK13: "Any other query?" is common in Indian support chats; international customers may find "query" formal and a little cold, so ask "anything else I can help you with?". | AL13: Voice: the same line, said warmly and not rushed. Email: "If there's anything else I can help with, just reply to this email." | AM13: Do not ask it on an unresolved case; tell the customer the next step and when they will hear back instead. | AN13: Customer: it's working now | Agent: I'm glad that's sorted. Is there anything else I can help you with today? | Customer: no that's all, thanks | Agent: You're welcome, Kiran. Have a great day! | AO13: Check the issue is resolved first, then ask "Is there anything else…?"; never ask it on an unresolved case. | AP13: I'm glad that's sorted. Is there anything else I can help you ____ today? | AQ13: with | AR13: When should you ask "Is there anything else I can help you with?" | AS13: A) In your very first message. | B) While you are still checking their order. | C) When the customer is angry, to change the topic. | D) After the customer confirms the problem is solved. | AT13: D | AU13: The question assumes the issue is finished, so ask it only after the customer confirms. B is tempting, but it makes the customer feel rushed. | AV13: help / Is / else / can / there / I / anything / with | AW13: Is there anything else I can help with | AX13: Kya main aapki aur kisi cheez mein madad kar sakti hoon? | AY13: Is there anything else I can help you with? | AZ13: no that's all, thanks | BA13: Great. I'll close the chat now. Thanks for getting in touch, Kiran, and take care! | BB13: Partner B has just fixed Partner A's login problem. B confirms it works, asks the "anything else" question, and A raises a second, small billing question. | BC13: Record yourself reading aloud both messages: the one confirming the fix and the one asking if there is anything else. | BD13: Did you confirm the problem was solved first? · Did you finish with "help you with today"? · Did your voice rise at the end of the question?
A14: CSC-B-012 | B14: Chat | C14: Basic | D14: B1 | E14: Say it | F14: Transfer | G14: I'm transferring you to our billing team now, because they can change your plan. I'll share our chat with them, so you won't need to repeat anything. | H14: Agent | I14: The customer wants to change their plan, which only the billing team can do. | J14: Another team must handle this request. What three things do you tell the customer before you pass the chat on? | K14: i'm-trans-FER-ring-you · to-our-BILL-ing-TEAM-NOW · they-can-CHANGE-your-PLAN · i'll-SHARE-our-CHAT · you-WON'T-need-to-re-PEAT-an-y-thing | L14: If read aloud: transferring_you → "trans-fer-ing-yoo" · share_our → "shair-rour" · need_to → "nee-tuh" | M14: If read aloud: steady and reassuring; fall on "plan" and on "anything", with a short pause between the two sentences. | N14: If read aloud: the verb "transfer" is trans-FER, with the stress at the end (the noun is TRANS-fer). Say "won't" with a long "oh" (like "own" + t), so it is not heard as "want". | O14: Neutral | P14: Reassuring, clear, responsible | Q14: 5 | R14: Worried about being passed around and having to explain everything again. | S14: Hand over the baton with the notes taped to it: the next runner already knows the race. | T14: मैं अभी आपको हमारी बिलिंग टीम के पास ट्रांसफ़र कर रहा/रही हूँ, क्योंकि वे आपका प्लान बदल सकते हैं। मैं हमारी चैट उनके साथ शेयर करूँगा/करूँगी, ताकि आपको कुछ दोहराना न पड़े। | U14: Main abhi aapko hamari billing team ke paas transfer kar raha/rahi hoon, kyunki woh aapka plan badal sakte hain. Main hamari chat unke saath share karoonga/karoongi, taaki aapko kuch dohraana na pade. | V14: Another team will take over because they can make this change. They will see what we wrote, so you don't need to explain again. | W14: It says who, why and what happens to the information, so the customer does not feel dropped and will not have to type the problem again. | X14: I'm transferring you to ___, because ___. I'll share ___, so you won't need to ___. | Y14: I'm + verb-ing + now · so + you + won't + need to + base verb | Z14: "So" here gives the result: because I share the chat, you won't need to repeat anything. | AA14: Giving the reason makes the transfer feel like help. "Transferring" on its own feels as if the agent is getting rid of the customer. | AB14: ✗ I'm transferring you to the billing team because they can to change your plan. → ✓ I'm transferring you to our billing team now, because they can change your plan. | AC14: "That's not my department." — it sounds as if you do not care, and it gives no next step. | AD14: Instead of "I can't do plan changes", say "I'm transferring you to our billing team now, because they can change your plan." | AE14: Our billing team can make that change for you, so I'll connect you with them now. They'll see our chat, so there's no need to explain again. | AF14: I'll pass you to a colleague in billing who can update your plan. I've added a note with all the details. | AG14: I will now transfer you to our billing team, who can change your plan. I have shared our conversation with them, so you will not need to repeat any details. | AH14: Is that all right with you? I'll stay in the chat until they join. | AI14: ok · how long will it take? · can't you just do it? | AJ14: Customer: "can't you just do it?" → Agent: "I'd like to, but plan changes are handled by billing. I'll stay here until they join, so you're not left waiting alone." | AK14: "Concerned team" and "concerned department" are common in Indian English; international customers may not expect them and want the team's real name ("our billing team"). | AL14: Voice: ask permission and brief your colleague before connecting (a warm transfer). Email: "I've passed your request to our billing team, and they will reply by tomorrow." | AM14: Do not transfer if you can solve the problem yourself; every transfer costs the customer time. | AN14: Customer: I want to change to the cheaper plan | Agent: I'm transferring you to our billing team now, because they can change your plan. I'll share our chat with them, so you won't need to repeat anything. | Customer: ok thanks | Agent: You're welcome. Ravi from billing will join you in about a minute. | AO14: Transfer warm: say who and why, and pass on the details so the customer does not repeat themselves. | AP14: I'll share our chat with them, so you won't need to ____ anything. (Hint: starts with "r") | AQ14: repeat | AR14: The customer needs the billing team. Which transfer message is best? | AS14: A) I can't change plans, sorry. I'm transferring you to another team now, so please wait a moment. | B) That's not my department, sorry. Please contact our billing team yourself through the website. | C) I'm transferring you to our billing team, because they can change your plan. I'll share our chat with them. | D) Billing handles plans, not me. I'm passing you to them now, but you may need to explain it all again. | AT14: C | AU14: C names the team, gives the reason and saves the customer from repeating the story. A does not say which team or why, B sends the customer away, and D admits the customer will have to explain everything again. | AV14: repeat / won't / anything / You / need / to | AW14: You won't need to repeat anything | AX14: Main aapko technical team ko transfer kar rahi hoon, kyunki woh yeh theek kar sakte hain. | AY14: I'm transferring you to our technical team, because they can fix this. | AZ14: how long will it take? | BA14: Ravi from billing should join in a minute or two. I'll stay here until he does. | BB14: Partner A wants to upgrade their plan in a general support chat. Partner B explains the transfer to billing with a reason and reassures A; then A asks "can't you just do it?". | BC14: Record yourself reading aloud your transfer message, then your answer when the customer asks "can't you just do it?". | BD14: Did you name the team? · Did you give a reason? · Did you tell the customer they won't need to repeat themselves?
... A62: CSC-A-020 | B62: Chat | C62: Advanced | D62: C1 | E62: Understand it | F62: Difficult customer | G62: why should I trust you? | H62: Customer | I62: The customer was promised an engineer visit twice last week and nobody came, and now you are promising a fix. | J62: A customer who was let down before asks why they should believe you. What earns trust in your reply: words or proof? | K62: WHY should i TRUST YOU | L62: If read aloud: should_I → "shu-dai" · trust_you → "trus-choo" | M62: If read aloud: a falling wh- question, slow and bitter; it is a challenge, not a real request for information. | N62: If you read it aloud, "trust" ends in a "-st" cluster; keep the final "t" (trust, not "trus"). "Why" starts with rounded lips, not a v sound. | O62: Neutral | P62: Doubtful, bitter, challenging | Q62: 5 | R62: Let down and suspicious after broken promises, afraid of being fooled again. | S62: Trust is a receipt, not a speech: show the customer something they can check. | T62: मैं आप पर भरोसा क्यों करूँ? | U62: Main aap par bharosa kyon karoon? | V62: You (the company) broke your promises before. Why should I believe this new promise? | W62: The customer has been let down and does not believe words any more. They need you to admit the broken promise, then give proof they can check: an action already done, a reference number, a time — and then keep it. | X62: why should I trust you? = you've let me down before; prove it this time | Y62: Why + should + I + base verb + you? (a challenge, not a real question) | Z62: "Should" here asks for a reason; the customer expects you to show, not tell. | AA62: Admit the past failure and show proof. "Trust me, sir" or "I assure you 100%" sounds empty to someone who was let down twice. | AB62: ✗ Trust me, this time it will be done 100%. → ✓ You've every reason to doubt us. I've already booked the engineer for Tuesday at 10 am, and your reference is EN-2287. | AC62: "I assure you, this time it will definitely happen." — it asks for trust without giving any proof. | AD62: Instead of "Please trust me", say "You've every reason to doubt us. Here's what I've already done, and here's the reference so you can check." | AE62: how do I know you won't forget me too? | AF62: you said that last time | AG62: Given what has happened, I'm not sure I can rely on what you're telling me. | AH62: You've every reason to doubt us after two missed visits. I've already booked the engineer for Tuesday at 10 am, reference EN-2287, and the confirmation is in your inbox now. | AI62: ok, I see the email · we'll see · and if nobody comes again? | AJ62: Customer: "And if nobody comes again?" → Agent: "Then message me here with that reference. I've added my name to the booking, and I'll check at 10:15 on Tuesday that the engineer has arrived." | AK62: "Trust me" and "I assure you" are common reassurances in Indian service English; international customers who were let down usually trust a checkable reference more than a promise. | AL62: Voice: say it slowly, admit the missed visits first, then read the reference clearly. Email: attach or forward the confirmation in the same message. | AM62: Do not promise a time or action you cannot control (for example a Tuesday check if you will be off shift); give only proof you can actually show. | AN62: Customer: why should I trust you? | Agent: You've every reason to doubt us after two missed visits. I've already booked the engineer for Tuesday at 10 am, reference EN-2287, and the confirmation is in your inbox now. | Customer: ok, I see the email | Agent: Thank you. I'll check on Tuesday at 10:15 that the engineer has arrived. | AO62: Ownership: replace vague promises with a clear time, a reference number and the next step. | AP62: You've every reason to doubt ____ (the company, not just you) after two missed visits. | AQ62: us | AR62: A customer who was let down twice writes "why should I trust you?". Which reply earns trust best? | AS62: A) You've every reason to doubt us. I've already booked the engineer for Tuesday at 10 am, reference EN-2287. | B) Trust me, sir, this time it will be done properly. I personally guarantee that nobody will let you down. | C) I assure you that we are a reliable company, and our customers have trusted us for many years now. | D) I am not the agent who booked you before, so I cannot say why the visits were missed last week. | AT62: A | AU62: A admits the failure and gives checkable proof. C sounds professional but is only a claim; B asks for blind trust and D shifts the blame. | AV62: doubt / reason / You've / every / us / to | AW62: You've every reason to doubt us | AX62: Aapke paas hum par shak karne ki poori wajah hai. Maine engineer pehle hi book kar diya hai, aur aapka reference number EN-2287 hai. | AY62: You've every reason to doubt us. I've already booked the engineer, and your reference number is EN-2287. | AZ62: and if nobody comes again? | BA62: Then message me here with the reference. I'll check on Tuesday at 10:15 that the engineer has arrived. | BB62: Partner A was promised two engineer visits that never happened and writes "why should I trust you?". Partner B admits the failure and gives proof: a booking, a reference and a check-in time. | BC62: Record yourself reading aloud your reply to "why should I trust you?" and your answer to "and if nobody comes again?". | BD62: Did you admit the past failure? · Did you give proof the customer can check? · Did you avoid "trust me" and "I assure you"?

Sheet Email
A1: CARD | G1: SIDE 1 · RECOGNITION | T1: SIDE 2 · MEANING & USE | AP1: SIDE 3 · PRACTICE | BE1: MY REVIEW (fill in)
A2: ID | B2: Channel | C2: Level | D2: CEFR | E2: Kind | F2: Stage | G2: Sentence | H2: Who says it | I2: Situation | J2: Recall first | K2: Say it like (stress) | L2: Linking | M2: Intonation & pace | N2: Indian speaker tip | O2: Register | P2: Tone | Q2: Importance (1-5) | R2: Customer feels | S2: Memory hook | T2: Hindi meaning | U2: Hindi (Roman) | V2: In simple English | W2: Why it works | X2: Key chunk | Y2: Grammar pattern | Z2: Grammar in one line | AA2: Tone note | AB2: Watch out | AC2: Don't say | AD2: Positive swap | AE2: Another way 1 | AF2: Another way 2 | AG2: More formal | AH2: Ask next | AI2: Replies you may hear | AJ2: If the customer pushes back | AK2: Indian English vs international | AL2: On other channels | AM2: When not to use | AN2: Mini conversation | AO2: Best-practice rule | AP2: Fill the blank | AQ2: Fill answer | AR2: MCQ question | AS2: MCQ options | AT2: MCQ answer | AU2: Why that answer | AV2: Put in order | AW2: Order answer | AX2: Say it in English | AY2: English answer | AZ2: Customer says next | BA2: Model reply | BB2: Role-play task | BC2: Record / write for audit | BD2: Self-check | BE2: Status | BF2: Day 1 | BG2: Day 3 | BH2: Day 7 | BI2: Day 15 | BJ2: Day 30 | BK2: Day 60 | BL2: My remark
A3: CSE-B-001 | B3: Email | C3: Basic | D3: A2 | E3: Say it | F3: Opening | G3: Update on your refund request – Ticket #55102 | H3: Agent | I3: You are sending the first update on a customer's refund, and your helpdesk lets you write the subject line of the email. | J3: Your email is about a refund and has a ticket number. What short subject tells the customer exactly what is inside? | K3: UP-date · on-your-REE-fund-re-QUEST · TICK-et-NUM-ber · five-five-one-oh-TWO | L3: If read aloud: update_on → "up-day-ton" · refund_request → "ree-fun-dri-kwest" | M3: If read aloud: a subject line is a label, so read it flat and falling, with a small pause before the ticket number. | N3: If read aloud, "update" is UP-date with stress on the first part, and the final "t" in "request" and "ticket" should be clear, not dropped. | O3: Neutral | P3: Clear, specific, businesslike | Q3: 4 | R3: Waiting for money back and checking the inbox for news. | S3: A subject line is the label on a box: the customer should know what is inside without opening the lid. | T3: आपकी रिफ़ंड रिक्वेस्ट पर अपडेट – टिकट #55102 | U3: Aapki refund request par update – ticket #55102 | V3: This email tells you the latest news about the money you asked to get back. | W3: The customer sees the topic and the ticket number before opening the email, so they can find it again and know it is not spam or a new problem. | X3: Update on your ___ – Ticket #___ | Y3: Noun (Update) + on + your + noun phrase + – + Ticket + number | Z3: Subject lines are short labels, so they skip "This is" and usually have no full stop. | AA3: A specific, calm label sounds professional. A subject like "URGENT!!!" or "Important information" sounds like spam and can worry the customer. | AB3: ✗ Regarding your query → ✓ Update on your refund request – Ticket #55102 | AC3: "Important information" — it says nothing about the content and looks like spam or a scam email. | AD3: Instead of "Your complaint", write "Update on your refund request – Ticket #55102". | AE3: Your refund for order 62408 – Ticket #55102 | AF3: Refund update for order 62408 (Ticket #55102) | AG3: Update regarding your refund request – Ticket #55102 | AH3: Hi Daniel, I have an update on your refund for order 62408. | AI3: Thanks, when will I get the money? · Is this about my old order? · Got it, thank you. | AJ3: Customer: "Why do you keep changing the subject line? I can't find your emails." → Agent: "I'm sorry the emails were hard to find. I'll keep the same subject line from now on so all our emails stay together." | AK3: Many Indian office emails use "Regarding your query" or "Reg: complaint". International customers expect a specific topic plus the ticket number. | AL3: Voice and chat: no subject line; say the topic in the first sentence instead. Email: if you reply in the customer's thread, keep their subject and the "Re:". | AM3: Do not change the subject when replying inside an existing thread; keep the customer's subject so the emails stay together. | AN3: Customer: I asked for a refund last week. | Agent: Subject: Update on your refund request – Ticket #55102. Hi Daniel, your refund is approved. | Customer: Great, when will I see it? | Agent: It should reach your card within five working days. | AO3: Email subject: specific, short and with the ticket number; keep it when replying. | AP3: Update on your refund request – ____ (starts with T) #55102 | AQ3: Ticket | AR3: You are writing the first update on a customer's refund. Which subject line is best? | AS3: A) Important information on your account – Ticket #55102 | B) Update on your refund request – Ticket #55102 | C) Reg: your refund query – see details below | D) URGENT – PLEASE READ – Refund Ticket #55102 | AT3: B | AU3: B names the topic and the ticket number in a calm label. A has a ticket number but does not say what the email is about, C has no ticket number and uses an office abbreviation, and D is in capital letters, which looks like spam. | AV3: refund / Update / Ticket / your / on / request / 55102 | AW3: Update on your refund request – Ticket #55102 | AX3: Subject line likhiye: aapke exchange request par update, ticket 60417. | AY3: Update on your exchange request – Ticket #60417 | AZ3: Thanks for the update. When will the money reach my card? | BA3: Your refund was sent today, and it should reach your card within five working days. | BB3: Partner A is a customer who asked for a refund on order 62408. Partner B writes three possible subject lines for the update email, and A chooses the clearest one and says why. | BC3: Write a subject line for an email updating a customer about a replacement order, Ticket #60233, and send it as text or a photo for audit. | BD3: Does the subject name the topic in a few clear words? · Did you include the ticket number? · Did you avoid ALL CAPS, "Reg:" and "Important"?
A4: CSE-B-002 | B4: Email | C4: Basic | D4: A2 | E4: Say it | F4: Opening | G4: Hi Daniel, this is Meera from the [Company] support team. | H4: Agent | I4: You are starting your first reply to a customer called Daniel Brooks, who signed his email with his first name. | J4: How do you open an email to a customer who signed off with his first name, and introduce yourself in one line? | K4: HI-DAN-yel · this-is-MEE-ra · from-the-COM-pa-ny · sup-PORT-team | L4: If read aloud: this_is → "thi-siz" · support_team → "su-por-team" | M4: If read aloud: a short pause after "Daniel", then a friendly, falling tone at the end. | N4: If read aloud, "this" starts with a soft "th" (tongue lightly between the teeth), not "dis"; "support" has the stress on PORT. | O4: Friendly | P4: Warm, personal, professional | Q4: 4 | R4: Hoping a real person has read the email. | S4: Use the name the customer gave you, like a shopkeeper who remembers a regular and says hello by name. | T4: नमस्ते डैनियल, मैं [Company] की सपोर्ट टीम से मीरा हूँ। | U4: Namaste Daniel, main [Company] ki support team se Meera hoon. | V4: Hello Daniel, my name is Meera and I work in the support team. | W4: Using the customer's name shows a person read the email, and giving your own name tells the customer who to reply to. | X4: Hi ___, this is ___ from ___. | Y4: Hi + first name + , + this is + your name + from + team | Z4: In emails we write "this is Meera", not "I am Meera speaking". | AA4: "Hi" plus a first name is friendly and normal in modern support. "Dear Customer" sounds like a machine, and "Respected Sir" sounds old-fashioned to many readers. | AB4: ✗ Dear Customer, I am Meera speaking from support. → ✓ Hi Daniel, this is Meera from the [Company] support team. | AC4: "Dear Customer," — it shows nobody looked at the customer's name and feels like a mass mailing. | AD4: Instead of "Dear Customer", write "Hi Daniel, this is Meera from the [Company] support team." | AE4: Hello Daniel, I'm Meera from the [Company] support team. | AF4: Hi Daniel, Meera here from [Company] support. | AG4: Dear Mr Brooks, my name is Meera and I work in the [Company] customer support team. | AH4: Thank you for writing to us about your order. | AI4: Hi Meera, thanks for getting back to me. · Hello, are you a real person? · Hi, I've been waiting for a reply. | AJ4: Customer: "Is this an automatic reply?" → Agent: "No, I'm Meera and I've read your email myself. I'm looking into your order now." | AK4: Many Indian emails start with "Respected Sir" or "Dear Sir/Madam". International customers usually expect their name; use "Hi" plus first name if they signed that way, or "Dear Mr/Ms" plus surname if they wrote formally. | AL4: Voice: "Thank you for calling [Company], this is Meera." Chat: "Hi Daniel, I'm Meera." Email: greeting and your name in the first line, then a blank line before the message. | AM4: Do not use "Hi" plus first name when the customer wrote formally and signed with a title and surname; use "Dear Mr Brooks" instead. | AN4: Customer: Hello, my blender stopped working. Thanks, Daniel | Agent: Hi Daniel, this is Meera from the [Company] support team. I'm sorry your blender stopped working. | Customer: Hi Meera, can you replace it? | Agent: I'll check your warranty now and email you the next step by 3 pm tomorrow. | AO4: Greet by name, not "Dear customer"; use a conversational voice. | AP4: Hi Daniel, ____ is Meera from the [Company] support team. | AQ4: this | AR4: The customer signed his email "Daniel". Which opening is best? | AS4: A) Dear Customer, I am Meera speaking from the support desk. | B) Respected Sir, this is Meera from the [Company] support team. | C) Hi Daniel, this is Meera from the [Company] support team. | D) Hello Mr Daniel, this is Meera from the [Company] support team. | AT4: C | AU4: C uses his name as he signed it and introduces you. D is tempting, but "Mr" goes with a surname (Mr Brooks), not a first name. A ignores his name and sounds like a mass mailing, and B uses "Respected Sir", which is polite in India but international customers may not expect it. | AV4: is / from / Hi / support / Meera / the / this / Company / team / Daniel | AW4: Hi Daniel, this is Meera from the [Company] support team. | AX4: Customer Priya ko greet kijiye aur bataiye ki aap Rahul hain, [Company] support se. | AY4: Hi Priya, this is Rahul from the [Company] support team. | AZ4: Hi Meera, thanks. Did you find my order? | BA4: Yes, I found it. Your order 51736 is with the courier and is due to arrive tomorrow. | BB4: Partner A writes a short email about a broken kettle and signs it "Sarah Jones". Partner B writes two openings, one friendly and one formal, and A says which fits her email better. | BC4: Write the greeting and first line of a reply to a customer who signed her email "Anita Kapoor", and send it as text or a photo for audit. | BD4: Did you use the customer's name as they wrote it? · Did you give your own name? · Did you avoid "Dear Customer", and "Respected Sir", which international customers may not expect?
A5: CSE-B-003 | B5: Email | C5: Basic | D5: A2 | E5: Say it | F5: Opening | G5: Thank you for writing to us about your missing parcel. | H5: Agent | I5: A customer has emailed to say a parcel marked as delivered never reached them, and you are starting your reply. | J5: The customer took time to tell you about a problem. What do you say first, and how do you show you read their email? | K5: THANK-you · for-WRY-ting-to-us · a-BOUT-your · MISS-ing-PAR-cel | L5: If read aloud: thank_you → "thang-kyoo" · about_your → "a-bou-chor" | M5: If read aloud: steady and warm, falling at "parcel" with no rush. | N5: If read aloud, "thank" starts with a soft "th" (tongue between the teeth), not "tank"; "parcel" is PAR-cel, not par-SEL. | O5: Neutral | P5: Grateful, attentive | Q5: 4 | R5: Annoyed and worried the parcel is lost. | S5: Thank the customer and name their problem, like a doctor who repeats your symptom so you know they listened. | T5: अपने गुम हुए पार्सल के बारे में हमें लिखने के लिए धन्यवाद। | U5: Apne gum hue parcel ke baare mein hamein likhne ke liye dhanyavaad. | V5: Thanks for telling us that your parcel has not arrived. | W5: Thanking the customer makes them feel heard, and naming the exact problem shows you read their email instead of sending a template. | X5: Thank you for writing to us about ___. | Y5: Thank you + for + verb-ing + about + noun | Z5: After "Thank you for" use the -ing form: "for writing", not "for write". | AA5: Thanking plus naming the problem sounds personal. "Thank you for your query" alone sounds like a template and may annoy an upset customer. | AB5: ✗ Thank you for write to us. → ✓ Thank you for writing to us about your missing parcel. | AC5: "Your query has been noted." — it sounds cold and robotic, and says nothing about the customer's problem. | AD5: Instead of "Your query has been noted", write "Thank you for writing to us about your missing parcel." | AE5: Thanks for letting us know that your parcel has not arrived. | AF5: Thank you for contacting us about your missing parcel. | AG5: Thank you for your email regarding the parcel that has not reached you. | AH5: I'm sorry it hasn't arrived. I have already asked the courier to trace it. | AI5: Thanks, any news? · I just want my parcel. · It says delivered but I don't have it. | AJ5: Customer: "I don't need thanks, I need my parcel." → Agent: "You're right, and I'm sorry you are still waiting. The courier is tracing it now, and I'll email you by 4 pm with an update." | AK5: Indian office emails often begin "This is with reference to your mail". International customers expect a short thank-you and the problem in plain words. | AL5: Voice: "Thanks for calling about your parcel." Chat: "Thanks for reaching out about your parcel." Email: one line, then the action. | AM5: Do not start with a thank-you to a very angry customer whose second complaint was ignored; apologise first. | AN5: Customer: My parcel says delivered, but it isn't here. | Agent: Thank you for writing to us about your missing parcel. I'm sorry it hasn't arrived. | Customer: What will you do? | Agent: I've asked the courier to trace it, and I'll update you by 4 pm today. | AO5: Thank the customer, name the issue, then give one clear next step. | AP5: Thank you for ____ (write) to us about your missing parcel. | AQ5: writing | AR5: A customer emails about a missing parcel. Which first line is best? | AS5: A) Your query has been noted and will be looked into. | B) Thank you for writing to us about your missing parcel. | C) This is with reference to your mail about the parcel. | D) Thank you for your query. We will look into it soon. | AT5: B | AU5: B thanks the customer and names the exact problem. D thanks but could be sent to anyone, C is a common Indian office opening that international customers may not expect, and it does not thank, and A is a cold office phrase. | AV5: writing / about / Thank / us / missing / you / to / parcel / for / your | AW5: Thank you for writing to us about your missing parcel. | AX5: Customer ko damaged phone ke baare mein likhne ke liye thanks kahiye. | AY5: Thank you for writing to us about your damaged phone. | AZ5: So where is my parcel? | BA5: I'm checking the courier's last scan myself right now. I'll email you by 4 pm today with what I find. | BB5: Partner A writes an email saying a parcel marked delivered is missing. Partner B writes the first two lines of the reply: a thank-you that names the problem, then the action taken. | BC5: Write the first two lines of a reply to a customer whose shoes arrived in the wrong size, and send it as text or a photo for audit. | BD5: Did you use "for" plus an -ing word? · Did you name the customer's exact problem? · Did you follow with an action?
A6: CSE-B-004 | B6: Email | C6: Basic | D6: A2 | E6: Say it | F6: Opening | G6: We have received your email, and I will send you a full answer by 5 pm tomorrow. | H6: Agent | I6: A customer has asked a question that needs a check with the billing team, so you confirm you got it and say when they will hear back. | J6: You cannot answer fully today. What do you tell the customer so they stop worrying their email was lost? | K6: we-have-re-CEIVED-your-EE-mail · and-I-will-SEND-you · a-FULL-AN-swer · by-FIVE-pee-EM-to-MOR-row | L6: If read aloud: received_your → "ri-SEEV-jer" (d + y join into a "j" sound) · send_you → "sen-joo" · full_answer → "fu-lan-ser" | M6: If read aloud: a small pause after "email", then a clear, falling tone on "tomorrow" to sound sure. | N6: If read aloud, say the "v" in "received" with your top teeth on your lower lip (vest, not west), and keep the final "d" in "received" and "send": ri-SEEVD, two syllables. | O6: Neutral | P6: Reassuring, clear promise | Q6: 5 | R6: Unsure whether anyone has read the email. | S6: Like a courier receipt: you show the parcel has arrived, and you write the delivery time on it. | T6: हमें आपका ईमेल मिल गया है, और मैं कल शाम 5 बजे तक आपको पूरा जवाब भेजूँगा/भेजूँगी। | U6: Hamein aapka email mil gaya hai, aur main kal shaam 5 baje tak aapko poora jawaab bhejunga/bhejungi. | V6: We got your email, and you will get a complete reply from me before 5 pm tomorrow. | W6: It tells the customer the email is not lost and gives a real time, so they do not need to write again or call to chase. | X6: I will send you ___ by ___. | Y6: We have + past participle · I will + base verb + by + time | Z6: "Have received" shows it has just happened; "will send" is your promise for the future. | AA6: "I will" plus a time sounds confident and responsible. "We will try to revert soon" sounds vague and uses a word international customers may not expect. | AB6: ✗ We have received your email and will reply you soon. → ✓ We have received your email, and I will send you a full answer by 5 pm tomorrow. | AC6: "We will get back to you shortly." — "shortly" is not a time, so the customer cannot plan and will probably chase you. | AD6: Instead of "We will try to reply soon", write "I will send you a full answer by 5 pm tomorrow." | AE6: Thanks for your email. I'm checking this with our billing team and will reply by 5 pm tomorrow. | AF6: I've received your message, and you'll have a full reply from me by tomorrow at 5 pm. | AG6: This is to confirm that we have received your email. I will send you a complete response by 5 pm tomorrow. | AH6: If you have a copy of the invoice, please attach it to your reply so I can check it faster. | AI6: OK, thanks for letting me know. · Can't you answer today? · Fine, but please don't forget. | AJ6: Customer: "Why can't you answer today?" → Agent: "I know you would like an answer today. I need our billing team to check two charges so that my answer is correct. I will email you by 5 pm tomorrow, and sooner if they finish early." | AK6: "We will revert" is common in Indian office email; Oxford lists "revert" meaning "reply" as Indian English. International customers expect "reply" or "get back to you". | AL6: Voice: "I'll call you back by 5 pm tomorrow." Chat: "I'll email you the full answer by 5 pm tomorrow." Email: one line near the top. | AM6: Do not send a holding reply when you can answer the whole question now; just answer it. | AN6: Customer: Why was I charged twice? | Agent: We have received your email, and I will send you a full answer by 5 pm tomorrow. | Customer: OK, please don't forget. | Agent: I won't. I'll check both charges with our billing team today. | AO6: Use "I will" plus a time instead of "we'll try" or "soon". | AP6: We have received your email, and I will send you a full answer ____ 5 pm tomorrow at the latest. | AQ6: by | AR6: You need one day to check a billing question. Which holding reply is best? | AS6: A) Thank you for your email. We will revert back to you with an answer very soon. | B) Your email has been forwarded to the billing team and is under process. | C) We have received your email, and I will send you a full answer by 5 pm tomorrow. | D) We have received your email, and someone from our team will contact you shortly. | AT6: C | AU6: C confirms the email arrived and gives a real time. A, B and D give no time ("very soon", "under process", "shortly"), and A also uses "revert back" and B "under process", which international readers may not expect. | AV6: send / I / full / will / answer / you / a | AW6: I will send you a full answer. | AX6: Customer ko bataiye ki email mil gaya hai aur aap Monday dopahar 12 baje tak jawaab denge. | AY6: We have received your email, and I will reply by 12 noon on Monday. | AZ6: OK. Do you need anything else from me? | BA6: Yes, please could you send a screenshot of the two charges on your bank statement? You can hide your account number. | BB6: Partner A emails about being charged twice. Partner B writes a holding reply that confirms the email arrived, explains the check in one line and gives a real time. | BC6: Write a two-line holding reply to a customer whose warranty question needs a check with the product team, and send it as text or a photo for audit. | BD6: Did you confirm you received the email? · Did you give a real day and time? · Did you use "I will" instead of "we will try"?
A7: CSE-B-005 | B7: Email | C7: Basic | D7: A2 | E7: Say it | F7: Verify | G7: To find your order quickly, could you send me the order number? It starts with ORD. | H7: Agent | I7: A customer has emailed about a late delivery but did not include an order number, and they have several orders with you. | J7: The customer forgot a detail you need to find their purchase. How do you ask for it and help them find it? | K7: to-FIND-your-OR-der-QUICK-ly · could-you-SEND-me · the-OR-der-NUM-ber · it-STARTS-with-oh-ar-DEE | L7: If read aloud: could_you → "cud-joo" · send_me → "sen-me" · starts_with → "star-tswith" | M7: If read aloud: rise on "order number?" because it is a yes/no question, then fall on "ORD". | N7: If read aloud, "order" is OR-der. For the "d", touch the ridge just behind your top teeth with the tip of your tongue; do not curl the tongue back, as in the Hindi ड. | O7: Neutral | P7: Polite, helpful request | Q7: 5 | R7: A little impatient because they expected you to know already. | S7: The order number is the key to the customer's locker; ask for the key and tell them which pocket it is in. | T7: आपका ऑर्डर जल्दी ढूँढने के लिए, क्या आप मुझे ऑर्डर नंबर भेज सकते हैं? यह ORD से शुरू होता है। | U7: Aapka order jaldi dhoondhne ke liye, kya aap mujhe order number bhej sakte hain? Yeh ORD se shuru hota hai. | V7: Please send me your order number so I can find your order fast; it begins with the letters ORD. | W7: It gives the reason first, so the request does not feel like a test, and tells the customer how to recognise the number. | X7: To ___, could you send me ___? | Y7: To + base verb (reason) + , + could you + base verb + object? | Z7: "To find" at the start gives the reason; "could you" makes the request polite. | AA7: Giving a reason and a hint sounds helpful. "Provide order number" or "May I know your order ID" sounds like a form. | AB7: ✗ Please provide order no. for further process. → ✓ To find your order quickly, could you send me the order number? It starts with ORD. | AC7: "Order number is mandatory to process your request." — it sounds like a rule and blames the customer. | AD7: Instead of "Provide your order ID", write "To find your order quickly, could you send me the order number?" | AE7: Could you reply with your order number? You'll find it in your confirmation email. | AF7: So I can check your delivery, could you send me the order number that begins with ORD? | AG7: So that I can locate your order, could you please send me the order number? It begins with the letters ORD. | AH7: Thank you. I can see order ORD-48213 and I'm checking the delivery now. | AI7: It's ORD-48213. · I can't find the email. · Can't you search by my email address? | AJ7: Customer: "Can't you just use my email address?" → Agent: "I can see three orders on your email address. The order number tells me which one is late, so I can fix the right one." | AK7: "May I know your order ID?" is common in Indian scripts and is grammatical. International customers more often hear "Could you send me…?" or "Could I have…?". | AL7: Voice: "Could I have your order number, please?" Chat: "Could you type your order number here?" Email: give the reason and where to find it, to avoid another round of emails. | AM7: Do not ask for the order number if it is already in the customer's email or subject line; read carefully first. | AN7: Customer: My delivery is late again. | Agent: I'm sorry your delivery is late again. To find your order quickly, could you send me the order number? It starts with ORD. | Customer: It's ORD-48213. | Agent: Thank you. I'm checking it now. | AO7: Verification: say the purpose and ask only for what you need. | AP7: ____ find your order quickly, could you send me the order number? It starts with ORD. | AQ7: To | AR7: A customer with three orders writes "My delivery is late." What is the best reply? | AS7: A) The order number is mandatory to process your request, so please send it. | B) To find your order quickly, could you send me the order number? It starts with ORD. | C) We cannot look into your delivery without further details from your side. | D) To confirm it is you, please send your full name, address, date of birth and phone number. | AT7: B | AU7: B gives a reason, asks for one thing and says how to find it. D gives a reason too, but asks for far more than you need. A and C sound like rules and give the customer no help. | AV7: send / number / you / me / Could / the / order | AW7: Could you send me the order number? | AX7: Customer se poochhiye ki kya woh ticket number bhej sakte hain, taaki aap complaint jaldi dhoondh saken. | AY7: To find your complaint quickly, could you send me the ticket number? | AZ7: I can't find the confirmation email. | BA7: That's fine. Could you tell me the date you ordered and the item name? I'll search for it that way. | BB7: Partner A emails "Where is my delivery?" with no details. Partner B writes a reply that asks for the order number with a reason and a hint; then A says they cannot find it, and B offers another way. | BC7: Write a reply asking a customer for their ticket number, with a reason and a hint where to find it, and send it as text or a photo for audit. | BD7: Did you give a reason first? · Did you ask for only one thing? · Did you tell the customer where to find it?
A8: CSE-B-006 | B8: Email | C8: Basic | D8: A2 | E8: Say it | F8: Listen & clarify | G8: Could you attach a photo of the damaged item to your reply? | H8: Agent | I8: A customer writes that their new lamp arrived broken, and you need to see the damage before you arrange a replacement. | J8: You need to see the damage before you can send a new item. What do you ask the customer to add to their next email? | K8: could-you-at-TACH · a-PHO-to · of-the-DAM-aged-I-tem · to-your-re-PLY | L8: If read aloud: attach_a → "a-ta-cha" · damaged_item → "dam-ij-dye-tem" | M8: If read aloud: rise at the end on "reply?" because it is a yes/no request. | N8: If read aloud, "photo" is FOH-toh with a long "oh". Start with "f", with your top teeth on your lower lip (fan, not pan), not a breathy "p"; "damaged" ends in a clear "d". | O8: Neutral | P8: Polite, practical request | Q8: 4 | R8: Disappointed and wanting a quick replacement. | S8: A photo is worth a thousand words, so ask for one picture instead of ten emails describing the crack. | T8: क्या आप अपने जवाब में क्षतिग्रस्त सामान की एक फ़ोटो लगा सकते हैं? | U8: Kya aap apne jawaab mein kshatigrast saamaan ki ek photo laga sakte hain? | V8: Please add a picture of the broken item when you write back. | W8: It asks for one clear thing in a polite question, so the customer knows exactly what to do and you avoid more emails. | X8: Could you attach ___ to your reply? | Y8: Could + you + attach + object + to + your reply? | Z8: We "attach" a file "to" an email; we do not "attach with" it. | AA8: A question sounds like a request. "Send photo" or "You have to send proof" sounds like the customer is not trusted. | AB8: ✗ Could you attach photo of damaged item to your reply? → ✓ Could you attach a photo of the damaged item to your reply? | AC8: "Send proof of damage." — "proof" sounds like you think the customer may be lying. | AD8: Instead of "You have to send proof", write "Could you attach a photo of the damaged item to your reply?" | AE8: Please could you send a photo of the broken lamp with your reply? | AF8: Could you reply with a photo that shows the damage? | AG8: Would you be able to attach a photograph of the damaged item when you reply? | AH8: A photo of the box and the label would also help, if you still have them. | AI8: Sure, here it is. · I threw the box away. · How do I attach a photo? | AJ8: Customer: "Why do you need a photo? Don't you believe me?" → Agent: "I do believe you, and I'm sorry it arrived broken. The photo goes to our courier so they can fix the packing problem, and it lets me send your replacement today." | AK8: Indian English often says "snap" for a photo and "the same" for the item. International customers say "photo" or "picture" and expect you to name the thing. | AL8: Voice: "Could you email us a photo of the damage?" Chat: "Could you upload a photo here using the clip icon?" Email: ask for it as an attachment to the reply. | AM8: Do not ask for a photo when the damage is already clear from the courier report or the customer already sent one. | AN8: Customer: My lamp arrived broken. | Agent: I'm sorry your lamp arrived broken. Could you attach a photo of the damaged item to your reply? | Customer: Here it is. | Agent: Thank you. I've booked a replacement lamp for you today. | AO8: Ask a clear question and give one clear next step. | AP8: Could you attach a photo of the damaged item ____ (starts with t) your reply? | AQ8: to | AR8: You need to see a broken item before replacing it. Which request is best? | AS8: A) Send proof of the damage today so that we can process your claim. | B) Kindly send the snap of the same so that we can look into the matter. | C) Could you attach a photo of the damaged item to your reply? | D) You have to send photos of the lamp, or we cannot arrange a replacement. | AT8: C | AU8: C is polite and clear. B is a common Indian-English habit that international customers may find unclear ("snap", "the same"), and A and D sound like you distrust the customer. | AV8: photo / Could / attach / you / a | AW8: Could you attach a photo? | AX8: Customer se kahiye ki apne jawaab mein error message ka screenshot attach karein. | AY8: Could you attach a screenshot of the error message to your reply? | AZ8: I'm on my phone. How do I attach it? | BA8: In most email apps, tap the paperclip icon, choose the photo and press send. | BB8: Partner A emails that a dinner plate arrived cracked. Partner B asks for a photo politely; A asks why it is needed, and B explains the reason calmly. | BC8: Write a two-line reply asking a customer for a screenshot of an error message, and send it as text or a photo for audit. | BD8: Did you ask with "Could you"? · Did you name the exact thing to photograph? · Did you avoid "proof" (it sounds like distrust) and "the same" (international customers may not expect it)?
A9: CSE-B-007 | B9: Email | C9: Basic | D9: A2 | E9: Say it | F9: Apologise | G9: I'm sorry your headphones arrived two days late. I have refunded the delivery charge to your card. | H9: Agent | I9: A customer paid for fast delivery, but their headphones arrived two days after the promised date. | J9: The delivery was late and the customer paid extra for speed. How do you say sorry for the exact problem and fix something? | K9: i'm-SOR-ry · your-HEAD-phones · a-RIVED · two-DAYS-LATE · i-have-re-FUND-ed · the-de-LIV-er-y-CHARGE | L9: If read aloud: arrived_two → "a-rive-too" · refunded_the → "ri-fun-di-the" | M9: If read aloud: low and sincere on the first sentence, then a clear, steady tone for the action. | N9: If read aloud, say the "v" in "delivery" with top teeth on the lower lip (vest, not west); "arrived" ends in a clear "d". | O9: Neutral | P9: Sincere, responsible | Q9: 5 | R9: Let down and feeling they paid for nothing. | S9: A real apology has two hands: one says sorry for the exact thing, the other gives something back. | T9: मुझे खेद है कि आपके हेडफ़ोन दो दिन देर से पहुँचे। मैंने डिलीवरी चार्ज आपके कार्ड में वापस कर दिया है। | U9: Mujhe khed hai ki aapke headphone do din der se pahunche. Maine delivery charge aapke card mein wapas kar diya hai. | V9: I apologise that your headphones came two days late, and I have given back the money you paid for delivery. | W9: It names the exact problem, so the customer knows you understood, and shows an action already done instead of only words. | X9: I'm sorry your ___. I have ___. | Y9: I'm sorry + (that) + subject + past verb · I have + past participle | Z9: Use "I'm sorry" plus what happened; "I have refunded" shows the action is already done. | AA9: A specific apology plus a fix sounds sincere. "Sorry for the inconvenience caused" sounds copied and does not say what went wrong. | AB9: ✗ Sorry for the inconvenience caused. → ✓ I'm sorry your headphones arrived two days late. I have refunded the delivery charge to your card. | AC9: "We regret the inconvenience caused." — it is a stock phrase that does not name the problem or take responsibility. | AD9: Instead of "Sorry for the inconvenience", write "I'm sorry your headphones arrived two days late." | AE9: I apologise that your headphones were two days late. I've refunded your delivery charge. | AF9: I'm sorry we missed the delivery date for your headphones. I've refunded the delivery charge, and it should reach your card within five working days. | AG9: Please accept my apologies for the two-day delay in delivering your headphones. I have refunded the delivery charge to your card. | AH9: You do not need to do anything. The refund should show on your card within five working days. | AI9: Thank you, that's fair. · It's not just the money, I needed them for a trip. · Will this happen again? | AJ9: Customer: "I needed them for my trip. A refund doesn't fix that." → Agent: "You're right, and I'm sorry it spoiled your plans. I've also added a note to your account so our team checks your next delivery closely." | AK9: "Sorry for the inconvenience caused" is very common in Indian support templates. International customers often read it as a copy-paste line; name the problem instead. | AL9: Voice: say it slowly, then pause for the customer. Chat: split into two short messages. Email: put it near the top, after the greeting. | AM9: Do not apologise for a delay before you have checked it really was late; first confirm the facts. | AN9: Customer: I paid for fast delivery and my headphones came two days late. | Agent: I'm sorry your headphones arrived two days late. I have refunded the delivery charge to your card. | Customer: Thanks. When will I see it? | Agent: It should reach your card within five working days. | AO9: Apologise specifically, take responsibility, then offer a fix. | AP9: I'm sorry your headphones arrived two days late. I ____ refunded the delivery charge to your card. | AQ9: have | AR9: A customer paid for fast delivery, but their headphones arrived two days late. Which apology is best? | AS9: A) We are sorry for the inconvenience caused to you by the delay in delivering your order. | B) I'm sorry, but delays can happen with couriers, and this one was outside our control. | C) I'm sorry your headphones arrived two days late. I have refunded the delivery charge to your card. | D) We regret any inconvenience this may have caused and thank you for your patience and understanding. | AT9: C | AU9: C names the problem and fixes something. A and D are stock phrases that do not say what went wrong or what you did, and B makes an excuse instead of taking responsibility. | AV9: headphones / sorry / late / I'm / arrived / your | AW9: I'm sorry your headphones arrived late. | AX9: Customer se maafi maangiye ki unka phone charger galat bheja gaya, aur bataiye ki sahi charger aaj bhej diya hai. | AY9: I'm sorry we sent you the wrong charger. I have sent the right one today. | AZ9: Will this happen again next time? | BA9: I have reported this delay to our delivery team today. If your next order is late, reply to this email and I will look into it myself. | BB9: Partner A emails that a birthday cake arrived a day late. Partner B writes a specific apology and one action already taken; A pushes back once, and B answers calmly. | BC9: Write a two-sentence apology to a customer who received the wrong colour of shirt, including one action you have taken, and send it as text or a photo for audit. | BD9: Did you name the exact problem? · Did you use "I", not only "we"? · Did you include an action already done?
A10: CSE-B-008 | B10: Email | C10: Basic | D10: A2 | E10: Say it | F10: Close | G10: Good news: your account is unlocked, and you can log in again now. | H10: Agent | I10: A customer was locked out after too many wrong passwords, and you have just reset the account. | J10: The problem is solved. How do you tell the customer in one line, and what can they do now? | K10: GOOD-NEWS · your-ac-COUNT-is-un-LOCKED · and-you-can-LOG-in-a-GAIN-NOW | L10: If read aloud: account_is → "a-coun-tis" · log_in → "lo-gin" · unlocked_and → "un-lock-tand" | M10: If read aloud: bright, rising energy on "Good news", then a clear fall on "now". | N10: If read aloud, "unlocked" ends in a "t" sound (un-LOKT), not "un-lock-ed" with an extra syllable. | O10: Friendly | P10: Positive, clear, upbeat | Q10: 4 | R10: Frustrated at being locked out and relieved to hear news. | S10: Lead with the good news like opening the door first, then tell them they can walk in. | T10: अच्छी ख़बर: आपका अकाउंट अनलॉक हो गया है, और अब आप फिर से लॉग इन कर सकते हैं। | U10: Achchhi khabar: aapka account unlock ho gaya hai, aur ab aap phir se log in kar sakte hain. | V10: Your account works again, and you can sign in right now. | W10: The customer reads the result in the first line and knows exactly what to do next, without searching through the email. | X10: Good news: your ___ is ___, and you can ___ now. | Y10: Good news + : + subject + is + adjective + , and + you can + base verb | Z10: "Unlocked" here is an adjective that describes the account now. | AA10: Starting with the result sounds confident and kind. "Your issue has been resolved from our end" sounds stiff and does not tell the customer what to do. | AB10: ✗ Good news: your account is unlock, and you can login again now. → ✓ Good news: your account is unlocked, and you can log in again now. | AC10: "The issue has been resolved at our end." — it is vague, and "at our end" hints the problem may still exist at the customer's end. | AD10: Instead of "Issue resolved from our end", write "Good news: your account is unlocked, and you can log in again now." | AE10: Your account is working again, so you can sign in now. | AF10: I've unlocked your account, and you can log in straight away. | AG10: I am pleased to confirm that your account has been unlocked, and you can now log in as usual. | AH10: If you still see an error when you log in, reply to this email and I'll check it right away. | AI10: Great, it works, thanks! · I still can't log in. · Do I need a new password? | AJ10: Customer: "It still doesn't work." → Agent: "I'm sorry it still isn't working. Could you send me a screenshot of the message you see? I'll check it straight away." | AK10: "Resolved from our end" is a common Indian support phrase. International customers prefer the actual result in plain words and what they can do now. | AL10: Voice: "Good news, your account is unlocked. Could you try logging in now while I'm on the line?" Chat: same short line, then wait for them to try. Email: put it in the first line. | AM10: Do not say an issue is fixed before you have tested it or before the change has gone through. | AN10: Customer: I'm locked out of my account. | Agent: Good news: your account is unlocked, and you can log in again now. | Customer: It works, thank you. | Agent: You're welcome. Is there anything else I can help with? | AO10: Give one clear next step in plain words. | AP10: Good ____: your account is unlocked, and you can log in again now. | AQ10: news | AR10: You have fixed a customer's locked account. Which line is best to start the email? | AS10: A) Your issue has been resolved from our end, so please check and confirm. | B) Good news: your account is unlocked, and you can log in again now. | C) The needful has been done on your account, and the ticket is now closed. | D) Please check and confirm if you are now able to access your account. | AT10: B | AU10: B gives the result and the next step. A sounds professional but vague, and "from our end" can sound like the problem may still be on the customer's side. C is fine in Indian office English, but international customers may not expect "the needful", and it does not say what was done, and D leaves the customer to find out the result alone. | AV10: you / account / is / unlocked / and / your / can / now / log / in | AW10: Your account is unlocked, and you can log in now. | AX10: Customer ko bataiye ki unka password reset ho gaya hai aur woh ab login kar sakte hain. | AY10: Good news: your password has been reset, and you can log in now. | AZ10: Do I need to change my password? | BA10: Your current password works again. If you would like a new one, go to Settings, then Security, after you log in. | BB10: Partner A emails that their gift card does not work. Partner B writes the "fixed" email: the good news first, then what A can do now, then a line in case it still fails. | BC10: Write a two-line email telling a customer that their delivery address is now corrected, and send it as text or a photo for audit. | BD10: Did the result come in the first line? · Did you say what the customer can do now? · Did you say what was fixed, not just "resolved from our end"?
